Workbook

Sheet Summary (2)
A1: GBP | J1: USD
A3: Customer | B3: Maintenance | C3: PS | D3: Def Licenses | E3: Perpetual Licenses | G3: Total Revenue 2024 (£) | J3: Maintenance | K3: PS | L3: Def Licenses | M3: Perpetual Licenses | O3: Total Revenue 2024 ($) | R3: COGS | T3: Net
A4: Frontier Agriculture | B4: =IFERROR(VLOOKUP(A4,'Annual Maintenance'!$A$1:$G$41,7,FALSE),0)+(21531*12) -> 1916081.5 | C4: =IFERROR(VLOOKUP(A4,#REF!,14,FALSE),0) -> 0 | D4: =IFERROR(VLOOKUP(A4,#REF!,14,FALSE),0) -> 0 | E4: =IFERROR(VLOOKUP(A4,'IFRS15 Licenses'!$U$12:$AH$28,14,FALSE),0) -> 0 | G4: =SUM(B4:F4) -> 1916081.5 | H4: =G4/$G$46 -> 0.3629409 | J4: =IFERROR(VLOOKUP(A4,'Annual Maintenance'!$A$1:$N$41,14,FALSE),0) -> 2189263.4 | K4: =IFERROR(VLOOKUP(A4,#REF!,14,FALSE),0) -> 0 | L4: =IFERROR(VLOOKUP(A4,#REF!,14,FALSE),0) -> 0 | M4: =IFERROR(VLOOKUP(A4,'IFRS15 Licenses'!#REF!,14,FALSE),0) -> 0 | O4: =SUM(J4:N4) -> 2189263.4 | R4: =IFERROR(VLOOKUP(A4,#REF!,14,FALSE),0) -> 0 | T4: =O4+R4 -> 2189263.4
A5: Openfield | B5: =IFERROR(VLOOKUP(A5,'Annual Maintenance'!$A$1:$G$41,7,FALSE),0) -> 829534.83 | C5: =IFERROR(VLOOKUP(A5,#REF!,14,FALSE),0) -> 0 | D5: =IFERROR(VLOOKUP(A5,#REF!,14,FALSE),0) -> 0 | E5: =IFERROR(VLOOKUP(A5,'IFRS15 Licenses'!$U$12:$AH$28,14,FALSE),0) -> 0 | G5: =SUM(B5:F5) -> 829534.83 | H5: =G5/$G$46 -> 0.15712908 | J5: =IFERROR(VLOOKUP(A5,'Annual Maintenance'!$A$1:$N$41,14,FALSE),0) -> 1095797.5 | K5: =IFERROR(VLOOKUP(A5,#REF!,14,FALSE),0) -> 0 | L5: =IFERROR(VLOOKUP(A5,#REF!,14,FALSE),0) -> 0 | M5: =IFERROR(VLOOKUP(A5,'IFRS15 Licenses'!#REF!,14,FALSE),0) -> 0 | O5: =SUM(J5:N5) -> 1095797.5 | R5: =IFERROR(VLOOKUP(A5,#REF!,14,FALSE),0) -> 0 | T5: =O5+R5 -> 1095797.5
A6: West Gaines Seeds | B6: =IFERROR(VLOOKUP(A6,'Annual Maintenance'!$A$1:$G$41,7,FALSE),0) -> 469478.42 | C6: =IFERROR(VLOOKUP(A6,#REF!,14,FALSE),0) -> 0 | D6: =IFERROR(VLOOKUP(A6,#REF!,14,FALSE),0) -> 0 | E6: =IFERROR(VLOOKUP(A6,'IFRS15 Licenses'!$U$12:$AH$28,14,FALSE),0) -> 8232.63 | G6: =SUM(B6:F6) -> 477711.05 | H6: =G6/$G$46 -> 0.090487214 | J6: =IFERROR(VLOOKUP(A6,'Annual Maintenance'!$A$1:$N$41,14,FALSE),0) -> 619973.78 | K6: =IFERROR(VLOOKUP(A6,#REF!,14,FALSE),0) -> 0 | L6: =IFERROR(VLOOKUP(A6,#REF!,14,FALSE),0) -> 0 | M6: =IFERROR(VLOOKUP(A6,'IFRS15 Licenses'!#REF!,14,FALSE),0) -> 0 | O6: =SUM(J6:N6) -> 619973.78 | R6: =IFERROR(VLOOKUP(A6,#REF!,14,FALSE),0) -> 0 | T6: =O6+R6 -> 619973.78
A7: Simpsons Malt | B7: =IFERROR(VLOOKUP(A7,'Annual Maintenance'!$A$1:$G$41,7,FALSE),0) -> 319982.68 | C7: =IFERROR(VLOOKUP(A7,#REF!,14,FALSE),0) -> 0 | D7: =IFERROR(VLOOKUP(A7,#REF!,14,FALSE),0) -> 0 | E7: =IFERROR(VLOOKUP(A7,'IFRS15 Licenses'!$U$12:$AH$28,14,FALSE),0) -> 22700.004 | G7: =SUM(B7:F7) -> 342682.68 | H7: =G7/$G$46 -> 0.06491037 | J7: =IFERROR(VLOOKUP(A7,'Annual Maintenance'!$A$1:$N$41,14,FALSE),0) -> 422658.16 | K7: =IFERROR(VLOOKUP(A7,#REF!,14,FALSE),0) -> 0 | L7: =IFERROR(VLOOKUP(A7,#REF!,14,FALSE),0) -> 0 | M7: =IFERROR(VLOOKUP(A7,'IFRS15 Licenses'!#REF!,14,FALSE),0) -> 0 | O7: =SUM(J7:N7) -> 422658.16 | R7: =IFERROR(VLOOKUP(A7,#REF!,14,FALSE),0) -> 0 | T7: =O7+R7 -> 422658.16
A8: Wynnstay Group | B8: =IFERROR(VLOOKUP(A8,'Annual Maintenance'!$A$1:$G$41,7,FALSE),0) -> 168704.17 | C8: =IFERROR(VLOOKUP(A8,#REF!,14,FALSE),0) -> 0 | D8: =IFERROR(VLOOKUP(A8,#REF!,14,FALSE),0) -> 0 | E8: =IFERROR(VLOOKUP(A8,'IFRS15 Licenses'!$U$12:$AH$28,14,FALSE),0) -> 307.3 | G8: =SUM(B8:F8) -> 169011.47 | H8: =G8/$G$46 -> 0.032013865 | J8: =IFERROR(VLOOKUP(A8,'Annual Maintenance'!$A$1:$N$41,14,FALSE),0) -> 222784.75 | K8: =IFERROR(VLOOKUP(A8,#REF!,14,FALSE),0) -> 0 | L8: =IFERROR(VLOOKUP(A8,#REF!,14,FALSE),0) -> 0 | M8: =IFERROR(VLOOKUP(A8,'IFRS15 Licenses'!#REF!,14,FALSE),0) -> 0 | O8: =SUM(J8:N8) -> 222784.75 | R8: =IFERROR(VLOOKUP(A8,#REF!,14,FALSE),0) -> 0 | T8: =O8+R8 -> 222784.75
A9: Oxbow Coal | B9: =IFERROR(VLOOKUP(A9,'Annual Maintenance'!$A$1:$G$41,7,FALSE),0) -> 191809.9 | C9: =IFERROR(VLOOKUP(A9,#REF!,14,FALSE),0) -> 0 | D9: =IFERROR(VLOOKUP(A9,#REF!,14,FALSE),0) -> 0 | E9: =IFERROR(VLOOKUP(A9,'IFRS15 Licenses'!$U$12:$AH$28,14,FALSE),0) -> 0 | G9: =SUM(B9:F9) -> 191809.9 | H9: =G9/$G$46 -> 0.036332304 | J9: =IFERROR(VLOOKUP(A9,'Annual Maintenance'!$A$1:$N$41,14,FALSE),0) -> 253302.62 | K9: =IFERROR(VLOOKUP(A9,#REF!,14,FALSE),0) -> 0 | L9: =IFERROR(VLOOKUP(A9,#REF!,14,FALSE),0) -> 0 | M9: =IFERROR(VLOOKUP(A9,'IFRS15 Licenses'!#REF!,14,FALSE),0) -> 0 | O9: =SUM(J9:N9) -> 253302.62 | R9: =IFERROR(VLOOKUP(A9,#REF!,14,FALSE),0) -> 0 | T9: =O9+R9 -> 253302.62
A10: Saxon Agriculture | B10: =IFERROR(VLOOKUP(A10,'Annual Maintenance'!$A$1:$G$41,7,FALSE),0) -> 133642.21 | C10: =IFERROR(VLOOKUP(A10,#REF!,14,FALSE),0) -> 0 | D10: =IFERROR(VLOOKUP(A10,#REF!,14,FALSE),0) -> 0 | E10: =IFERROR(VLOOKUP(A10,'IFRS15 Licenses'!$U$12:$AH$28,14,FALSE),0) -> 11917 | G10: =SUM(B10:F10) -> 145559.21 | H10: =G10/$G$46 -> 0.027571577 | J10: =IFERROR(VLOOKUP(A10,'Annual Maintenance'!$A$1:$N$41,14,FALSE),0) -> 176676.87 | K10: =IFERROR(VLOOKUP(A10,#REF!,14,FALSE),0) -> 0 | L10: =IFERROR(VLOOKUP(A10,#REF!,14,FALSE),0) -> 0 | M10: =IFERROR(VLOOKUP(A10,'IFRS15 Licenses'!#REF!,14,FALSE),0) -> 0 | O10: =SUM(J10:N10) -> 176676.87 | R10: =IFERROR(VLOOKUP(A10,#REF!,14,FALSE),0) -> 0 | T10: =O10+R10 -> 176676.87
A11: Denholm Fish Selling Ltd | B11: =IFERROR(VLOOKUP(A11,'Annual Maintenance'!$A$1:$G$41,7,FALSE),0) -> 55553.323 | C11: =IFERROR(VLOOKUP(A11,#REF!,14,FALSE),0) -> 0 | D11: =IFERROR(VLOOKUP(A11,#REF!,14,FALSE),0) -> 0 | E11: =IFERROR(VLOOKUP(A11,'IFRS15 Licenses'!$U$12:$AH$28,14,FALSE),0) -> 0 | G11: =SUM(B11:F11) -> 55553.323 | H11: =G11/$G$46 -> 0.010522816 | J11: =IFERROR(VLOOKUP(A11,'Annual Maintenance'!$A$1:$N$41,14,FALSE),0) -> 73384.077 | K11: =IFERROR(VLOOKUP(A11,#REF!,14,FALSE),0) -> 0 | L11: =IFERROR(VLOOKUP(A11,#REF!,14,FALSE),0) -> 0 | M11: =IFERROR(VLOOKUP(A11,'IFRS15 Licenses'!#REF!,14,FALSE),0) -> 0 | O11: =SUM(J11:N11) -> 73384.077 | R11: =IFERROR(VLOOKUP(A11,#REF!,14,FALSE),0) -> 0 | T11: =O11+R11 -> 73384.077
A12: Grainco | B12: =IFERROR(VLOOKUP(A12,'Annual Maintenance'!$A$1:$G$41,7,FALSE),0) -> 94530.098 | C12: =IFERROR(VLOOKUP(A12,#REF!,14,FALSE),0) -> 0 | D12: =IFERROR(VLOOKUP(A12,#REF!,14,FALSE),0) -> 0 | E12: =IFERROR(VLOOKUP(A12,'IFRS15 Licenses'!$U$12:$AH$28,14,FALSE),0) -> 0 | G12: =SUM(B12:F12) -> 94530.098 | H12: =G12/$G$46 -> 0.01790573 | J12: =IFERROR(VLOOKUP(A12,'Annual Maintenance'!$A$1:$N$41,14,FALSE),0) -> 124842.02 | K12: =IFERROR(VLOOKUP(A12,#REF!,14,FALSE),0) -> 0 | L12: =IFERROR(VLOOKUP(A12,#REF!,14,FALSE),0) -> 0 | M12: =IFERROR(VLOOKUP(A12,'IFRS15 Licenses'!#REF!,14,FALSE),0) -> 0 | O12: =SUM(J12:N12) -> 124842.02 | R12: =IFERROR(VLOOKUP(A12,#REF!,14,FALSE),0) -> 0 | T12: =O12+R12 -> 124842.02
A13: AB Agri | B13: =IFERROR(VLOOKUP(A13,'Annual Maintenance'!$A$1:$G$41,7,FALSE),0) -> 86882.937 | C13: =IFERROR(VLOOKUP(A13,#REF!,14,FALSE),0) -> 0 | D13: =IFERROR(VLOOKUP(A13,#REF!,14,FALSE),0) -> 0 | E13: =IFERROR(VLOOKUP(A13,'IFRS15 Licenses'!$U$12:$AH$28,14,FALSE),0) -> 0 | F13: =IFERROR(VLOOKUP(#REF!,'IFRS15 Licenses'!$U$12:$AH$25,14,FALSE),0) -> 0 | G13: =SUM(B13:F13) -> 86882.937 | H13: =G13/$G$46 -> 0.016457218 | J13: =IFERROR(VLOOKUP(A13,'Annual Maintenance'!$A$1:$N$41,14,FALSE),0) -> 114783.73 | K13: =IFERROR(VLOOKUP(A13,#REF!,14,FALSE),0) -> 0 | L13: =IFERROR(VLOOKUP(A13,#REF!,14,FALSE),0) -> 0 | M13: =IFERROR(VLOOKUP(A13,'IFRS15 Licenses'!#REF!,14,FALSE),0) -> 0 | O13: =SUM(J13:N13) -> 114783.73 | R13: =IFERROR(VLOOKUP(A13,#REF!,14,FALSE),0) -> 0 | T13: =O13+R13 -> 114783.73
A14: Glasson Grain | B14: =IFERROR(VLOOKUP(A14,'Annual Maintenance'!$A$1:$G$41,7,FALSE),0) -> 98202.427 | C14: =IFERROR(VLOOKUP(A14,#REF!,14,FALSE),0) -> 0 | D14: =IFERROR(VLOOKUP(A14,#REF!,14,FALSE),0) -> 0 | E14: =IFERROR(VLOOKUP(A14,'IFRS15 Licenses'!$U$12:$AH$28,14,FALSE),0) -> 350 | G14: =SUM(B14:F14) -> 98552.427 | H14: =G14/$G$46 -> 0.018667633 | J14: =IFERROR(VLOOKUP(A14,'Annual Maintenance'!$A$1:$N$41,14,FALSE),0) -> 129721.69 | K14: =IFERROR(VLOOKUP(A14,#REF!,14,FALSE),0) -> 0 | L14: =IFERROR(VLOOKUP(A14,#REF!,14,FALSE),0) -> 0 | M14: =IFERROR(VLOOKUP(A14,'IFRS15 Licenses'!#REF!,14,FALSE),0) -> 0 | O14: =SUM(J14:N14) -> 129721.69 | R14: =IFERROR(VLOOKUP(A14,#REF!,14,FALSE),0) -> 0 | T14: =O14+R14 -> 129721.69
A15: Canterra Seeds | B15: =IFERROR(VLOOKUP(A15,'Annual Maintenance'!$A$1:$G$41,7,FALSE),0) -> 62095.212 | C15: =IFERROR(VLOOKUP(A15,#REF!,14,FALSE),0) -> 0 | D15: =IFERROR(VLOOKUP(A15,#REF!,14,FALSE),0) -> 0 | E15: =IFERROR(VLOOKUP(A15,'IFRS15 Licenses'!$U$12:$AH$28,14,FALSE),0) -> 5751.166 | G15: =SUM(B15:F15) -> 67846.378 | H15: =G15/$G$46 -> 0.012851345 | J15: =IFERROR(VLOOKUP(A15,'Annual Maintenance'!$A$1:$N$41,14,FALSE),0) -> 82024.538 | K15: =IFERROR(VLOOKUP(A15,#REF!,14,FALSE),0) -> 0 | L15: =IFERROR(VLOOKUP(A15,#REF!,14,FALSE),0) -> 0 | M15: =IFERROR(VLOOKUP(A15,'IFRS15 Licenses'!#REF!,14,FALSE),0) -> 0 | O15: =SUM(J15:N15) -> 82024.538 | R15: =IFERROR(VLOOKUP(A15,#REF!,14,FALSE),0) -> 0 | T15: =O15+R15 -> 82024.538
A16: Harlow Agriculture | B16: =IFERROR(VLOOKUP(A16,'Annual Maintenance'!$A$1:$G$41,7,FALSE),0) -> 92092.844 | C16: =IFERROR(VLOOKUP(A16,#REF!,14,FALSE),0) -> 0 | D16: =IFERROR(VLOOKUP(A16,#REF!,14,FALSE),0) -> 0 | E16: =IFERROR(VLOOKUP(A16,'IFRS15 Licenses'!$U$12:$AH$28,14,FALSE),0) -> 522.2 | G16: =SUM(B16:F16) -> 92615.044 | H16: =G16/$G$46 -> 0.017542984 | J16: =IFERROR(VLOOKUP(A16,'Annual Maintenance'!$A$1:$N$41,14,FALSE),0) -> 121654.52 | K16: =IFERROR(VLOOKUP(A16,#REF!,14,FALSE),0) -> 0 | L16: =IFERROR(VLOOKUP(A16,#REF!,14,FALSE),0) -> 0 | M16: =IFERROR(VLOOKUP(A16,'IFRS15 Licenses'!#REF!,14,FALSE),0) -> 0 | O16: =SUM(J16:N16) -> 121654.52 | R16: =IFERROR(VLOOKUP(A16,#REF!,14,FALSE),0) -> 0 | T16: =O16+R16 -> 121654.52
A17: H J Lea | B17: =IFERROR(VLOOKUP(A17,'Annual Maintenance'!$A$1:$G$41,7,FALSE),0) -> 82017.101 | C17: =IFERROR(VLOOKUP(A17,#REF!,14,FALSE),0) -> 0 | D17: =IFERROR(VLOOKUP(A17,#REF!,14,FALSE),0) -> 0 | E17: =IFERROR(VLOOKUP(A17,'IFRS15 Licenses'!$U$12:$AH$28,14,FALSE),0) -> 1000 | G17: =SUM(B17:F17) -> 83017.101 | H17: =G17/$G$46 -> 0.015724958 | J17: =IFERROR(VLOOKUP(A17,'Annual Maintenance'!$A$1:$N$41,14,FALSE),0) -> 108214.26 | K17: =IFERROR(VLOOKUP(A17,#REF!,14,FALSE),0) -> 0 | L17: =IFERROR(VLOOKUP(A17,#REF!,14,FALSE),0) -> 0 | M17: =IFERROR(VLOOKUP(A17,'IFRS15 Licenses'!#REF!,14,FALSE),0) -> 0 | O17: =SUM(J17:N17) -> 108214.26 | R17: =IFERROR(VLOOKUP(A17,#REF!,14,FALSE),0) -> 0 | T17: =O17+R17 -> 108214.26
A18: WCF | B18: =IFERROR(VLOOKUP(A18,'Annual Maintenance'!$A$1:$G$41,7,FALSE),0) -> 73052.513 | C18: =IFERROR(VLOOKUP(A18,#REF!,14,FALSE),0) -> 0 | D18: =IFERROR(VLOOKUP(A18,#REF!,14,FALSE),0) -> 0 | E18: =IFERROR(VLOOKUP(A18,'IFRS15 Licenses'!$U$12:$AH$28,14,FALSE),0) -> 0 | G18: =SUM(B18:F18) -> 73052.513 | H18: =G18/$G$46 -> 0.013837483 | J18: =IFERROR(VLOOKUP(A18,'Annual Maintenance'!$A$1:$N$41,14,FALSE),0) -> 96486.212 | K18: =IFERROR(VLOOKUP(A18,#REF!,14,FALSE),0) -> 0 | L18: =IFERROR(VLOOKUP(A18,#REF!,14,FALSE),0) -> 0 | M18: =IFERROR(VLOOKUP(A18,'IFRS15 Licenses'!#REF!,14,FALSE),0) -> 0 | O18: =SUM(J18:N18) -> 96486.212 | R18: =IFERROR(VLOOKUP(A18,#REF!,14,FALSE),0) -> 0 | T18: =O18+R18 -> 96486.212
A19: Fram Farmers | B19: =IFERROR(VLOOKUP(A19,'Annual Maintenance'!$A$1:$G$41,7,FALSE),0) -> 29460.291 | C19: =IFERROR(VLOOKUP(A19,#REF!,14,FALSE),0) -> 0 | D19: =IFERROR(VLOOKUP(A19,#REF!,14,FALSE),0) -> 0 | E19: =IFERROR(VLOOKUP(A19,'IFRS15 Licenses'!$U$12:$AH$28,14,FALSE),0) -> 8139 | G19: =SUM(B19:F19) -> 37599.291 | H19: =G19/$G$46 -> 0.0071219937 | J19: =IFERROR(VLOOKUP(A19,'Annual Maintenance'!$A$1:$N$41,14,FALSE),0) -> 38924.124 | K19: =IFERROR(VLOOKUP(A19,#REF!,14,FALSE),0) -> 0 | L19: =IFERROR(VLOOKUP(A19,#REF!,14,FALSE),0) -> 0 | M19: =IFERROR(VLOOKUP(A19,'IFRS15 Licenses'!#REF!,14,FALSE),0) -> 0 | O19: =SUM(J19:N19) -> 38924.124 | R19: =IFERROR(VLOOKUP(A19,#REF!,14,FALSE),0) -> 0 | T19: =O19+R19 -> 38924.124
A20: Barenbrug | B20: =IFERROR(VLOOKUP(A20,'Annual Maintenance'!$A$1:$G$41,7,FALSE),0) -> 59091.87 | C20: =IFERROR(VLOOKUP(A20,#REF!,14,FALSE),0) -> 0 | D20: =IFERROR(VLOOKUP(A20,#REF!,14,FALSE),0) -> 0 | E20: =IFERROR(VLOOKUP(A20,'IFRS15 Licenses'!$U$12:$AH$28,14,FALSE),0) -> 3153.2 | G20: =SUM(B20:F20) -> 62245.07 | H20: =G20/$G$46 -> 0.011790355 | J20: =IFERROR(VLOOKUP(A20,'Annual Maintenance'!$A$1:$N$41,14,FALSE),0) -> 78042.149 | K20: =IFERROR(VLOOKUP(A20,#REF!,14,FALSE),0) -> 0 | L20: =IFERROR(VLOOKUP(A20,#REF!,14,FALSE),0) -> 0 | M20: =IFERROR(VLOOKUP(A20,'IFRS15 Licenses'!#REF!,14,FALSE),0) -> 0 | O20: =SUM(J20:N20) -> 78042.149 | R20: =IFERROR(VLOOKUP(A20,#REF!,14,FALSE),0) -> 0 | T20: =O20+R20 -> 78042.149
A21: Dugdale Nutrition | B21: =IFERROR(VLOOKUP(A21,'Annual Maintenance'!$A$1:$G$41,7,FALSE),0) -> 64354.47 | C21: =IFERROR(VLOOKUP(A21,#REF!,14,FALSE),0) -> 0 | D21: =IFERROR(VLOOKUP(A21,#REF!,14,FALSE),0) -> 0 | E21: =IFERROR(VLOOKUP(A21,'IFRS15 Licenses'!$U$12:$AH$28,14,FALSE),0) -> 450 | G21: =SUM(B21:F21) -> 64804.47 | H21: =G21/$G$46 -> 0.012275152 | J21: =IFERROR(VLOOKUP(A21,'Annual Maintenance'!$A$1:$N$41,14,FALSE),0) -> 85005.466 | K21: =IFERROR(VLOOKUP(A21,#REF!,14,FALSE),0) -> 0 | L21: =IFERROR(VLOOKUP(A21,#REF!,14,FALSE),0) -> 0 | M21: =IFERROR(VLOOKUP(A21,'IFRS15 Licenses'!#REF!,14,FALSE),0) -> 0 | O21: =SUM(J21:N21) -> 85005.466 | R21: =IFERROR(VLOOKUP(A21,#REF!,14,FALSE),0) -> 0 | T21: =O21+R21 -> 85005.466
A22: COFCO International | B22: =IFERROR(VLOOKUP(A22,'Annual Maintenance'!$A$1:$G$41,7,FALSE),0) -> 62529.616 | C22: =IFERROR(VLOOKUP(A22,#REF!,14,FALSE),0) -> 0 | D22: =IFERROR(VLOOKUP(A22,#REF!,14,FALSE),0) -> 0 | E22: =IFERROR(VLOOKUP(A22,'IFRS15 Licenses'!$U$12:$AH$28,14,FALSE),0) -> 0 | G22: =SUM(B22:F22) -> 62529.616 | H22: =G22/$G$46 -> 0.011844253 | J22: =IFERROR(VLOOKUP(A22,'Annual Maintenance'!$A$1:$N$41,14,FALSE),0) -> 82579.986 | K22: =IFERROR(VLOOKUP(A22,#REF!,14,FALSE),0) -> 0 | L22: =IFERROR(VLOOKUP(A22,#REF!,14,FALSE),0) -> 0 | M22: =IFERROR(VLOOKUP(A22,'IFRS15 Licenses'!#REF!,14,FALSE),0) -> 0 | O22: =SUM(J22:N22) -> 82579.986 | R22: =IFERROR(VLOOKUP(A22,#REF!,14,FALSE),0) -> 0 | T22: =O22+R22 -> 82579.986
A23: Robin Appel | B23: =IFERROR(VLOOKUP(A23,'Annual Maintenance'!$A$1:$G$41,7,FALSE),0) -> 49718.13 | C23: =IFERROR(VLOOKUP(A23,#REF!,14,FALSE),0) -> 0 | D23: =IFERROR(VLOOKUP(A23,#REF!,14,FALSE),0) -> 0 | E23: =IFERROR(VLOOKUP(A23,'IFRS15 Licenses'!$U$12:$AH$28,14,FALSE),0) -> 0 | G23: =SUM(B23:F23) -> 49718.13 | H23: =G23/$G$46 -> 0.0094175235 | J23: =IFERROR(VLOOKUP(A23,'Annual Maintenance'!$A$1:$N$41,14,FALSE),0) -> 65674.384 | K23: =IFERROR(VLOOKUP(A23,#REF!,14,FALSE),0) -> 0 | L23: =IFERROR(VLOOKUP(A23,#REF!,14,FALSE),0) -> 0 | M23: =IFERROR(VLOOKUP(A23,'IFRS15 Licenses'!#REF!,14,FALSE),0) -> 0 | O23: =SUM(J23:N23) -> 65674.384 | R23: =IFERROR(VLOOKUP(A23,#REF!,14,FALSE),0) -> 0 | T23: =O23+R23 -> 65674.384
A24: ADM Direct | B24: =IFERROR(VLOOKUP(A24,'Annual Maintenance'!$A$1:$G$41,7,FALSE),0) -> 24683.533 | C24: =IFERROR(VLOOKUP(A24,#REF!,14,FALSE),0) -> 0 | D24: =IFERROR(VLOOKUP(A24,#REF!,14,FALSE),0) -> 0 | E24: =IFERROR(VLOOKUP(A24,'IFRS15 Licenses'!$U$12:$AH$28,14,FALSE),0) -> 0 | G24: =SUM(B24:F24) -> 24683.533 | H24: =G24/$G$46 -> 0.0046755127 | J24: =IFERROR(VLOOKUP(A24,'Annual Maintenance'!$A$1:$N$41,14,FALSE),0) -> 32178.468 | K24: =IFERROR(VLOOKUP(A24,#REF!,14,FALSE),0) -> 0 | L24: =IFERROR(VLOOKUP(A24,#REF!,14,FALSE),0) -> 0 | M24: =IFERROR(VLOOKUP(A24,'IFRS15 Licenses'!#REF!,14,FALSE),0) -> 0 | O24: =SUM(J24:N24) -> 32178.468 | R24: =IFERROR(VLOOKUP(A24,#REF!,14,FALSE),0) -> 0 | T24: =O24+R24 -> 32178.468
A25: Banff & Moray Grain (Marketing) Ltd | B25: =IFERROR(VLOOKUP(A25,'Annual Maintenance'!$A$1:$G$41,7,FALSE),0) -> 13137.103 | C25: =IFERROR(VLOOKUP(A25,#REF!,14,FALSE),0) -> 0 | D25: =IFERROR(VLOOKUP(A25,#REF!,14,FALSE),0) -> 0 | E25: =IFERROR(VLOOKUP(A25,'IFRS15 Licenses'!$U$12:$AH$28,14,FALSE),0) -> 6510 | G25: =SUM(B25:F25) -> 19647.103 | H25: =G25/$G$46 -> 0.0037215208 | J25: =IFERROR(VLOOKUP(A25,'Annual Maintenance'!$A$1:$N$41,14,FALSE),0) -> 17352.92 | K25: =IFERROR(VLOOKUP(A25,#REF!,14,FALSE),0) -> 0 | L25: =IFERROR(VLOOKUP(A25,#REF!,14,FALSE),0) -> 0 | M25: =IFERROR(VLOOKUP(A25,'IFRS15 Licenses'!#REF!,14,FALSE),0) -> 0 | O25: =SUM(J25:N25) -> 17352.92 | R25: =IFERROR(VLOOKUP(A25,#REF!,14,FALSE),0) -> 0 | T25: =O25+R25 -> 17352.92
... A43: E B Bradshaws | B43: =IFERROR(VLOOKUP(A43,'Annual Maintenance'!$A$1:$G$41,7,FALSE),0) -> 0 | C43: =IFERROR(VLOOKUP(A43,#REF!,14,FALSE),0) -> 0 | D43: =IFERROR(VLOOKUP(A43,#REF!,14,FALSE),0) -> 0 | E43: =IFERROR(VLOOKUP(A43,'IFRS15 Licenses'!$U$12:$AH$28,14,FALSE),0) -> 0 | G43: =SUM(B43:F43) -> 0 | H43: =G43/$G$46 -> 0 | J43: =IFERROR(VLOOKUP(A43,'Annual Maintenance'!$A$1:$N$41,14,FALSE),0) -> 0 | K43: =IFERROR(VLOOKUP(A43,#REF!,14,FALSE),0) -> 0 | L43: =IFERROR(VLOOKUP(A43,#REF!,14,FALSE),0) -> 0 | M43: =IFERROR(VLOOKUP(A43,'IFRS15 Licenses'!#REF!,14,FALSE),0) -> 0 | O43: =SUM(J43:N43) -> 0 | R43: =IFERROR(VLOOKUP(A43,#REF!,14,FALSE),0) -> 0 | T43: =O43+R43 -> 0
A44: Humphrey Farms | B44: =IFERROR(VLOOKUP(A44,'Annual Maintenance'!$A$1:$G$41,7,FALSE),0) -> 0 | C44: =IFERROR(VLOOKUP(A44,#REF!,14,FALSE),0) -> 0 | D44: =IFERROR(VLOOKUP(A44,#REF!,14,FALSE),0) -> 0 | E44: =IFERROR(VLOOKUP(A44,'IFRS15 Licenses'!$U$12:$AH$28,14,FALSE),0) -> 0 | G44: =SUM(B44:F44) -> 0 | H44: =G44/$G$46 -> 0 | J44: =IFERROR(VLOOKUP(A44,'Annual Maintenance'!$A$1:$N$41,14,FALSE),0) -> 0 | K44: =IFERROR(VLOOKUP(A44,#REF!,14,FALSE),0) -> 0 | L44: =IFERROR(VLOOKUP(A44,#REF!,14,FALSE),0) -> 0 | M44: =IFERROR(VLOOKUP(A44,'IFRS15 Licenses'!#REF!,14,FALSE),0) -> 0 | O44: =SUM(J44:N44) -> 0
B46: =SUM(B4:B45) -> 5207788.5 | C46: =SUM(C4:C45) -> 0 | D46: =SUM(D4:D45) -> 0 | E46: =SUM(E4:E45) -> 71532.5 | F46: =SUM(F4:F45) -> 0 | G46: =SUM(G4:G45) -> 5279321 | J46: =SUM(J4:J45) -> 6536804.9 | K46: =SUM(K4:K45) -> 0 | L46: =SUM(L4:L45) -> 0 | M46: =SUM(M4:M45) -> 0 | N46: =SUM(N4:N45) -> 0 | O46: =SUM(O4:O45) -> 6536804.9 | P46: =SUM(P4:P45) -> 0 | Q46: =SUM(Q4:Q45) -> 0 | ... T46: =SUM(T4:T45) -> 6536804.9

Sheet Summary
A1: GBP | J1: USD
A3: Customer | C3: Maintenance | D3: PS | E3: Def Licenses | F3: Perpetual Licenses | H3: Total Revenue 2025 Q3 (£) | J3: Maintenance | K3: PS | L3: Def Licenses | M3: Perpetual Licenses | O3: Total Revenue 2024 ($) | P3: COGS | R3: COGS License
A4: AB Agri | B4: UK | C4: =IFERROR(VLOOKUP(A4,'Annual Maintenance'!$A$1:$G$41,7,FALSE),0) -> 86882.937 | D4: =-IFERROR(VLOOKUP(A4,'PS Pivot'!$B$5:$O$39,14,FALSE),0) -> 0 | E4: =IFERROR(VLOOKUP(A4,Licenses!$A$4:$N$25,14,FALSE),0) -> 0 | F4: =IFERROR(VLOOKUP(A4,'IFRS15 Licenses'!$U$10:$AH$26,14,FALSE),0) -> 0 | G4: =IFERROR(VLOOKUP(B4,'IFRS15 Licenses'!$U$12:$AH$25,14,FALSE),0) -> 0 | H4: =SUM(C4:G4) -> 86882.937 | J4: =IFERROR(VLOOKUP(A4,'Annual Maintenance'!$A$1:$N$41,14,FALSE),0) -> 114783.73 | K4: =IFERROR(VLOOKUP(A4,'PS Pivot'!$B$35:$O$56,14,FALSE),0) -> 0 | L4: =IFERROR(VLOOKUP(A4,Licenses!$A$35:$N$53,14,FALSE),0) -> 0 | M4: =IFERROR(VLOOKUP(A4,'IFRS15 Licenses'!$U$37:$AH$51,14,FALSE),0) -> 0 | O4: =SUM(J4:N4) -> 114783.73 | P4: =IFERROR(VLOOKUP(A4,COGS!$A$204:$N$238,14,FALSE),0) -> 0 | R4: =IFERROR(VLOOKUP(A4,'COGS License'!$A$23:$N$34,14,FALSE),0) -> 0
A5: Adams & Howling | B5: UK | C5: =IFERROR(VLOOKUP(A5,'Annual Maintenance'!$A$1:$G$41,7,FALSE),0) -> 34651.316 | D5: =-IFERROR(VLOOKUP(A5,'PS Pivot'!$B$5:$O$39,14,FALSE),0) -> 2960 | E5: =IFERROR(VLOOKUP(A5,Licenses!$A$4:$N$25,14,FALSE),0) -> 0 | F5: =IFERROR(VLOOKUP(A5,'IFRS15 Licenses'!$U$10:$AH$26,14,FALSE),0) -> 0 | H5: =SUM(C5:G5) -> 37611.316 | J5: =IFERROR(VLOOKUP(A5,'Annual Maintenance'!$A$1:$N$41,14,FALSE),0) -> 45771.226 | K5: =IFERROR(VLOOKUP(A5,'PS Pivot'!$B$35:$O$56,14,FALSE),0) -> -3981.2772 | L5: =IFERROR(VLOOKUP(A5,Licenses!$A$35:$N$53,14,FALSE),0) -> 0 | M5: =IFERROR(VLOOKUP(A5,'IFRS15 Licenses'!$U$37:$AH$51,14,FALSE),0) -> 0 | O5: =SUM(J5:N5) -> 41789.949 | P5: =IFERROR(VLOOKUP(A5,COGS!$A$204:$N$238,14,FALSE),0) -> -2391.4921 | R5: =IFERROR(VLOOKUP(A5,'COGS License'!$A$23:$N$34,14,FALSE),0) -> 0
A6: ADM Direct | B6: UK | C6: =IFERROR(VLOOKUP(A6,'Annual Maintenance'!$A$1:$G$41,7,FALSE),0) -> 24683.533 | D6: =-IFERROR(VLOOKUP(A6,'PS Pivot'!$B$5:$O$39,14,FALSE),0) -> 0 | E6: =IFERROR(VLOOKUP(A6,Licenses!$A$4:$N$25,14,FALSE),0) -> 0 | F6: =IFERROR(VLOOKUP(A6,'IFRS15 Licenses'!$U$10:$AH$26,14,FALSE),0) -> 0 | H6: =SUM(C6:G6) -> 24683.533 | J6: =IFERROR(VLOOKUP(A6,'Annual Maintenance'!$A$1:$N$41,14,FALSE),0) -> 32178.468 | K6: =IFERROR(VLOOKUP(A6,'PS Pivot'!$B$35:$O$56,14,FALSE),0) -> 0 | L6: =IFERROR(VLOOKUP(A6,Licenses!$A$35:$N$53,14,FALSE),0) -> 0 | M6: =IFERROR(VLOOKUP(A6,'IFRS15 Licenses'!$U$37:$AH$51,14,FALSE),0) -> 0 | O6: =SUM(J6:N6) -> 32178.468 | P6: =IFERROR(VLOOKUP(A6,COGS!$A$204:$N$238,14,FALSE),0) -> 0 | R6: =IFERROR(VLOOKUP(A6,'COGS License'!$A$23:$N$34,14,FALSE),0) -> 0
A7: Banff & Moray Grain (Marketing) Ltd | B7: UK | C7: =IFERROR(VLOOKUP(A7,'Annual Maintenance'!$A$1:$G$41,7,FALSE),0) -> 13137.103 | D7: =-IFERROR(VLOOKUP(A7,'PS Pivot'!$B$5:$O$39,14,FALSE),0) -> 2619.6 | E7: =IFERROR(VLOOKUP(A7,Licenses!$A$4:$N$25,14,FALSE),0) -> 0 | F7: =IFERROR(VLOOKUP(A7,'IFRS15 Licenses'!$U$10:$AH$26,14,FALSE),0) -> 6510 | H7: =SUM(C7:G7) -> 22266.703 | J7: =IFERROR(VLOOKUP(A7,'Annual Maintenance'!$A$1:$N$41,14,FALSE),0) -> 17352.92 | K7: =IFERROR(VLOOKUP(A7,'PS Pivot'!$B$35:$O$56,14,FALSE),0) -> -3531.6928 | L7: =IFERROR(VLOOKUP(A7,Licenses!$A$35:$N$53,14,FALSE),0) -> 0 | M7: =IFERROR(VLOOKUP(A7,'IFRS15 Licenses'!$U$37:$AH$51,14,FALSE),0) -> 8725.0203 | O7: =SUM(J7:N7) -> 22546.247 | P7: =IFERROR(VLOOKUP(A7,COGS!$A$204:$N$238,14,FALSE),0) -> -1189.5022 | R7: =IFERROR(VLOOKUP(A7,'COGS License'!$A$23:$N$34,14,FALSE),0) -> 0
A8: Barenbrug | B8: UK | C8: =IFERROR(VLOOKUP(A8,'Annual Maintenance'!$A$1:$G$41,7,FALSE),0) -> 59091.87 | D8: =-IFERROR(VLOOKUP(A8,'PS Pivot'!$B$5:$O$39,14,FALSE),0) -> 0 | E8: =IFERROR(VLOOKUP(A8,Licenses!$A$4:$N$25,14,FALSE),0) -> 448.37 | F8: =IFERROR(VLOOKUP(A8,'IFRS15 Licenses'!$U$10:$AH$26,14,FALSE),0) -> 3153.2 | H8: =SUM(C8:G8) -> 62693.44 | J8: =IFERROR(VLOOKUP(A8,'Annual Maintenance'!$A$1:$N$41,14,FALSE),0) -> 78042.149 | K8: =IFERROR(VLOOKUP(A8,'PS Pivot'!$B$35:$O$56,14,FALSE),0) -> 0 | L8: =IFERROR(VLOOKUP(A8,Licenses!$A$35:$N$53,14,FALSE),0) -> 556.64254 | M8: =IFERROR(VLOOKUP(A8,'IFRS15 Licenses'!$U$37:$AH$51,14,FALSE),0) -> 3992.6057 | O8: =SUM(J8:N8) -> 82591.397 | P8: =IFERROR(VLOOKUP(A8,COGS!$A$204:$N$238,14,FALSE),0) -> -9657.39 | R8: =IFERROR(VLOOKUP(A8,'COGS License'!$A$23:$N$34,14,FALSE),0) -> -415.06412
A9: Canterra Seeds | B9: Canada | C9: =IFERROR(VLOOKUP(A9,'Annual Maintenance'!$A$1:$G$41,7,FALSE),0) -> 62095.212 | D9: =-IFERROR(VLOOKUP(A9,'PS Pivot'!$B$5:$O$39,14,FALSE),0) -> 19640.28 | E9: =IFERROR(VLOOKUP(A9,Licenses!$A$4:$N$25,14,FALSE),0) -> 14016.59 | F9: =IFERROR(VLOOKUP(A9,'IFRS15 Licenses'!$U$10:$AH$26,14,FALSE),0) -> 5751.166 | H9: =SUM(C9:G9) -> 101503.25 | J9: =IFERROR(VLOOKUP(A9,'Annual Maintenance'!$A$1:$N$41,14,FALSE),0) -> 82024.538 | K9: =IFERROR(VLOOKUP(A9,'PS Pivot'!$B$35:$O$56,14,FALSE),0) -> -25933.726 | L9: =IFERROR(VLOOKUP(A9,Licenses!$A$35:$N$53,14,FALSE),0) -> 18602.402 | M9: =IFERROR(VLOOKUP(A9,'IFRS15 Licenses'!$U$37:$AH$51,14,FALSE),0) -> 7664.9633 | O9: =SUM(J9:N9) -> 82358.177 | P9: =IFERROR(VLOOKUP(A9,COGS!$A$204:$N$238,14,FALSE),0) -> -3331.9444 | R9: =IFERROR(VLOOKUP(A9,'COGS License'!$A$23:$N$34,14,FALSE),0) -> 0
A10: COFCO International | B10: UK | C10: =IFERROR(VLOOKUP(A10,'Annual Maintenance'!$A$1:$G$41,7,FALSE),0) -> 62529.616 | D10: =-IFERROR(VLOOKUP(A10,'PS Pivot'!$B$5:$O$39,14,FALSE),0) -> 6849.7 | E10: =IFERROR(VLOOKUP(A10,Licenses!$A$4:$N$25,14,FALSE),0) -> 0 | F10: =IFERROR(VLOOKUP(A10,'IFRS15 Licenses'!$U$10:$AH$26,14,FALSE),0) -> 0 | H10: =SUM(C10:G10) -> 69379.316 | J10: =IFERROR(VLOOKUP(A10,'Annual Maintenance'!$A$1:$N$41,14,FALSE),0) -> 82579.986 | K10: =IFERROR(VLOOKUP(A10,'PS Pivot'!$B$35:$O$56,14,FALSE),0) -> -8768.1393 | L10: =IFERROR(VLOOKUP(A10,Licenses!$A$35:$N$53,14,FALSE),0) -> 0 | M10: =IFERROR(VLOOKUP(A10,'IFRS15 Licenses'!$U$37:$AH$51,14,FALSE),0) -> 0 | O10: =SUM(J10:N10) -> 73811.847 | P10: =IFERROR(VLOOKUP(A10,COGS!$A$204:$N$238,14,FALSE),0) -> -16786.695 | R10: =IFERROR(VLOOKUP(A10,'COGS License'!$A$23:$N$34,14,FALSE),0) -> 0
A11: Cope Seeds | B11: UK | C11: =IFERROR(VLOOKUP(A11,'Annual Maintenance'!$A$1:$G$41,7,FALSE),0) -> 0 | D11: =-IFERROR(VLOOKUP(A11,'PS Pivot'!$B$5:$O$39,14,FALSE),0) -> 2520 | E11: =IFERROR(VLOOKUP(A11,Licenses!$A$4:$N$25,14,FALSE),0) -> 0 | F11: =IFERROR(VLOOKUP(A11,'IFRS15 Licenses'!$U$10:$AH$26,14,FALSE),0) -> 0 | H11: =SUM(C11:G11) -> 2520 | K11: =IFERROR(VLOOKUP(A11,'PS Pivot'!$B$35:$O$56,14,FALSE),0) -> -3390.6515 | L11: =IFERROR(VLOOKUP(A11,Licenses!$A$35:$N$53,14,FALSE),0) -> 0 | M11: =IFERROR(VLOOKUP(A11,'IFRS15 Licenses'!$U$37:$AH$51,14,FALSE),0) -> 0 | O11: =SUM(J11:N11) -> -3390.6515 | P11: =IFERROR(VLOOKUP(A11,COGS!$A$204:$N$238,14,FALSE),0) -> 0 | R11: =IFERROR(VLOOKUP(A11,'COGS License'!$A$23:$N$34,14,FALSE),0) -> 0
A12: Confluence Genetics | B12: USA | C12: =IFERROR(VLOOKUP(A12,'Annual Maintenance'!$A$1:$G$41,7,FALSE),0) -> 0 | D12: =-IFERROR(VLOOKUP(A12,'PS Pivot'!$B$5:$O$39,14,FALSE),0) -> 26212.614 | E12: =IFERROR(VLOOKUP(A12,Licenses!$A$4:$N$25,14,FALSE),0) -> 8404.03 | F12: =IFERROR(VLOOKUP(A12,'IFRS15 Licenses'!$U$10:$AH$26,14,FALSE),0) -> 0 | H12: =SUM(C12:G12) -> 34616.644 | K12: =IFERROR(VLOOKUP(A12,'PS Pivot'!$B$35:$O$56,14,FALSE),0) -> -35116.341 | L12: =IFERROR(VLOOKUP(A12,Licenses!$A$35:$N$53,14,FALSE),0) -> 11115.119 | M12: =IFERROR(VLOOKUP(A12,'IFRS15 Licenses'!$U$37:$AH$51,14,FALSE),0) -> 0 | O12: =SUM(J12:N12) -> -24001.222 | P12: =IFERROR(VLOOKUP(A12,COGS!$A$204:$N$238,14,FALSE),0) -> -0.51428724 | R12: =IFERROR(VLOOKUP(A12,'COGS License'!$A$23:$N$34,14,FALSE),0) -> -7445.7053
A13: Denholm Fish Selling Ltd | B13: UK | C13: =IFERROR(VLOOKUP(A13,'Annual Maintenance'!$A$1:$G$41,7,FALSE),0) -> 55553.323 | D13: =-IFERROR(VLOOKUP(A13,'PS Pivot'!$B$5:$O$39,14,FALSE),0) -> -14337.5 | E13: =IFERROR(VLOOKUP(A13,Licenses!$A$4:$N$25,14,FALSE),0) -> 6109.5 | F13: =IFERROR(VLOOKUP(A13,'IFRS15 Licenses'!$U$10:$AH$26,14,FALSE),0) -> 0 | H13: =SUM(C13:G13) -> 47325.323 | J13: =IFERROR(VLOOKUP(A13,'Annual Maintenance'!$A$1:$N$41,14,FALSE),0) -> 73384.077 | K13: =IFERROR(VLOOKUP(A13,'PS Pivot'!$B$35:$O$56,14,FALSE),0) -> 19122.074 | L13: =IFERROR(VLOOKUP(A13,Licenses!$A$35:$N$53,14,FALSE),0) -> 8377.9003 | M13: =IFERROR(VLOOKUP(A13,'IFRS15 Licenses'!$U$37:$AH$51,14,FALSE),0) -> 0 | O13: =SUM(J13:N13) -> 100884.05 | P13: =IFERROR(VLOOKUP(A13,COGS!$A$204:$N$238,14,FALSE),0) -> -1189.6497 | R13: =IFERROR(VLOOKUP(A13,'COGS License'!$A$23:$N$34,14,FALSE),0) -> 0
A14: DL Seeds | B14: Canada | C14: =IFERROR(VLOOKUP(A14,'Annual Maintenance'!$A$1:$G$41,7,FALSE),0) -> 9008.3644 | D14: =-IFERROR(VLOOKUP(A14,'PS Pivot'!$B$5:$O$39,14,FALSE),0) -> 2027.07 | E14: =IFERROR(VLOOKUP(A14,Licenses!$A$4:$N$25,14,FALSE),0) -> 4604.18 | F14: =IFERROR(VLOOKUP(A14,'IFRS15 Licenses'!$U$10:$AH$26,14,FALSE),0) -> 0 | H14: =SUM(C14:G14) -> 15639.614 | J14: =IFERROR(VLOOKUP(A14,'Annual Maintenance'!$A$1:$N$41,14,FALSE),0) -> 11698.342 | K14: =IFERROR(VLOOKUP(A14,'PS Pivot'!$B$35:$O$56,14,FALSE),0) -> -2752.3801 | L14: =IFERROR(VLOOKUP(A14,Licenses!$A$35:$N$53,14,FALSE),0) -> 6192.7422 | M14: =IFERROR(VLOOKUP(A14,'IFRS15 Licenses'!$U$37:$AH$51,14,FALSE),0) -> 0 | O14: =SUM(J14:N14) -> 15138.704 | P14: =IFERROR(VLOOKUP(A14,COGS!$A$204:$N$238,14,FALSE),0) -> -1334.877 | R14: =IFERROR(VLOOKUP(A14,'COGS License'!$A$23:$N$34,14,FALSE),0) -> 0
A15: Dugdale Nutrition | B15: UK | C15: =IFERROR(VLOOKUP(A15,'Annual Maintenance'!$A$1:$G$41,7,FALSE),0) -> 64354.47 | D15: =-IFERROR(VLOOKUP(A15,'PS Pivot'!$B$5:$O$39,14,FALSE),0) -> 6628 | E15: =IFERROR(VLOOKUP(A15,Licenses!$A$4:$N$25,14,FALSE),0) -> 553.82 | F15: =IFERROR(VLOOKUP(A15,'IFRS15 Licenses'!$U$10:$AH$26,14,FALSE),0) -> 450 | H15: =SUM(C15:G15) -> 71986.29 | J15: =IFERROR(VLOOKUP(A15,'Annual Maintenance'!$A$1:$N$41,14,FALSE),0) -> 85005.466 | K15: =IFERROR(VLOOKUP(A15,'PS Pivot'!$B$35:$O$56,14,FALSE),0) -> -8859.6605 | L15: =IFERROR(VLOOKUP(A15,Licenses!$A$35:$N$53,14,FALSE),0) -> 747.56692 | M15: =IFERROR(VLOOKUP(A15,'IFRS15 Licenses'!$U$37:$AH$51,14,FALSE),0) -> 591.26504 | O15: =SUM(J15:N15) -> 77484.637 | P15: =IFERROR(VLOOKUP(A15,COGS!$A$204:$N$238,14,FALSE),0) -> -5441.817 | R15: =IFERROR(VLOOKUP(A15,'COGS License'!$A$23:$N$34,14,FALSE),0) -> -451.29112
A16: Elevator | B16: UK | C16: =IFERROR(VLOOKUP(A16,'Annual Maintenance'!$A$1:$G$41,7,FALSE),0) -> 10882.453 | D16: =-IFERROR(VLOOKUP(A16,'PS Pivot'!$B$5:$O$39,14,FALSE),0) -> 0 | E16: =IFERROR(VLOOKUP(A16,Licenses!$A$4:$N$25,14,FALSE),0) -> 0 | F16: =IFERROR(VLOOKUP(A16,'IFRS15 Licenses'!$U$10:$AH$26,14,FALSE),0) -> 0 | H16: =SUM(C16:G16) -> 10882.453 | J16: =IFERROR(VLOOKUP(A16,'Annual Maintenance'!$A$1:$N$41,14,FALSE),0) -> 14371.647 | K16: =IFERROR(VLOOKUP(A16,'PS Pivot'!$B$35:$O$56,14,FALSE),0) -> 0 | L16: =IFERROR(VLOOKUP(A16,Licenses!$A$35:$N$53,14,FALSE),0) -> 0 | M16: =IFERROR(VLOOKUP(A16,'IFRS15 Licenses'!$U$37:$AH$51,14,FALSE),0) -> 0 | O16: =SUM(J16:N16) -> 14371.647 | P16: =IFERROR(VLOOKUP(A16,COGS!$A$204:$N$238,14,FALSE),0) -> -9402.8672 | R16: =IFERROR(VLOOKUP(A16,'COGS License'!$A$23:$N$34,14,FALSE),0) -> 0
A17: E B Bradshaws | K17: =IFERROR(VLOOKUP(A17,'PS Pivot'!$B$35:$O$56,14,FALSE),0) -> 0 | L17: =IFERROR(VLOOKUP(A17,Licenses!$A$35:$N$53,14,FALSE),0) -> 0 | M17: =IFERROR(VLOOKUP(A17,'IFRS15 Licenses'!$U$37:$AH$51,14,FALSE),0) -> 0 | O17: =SUM(J17:N17) -> 0 | P17: =IFERROR(VLOOKUP(A17,COGS!$A$204:$N$238,14,FALSE),0) -> -843.94888 | R17: =IFERROR(VLOOKUP(A17,'COGS License'!$A$23:$N$34,14,FALSE),0) -> 0
A18: Fram Farmers | B18: UK | C18: =IFERROR(VLOOKUP(A18,'Annual Maintenance'!$A$1:$G$41,7,FALSE),0) -> 29460.291 | D18: =-IFERROR(VLOOKUP(A18,'PS Pivot'!$B$5:$O$39,14,FALSE),0) -> 296 | E18: =IFERROR(VLOOKUP(A18,Licenses!$A$4:$N$25,14,FALSE),0) -> 3796.28 | F18: =IFERROR(VLOOKUP(A18,'IFRS15 Licenses'!$U$10:$AH$26,14,FALSE),0) -> 8139 | H18: =SUM(C18:G18) -> 41691.571 | J18: =IFERROR(VLOOKUP(A18,'Annual Maintenance'!$A$1:$N$41,14,FALSE),0) -> 38924.124 | K18: =IFERROR(VLOOKUP(A18,'PS Pivot'!$B$35:$O$56,14,FALSE),0) -> -397.84946 | L18: =IFERROR(VLOOKUP(A18,Licenses!$A$35:$N$53,14,FALSE),0) -> 5020.9367 | M18: =IFERROR(VLOOKUP(A18,'IFRS15 Licenses'!$U$37:$AH$51,14,FALSE),0) -> 10104.408 | O18: =SUM(J18:N18) -> 53651.619 | P18: =IFERROR(VLOOKUP(A18,COGS!$A$204:$N$238,14,FALSE),0) -> -1392.8744 | R18: =IFERROR(VLOOKUP(A18,'COGS License'!$A$23:$N$34,14,FALSE),0) -> 0
A19: Frontier Agriculture | B19: UK | C19: =IFERROR(VLOOKUP(A19,'Annual Maintenance'!$A$1:$G$41,7,FALSE),0)+520000 -> 2177709.5 | D19: =-IFERROR(VLOOKUP(A19,'PS Pivot'!$B$5:$O$39,14,FALSE),0) -> 0 | E19: =IFERROR(VLOOKUP(A19,Licenses!$A$4:$N$25,14,FALSE),0) -> 0 | F19: =IFERROR(VLOOKUP(A19,'IFRS15 Licenses'!$U$10:$AH$26,14,FALSE),0) -> 0 | H19: =SUM(C19:G19) -> 2177709.5 | J19: =IFERROR(VLOOKUP(A19,'Annual Maintenance'!$A$1:$N$41,14,FALSE),0) -> 2189263.4 | K19: =IFERROR(VLOOKUP(A19,'PS Pivot'!$B$35:$O$56,14,FALSE),0) -> 0 | L19: =IFERROR(VLOOKUP(A19,Licenses!$A$35:$N$53,14,FALSE),0) -> 0 | M19: =IFERROR(VLOOKUP(A19,'IFRS15 Licenses'!$U$37:$AH$51,14,FALSE),0) -> 0 | O19: =SUM(J19:N19) -> 2189263.4 | P19: =IFERROR(VLOOKUP(A19,COGS!$A$204:$N$238,14,FALSE),0) -> -174087.37 | R19: =IFERROR(VLOOKUP(A19,'COGS License'!$A$23:$N$34,14,FALSE),0) -> 0
A20: G Williams Seeds | B20: UK | C20: =IFERROR(VLOOKUP(A20,'Annual Maintenance'!$A$1:$G$41,7,FALSE),0) -> 20776.969 | D20: =-IFERROR(VLOOKUP(A20,'PS Pivot'!$B$5:$O$39,14,FALSE),0) -> 7844 | E20: =IFERROR(VLOOKUP(A20,Licenses!$A$4:$N$25,14,FALSE),0) -> 786.47 | F20: =IFERROR(VLOOKUP(A20,'IFRS15 Licenses'!$U$10:$AH$26,14,FALSE),0) -> 0 | H20: =SUM(C20:G20) -> 29407.439 | J20: =IFERROR(VLOOKUP(A20,'Annual Maintenance'!$A$1:$N$41,14,FALSE),0) -> 27449.414 | K20: =IFERROR(VLOOKUP(A20,'PS Pivot'!$B$35:$O$56,14,FALSE),0) -> -10513.151 | L20: =IFERROR(VLOOKUP(A20,Licenses!$A$35:$N$53,14,FALSE),0) -> 1050.7562 | M20: =IFERROR(VLOOKUP(A20,'IFRS15 Licenses'!$U$37:$AH$51,14,FALSE),0) -> 0 | O20: =SUM(J20:N20) -> 17987.02 | P20: =IFERROR(VLOOKUP(A20,COGS!$A$204:$N$238,14,FALSE),0) -> -2284.7658 | R20: =IFERROR(VLOOKUP(A20,'COGS License'!$A$23:$N$34,14,FALSE),0) -> -642.41136
A21: Glasson Grain | B21: UK | C21: =IFERROR(VLOOKUP(A21,'Annual Maintenance'!$A$1:$G$41,7,FALSE),0) -> 98202.427 | D21: =-IFERROR(VLOOKUP(A21,'PS Pivot'!$B$5:$O$39,14,FALSE),0) -> 24009.603 | E21: =IFERROR(VLOOKUP(A21,Licenses!$A$4:$N$25,14,FALSE),0) -> 4258.77 | F21: =IFERROR(VLOOKUP(A21,'IFRS15 Licenses'!$U$10:$AH$26,14,FALSE),0) -> 350 | H21: =SUM(C21:G21) -> 126820.8 | J21: =IFERROR(VLOOKUP(A21,'Annual Maintenance'!$A$1:$N$41,14,FALSE),0) -> 129721.69 | K21: =IFERROR(VLOOKUP(A21,'PS Pivot'!$B$35:$O$56,14,FALSE),0) -> -32332.611 | L21: =IFERROR(VLOOKUP(A21,Licenses!$A$35:$N$53,14,FALSE),0) -> 5840.0115 | M21: =IFERROR(VLOOKUP(A21,'IFRS15 Licenses'!$U$37:$AH$51,14,FALSE),0) -> 459.87281 | O21: =SUM(J21:N21) -> 103688.96 | P21: =IFERROR(VLOOKUP(A21,COGS!$A$204:$N$238,14,FALSE),0) -> -16129.282 | R21: =IFERROR(VLOOKUP(A21,'COGS License'!$A$23:$N$34,14,FALSE),0) -> -4153.609
A22: Gover Horowitz | B22: UK | C22: =IFERROR(VLOOKUP(A22,'Annual Maintenance'!$A$1:$G$41,7,FALSE),0) -> 10386.781 | D22: =-IFERROR(VLOOKUP(A22,'PS Pivot'!$B$5:$O$39,14,FALSE),0) -> 0 | E22: =IFERROR(VLOOKUP(A22,Licenses!$A$4:$N$25,14,FALSE),0) -> 0 | F22: =IFERROR(VLOOKUP(A22,'IFRS15 Licenses'!$U$10:$AH$26,14,FALSE),0) -> 0 | H22: =SUM(C22:G22) -> 10386.781 | J22: =IFERROR(VLOOKUP(A22,'Annual Maintenance'!$A$1:$N$41,14,FALSE),0) -> 13718.317 | K22: =IFERROR(VLOOKUP(A22,'PS Pivot'!$B$35:$O$56,14,FALSE),0) -> 0 | L22: =IFERROR(VLOOKUP(A22,Licenses!$A$35:$N$53,14,FALSE),0) -> 0 | M22: =IFERROR(VLOOKUP(A22,'IFRS15 Licenses'!$U$37:$AH$51,14,FALSE),0) -> 0 | O22: =SUM(J22:N22) -> 13718.317 | P22: =IFERROR(VLOOKUP(A22,COGS!$A$204:$N$238,14,FALSE),0) -> -489.92733 | R22: =IFERROR(VLOOKUP(A22,'COGS License'!$A$23:$N$34,14,FALSE),0) -> 0
A23: Grainco | B23: UK | C23: =IFERROR(VLOOKUP(A23,'Annual Maintenance'!$A$1:$G$41,7,FALSE),0) -> 94530.098 | D23: =-IFERROR(VLOOKUP(A23,'PS Pivot'!$B$5:$O$39,14,FALSE),0) -> 9994.6 | E23: =IFERROR(VLOOKUP(A23,Licenses!$A$4:$N$25,14,FALSE),0) -> 7510.77 | F23: =IFERROR(VLOOKUP(A23,'IFRS15 Licenses'!$U$10:$AH$26,14,FALSE),0) -> 0 | H23: =SUM(C23:G23) -> 112035.47 | J23: =IFERROR(VLOOKUP(A23,'Annual Maintenance'!$A$1:$N$41,14,FALSE),0) -> 124842.02 | K23: =IFERROR(VLOOKUP(A23,'PS Pivot'!$B$35:$O$56,14,FALSE),0) -> -13098.999 | L23: =IFERROR(VLOOKUP(A23,Licenses!$A$35:$N$53,14,FALSE),0) -> 9901.1603 | M23: =IFERROR(VLOOKUP(A23,'IFRS15 Licenses'!$U$37:$AH$51,14,FALSE),0) -> 0 | O23: =SUM(J23:N23) -> 121644.18 | P23: =IFERROR(VLOOKUP(A23,COGS!$A$204:$N$238,14,FALSE),0) -> -11966.405 | R23: =IFERROR(VLOOKUP(A23,'COGS License'!$A$23:$N$34,14,FALSE),0) -> -1482.402
A24: H J Lea | B24: UK | C24: =IFERROR(VLOOKUP(A24,'Annual Maintenance'!$A$1:$G$41,7,FALSE),0) -> 82017.101 | D24: =-IFERROR(VLOOKUP(A24,'PS Pivot'!$B$5:$O$39,14,FALSE),0) -> 4365 | E24: =IFERROR(VLOOKUP(A24,Licenses!$A$4:$N$25,14,FALSE),0) -> 0 | F24: =IFERROR(VLOOKUP(A24,'IFRS15 Licenses'!$U$10:$AH$26,14,FALSE),0) -> 1000 | H24: =SUM(C24:G24) -> 87382.101 | J24: =IFERROR(VLOOKUP(A24,'Annual Maintenance'!$A$1:$N$41,14,FALSE),0) -> 108214.26 | K24: =IFERROR(VLOOKUP(A24,'PS Pivot'!$B$35:$O$56,14,FALSE),0) -> -5543.214 | L24: =IFERROR(VLOOKUP(A24,Licenses!$A$35:$N$53,14,FALSE),0) -> 0 | M24: =IFERROR(VLOOKUP(A24,'IFRS15 Licenses'!$U$37:$AH$51,14,FALSE),0) -> 1293.4603 | O24: =SUM(J24:N24) -> 103964.5 | P24: =IFERROR(VLOOKUP(A24,COGS!$A$204:$N$238,14,FALSE),0) -> -10440.949 | R24: =IFERROR(VLOOKUP(A24,'COGS License'!$A$23:$N$34,14,FALSE),0) -> 0
A25: Harlow Agriculture | B25: UK | C25: =IFERROR(VLOOKUP(A25,'Annual Maintenance'!$A$1:$G$41,7,FALSE),0) -> 92092.844 | D25: =-IFERROR(VLOOKUP(A25,'PS Pivot'!$B$5:$O$39,14,FALSE),0) -> 0 | E25: =IFERROR(VLOOKUP(A25,Licenses!$A$4:$N$25,14,FALSE),0) -> 0 | F25: =IFERROR(VLOOKUP(A25,'IFRS15 Licenses'!$U$10:$AH$26,14,FALSE),0) -> 522.2 | H25: =SUM(C25:G25) -> 92615.044 | J25: =IFERROR(VLOOKUP(A25,'Annual Maintenance'!$A$1:$N$41,14,FALSE),0) -> 121654.52 | K25: =IFERROR(VLOOKUP(A25,'PS Pivot'!$B$35:$O$56,14,FALSE),0) -> 0 | L25: =IFERROR(VLOOKUP(A25,Licenses!$A$35:$N$53,14,FALSE),0) -> 0 | M25: =IFERROR(VLOOKUP(A25,'IFRS15 Licenses'!$U$37:$AH$51,14,FALSE),0) -> 690.96924 | O25: =SUM(J25:N25) -> 122345.49 | P25: =IFERROR(VLOOKUP(A25,COGS!$A$204:$N$238,14,FALSE),0) -> -11611.247 | R25: =IFERROR(VLOOKUP(A25,'COGS License'!$A$23:$N$34,14,FALSE),0) -> 0
A26: Humphrey Feeds | B26: UK | C26: =IFERROR(VLOOKUP(A26,'Annual Maintenance'!$A$1:$G$41,7,FALSE),0) -> 36582.778 | D26: =-IFERROR(VLOOKUP(A26,'PS Pivot'!$B$5:$O$39,14,FALSE),0) -> 0 | E26: =IFERROR(VLOOKUP(A26,Licenses!$A$4:$N$25,14,FALSE),0) -> 0 | F26: =IFERROR(VLOOKUP(A26,'IFRS15 Licenses'!$U$10:$AH$26,14,FALSE),0) -> 0 | H26: =SUM(C26:G26) -> 36582.778 | J26: =IFERROR(VLOOKUP(A26,'Annual Maintenance'!$A$1:$N$41,14,FALSE),0) -> 48823.803 | K26: =IFERROR(VLOOKUP(A26,'PS Pivot'!$B$35:$O$56,14,FALSE),0) -> 0 | L26: =IFERROR(VLOOKUP(A26,Licenses!$A$35:$N$53,14,FALSE),0) -> 0 | M26: =IFERROR(VLOOKUP(A26,'IFRS15 Licenses'!$U$37:$AH$51,14,FALSE),0) -> 0 | O26: =SUM(J26:N26) -> 48823.803 | P26: =IFERROR(VLOOKUP(A26,COGS!$A$204:$N$238,14,FALSE),0) -> -9113.4149 | R26: =IFERROR(VLOOKUP(A26,'COGS License'!$A$23:$N$34,14,FALSE),0) -> 0
A27: Integra Petrochemicals | B27: Singapore | C27: =IFERROR(VLOOKUP(A27,'Annual Maintenance'!$A$1:$G$41,7,FALSE),0) -> 12790.307 | D27: =-IFERROR(VLOOKUP(A27,'PS Pivot'!$B$5:$O$39,14,FALSE),0) -> 0 | E27: =IFERROR(VLOOKUP(A27,Licenses!$A$4:$N$25,14,FALSE),0) -> 0 | F27: =IFERROR(VLOOKUP(A27,'IFRS15 Licenses'!$U$10:$AH$26,14,FALSE),0) -> 0 | H27: =SUM(C27:G27) -> 12790.307 | J27: =IFERROR(VLOOKUP(A27,'Annual Maintenance'!$A$1:$N$41,14,FALSE),0) -> 16852.115 | K27: =IFERROR(VLOOKUP(A27,'PS Pivot'!$B$35:$O$56,14,FALSE),0) -> 0 | L27: =IFERROR(VLOOKUP(A27,Licenses!$A$35:$N$53,14,FALSE),0) -> 0 | M27: =IFERROR(VLOOKUP(A27,'IFRS15 Licenses'!$U$37:$AH$51,14,FALSE),0) -> 0 | O27: =SUM(J27:N27) -> 16852.115 | P27: =IFERROR(VLOOKUP(A27,COGS!$A$204:$N$238,14,FALSE),0) -> -7250.5217 | R27: =IFERROR(VLOOKUP(A27,'COGS License'!$A$23:$N$34,14,FALSE),0) -> 0
A28: J E Porter | B28: UK | C28: =IFERROR(VLOOKUP(A28,'Annual Maintenance'!$A$1:$G$41,7,FALSE),0) -> 48.485962 | D28: =-IFERROR(VLOOKUP(A28,'PS Pivot'!$B$5:$O$39,14,FALSE),0) -> 0 | E28: =IFERROR(VLOOKUP(A28,Licenses!$A$4:$N$25,14,FALSE),0) -> 0 | F28: =IFERROR(VLOOKUP(A28,'IFRS15 Licenses'!$U$10:$AH$26,14,FALSE),0) -> 2000 | H28: =SUM(C28:G28) -> 2048.486 | J28: =IFERROR(VLOOKUP(A28,'Annual Maintenance'!$A$1:$N$41,14,FALSE),0) -> 62.698495 | K28: =IFERROR(VLOOKUP(A28,'PS Pivot'!$B$35:$O$56,14,FALSE),0) -> 0 | L28: =IFERROR(VLOOKUP(A28,Licenses!$A$35:$N$53,14,FALSE),0) -> 0 | M28: =IFERROR(VLOOKUP(A28,'IFRS15 Licenses'!$U$37:$AH$51,14,FALSE),0) -> 2586.5064 | O28: =SUM(J28:N28) -> 2649.2049 | P28: =IFERROR(VLOOKUP(A28,COGS!$A$204:$N$238,14,FALSE),0) -> -36.56371 | R28: =IFERROR(VLOOKUP(A28,'COGS License'!$A$23:$N$34,14,FALSE),0) -> 0
A29: J Stobart & Sons | B29: UK | C29: =IFERROR(VLOOKUP(A29,'Annual Maintenance'!$A$1:$G$41,7,FALSE),0) -> 18684.074 | D29: =-IFERROR(VLOOKUP(A29,'PS Pivot'!$B$5:$O$39,14,FALSE),0) -> 1950 | E29: =IFERROR(VLOOKUP(A29,Licenses!$A$4:$N$25,14,FALSE),0) -> 545.41 | F29: =IFERROR(VLOOKUP(A29,'IFRS15 Licenses'!$U$10:$AH$26,14,FALSE),0) -> 500 | H29: =SUM(C29:G29) -> 21679.484 | J29: =IFERROR(VLOOKUP(A29,'Annual Maintenance'!$A$1:$N$41,14,FALSE),0) -> 24680.946 | K29: =IFERROR(VLOOKUP(A29,'PS Pivot'!$B$35:$O$56,14,FALSE),0) -> -2454.7755 | L29: =IFERROR(VLOOKUP(A29,Licenses!$A$35:$N$53,14,FALSE),0) -> 733.07796 | M29: =IFERROR(VLOOKUP(A29,'IFRS15 Licenses'!$U$37:$AH$51,14,FALSE),0) -> 656.96116 | O29: =SUM(J29:N29) -> 23616.21 | P29: =IFERROR(VLOOKUP(A29,COGS!$A$204:$N$238,14,FALSE),0) -> -6151.4492 | R29: =IFERROR(VLOOKUP(A29,'COGS License'!$A$23:$N$34,14,FALSE),0) -> -450.20161
A30: London Metals Ltd | B30: UK | C30: =IFERROR(VLOOKUP(A30,'Annual Maintenance'!$A$1:$G$41,7,FALSE),0) -> 29008.939 | D30: =-IFERROR(VLOOKUP(A30,'PS Pivot'!$B$5:$O$39,14,FALSE),0) -> 0 | E30: =IFERROR(VLOOKUP(A30,Licenses!$A$4:$N$25,14,FALSE),0) -> 0 | F30: =IFERROR(VLOOKUP(A30,'IFRS15 Licenses'!$U$10:$AH$26,14,FALSE),0) -> 0 | H30: =SUM(C30:G30) -> 29008.939 | J30: =IFERROR(VLOOKUP(A30,'Annual Maintenance'!$A$1:$N$41,14,FALSE),0) -> 38311.778 | K30: =IFERROR(VLOOKUP(A30,'PS Pivot'!$B$35:$O$56,14,FALSE),0) -> 0 | L30: =IFERROR(VLOOKUP(A30,Licenses!$A$35:$N$53,14,FALSE),0) -> 0 | M30: =IFERROR(VLOOKUP(A30,'IFRS15 Licenses'!$U$37:$AH$51,14,FALSE),0) -> 0 | O30: =SUM(J30:N30) -> 38311.778 | P30: =IFERROR(VLOOKUP(A30,COGS!$A$204:$N$238,14,FALSE),0) -> -3246.9289 | R30: =IFERROR(VLOOKUP(A30,'COGS License'!$A$23:$N$34,14,FALSE),0) -> 0
A31: Morning Foods | B31: UK | C31: =IFERROR(VLOOKUP(A31,'Annual Maintenance'!$A$1:$G$41,7,FALSE),0) -> 0 | D31: =-IFERROR(VLOOKUP(A31,'PS Pivot'!$B$5:$O$39,14,FALSE),0) -> 0 | E31: =IFERROR(VLOOKUP(A31,Licenses!$A$4:$N$25,14,FALSE),0) -> 2489.66 | F31: =IFERROR(VLOOKUP(A31,'IFRS15 Licenses'!$U$10:$AH$26,14,FALSE),0) -> 0 | H31: =SUM(C31:G31) -> 2489.66 | J31: =IFERROR(VLOOKUP(A31,'Annual Maintenance'!$A$1:$N$41,14,FALSE),0) -> 0 | K31: =IFERROR(VLOOKUP(A31,'PS Pivot'!$B$35:$O$56,14,FALSE),0) -> 0 | L31: =IFERROR(VLOOKUP(A31,Licenses!$A$35:$N$53,14,FALSE),0) -> 3090.8639 | M31: =IFERROR(VLOOKUP(A31,'IFRS15 Licenses'!$U$37:$AH$51,14,FALSE),0) -> 0 | O31: =SUM(J31:N31) -> 3090.8639 | P31: =IFERROR(VLOOKUP(A31,COGS!$A$204:$N$238,14,FALSE),0) -> 0 | R31: =IFERROR(VLOOKUP(A31,'COGS License'!$A$23:$N$34,14,FALSE),0) -> 0
... A43: Wynnstay Group | B43: UK | C43: =IFERROR(VLOOKUP(A43,'Annual Maintenance'!$A$1:$G$41,7,FALSE),0) -> 168704.17 | D43: =-IFERROR(VLOOKUP(A43,'PS Pivot'!$B$5:$O$39,14,FALSE),0) -> 0 | E43: =IFERROR(VLOOKUP(A43,Licenses!$A$4:$N$25,14,FALSE),0) -> 0 | F43: =IFERROR(VLOOKUP(A43,'IFRS15 Licenses'!$U$10:$AH$26,14,FALSE),0) -> 307.3 | H43: =SUM(C43:G43) -> 169011.47 | J43: =IFERROR(VLOOKUP(A43,'Annual Maintenance'!$A$1:$N$41,14,FALSE),0) -> 222784.75 | K43: =IFERROR(VLOOKUP(A43,'PS Pivot'!$B$35:$O$56,14,FALSE),0) -> 0 | L43: =IFERROR(VLOOKUP(A43,Licenses!$A$35:$N$53,14,FALSE),0) -> 0 | M43: =IFERROR(VLOOKUP(A43,'IFRS15 Licenses'!$U$37:$AH$51,14,FALSE),0) -> 413.32652 | O43: =SUM(J43:N43) -> 223198.07 | P43: =IFERROR(VLOOKUP(A43,COGS!$A$204:$N$238,14,FALSE),0) -> -79029.882 | R43: =IFERROR(VLOOKUP(A43,'COGS License'!$A$23:$N$34,14,FALSE),0) -> 0
E44: =IFERROR(VLOOKUP(A44,Licenses!$A$4:$N$25,14,FALSE),0) -> 0 | F44: =IFERROR(VLOOKUP(A44,'IFRS15 Licenses'!$U$10:$AH$26,14,FALSE),0) -> 0 | H44: =SUM(C44:G44) -> 0
A45: Total | C45: =SUM(C4:C43) -> 5469416.5 | D45: =SUM(D4:D43) -> 313342.2 | E45: =SUM(E4:E43) -> 127309.38 | F45: =SUM(F4:F44) -> 71532.5 | H45: =SUM(C45:G45) -> 5981600.6 | J45: =SUM(J4:J44) -> 6536804.9 | K45: =SUM(K4:K44) -> -415245.8 | L45: =SUM(L4:L44) -> 168655.36 | M45: =SUM(M4:M44) -> 93858.738 | N45: =SUM(N4:N44) -> 0 | O45: =SUM(O4:O44) -> 6384073.2 | P45: =SUM(P4:P44) -> -584770.7 | R45: =SUM(R4:R44) -> -17599.002
A49: UK | B49: =SUMIF($B$4:$B$43,A49,$H$4:$H$43) -> 5120353.7 | C49: =B49/$B$54 -> 0.85601731
A50: USA | B50: =SUMIF($B$4:$B$43,A50,$H$4:$H$43) -> 539503.86 | C50: =B50/$B$54 -> 0.090193895
A51: Canada | B51: =SUMIF($B$4:$B$43,A51,$H$4:$H$43) -> 117142.86 | C51: =B51/$B$54 -> 0.019583866
A52: Netherlands | B52: =SUMIF($B$4:$B$43,A52,$H$4:$H$43) -> 191809.9 | C52: =B52/$B$54 -> 0.032066651
A53: Singapore | B53: =SUMIF($B$4:$B$43,A53,$H$4:$H$43) -> 12790.307 | C53: =B53/$B$54 -> 0.0021382749
B54: =SUM(B49:B53) -> 5981600.6 | C54: =SUM(C49:C53) -> 1

Sheet COGS License
A2: Row Labels | B2: Sum of Jan-25 | C2: Sum of Feb-25 | D2: Sum of Mar-25 | E2: Sum of Apr-25 | F2: Sum of May-25 | G2: Sum of Jun-25 | H2: Sum of Jul-25 | I2: Sum of Aug-25 | J2: Sum of Sep-25 | K2: Sum of Oct-25 | L2: Sum of Nov-25 | M2: Sum of Dec-25 | N2: Sum of Total Income 2025
A3: North Herts Farmers | E3: -246.29 | N3: -246.29
A4: Barenbrug | B4: -334.33 | N4: -334.33
A5: Confluence Genetics | H5: -5720 | J5: 5720 | L5: -5720 | N5: -5720
A6: Dugdale Nutrition | I6: -334.33 | N6: -334.33
A7: G Williams Seeds | F7: -477.62 | N7: -477.62
A8: Glasson Grain | H8: -3139.09 | N8: -3139.09
A9: Grainco | B9: -1194.06 | N9: -1194.06
A10: J Stobart & Sons | J10: -334.95 | N10: -334.95
A11: Openfield | K11: -574.41 | N11: -574.41
A12: Robin Appel | M12: -396.6 | N12: -396.6
A13: Saxon Agriculture | E13: -334.33 | N13: -334.33
A14: Scott & Newman | D14: -382.1 | N14: -382.1
A15: Grand Total | B15: -1528.39 | D15: -382.1 | E15: -580.62 | F15: -477.62 | H15: -8859.09 | I15: -334.33 | J15: 5385.05 | K15: -574.41 | L15: -5720 | M15: -396.6 | N15: -13468.11
B16: 1528 | C16: 0 | D16: 382 | E16: 581 | F16: 478 | G16: 0 | H16: 8859 | I16: 334 | J16: 5385 | K16: 574 | L16: 5720 | M16: 397
B17: =B16+B15 -> -0.39 | C17: =C16+C15 -> 0 | D17: =D16+D15 -> -0.1 | E17: =E16+E15 -> 0.38 | F17: =F16+F15 -> 0.38 | G17: =G16+G15 -> 0 | H17: =H16+H15 -> -0.09 | I17: =I16+I15 -> -0.33 | J17: =J16-J15 -> -0.05 | K17: =K16+K15 -> -0.41 | L17: =L16+L15 -> 0 | M17: =M16+M15 -> 0.4
A22: FX RATE | B22: 0.80549 | C22: 0.79437 | D22: 0.77312 | E22: 0.74848 | F22: 0.74348 | G22: 0.72924 | H22: 0.75575 | I22: 0.74083 | J22: 0.744 | K22: 0.76108 | L22: 0.75609 | M22: 0.74322
A23: North Herts Farmers | B23: =B3/$B$22 -> 0 | C23: =C3/$C$22 -> 0 | D23: =D3/$D$22 -> 0 | E23: =E3/$E$22 -> -329.05355 | F23: =F3/$F$22 -> 0 | G23: =G3/$G$22 -> 0 | H23: =H3/$H$22 -> 0 | I23: =I3/$I$22 -> 0 | J23: =J3/$J$22 -> 0 | K23: =K3/$K$22 -> 0 | L23: =L3/$L$22 -> 0 | M23: =M3/$M$22 -> 0 | N23: =SUM(B23:M23) -> -329.05355
A24: Barenbrug | B24: =B4/$B$22 -> -415.06412 | C24: =C4/$C$22 -> 0 | D24: =D4/$D$22 -> 0 | E24: =E4/$E$22 -> 0 | F24: =F4/$F$22 -> 0 | G24: =G4/$G$22 -> 0 | H24: =H4/$H$22 -> 0 | I24: =I4/$I$22 -> 0 | J24: =J4/$J$22 -> 0 | K24: =K4/$K$22 -> 0 | L24: =L4/$L$22 -> 0 | M24: =M4/$M$22 -> 0 | N24: =SUM(B24:M24) -> -415.06412
A25: Confluence Genetics | B25: =B5/$B$22 -> 0 | C25: =C5/$C$22 -> 0 | D25: =D5/$D$22 -> 0 | E25: =E5/$E$22 -> 0 | F25: =F5/$F$22 -> 0 | G25: =G5/$G$22 -> 0 | H25: =H5/$H$22 -> -7568.6404 | I25: =I5/$I$22 -> 0 | J25: =J5/$J$22 -> 7688.172 | K25: =K5/$K$22 -> 0 | L25: =L5/$L$22 -> -7565.2369 | M25: =M5/$M$22 -> 0 | N25: =SUM(B25:M25) -> -7445.7053
A26: Dugdale Nutrition | B26: =B6/$B$22 -> 0 | C26: =C6/$C$22 -> 0 | D26: =D6/$D$22 -> 0 | E26: =E6/$E$22 -> 0 | F26: =F6/$F$22 -> 0 | G26: =G6/$G$22 -> 0 | H26: =H6/$H$22 -> 0 | I26: =I6/$I$22 -> -451.29112 | J26: =J6/$J$22 -> 0 | K26: =K6/$K$22 -> 0 | L26: =L6/$L$22 -> 0 | M26: =M6/$M$22 -> 0 | N26: =SUM(B26:M26) -> -451.29112
A27: G Williams Seeds | B27: =B7/$B$22 -> 0 | C27: =C7/$C$22 -> 0 | D27: =D7/$D$22 -> 0 | E27: =E7/$E$22 -> 0 | F27: =F7/$F$22 -> -642.41136 | G27: =G7/$G$22 -> 0 | H27: =H7/$H$22 -> 0 | I27: =I7/$I$22 -> 0 | J27: =J7/$J$22 -> 0 | K27: =K7/$K$22 -> 0 | L27: =L7/$L$22 -> 0 | M27: =M7/$M$22 -> 0 | N27: =SUM(B27:M27) -> -642.41136
A28: Glasson Grain | B28: =B8/$B$22 -> 0 | C28: =C8/$C$22 -> 0 | D28: =D8/$D$22 -> 0 | E28: =E8/$E$22 -> 0 | F28: =F8/$F$22 -> 0 | G28: =G8/$G$22 -> 0 | H28: =H8/$H$22 -> -4153.609 | I28: =I8/$I$22 -> 0 | J28: =J8/$J$22 -> 0 | K28: =K8/$K$22 -> 0 | L28: =L8/$L$22 -> 0 | M28: =M8/$M$22 -> 0 | N28: =SUM(B28:M28) -> -4153.609
A29: Grainco | B29: =B9/$B$22 -> -1482.402 | C29: =C9/$C$22 -> 0 | D29: =D9/$D$22 -> 0 | E29: =E9/$E$22 -> 0 | F29: =F9/$F$22 -> 0 | G29: =G9/$G$22 -> 0 | H29: =H9/$H$22 -> 0 | I29: =I9/$I$22 -> 0 | J29: =J9/$J$22 -> 0 | K29: =K9/$K$22 -> 0 | L29: =L9/$L$22 -> 0 | M29: =M9/$M$22 -> 0 | N29: =SUM(B29:M29) -> -1482.402
A30: J Stobart & Sons | B30: =B10/$B$22 -> 0 | C30: =C10/$C$22 -> 0 | D30: =D10/$D$22 -> 0 | E30: =E10/$E$22 -> 0 | F30: =F10/$F$22 -> 0 | G30: =G10/$G$22 -> 0 | H30: =H10/$H$22 -> 0 | I30: =I10/$I$22 -> 0 | J30: =J10/$J$22 -> -450.20161 | K30: =K10/$K$22 -> 0 | L30: =L10/$L$22 -> 0 | M30: =M10/$M$22 -> 0 | N30: =SUM(B30:M30) -> -450.20161
A31: Openfield | B31: =B11/$B$22 -> 0 | C31: =C11/$C$22 -> 0 | D31: =D11/$D$22 -> 0 | E31: =E11/$E$22 -> 0 | F31: =F11/$F$22 -> 0 | G31: =G11/$G$22 -> 0 | H31: =H11/$H$22 -> 0 | I31: =I11/$I$22 -> 0 | J31: =J11/$J$22 -> 0 | K31: =K11/$K$22 -> -754.73012 | L31: =L11/$L$22 -> 0 | M31: =M11/$M$22 -> 0 | N31: =SUM(B31:M31) -> -754.73012
A32: Robin Appel | B32: =B12/$B$22 -> 0 | C32: =C12/$C$22 -> 0 | D32: =D12/$D$22 -> 0 | E32: =E12/$E$22 -> 0 | F32: =F12/$F$22 -> 0 | G32: =G12/$G$22 -> 0 | H32: =H12/$H$22 -> 0 | I32: =I12/$I$22 -> 0 | J32: =J12/$J$22 -> 0 | K32: =K12/$K$22 -> 0 | L32: =L12/$L$22 -> 0 | M32: =M12/$M$22 -> -533.62396 | N32: =SUM(B32:M32) -> -533.62396
A33: Saxon Agriculture | B33: =B13/$B$22 -> 0 | C33: =C13/$C$22 -> 0 | D33: =D13/$D$22 -> 0 | E33: =E13/$E$22 -> -446.6786 | F33: =F13/$F$22 -> 0 | G33: =G13/$G$22 -> 0 | H33: =H13/$H$22 -> 0 | I33: =I13/$I$22 -> 0 | J33: =J13/$J$22 -> 0 | K33: =K13/$K$22 -> 0 | L33: =L13/$L$22 -> 0 | M33: =M13/$M$22 -> 0 | N33: =SUM(B33:M33) -> -446.6786
A34: Scott & Newman | B34: =B14/$B$22 -> 0 | C34: =C14/$C$22 -> 0 | D34: =D14/$D$22 -> -494.23117 | E34: =E14/$E$22 -> 0 | F34: =F14/$F$22 -> 0 | G34: =G14/$G$22 -> 0 | H34: =H14/$H$22 -> 0 | I34: =I14/$I$22 -> 0 | J34: =J14/$J$22 -> 0 | K34: =K14/$K$22 -> 0 | L34: =L14/$L$22 -> 0 | M34: =M14/$M$22 -> 0 | N34: =SUM(B34:M34) -> -494.23117
N36: =SUM(N23:N35) -> -17599.002

Sheet COGS
A1: Location | B1: Customer Level | C1: Customer | D1: Inv Number | E1: Description | F1: Inv Value | G1: Start Date | H1: End Date | I1: No Of Days | J1: Def rev remaining @ 31.12.24 (B/F) | K1: 45658 | L1: 45689 | M1: 45717 | N1: 45748 | O1: 45778 | P1: 45809 | Q1: 45839 | R1: 45870 | S1: 45901 | T1: 45931 | U1: 45962 | V1: 45992 | W1: Total Income 2025 | X1: Invoiced YTD | Y1: Amount Deferred YTD Rev
K2: 31 | L2: 29 | M2: 31 | N2: 30 | O2: 31 | P2: 30 | Q2: 31 | R2: 31 | S2: 30 | T2: 31 | U2: 30 | V2: 31
A3: Primetics GEN NA | B3: SEED | C3: Barenbrug | D3: RCT000901 | E3: Annual Progress Maintenance | F3: -5230.5 | G3: 45561 | H3: 45925 | I3: 364 | J3: -3836.658 | K3: -445.45467 | L3: -416.71566 | M3: -445.45467 | N3: -431.08516 | O3: -445.45467 | P3: -431.08516 | Q3: -445.45467 | R3: -445.45467 | S3: -330.5 | W3: -3836.6593
A4: Primetics GEN NA | B4: SEED | C4: Barenbrug | D4: INV-175452 | E4: Annual Open Accounts Maintenance | F4: -2270.3 | G4: 45323 | H4: 45688 | I4: 365 | J4: -186.6 | K4: -186.6 | W4: -186.6
A5: Primetics GEN NA | B5: SEED | C5: Barenbrug | D5: INV-256165 | E5: Annual Open Accounts Maintenance | F5: -2004.12 | G5: 45689 | H5: 46053 | I5: 364 | J5: -2004.12 | L5: -159.6689 | M5: -170.68055 | N5: -165.17473 | O5: -170.68055 | P5: -165.17473 | Q5: -170.68055 | R5: -170.68055 | S5: -165.17473 | T5: -170.68055 | U5: -165.17473 | V5: -170.68055 | W5: -1844.4511
A6: Primetics GEN NA | B6: SEED | C6: Barenbrug | D6: RCT000935 | E6: Annual Progress Maintenance | F6: -5486.25 | G6: 45926 | H6: 46290 | I6: 364 | S6: -60.288462 | T6: -467.23558 | U6: -452.16346 | V6: -467.23558 | W6: -1446.9231 | X6: -5486.25
A7: Primetics GEN NA | B7: SEED | C7: Canterra Seeds | D7: RCT000880 | E7: Annual Progress Maintenance | F7: -2510.18 | G7: 45313 | H7: 45679 | I7: 366 | J7: -150.88514 | K7: -150.89 | W7: -150.89
A8: Primetics GEN NA | B8: SEED | C8: Canterra Seeds | D8: RCT000911 | E8: Annual Progress Maintenance | F8: -2510.18 | G8: 45679 | H8: 46043 | I8: 364 | K8: -62.06489 | L8: -199.98687 | M8: -213.77907 | N8: -206.88297 | O8: -213.77907 | P8: -206.88297 | Q8: -213.77907 | R8: -213.77907 | S8: -206.88297 | T8: -213.77907 | U8: -206.88297 | V8: -213.77907 | W8: -2372.258 | X8: -2510.18
A9: PRTH | B9: KIT | C9: COFCO International | D9: UK00095422 | E9: Annual Microsoft GP Maintenance | F9: -12461.42 | G9: 45668 | H9: 46032 | I9: 364 | J9: -12461.42 | K9: -684.69341 | L9: -992.80544 | M9: -1061.2748 | N9: -1027.0401 | O9: -1061.2748 | P9: -1027.0401 | Q9: -1061.2748 | R9: -1061.2748 | S9: -1027.0401 | T9: -1061.2748 | U9: -1027.0401 | V9: -1061.2748 | W9: -12153.308
A10: PRTH | B10: KIT | C10: COFCO International | D10: UK00081499 | E10: Annual Microsoft GP Maintenance | F10: -9882.68 | G10: 45302 | H10: 45667 | I10: 365 | J10: -270.75836 | K10: -270.76 | W10: -270.76
A11: PRTH | B11: KIT | C11: COFCO International | D11: INV276588 | E11: Smartlist builder | F11: -1276.8 | G11: 45959 | H11: 46323 | I11: 364 | U11: -112.24615 | V11: -108.73846 | W11: -220.98462 | X11: -1276.8
A12: PRTH | B12: KIT | C12: COFCO International | D12: INV276589 | E12: Smartlist builder | F12: -500 | G12: 45980 | H12: 46344 | I12: 364 | U12: -15.10989 | V12: -42.582418 | W12: -57.692308 | X12: -500
A13: PRTH | B13: KIT | C13: COFCO International | D13: UK00112807 | E13: Annual Microsoft GP Maintenance | F13: -13117.28 | G13: 46033 | H13: 46397 | I13: 364 | W13: 0 | X13: -13117.28
A14: Primetics GEN NA | B14: SEED | C14: Confluence Genetics | D14: RCT000929 | E14: Annual Progress Maintenance | F14: -1188.01 | G14: 45869 | H14: 46233 | I14: 364 | Q14: -3.2637637 | R14: -101.17668 | S14: 104.44 | W14: -0.00043956044 | X14: -1188.01
A15: PRTH | B15: KIT | C15: Denholm Fish Selling Ltd | D15: 129170 | E15: Annual NCC Deposit | F15: -1835 | G15: 45474 | H15: 45838 | I15: 365 | J15: -909.9589 | K15: -155.84932 | L15: -145.79452 | M15: -155.84932 | N15: -150.82192 | O15: -155.84932 | P15: -145.79 | W15: -909.95438
A16: Primetics GEN NA | B16: SEED | C16: DL Seeds | D16: UK00082155 | E16: Annual Microsoft GP Maintenance | F16: -812.24 | G16: 45340 | H16: 45705 | I16: 365 | J16: -106.81512 | K16: -68.984767 | L16: -37.83 | W16: -106.81477
A17: Primetics GEN NA | B17: SEED | C17: DL Seeds | D17: RCT000891 | E17: Annual Progress Maintenance | F17: -153 | G17: 45426 | H17: 45790 | I17: 364 | J17: -56.324176 | K17: -13.03022 | L17: -12.18956 | M17: -13.03022 | N17: -12.60989 | O17: -5.46 | W17: -56.31989
A18: Primetics GEN NA | B18: SEED | C18: DL Seeds | D18: RCT000924 | E18: Annual Progress Maintenance | F18: -58.58 | G18: 45791 | H18: 46155 | I18: 364 | O18: -2.7358791 | P18: -4.828022 | Q18: -4.988956 | R18: -4.988956 | S18: -4.828022 | T18: -4.988956 | U18: -4.828022 | V18: -4.988956 | W18: -37.175769 | X18: -58.58
A19: Primetics GEN NA | B19: SEED | C19: DL Seeds | D19: UK00096030 | E19: Annual Microsoft GP Maintenance | F19: -918.55 | G19: 45706 | H19: 46070 | I19: 364 | P19: -335.62404 | Q19: -78.228159 | R19: -78.228159 | S19: -75.70467 | T19: -78.228159 | U19: -75.70467 | V19: -78.228159 | W19: -799.94602 | X19: -918.55
A20: PRTH | B20: KIT | C20: Elevator | D20: UK00095427 | E20: Annual Microsoft GP Maintenance | F20: -7129.73 | G20: 45668 | H20: 46032 | I20: 364 | J20: -7129.74 | K20: -391.74341 | L20: -568.02794 | M20: -607.20228 | N20: -587.61511 | O20: -607.20228 | P20: -587.61511 | Q20: -607.20228 | R20: -607.20228 | S20: -587.61511 | T20: -607.20228 | U20: -587.61511 | V20: -607.20228 | W20: -6953.4455
A21: PRTH | B21: KIT | C21: Elevator | D21: UK00080835 | E21: Annual Microsoft GP Maintenance | F21: -5986.94 | G21: 45302 | H21: 45667 | I21: 365 | J21: -164.02575 | K21: -164.03 | W21: -164.03
A22: PRTH | B22: KIT | C22: Elevator | D22: UK00112809 | E22: Annual Microsoft GP Maintenance | F22: -7504.99 | G22: 46033 | H22: 46397 | I22: 364 | W22: 0 | X22: -7504.99
A23: PRTH | B23: KIT | C23: Gover Horowitz | D23: INV271621 | E23: Smartlist builder | F23: -1388.8 | G23: 45933 | H23: 46268 | I23: 335 | T23: -116.07881 | U23: -124.37015 | V23: -128.51582 | W23: -368.96478 | X23: -1388.8
A24: PRTH | B24: KIT | C24: Integra Petrochemicals | D24: UK00081514 | E24: Annual Microsoft GP Maintenance | F24: -4576.5 | G24: 45303 | H24: 45668 | I24: 365 | J24: -137.92192 | K24: -137.92 | W24: -137.92
A25: PRTH | B25: KIT | C25: Integra Petrochemicals | D25: UK00095435 | E25: Annual Microsoft GP Maintenance | F25: -5501.25 | G25: 45669 | H25: 46033 | I25: 364 | K25: -287.15316 | L25: -438.2864 | M25: -468.51305 | N25: -453.39973 | O25: -468.51305 | P25: -453.39973 | Q25: -468.51305 | R25: -468.51305 | S25: -453.39973 | T25: -468.51305 | U25: -453.39973 | V25: -468.51305 | W25: -5350.1168 | X25: -5501.25
A26: PRTH | B26: KIT | C26: London Metals Ltd | D26: UK00095426 | E26: Annual Microsoft Maintenance | F26: -2355.01 | G26: 45668 | H26: 46032 | I26: 364 | J26: -2355.01 | K26: -129.39615 | L26: -187.62442 | M26: -200.56404 | N26: -194.09423 | O26: -200.56404 | P26: -194.09423 | Q26: -200.56404 | R26: -200.56404 | S26: -194.09423 | T26: -200.56404 | U26: -194.09423 | V26: -200.56404 | W26: -2296.7817
A27: PRTH | B27: KIT | C27: London Metals Ltd | D27: UK00081510 | E27: Annual Microsoft Maintenance | F27: -1977.53 | G27: 45302 | H27: 45667 | I27: 365 | J27: -54.178904 | K27: -54.18 | W27: -54.18
A28: PRTH | B28: KIT | C28: London Metals Ltd | D28: 607269 | E28: Advanced Smartlist Maintenance | F28: -155.45 | G28: 45505 | H28: 45869 | I28: 364 | J28: -90.109753 | K28: -13.238874 | L28: -12.384753 | M28: -13.238874 | N28: -12.811813 | O28: -13.238874 | P28: -12.811813 | Q28: -12.38 | W28: -90.105
A29: PRTH | B29: KIT | C29: London Metals Ltd | D29: 608410 | E29: Advanced Smartlist Maintenance | F29: -118.54 | G29: 45969 | H29: 46333 | I29: 364 | U29: -7.1645055 | V29: -10.09544 | W29: -17.259945 | X29: -118.54
A30: PRTH | B30: KIT | C30: London Metals Ltd | D30: UK00112806 | E30: Annual Microsoft Maintenance | F30: -2478.96 | G30: 46033 | H30: 46397 | I30: 364 | W30: 0 | X30: -2478.96
A31: PRTH | B31: KIT | C31: Oxbow Coal | D31: UK00095429 | E31: Annual Microsoft GP Maintenance | F31: -6885.45 | G31: 45668 | H31: 46032 | I31: 364 | J31: -6885.46 | K31: -378.32143 | L31: -548.56607 | M31: -586.39821 | N31: -567.48214 | O31: -586.39821 | P31: -567.48214 | Q31: -586.39821 | R31: -586.39821 | S31: -567.48214 | T31: -586.39821 | U31: -567.48214 | V31: -586.39821 | W31: -6715.2054
A32: PRTH | B32: KIT | C32: Oxbow Coal | D32: UK00081499 | E32: Annual Microsoft GP Maintenance | F32: -6000.7 | G32: 45302 | H32: 45667 | I32: 365 | J32: -164.40274 | K32: -164.4 | W32: -164.4
A33: PRTH | B33: KIT | C33: Oxbow Coal | D33: INVMHL116414 | E33: Annual M-Hance Maintenance | F33: -376.23 | G33: 45505 | H33: 45869 | I33: 364 | J33: -218.08937 | K33: -32.041566 | L33: -29.974368 | M33: -32.041566 | N33: -31.007967 | O33: -32.041566 | P33: -31.007967 | Q33: -29.97 | W33: -218.085
A34: PRTH | B34: KIT | C34: Oxbow Coal | D34: EU_IN80594 | E34: Annual M-Hance Maintenance | F34: -362.45 | G34: 45657 | H34: 46021 | I34: 364 | J34: -361.4742 | K34: -30.867995 | L34: -28.876511 | M34: -30.867995 | N34: -29.872253 | O34: -30.867995 | P34: -29.872253 | Q34: -30.867995 | R34: -30.867995 | S34: -29.872253 | T34: -30.867995 | U34: -29.872253 | V34: -27.9 | W34: -361.47349
A35: PRTH | B35: KIT | C35: Oxbow Coal | D35: EU_IN80595 | E35: Annual M-Hance Maintenance | F35: -359.97 | G35: 45657 | H35: 46021 | I35: 364 | J35: -358.98107 | K35: -30.656786 | L35: -28.678929 | M35: -30.656786 | N35: -29.667857 | O35: -30.656786 | P35: -29.667857 | Q35: -30.656786 | R35: -30.656786 | S35: -29.667857 | T35: -30.656786 | U35: -29.667857 | V35: -27.69 | W35: -358.98107
A36: PRTH | B36: KIT | C36: Oxbow Coal | D36: 601577 | E36: Advanced Smartlist Maintenance | F36: -126.37 | G36: 45413 | H36: 45777 | I36: 364 | J36: -41.313269 | K36: -10.76228 | L36: -10.06794 | M36: -10.76228 | N36: -9.72 | W36: -41.3125
A37: PRTH | B37: KIT | C37: Oxbow Coal | D37: 607762 | E37: Advanced Smartlist Maintenance | F37: -126.61 | G37: 45759 | H37: 46123 | I37: 364 | N37: -6.2609341 | O37: -10.78272 | P37: -10.43489 | Q37: -10.78272 | R37: -10.78272 | S37: -10.43489 | T37: -10.78272 | U37: -10.43489 | V37: -10.78272 | W37: -91.479203 | X37: -126.61
A38: PRTH | B38: KIT | C38: Oxbow Coal | D38: INVMHL120169 | E38: Annual M-Hance Maintenance | F38: -395.04 | G38: 45931 | H38: 46295 | I38: 364 | T38: -33.643516 | U38: -32.558242 | V38: -33.643516 | W38: -99.845275 | X38: -395.04
A39: PRTH | B39: KIT | C39: Oxbow Coal | D39: UK00112805 | E39: Annual Microsoft GP Maintenance | F39: -7623.63 | G39: 46033 | H39: 46397 | I39: 364 | W39: 0 | X39: -7623.63
A40: Primetics GEN NA | B40: SEED | C40: Pearce Seeds | D40: RCT000891 | E40: Annual Progress Maintenance | F40: -787.5 | G40: 45431 | H40: 45795 | I40: 364 | J40: -298.55769 | K40: -67.067308 | L40: -62.740385 | M40: -67.067308 | N40: -64.903846 | O40: -36.78 | W40: -298.55885
A41: Primetics GEN NA | B41: SEED | C41: Pearce Seeds | D41: RCT000924 | E41: Annual Progress Maintenance | F41: -907.5 | G41: 45796 | H41: 46160 | I41: 364 | O41: -29.917582 | P41: -74.793956 | Q41: -77.287088 | R41: -77.287088 | S41: -74.793956 | T41: -77.287088 | U41: -74.793956 | V41: -77.287088 | W41: -563.4478 | X41: -907.5
A42: Primetics GEN NA | B42: SEED | C42: West Gaines Seeds | D42: RCT000891 | E42: Annual Progress Maintenance | F42: -8190 | G42: 45443 | H42: 45807 | I42: 364 | J42: -3352.5 | K42: -697.5 | L42: -652.5 | M42: -697.5 | N42: -675 | O42: -630 | W42: -3352.5
A43: Primetics GEN NA | B43: SEED | C43: West Gaines Seeds | D43: 10010393-1 | E43: Progress Maintenance | F43: -110.38 | G43: 45576 | H43: 45807 | I43: 231 | J43: -71.372294 | K43: -14.8129 | L43: -13.857229 | M43: -14.8129 | N43: -14.335065 | O43: -13.55 | W43: -71.368095
A44: Primetics GEN NA | B44: SEED | C44: West Gaines Seeds | D44: RCT000924 | E44: Annual Progress Maintenance | F44: -9627.75 | G44: 45808 | H44: 46172 | I44: 364 | O44: -26.449863 | P44: -793.49588 | Q44: -819.94574 | R44: -819.94574 | S44: -793.49588 | T44: -819.94574 | U44: -793.49588 | V44: -819.94574 | W44: -5686.7205 | X44: -9627.75
A45: PRTH | B45: KIT | C45: Wynnstay Group | D45: UK00084265 | E45: Annual Microsoft GP Maintenance | F45: -48607.43 | G45: 45405 | H45: 45769 | I45: 364 | J45: -14956.132 | K45: -4139.6438 | L45: -3872.57 | M45: -4139.6438 | N45: -2804.27 | W45: -14956.127
A46: Primetics CHO | B46: PRIME | C46: Adams & Howling | E46: Annual Progress Maintenance | F46: -1272 | G46: 45379 | H46: 45743 | I46: 364 | J46: -300.52747 | K46: -108.32967 | L46: -101.34066 | M46: -90.86 | W46: -300.53033
A47: Primetics CHO | B47: PRIME | C47: Adams & Howling | D47: INV-190906 | E47: Annual Open Accounts Maintenance | F47: -378.64 | G47: 45383 | H47: 45747 | I47: 364 | J47: -92.57956 | K47: -32.246813 | L47: -30.166374 | M47: -30.17 | W47: -92.583187
A48: Primetics CHO | B48: PRIME | C48: Adams & Howling | D48: INV174350 | E48: Annual Open Accounts Maintenance | F48: -390 | G48: 45748 | H48: 46112 | I48: 364 | N48: -32.142857 | O48: -33.214286 | P48: -32.142857 | Q48: -33.214286 | R48: -33.214286 | S48: -32.142857 | T48: -33.214286 | U48: -32.142857 | V48: -33.214286 | W48: -294.64286 | X48: -390
A49: Primetics CHO | B49: PRIME | C49: Adams & Howling | D49: RCT000917 | E49: Annual Progress Maintenance | F49: -1467.68 | G49: 45744 | H49: 46108 | I49: 364 | M49: -12.096264 | N49: -120.96264 | O49: -124.99473 | P49: -120.96264 | Q49: -124.99473 | R49: -124.99473 | S49: -120.96264 | T49: -124.99473 | U49: -120.96264 | V49: -124.99473 | W49: -1120.9204 | X49: -1467.68
A50: Primetics CHO | B50: PRIME | C50: Banff & Moray Grain (Marketing) Ltd | D50: PO001149 | E50: Annual Progress Maintenance | F50: -798 | G50: 45413 | H50: 45777 | I50: 364 | J50: -260.88462 | K50: -67.961538 | L50: -63.576923 | M50: -67.961538 | N50: -61.38 | W50: -260.88
A51: Primetics CHO | B51: PRIME | C51: Banff & Moray Grain (Marketing) Ltd | D51: RCT000919 | E51: Annual Progress Maintenance | F51: -922.35 | G51: 45770 | H51: 46134 | I51: 364 | N51: -17.7375 | O51: -78.551786 | P51: -76.017857 | Q51: -78.551786 | R51: -78.551786 | S51: -76.017857 | T51: -78.551786 | U51: -76.017857 | V51: -78.551786 | W51: -638.55 | X51: -922.35
A52: Primetics CHO | B52: PRIME | C52: Dugdale Nutrition | D52: RCT000880 | E52: Annual Progress Maintenance | F52: -2044.5 | G52: 45305 | H52: 45670 | I52: 365 | J52: -72.817808 | K52: -72.82 | W52: -72.82
A53: Primetics CHO | B53: PRIME | C53: Dugdale Nutrition | D53: INV-209720 | E53: Annual Open Accounts Maintenance | F53: -1211.3 | G53: 45510 | H53: 45874 | I53: 364 | J53: -699.82788 | K53: -103.16016 | L53: -96.50467 | M53: -103.16016 | N53: -99.832418 | O53: -103.16016 | P53: -99.832418 | Q53: -103.16016 | R53: 8.98 | W53: -699.83016
A54: Primetics CHO | B54: PRIME | C54: Dugdale Nutrition | D54: RCT000891 | E54: Annual Progress Maintenance | F54: -609 | G54: 45434 | H54: 45798 | I54: 364 | J54: -235.90385 | K54: -51.865385 | L54: -48.519231 | M54: -51.865385 | N54: -50.192308 | O54: -33.46 | W54: -235.90231
A55: Primetics CHO | B55: PRIME | C55: Dugdale Nutrition | E55: Annual Progress Maintenance | F55: -2248.95 | G55: 45671 | H55: 46035 | I55: 364 | K55: -105.03338 | L55: -179.17459 | M55: -191.53146 | N55: -185.35302 | O55: -191.53146 | P55: -185.35302 | Q55: -191.53146 | R55: -191.53146 | S55: -185.35302 | T55: -191.53146 | U55: -185.35302 | V55: -191.53146 | W55: -2174.8088 | X55: -2248.95
A56: Primetics CHO | B56: PRIME | C56: Dugdale Nutrition | E56: Annual Progress Maintenance | F56: -706.2 | G56: 45799 | H56: 46163 | I56: 364 | O56: -17.460989 | P56: -58.203297 | Q56: -60.143407 | R56: -60.143407 | S56: -58.203297 | T56: -60.143407 | U56: -58.203297 | V56: -60.143407 | W56: -432.64451 | X56: -706.2
A57: Primetics CHO | B57: PRIME | C57: Dugdale Nutrition | D57: INV203896 | E57: Annual Open Accounts Maintenance | F57: -1247.63 | G57: 45875 | H57: 46239 | I57: 364 | R57: -85.688874 | S57: -102.82665 | T57: -106.2542 | U57: -102.82665 | V57: -106.2542 | W57: -503.85058 | X57: -1247.63
A58: Primetics CHO | B58: PRIME | C58: E B Bradshaws | D58: INV-175809 | E58: Annual Open Accounts Maintenance | F58: -502.5 | I58: 0 | J58: -502.49658 | L58: -502.5 | W58: -502.5
A59: Primetics CHO | B59: PRIME | C59: E B Bradshaws | D59: 21681 | E59: Advanced credit note | F59: 780.72 | G59: 45344 | H59: 45709 | I59: 365 | J59: 111.22586 | K59: 66.307726 | L59: 44.92 | W59: 111.22773
A60: Primetics CHO | B60: PRIME | C60: Fram Farmers | D60: RCT000909 | E60: Annual Progress Maintenance | F60: -1052.7 | G60: 45643 | H60: 46007 | I60: 364 | J60: -1012.2115 | K60: -89.653022 | L60: -83.868956 | M60: -89.653022 | N60: -86.760989 | O60: -89.653022 | P60: -86.760989 | Q60: -89.653022 | R60: -89.653022 | S60: -86.760989 | T60: -89.653022 | U60: -86.760989 | V60: -43.38 | W60: -1012.211
A61: Primetics CHO | B61: PRIME | C61: Fram Farmers | D61: RCT000942 | E61: Annual Progress Maintenance | F61: -1108.8 | G61: 46008 | H61: 46372 | I61: 364 | V61: -42.646154 | W61: -42.646154 | X61: -1108.8
A62: Primetics CHO | B62: PRIME | C62: G Williams Seeds | D62: RCT000885 | E62: Annual Progress Maintenance | F62: -1032 | G62: 45396 | H62: 45760 | I62: 364 | J62: -292.02198 | K62: -87.89011 | L62: -82.21978 | M62: -87.89011 | N62: -34.02 | W62: -292.02
A63: Primetics CHO | B63: PRIME | C63: G Williams Seeds | D63: INV-190905 | E63: Annual Open Accounts Maintenance | F63: -573.03 | G63: 45413 | H63: 45777 | I63: 364 | J63: -187.33673 | K63: -48.802005 | L63: -45.653489 | M63: -48.802005 | N63: -44.08 | W63: -187.3375
A64: Primetics CHO | B64: PRIME | C64: G Williams Seeds | D64: INV181318 | E64: Annual Open Accounts Maintenance | F64: -40.95 | G64: 45777 | H64: 46141 | I64: 364 | N64: -0.1125 | O64: -3.4875 | P64: -3.375 | Q64: -3.4875 | R64: -3.4875 | S64: -3.375 | T64: -3.4875 | U64: -3.375 | V64: -3.4875 | W64: -27.675 | X64: -40.95
A65: Primetics CHO | B65: PRIME | C65: G Williams Seeds | E65: Annual Open Accounts Maintenance | F65: -549.24 | G65: 45778 | H65: 46142 | I65: 364 | O65: -46.775934 | P65: -45.267033 | Q65: -46.775934 | R65: -46.775934 | S65: -45.267033 | T65: -46.775934 | U65: -45.267033 | V65: -46.775934 | W65: -369.68077 | X65: -549.24
A66: Primetics CHO | B66: PRIME | C66: G Williams Seeds | D66: RCT000919 | E66: Annual Progress Maintenance | F66: -1188.01 | G66: 45761 | H66: 46125 | I66: 364 | N66: -52.22022 | O66: -101.17668 | P66: -97.912912 | Q66: -101.17668 | R66: -101.17668 | S66: -97.912912 | T66: -101.17668 | U66: -97.912912 | V66: -101.17668 | W66: -851.84234 | X66: -1188.01
A67: Primetics CHO | B67: KEY | C67: Glasson Grain | D67: RCT000893 | E67: Annual Progress Maintenance | F67: -7644 | G67: 45471 | H67: 45835 | I67: 364 | J67: -3738 | K67: -651 | L67: -609 | M67: -651 | N67: -630 | O67: -651 | P67: -546 | W67: -3738
A68: Primetics CHO | B68: KEY | C68: Glasson Grain | D68: INV-206942 | E68: Annual Open Accounts Maintenance | F68: -2326.84 | G68: 45474 | H68: 45838 | I68: 364 | J68: -1150.6451 | K68: -198.16495 | L68: -185.38011 | M68: -198.16495 | N68: -191.77253 | O68: -198.16495 | P68: -179 | W68: -1150.6475
A69: Primetics CHO | B69: KEY | C69: Glasson Grain | D69: RCT000905 | E69: Annual Progress Maintenance | F69: -831.6 | G69: 45611 | H69: 45975 | I69: 364 | J69: -726.50769 | K69: -70.823077 | L69: -66.253846 | M69: -70.823077 | N69: -68.538462 | O69: -70.823077 | P69: -68.538462 | Q69: -70.823077 | R69: -70.823077 | S69: -68.538462 | T69: -70.823077 | U69: -29.7 | W69: -726.50769
A70: Primetics CHO | B70: KEY | C70: Glasson Grain | D70: INV-206941 | E70: Annual Open Accounts Maintenance | F70: -586.79 | G70: 45474 | H70: 45838 | I70: 364 | J70: -290.17088 | K70: -49.973874 | L70: -46.749753 | M70: -49.973874 | N70: -48.361813 | O70: -49.973874 | P70: -45.14 | W70: -290.17319
A71: Primetics CHO | B71: KEY | C71: Glasson Grain | D71: RCT000904 | E71: Annual Progress Maintenance | F71: -85.81 | G71: 45589 | H71: 45835 | I71: 246 | J71: -62.097398 | K71: -10.813455 | L71: -10.115813 | M71: -10.813455 | N71: -10.464634 | O71: -10.813455 | P71: -9.08 | W71: -62.100813
A72: Primetics CHO | B72: KEY | C72: Glasson Grain | D72: INV198318 | E72: Annual Open Accounts Maintenance | F72: -604.4 | G72: 45839 | H72: 46203 | I72: 364 | Q72: -51.473626 | R72: -51.473626 | S72: -49.813187 | T72: -51.473626 | U72: -49.813187 | V72: -51.473626 | W72: -305.52088 | X72: -604.4
A73: Primetics CHO | B73: KEY | C73: Glasson Grain | D73: INV204022 | E73: Annual Open Accounts Maintenance | F73: -2396.68 | G73: 45839 | H73: 46203 | I73: 364 | Q73: -204.11286 | R73: -204.11286 | S73: -197.52857 | T73: -204.11286 | U73: -197.52857 | V73: -204.11286 | W73: -1211.5086 | X73: -2396.68
A74: Primetics CHO | B74: KEY | C74: Glasson Grain | D74: RCT000926 | E74: Annual Progress Maintenance | F74: -8934.76 | G74: 45836 | H74: 46200 | I74: 364 | Q74: -810.01945 | R74: -760.92736 | S74: -736.38132 | T74: -760.92736 | U74: -736.38132 | V74: -760.92736 | W74: -4565.5642 | X74: -8934.76
A75: Primetics CHO | B75: KEY | C75: Glasson Grain | D75: RCT000938 | E75: Annual Progress Maintenance | F75: -874.5 | G75: 45976 | H75: 46340 | I75: 364 | U75: -36.037088 | V75: -74.476648 | W75: -110.51374 | X75: -874.5
A76: Primetics CHO | B76: KEY | C76: Glasson Grain | D76: RCT000941 | E76: Annual Progress Maintenance | F76: -522.58 | G76: 45988 | H76: 46340 | I76: 352 | V76: -50.476477 | W76: -50.476477 | X76: -522.58
A77: Primetics CHO | B77: PRIME | C77: Grainco | D77: INV-250985 | E77: Annual Open Accounts Maintenance | F77: -5595.01 | G77: 45658 | H77: 46022 | I77: 364 | J77: -5595.01 | K77: -476.4981 | L77: -445.75629 | M77: -476.4981 | N77: -461.1272 | O77: -476.4981 | P77: -461.1272 | Q77: -476.4981 | R77: -476.4981 | S77: -461.1272 | T77: -476.4981 | U77: -461.1272 | V77: -445.76 | W77: -5595.0137
A78: Primetics CHO | B78: PRIME | C78: Grainco | D78: RCT000901 | E78: Annual Progress Maintenance | F78: -2706 | G78: 45545 | H78: 45909 | I78: 364 | J78: -1873.3846 | K78: -230.45604 | L78: -215.58791 | M78: -230.45604 | N78: -223.02198 | O78: -230.45604 | P78: -223.02198 | Q78: -230.45604 | R78: -230.45604 | S78: -59.47 | W78: -1873.3821
A79: Primetics CHO | B79: PRIME | C79: Grainco | E79: Annual Progress Maintenance | F79: -718.83 | G79: 45490 | H79: 45854 | I79: 364 | J79: -389.03712 | K79: -61.219038 | L79: -57.269423 | M79: -61.219038 | N79: -59.244231 | O79: -61.219038 | P79: -59.244231 | Q79: -29.62 | W79: -389.035
A80: Primetics CHO | B80: PRIME | C80: Grainco | D80: RCT000927 | E80: Annual Progress Maintenance | F80: -790.71 | G80: 45868 | H80: 46232 | I80: 364 | Q80: -2.1722802 | R80: -67.340687 | S80: -65.168407 | T80: -67.340687 | U80: -65.168407 | V80: -67.340687 | W80: -334.53115 | X80: -790.71
A81: Primetics CHO | B81: PRIME | C81: Grainco | D81: RCT000935 | E81: Annual Progress Maintenance | F81: -2828.1 | G81: 45910 | H81: 46274 | I81: 364 | S81: -155.39011 | T81: -240.85467 | U81: -233.08516 | V81: -240.85467 | W81: -870.18462 | X81: -2828.1
A82: Primetics CHO | B82: PRIME | C82: Grainco | D82: INV241979 | E82: Annual Open Accounts Maintenance | F82: -5762.89 | G82: 46023 | H82: 46387 | I82: 364 | W82: 0 | X82: -5762.89
A83: Primetics CHO | B83: PRIME | C83: H J Lea | E83: Annual Progress Maintenance | F83: -7402.5 | G83: 45496 | H83: 45860 | I83: 364 | J83: -4128.3173 | K83: -630.43269 | L83: -589.75962 | M83: -630.43269 | N83: -610.09615 | O83: -630.43269 | P83: -610.09615 | Q83: -427.07 | W83: -4128.32
A84: Primetics CHO | B84: PRIME | C84: H J Lea | D84: RCT000927 | E84: Annual Progress Maintenance | F84: -8530.5 | G84: 45861 | H84: 46225 | I84: 364 | Q84: -187.48352 | R84: -726.49863 | S84: -703.06319 | T84: -726.49863 | U84: -703.06319 | V84: -726.49863 | W84: -3773.1058 | X84: -8530.5
A85: Primetics CHO | B85: PRIME | C85: Harlow Agriculture | E85: Annual Progress Maintenance | F85: -4660.5 | G85: 45490 | H85: 45854 | I85: 364 | J85: -2522.3036 | K85: -396.91071 | L85: -371.30357 | M85: -396.91071 | N85: -384.10714 | O85: -396.91071 | P85: -384.10714 | Q85: -192.05 | W85: -2522.3
A86: Primetics CHO | B86: PRIME | C86: Harlow Agriculture | D86: INV-209719 | E86: Annual OA Maintenance | F86: -3291.34 | G86: 45505 | H86: 45869 | I86: 364 | J86: -1907.8921 | K86: -280.30643 | L86: -262.22214 | M86: -280.30643 | N86: -271.26429 | O86: -280.30643 | P86: -271.26429 | Q86: -262.22 | W86: -1907.89
A87: Primetics CHO | B87: PRIME | C87: Harlow Agriculture | D87: RCT000894 | E87: Annual OA Maintenance | F87: -370.88 | G87: 45490 | H87: 45854 | I87: 364 | J87: -200.72352 | K87: -31.585934 | L87: -29.548132 | M87: -31.585934 | N87: -30.567033 | O87: -31.585934 | P87: -30.567033 | Q87: -15.28 | W87: -200.72
A88: Primetics CHO | B88: PRIME | C88: Harlow Agriculture | E88: Annual OA Maintenance | F88: -382.01 | G88: 45855 | H88: 46219 | I88: 364 | Q88: -14.692692 | R88: -32.533819 | S88: -31.484341 | T88: -32.533819 | U88: -31.484341 | V88: -32.533819 | W88: -175.26283 | X88: -382.01
A89: Primetics CHO | B89: PRIME | C89: Harlow Agriculture | D89: INV203906 | E89: Annual OA Maintenance | F89: -3390.1 | G89: 45870 | H89: 46234 | I89: 364 | R89: -288.71731 | S89: -279.40385 | T89: -288.71731 | U89: -279.40385 | V89: -288.71731 | W89: -1424.9596 | X89: -3390.1
A90: Primetics CHO | B90: PRIME | C90: Harlow Agriculture | D90: RCT000927 | E90: Annual Progress Maintenance | F90: -5370.75 | G90: 45855 | H90: 46219 | I90: 364 | Q90: -206.56731 | R90: -457.39904 | S90: -442.64423 | T90: -457.39904 | U90: -442.64423 | V90: -457.39904 | W90: -2464.0529 | X90: -5370.75
A91: Primetics CHO | B91: PRIME | C91: Harlow Agriculture | E91: Annual OA Maintenance | F91: -382.01 | G91: 45933 | H91: 46297 | I91: 364 | T91: -29.385385 | U91: -31.484341 | V91: -32.533819 | W91: -93.403544 | X91: -382.01
A92: Primetics CHO | B92: PRIME | C92: Humphrey Feeds | D92: INV-202743 | E92: Annual Open Accounts Maintenance | F92: -2848.56 | G92: 45352 | H92: 45716 | I92: 364 | J92: -453.89143 | K92: -242.59714 | L92: -211.38 | W92: -453.97714
A93: Primetics CHO | B93: PRIME | C93: Humphrey Feeds | D93: RCT000882 | E93: Annual Progress Maintenance | F93: -4932 | G93: 45352 | H93: 45716 | I93: 364 | J93: -785.86813 | K93: -420.03297 | L93: -365.84 | W93: -785.87297
A94: Primetics CHO | B94: PRIME | C94: Humphrey Feeds | D94: INV-205210 | E94: Annual Open Accounts Maintenance | F94: -3089.38 | G94: 45352 | H94: 45716 | I94: 364 | J94: -492.26385 | K94: -263.10654 | L94: -229.16 | W94: -492.26654
A95: Primetics CHO | B95: PRIME | C95: Humphrey Feeds | D95: INV-171453 | E95: Annual Open Accounts Maintenance | F95: -802.74 | G95: 45352 | H95: 45716 | I95: 364 | J95: -127.90912 | K95: -68.36522 | L95: -59.54 | W95: -127.90522
A96: Primetics CHO | B96: PRIME | C96: Humphrey Feeds | D96: RCT000915 | E96: Annual Progress Maintenance | F96: -181.5 | G96: 45697 | H96: 46061 | I96: 364 | L96: -9.4739011 | M96: -15.457418 | N96: -14.958791 | O96: -15.457418 | P96: -14.958791 | Q96: -15.457418 | R96: -15.457418 | S96: -14.958791 | T96: -15.457418 | U96: -14.958791 | V96: -15.457418 | W96: -162.05357 | X96: -181.5
A97: Primetics CHO | B97: PRIME | C97: Humphrey Feeds | D97: RCT000916 | E97: Annual Progress Maintenance | F97: -5511 | G97: 45697 | H97: 46061 | I97: 364 | M97: -772.1456 | N97: -454.2033 | O97: -469.34341 | P97: -454.2033 | Q97: -469.34341 | R97: -469.34341 | S97: -454.2033 | T97: -469.34341 | U97: -454.2033 | V97: -469.34341 | W97: -4935.6758 | X97: -5511
A98: Primetics CHO | B98: PRIME | C98: J E Porter | D98: RCT000891 | E98: Annual Progress Maintenance | F98: -70.5 | G98: 45439 | H98: 45803 | I98: 364 | J98: -28.277473 | K98: -6.0041209 | L98: -5.6167582 | M98: -6.0041209 | N98: -5.8104396 | O98: -4.84 | W98: -28.27544
A99: Primetics CHO | B99: PRIME | C99: J Stobart & Sons | D99: RCT000898 | E99: Annual Progress Maintenance | F99: -2922.15 | G99: 45588 | H99: 45952 | I99: 364 | J99: -2368.226 | K99: -248.86442 | L99: -232.80865 | M99: -248.86442 | N99: -240.83654 | O99: -248.86442 | P99: -240.83654 | Q99: -248.86442 | R99: -248.86442 | S99: -240.83654 | T99: -168.59 | W99: -2368.2304
A100: Primetics CHO | B100: PRIME | C100: J Stobart & Sons | D100: INV-216810 | E100: Annual Progress Maintenance | F100: -1234.15 | G100: 45552 | H100: 45916 | I100: 364 | J100: -878.15231 | K100: -105.10618 | L100: -98.325137 | M100: -105.10618 | N100: -101.71566 | O100: -105.10618 | P100: -101.71566 | Q100: -105.10618 | R100: -105.10618 | S100: -50.86 | W100: -878.14736
...

Sheet IFRS15 Licenses
A1: IFRS 15 - Licenses
B3: Key | C3: Status | D3: GL account | E3: Value | F3: 45930
C4: Released to P&L | F4: GP
C5: To be released in next 12 months | D5: 2600-91-5-000 | E5: 41164.097 | F5: 41164.1 | G5: =E5-F5 -> -0.003 | H5: CR
C6: To be released in > 12 months | D6: 3100-17-5-000 | E6: 46852.614 | F6: 46852.61 | G6: =E6-F6 -> 0.004 | H6: DR
D7: Total | E7: 88016.711 | F7: 88016.71 | O7: 2025
A9: Quote Ref | B9: P&L | C9: Customer | D9: Description | E9: Invoice Ref | F9: Total License Val. | G9: Annual License Start Date | H9: Revenue Rec Renewal Date | I9: License renewal Month | J9: 2020 | K9: 2021 | L9: 2022 | M9: 2023 | N9: 2024 | O9: 2025 | P9: 2026 | Q9: 2027 | R9: 2028 | S9: Total
A10: Q-21-0002 | B10: 5000-91-5-454 | C10: Barenbrug | D10: Additional Users | E10: DQ21010047 | F10: 8266 | G10: 44197 | H10: 44562 | I10: January | K10: 1653.2 | L10: 1653.2 | M10: 1653.2 | N10: 1653.2 | O10: 1653.2 | S10: 8266 | U10: Sum of 2025 | V10: Column Labels
A11: Q-20-0240 | B11: 5000-91-5-604 | C11: Fram Farmers | D11: Gold User Licences - KIT Migration | E11: DQ21010024 | F11: 40695 | G11: 44197 | H11: 44562 | I11: January | K11: 8139 | L11: 8139 | M11: 8139 | N11: 8139 | O11: 8139 | S11: 40695 | U11: Row Labels | V11: January | W11: February | X11: March | Y11: April | Z11: May | AA11: June | AB11: July | AC11: August | AD11: September | AE11: October | AF11: November | AG11: December | AH11: Grand Total | AI11: Q3 Total
A12: Q-20-0279 | B12: 5000-91-5-604 | C12: J E Porter | D12: Weighbridge Integration | E12: DQ21010044 | F12: 5000 | G12: 44197 | H12: 44562 | I12: January | K12: 1000 | L12: 1000 | M12: 1000 | N12: 1000 | O12: 1000 | S12: 5000 | U12: Banff & Moray Grain (Marketing) Ltd | Y12: 3105 | AD12: 3405 | AH12: 6510 | AI12: =V12+W12+X12+Y12+Z12+AA12+AB12+AC12+AD12 -> 6510
A13: Q-21-0006 | B13: 5000-91-5-604 | C13: Saxon Agriculture | D13: Additional Gold User Licences | E13: DQ21010017 | F13: 11700 | G13: 44197 | H13: 44562 | I13: January | K13: 2340 | L13: 2340 | M13: 2340 | N13: 2340 | O13: 2340 | S13: 11700 | U13: Barenbrug | V13: 1653.2 | X13: 1500 | AH13: 3153.2 | AI13: =V13+W13+X13+Y13+Z13+AA13+AB13+AC13+AD13 -> 3153.2
A14: Q-20-0265 | B14: 5000-91-5-604 | C14: Saxon Agriculture | D14: Document Transmission | E14: DQ21010043 | F14: 6500 | G14: 44197 | H14: 44562 | I14: January | K14: 1300 | L14: 1300 | M14: 1300 | N14: 1300 | O14: 1300 | S14: 6500 | U14: Canterra Seeds | W14: 1391.202 | Z14: 2480.226 | AA14: 1879.738 | AH14: 5751.166 | AI14: =V14+W14+X14+Y14+Z14+AA14+AB14+AC14+AD14 -> 5751.166
A15: Q-19-0431 | B15: 5000-91-5-604 | C15: Saxon Agriculture | D15: Generation Licenses | E15: DQ21020103 | F15: 11875 | G15: 44228 | H15: 44593 | I15: February | K15: 2375 | L15: 2375 | M15: 2375 | N15: 2375 | O15: 2375 | S15: 11875 | U15: Confluence Genetics | AI15: =V15+W15+X15+Y15+Z15+AA15+AB15+AC15+AD15 -> 0
A16: Q-20-0208 | B16: 5000-91-5-454 | C16: West Gaines Seeds | D16: Genware | E16: DQ21020056 | F16: 3666.25 | G16: 44228 | H16: 44593 | I16: February | K16: 733.25 | L16: 733.25 | M16: 733.25 | N16: 733.25 | O16: 733.25 | S16: 3666.25 | U16: Dugdale Nutrition | AE16: 450 | AH16: 450 | AI16: =V16+W16+X16+Y16+Z16+AA16+AB16+AC16+AD16 -> 0
B17: 5000-91-5-454 | C17: Barenbrug | D17: Barenbrug Doc Storage | E17: DQ21030128 | F17: 7500 | G17: 44256 | H17: 44621 | I17: March | K17: 1500 | L17: 1500 | M17: 1500 | N17: 1500 | O17: 1500 | S17: 7500 | U17: Fram Farmers | V17: 8139 | AH17: 8139 | AI17: =V17+W17+X17+Y17+Z17+AA17+AB17+AC17+AD17 -> 8139
B18: 5000-91-5-604 | C18: H J Lea | D18: 2 x Gold User Licences | E18: DQ21030117 | F18: 5000 | G18: 44256 | H18: 44621 | I18: March | K18: 1000 | L18: 1000 | M18: 1000 | N18: 1000 | O18: 1000 | S18: 5000 | U18: Glasson Grain | AE18: 350 | AH18: 350 | AI18: =V18+W18+X18+Y18+Z18+AA18+AB18+AC18+AD18 -> 0
B19: 5000-91-5-604 | C19: Saxon Agriculture | D19: 6 x Gold User Licences | E19: DQ21003160 | F19: 13500 | G19: 44256 | H19: 44621 | I19: March | K19: 2700 | L19: 2700 | M19: 2700 | N19: 2700 | O19: 2700 | S19: 13500 | U19: H J Lea | X19: 1000 | AH19: 1000 | AI19: =V19+W19+X19+Y19+Z19+AA19+AB19+AC19+AD19 -> 1000
B20: 5000-91-5-604 | C20: J E Porter | D20: 2 x Gold User Licences | E20: DQ21050229 | F20: 5000 | G20: 44317 | H20: 44682 | I20: May | K20: 1000 | L20: 1000 | M20: 1000 | N20: 1000 | O20: 1000 | S20: 5000 | U20: Harlow Agriculture | AB20: 522.2 | AH20: 522.2 | AI20: =V20+W20+X20+Y20+Z20+AA20+AB20+AC20+AD20 -> 522.2
A21: Q-19-0431 | B21: 5000-91-5-604 | C21: Saxon Agriculture | D21: Generaton Licences | E21: DQ21060303 | F21: 11875 | G21: 44348 | H21: 44713 | I21: June | K21: 2375 | L21: 2375 | M21: 2375 | N21: 2375 | O21: 2375 | S21: 11875 | U21: J E Porter | V21: 1000 | Z21: 1000 | AH21: 2000 | AI21: =V21+W21+X21+Y21+Z21+AA21+AB21+AC21+AD21 -> 2000
A22: Q-21-0060 | B22: 5000-91-5-604 | C22: Simpsons Malt | D22: 10 Gold Licences | E22: DQ21080374 | F22: 37500 | G22: 44409 | H22: 44408 | I22: August | K22: 7500 | L22: 7500 | M22: 7500 | N22: 7500 | O22: 7500 | S22: 37500 | U22: J Stobart & Sons | AE22: 500 | AH22: 500 | AI22: =V22+W22+X22+Y22+Z22+AA22+AB22+AC22+AD22 -> 0
A23: Q-21-00 | B23: 5000-91-5-604 | C23: J Stobart & Sons | D23: 1 x Gold Licence | E23: DQ21100447 | F23: 2500 | G23: 44470 | H23: 44835 | I23: October | K23: 500 | L23: 500 | M23: 500 | N23: 500 | O23: 500 | S23: 2500 | U23: Saxon Agriculture | V23: 3640 | W23: 2375 | X23: 3527 | AA23: 2375 | AH23: 11917 | AI23: =V23+W23+X23+Y23+Z23+AA23+AB23+AC23+AD23 -> 11917
A24: Q-21-0074 | B24: 5000-91-5-454 | C24: West Gaines Seeds | D24: Genscout Module 40% deposit Invoice | E24: DQ21100443 | F24: 9161.56 | G24: 44470 | H24: 44835 | I24: October | K24: 1832.312 | L24: 1832.312 | M24: 1832.312 | N24: 1832.312 | O24: 1832.312 | S24: 9161.56 | U24: Simpsons Malt | AA24: 1400 | AC24: 7500 | AE24: 6300 | AG24: 7500.004 | AH24: 22700.004 | AI24: =V24+W24+X24+Y24+Z24+AA24+AB24+AC24+AD24 -> 8900
B25: 5000-91-5-604 | C25: Simpsons Malt | D25: 10 Gold Licences | E25: DQ22010012 | F25: 37500 | G25: 44531 | H25: 44896 | I25: December | K25: 7500 | L25: 7500 | M25: 7500 | N25: 7500 | O25: 7500.004 | S25: 37500.004 | U25: West Gaines Seeds | W25: 733.25 | AA25: 2445.348 | AE25: 2485.252 | AF25: 2568.78 | AH25: 8232.63 | AI25: =V25+W25+X25+Y25+Z25+AA25+AB25+AC25+AD25 -> 3178.598
A26: Q-21-0098 | B26: 5000-91-5-454 | C26: Canterra Seeds | D26: Notification Centre Module Licence | E26: DQ22020072 | F26: 3743.97 | G26: 44593 | H26: 44958 | I26: February | L26: 748.794 | M26: 748.794 | N26: 748.794 | O26: 748.794 | P26: 748.794 | S26: 3743.97 | U26: Wynnstay Group | Z26: 307.3 | AH26: 307.3 | AI26: =V26+W26+X26+Y26+Z26+AA26+AB26+AC26+AD26 -> 307.3
A27: Q-22-0029 | B27: 5000-91-5-604 | C27: Saxon Agriculture | D27: Multi Company Licence | E27: DQ22030110 | F27: 990 | G27: 44621 | H27: 44958 | I27: March | L27: 198 | M27: 198 | N27: 198 | O27: 198 | P27: 198 | S27: 990 | U27: Grand Total | V27: 14432.2 | W27: 4499.452 | X27: 6027 | Y27: 3105 | Z27: 3787.526 | AA27: 8100.086 | AB27: 522.2 | AC27: 7500 | AD27: 3405 | AE27: 10085.252 | AF27: 2568.78 | AG27: 7500.004 | AH27: 71532.5 | AI27: =SUM(AI12:AI26) -> 51378.464
A28: Q-22-0046 | B28: 5000-91-5-604 | C28: Saxon Agriculture | D28: Additional Gold User Licences | E28: DQ22030113 | F28: 3145 | G28: 44621 | H28: 44958 | I28: March | L28: 629 | M28: 629 | N28: 629 | O28: 629 | P28: 629 | S28: 3145 | V28: 14432 | W28: 4499 | X28: 6027 | Y28: 3105 | Z28: 3788 | AA28: 8100 | AB28: 522 | AC28: 7500 | AD28: 3405 | AE28: 10085 | AF28: 2569 | AG28: 7500
A29: Q-22-0048 | B29: 5000-91-5-474 | C29: Wynnstay Group | D29: Additional KIT Licence | E29: DQ22040120 | F29: 1536.5 | G29: 44682 | H29: 45047 | I29: May | L29: 307.3 | M29: 307.3 | N29: 307.3 | O29: 307.3 | P29: 307.3 | S29: 1536.5 | V29: =V28-V27 -> -0.2 | W29: =W28-W27 -> -0.452 | X29: =X28-X27 -> 0 | Y29: =Y28-Y27 -> 0 | Z29: =Z28-Z27 -> 0.474 | AA29: =AA28-AA27 -> -0.086 | AB29: =AB28-AB27 -> -0.2 | AC29: =AC28-AC27 -> 0 | ... AG29: =AG28-AG27 -> -0.004
A30: Q-20-0174 | B30: 5000-91-5-454 | C30: Canterra Seeds | D30: G View | E30: DQ22060204 | F30: 9398.69 | G30: 44713 | H30: 45078 | I30: June | L30: 1879.738 | M30: 1879.738 | N30: 1879.738 | O30: 1879.738 | P30: 1879.738 | S30: 9398.69
B31: 5000-91-5-454 | C31: West Gaines Seeds | D31: Genscout | E31: DQ22060203 | F31: 12226.74 | G31: 44713 | H31: 45078 | I31: June | L31: 2445.348 | M31: 2445.348 | N31: 2445.348 | O31: 2445.348 | P31: 2445.348 | S31: 12226.74
A32: Q-22-0089 | B32: 5000-91-5-604 | C32: Dugdale Nutrition | D32: 1x Additional Gold License | E32: DQ22100302 | F32: 2250 | G32: 44835 | H32: 45200 | I32: October | L32: 450 | M32: 450 | N32: 450 | O32: 450 | P32: 450 | S32: 2250 | AB32: =GETPIVOTDATA("2024",$U$10,"License renewal Month","July")-AB29 -> #REF!
A33: Q-22-0085 | B33: 5000-91-5-604 | C33: Simpsons Malt | D33: 12x Additional Gold Licenses | E33: DQ22100298 | F33: 31500 | G33: 44835 | H33: 45200 | I33: October | L33: 6300 | M33: 6300 | N33: 6300 | O33: 6300 | P33: 6300 | S33: 31500
A34: Q-21-0097 | B34: 5000-91-5-454 | C34: West Gaines Seeds | D34: WGS Return Requisition Module | E34: DQ22110328 | F34: 12843.95 | G34: 44866 | H34: 45200 | I34: November | L34: 2568.79 | M34: 2568.79 | N34: 2568.79 | O34: 2568.78 | P34: 2568.79 | S34: 12843.94
B35: 5000-91-5-454 | C35: Canterra Seeds | D35: GenView Tech Fee 2 | E35: DQ23020088 | F35: 3212.04 | G35: 44958 | H35: 45323 | I35: February | M35: 642.408 | N35: 642.408 | O35: 642.408 | P35: 642.405 | Q35: 642.408 | S35: 3212.037 | U35: FX RATE | V35: 0.80549 | W35: 0.79437 | X35: 0.77312 | Y35: 0.74848 | Z35: 0.74348 | AA35: 0.72924 | AB35: 0.75575 | AC35: 0.74083 | AD35: 0.744 | AE35: 0.76108 | AF35: 0.75609 | AG35: 0.74322
B36: 5000-91-5-454 | C36: Canterra Seeds | D36: Return Requisition Module | E36: DQ23060152 | F36: 4652.03 | G36: 45047 | H36: 45413 | I36: May | M36: 930.406 | N36: 930.406 | O36: 930.406 | P36: 930.406 | Q36: 930.406 | S36: 4652.03
B37: 5000-91-5-604 | C37: Banff & Moray Grain (Marketing) Ltd | D37: Compac gold + additional modules | E37: DQ24040100 | F37: 15525 | G37: 45383 | H37: 45748 | I37: April | N37: 3105 | O37: 3105 | P37: 3105 | Q37: 3105 | R37: 3105 | S37: 15525 | U37: Banff & Moray Grain (Marketing) Ltd | V37: =V12/$V$35 -> 0 | W37: =W12/$W$35 -> 0 | X37: =X12/$X$35 -> 0 | Y37: =Y12/$Y$35 -> 4148.4074 | Z37: =Z12/$Z$35 -> 0 | AA37: =AA12/$AA$35 -> 0 | AB37: =AB12/$AB$35 -> 0 | AC37: =AC12/$AC$35 -> 0 | AD37: =AD12/$AD$35 -> 4576.6129 | AE37: =AE12/$AE$35 -> 0 | AF37: =AF12/$AF$35 -> 0 | AG37: =AG12/$AG$35 -> 0 | AH37: =SUM(V37:AG37) -> 8725.0203
B38: 5000-91-5-454 | C38: Canterra Seeds | D38: GenScout Base License | E38: DQ24050118 | F38: 7749.14 | G38: 45413 | H38: 45778 | I38: May | N38: 1549.83 | O38: 1549.82 | P38: 1549.83 | Q38: 1549.83 | R38: 1549.82 | S38: 7749.13 | U38: Barenbrug | V38: =V13/$V$35 -> 2052.4153 | W38: =W13/$W$35 -> 0 | X38: =X13/$X$35 -> 1940.1904 | Y38: =Y13/$Y$35 -> 0 | Z38: =Z13/$Z$35 -> 0 | AA38: =AA13/$AA$35 -> 0 | AB38: =AB13/$AB$35 -> 0 | AC38: =AC13/$AC$35 -> 0 | AD38: =AD13/$AD$35 -> 0 | AE38: =AE13/$AE$35 -> 0 | AF38: =AF13/$AF$35 -> 0 | AG38: =AG13/$AG$35 -> 0 | AH38: =SUM(V38:AG38) -> 3992.6057
B39: 5000-91-5-604 | C39: Simpsons Malt | D39: Background Processor Licenses | E39: DQ24060128 | F39: 7000 | G39: 45444 | H39: 45809 | I39: June | N39: 1400 | O39: 1400 | P39: 1400 | Q39: 1400 | R39: 1400 | S39: 7000 | U39: Canterra Seeds | V39: =V14/$V$35 -> 0 | W39: =W14/$W$35 -> 1751.3275 | X39: =X14/$X$35 -> 0 | Y39: =Y14/$Y$35 -> 0 | Z39: =Z14/$Z$35 -> 3335.9687 | AA39: =AA14/$AA$35 -> 2577.6672 | AB39: =AB14/$AB$35 -> 0 | AC39: =AC14/$AC$35 -> 0 | AD39: =AD14/$AD$35 -> 0 | AE39: =AE14/$AE$35 -> 0 | AF39: =AF14/$AF$35 -> 0 | AG39: =AG14/$AG$35 -> 0 | AH39: =SUM(V39:AG39) -> 7664.9633
B40: 5000-91-5-604 | C40: Harlow Agriculture | D40: OA EDR Enquiry & Reporting License | E40: DQ24070159 | F40: 2611 | G40: 45474 | H40: 45839 | I40: July | N40: 522.2 | O40: 522.2 | P40: 522.2 | Q40: 522.2 | R40: 522.2 | S40: 2611 | U40: Confluence Genetics | V40: =V15/$V$35 -> 0 | W40: =W15/$W$35 -> 0 | X40: =X15/$X$35 -> 0 | Y40: =Y15/$Y$35 -> 0 | Z40: =Z15/$Z$35 -> 0 | AA40: =AA15/$AA$35 -> 0 | AB40: =AB15/$AB$35 -> 0 | AC40: =AC15/$AC$35 -> 0 | AD40: =AD15/$AD$35 -> 0 | AE40: =AE15/$AE$35 -> 0 | AF40: =AF15/$AF$35 -> 0 | AG40: =AG15/$AG$35 -> 0 | AH40: =SUM(V40:AG40) -> 0
B41: 5000-91-5-604 | C41: Banff & Moray Grain (Marketing) Ltd | D41: Compac gold + additional modules | E41: DQ24090189 | F41: 17025 | G41: 45536 | H41: 45901 | I41: September | N41: 3405 | O41: 3405 | P41: 3405 | Q41: 3405 | R41: 3405 | S41: 17025 | U41: Dugdale Nutrition | V41: =V16/$V$35 -> 0 | W41: =W16/$W$35 -> 0 | X41: =X16/$X$35 -> 0 | Y41: =Y16/$Y$35 -> 0 | Z41: =Z16/$Z$35 -> 0 | AA41: =AA16/$AA$35 -> 0 | AB41: =AB16/$AB$35 -> 0 | AC41: =AC16/$AC$35 -> 0 | AD41: =AD16/$AD$35 -> 0 | AE41: =AE16/$AE$35 -> 591.26504 | AF41: =AF16/$AF$35 -> 0 | AG41: =AG16/$AG$35 -> 0 | AH41: =SUM(V41:AG41) -> 591.26504
B42: 5000-91-5-604 | C42: Glasson Grain | D42: Background Processor Licenses | E42: DQ24100223 | F42: 1750 | G42: 45566 | H42: 45931 | I42: October | N42: 350 | O42: 350 | P42: 350 | Q42: 350 | R42: 350 | S42: 1750 | U42: Fram Farmers | V42: =V17/$V$35 -> 10104.408 | W42: =W17/$W$35 -> 0 | X42: =X17/$X$35 -> 0 | Y42: =Y17/$Y$35 -> 0 | Z42: =Z17/$Z$35 -> 0 | AA42: =AA17/$AA$35 -> 0 | AB42: =AB17/$AB$35 -> 0 | AC42: =AC17/$AC$35 -> 0 | AD42: =AD17/$AD$35 -> 0 | AE42: =AE17/$AE$35 -> 0 | AF42: =AF17/$AF$35 -> 0 | AG42: =AG17/$AG$35 -> 0 | AH42: =SUM(V42:AG42) -> 10104.408
B43: 5000-91-5-454 | C43: West Gaines Seeds | D43: Background Processor Licenses | E43: DQ24100221 | F43: 1770.7 | G43: 45566 | H43: 45931 | I43: October | N43: 354.14 | O43: 354.14 | P43: 354.14 | Q43: 354.14 | R43: 354.14 | S43: 1770.7 | U43: Glasson Grain | V43: =V18/$V$35 -> 0 | W43: =W18/$W$35 -> 0 | X43: =X18/$X$35 -> 0 | Y43: =Y18/$Y$35 -> 0 | Z43: =Z18/$Z$35 -> 0 | AA43: =AA18/$AA$35 -> 0 | AB43: =AB18/$AB$35 -> 0 | AC43: =AC18/$AC$35 -> 0 | AD43: =AD18/$AD$35 -> 0 | AE43: =AE18/$AE$35 -> 459.87281 | AF43: =AF18/$AF$35 -> 0 | AG43: =AG18/$AG$35 -> 0 | AH43: =SUM(V43:AG43) -> 459.87281
B44: 5000-91-5-454 | C44: West Gaines Seeds | D44: Additional GenWARE Licenses | E44: DQ24090198 | F44: 1494 | G44: 45566 | H44: 45931 | I44: October | N44: 298.8 | O44: 298.8 | P44: 298.8 | Q44: 298.8 | R44: 298.8 | S44: 1494 | U44: H J Lea | V44: =V19/$V$35 -> 0 | W44: =W19/$W$35 -> 0 | X44: =X19/$X$35 -> 1293.4603 | Y44: =Y19/$Y$35 -> 0 | Z44: =Z19/$Z$35 -> 0 | AA44: =AA19/$AA$35 -> 0 | AB44: =AB19/$AB$35 -> 0 | AC44: =AC19/$AC$35 -> 0 | AD44: =AD19/$AD$35 -> 0 | AE44: =AE19/$AE$35 -> 0 | AF44: =AF19/$AF$35 -> 0 | AG44: =AG19/$AG$35 -> 0 | AH44: =SUM(V44:AG44) -> 1293.4603
B45: 5000-91-5-454 | C45: Confluence Genetics | D45: Generation 2025 | E45: DQ25090153 | F45: 16235.1 | G45: 45992 | I45: December | P45: 3247.04 | Q45: 3247.04 | R45: 6494.06 | S45: 16235.18 | U45: Harlow Agriculture | V45: =V20/$V$35 -> 0 | W45: =W20/$W$35 -> 0 | X45: =X20/$X$35 -> 0 | Y45: =Y20/$Y$35 -> 0 | Z45: =Z20/$Z$35 -> 0 | AA45: =AA20/$AA$35 -> 0 | AB45: =AB20/$AB$35 -> 690.96924 | AC45: =AC20/$AC$35 -> 0 | AD45: =AD20/$AD$35 -> 0 | AE45: =AE20/$AE$35 -> 0 | AF45: =AF20/$AF$35 -> 0 | AG45: =AG20/$AG$35 -> 0 | AH45: =SUM(V45:AG45) -> 690.96924
F46: 373897.67 | J46: 0 | K46: 43447.762 | L46: 58974.732 | M46: 60547.546 | N46: 71532.516 | O46: =SUM(O10:O45) -> 71532.5 | P46: 31331.791 | Q46: 15804.824 | R46: 17479.02 | S46: 373897.73 | U46: J E Porter | V46: =V21/$V$35 -> 1241.4803 | W46: =W21/$W$35 -> 0 | X46: =X21/$X$35 -> 0 | Y46: =Y21/$Y$35 -> 0 | Z46: =Z21/$Z$35 -> 1345.0261 | AA46: =AA21/$AA$35 -> 0 | AB46: =AB21/$AB$35 -> 0 | AC46: =AC21/$AC$35 -> 0 | AD46: =AD21/$AD$35 -> 0 | AE46: =AE21/$AE$35 -> 0 | AF46: =AF21/$AF$35 -> 0 | AG46: =AG21/$AG$35 -> 0 | AH46: =SUM(V46:AG46) -> 2586.5064
U47: J Stobart & Sons | V47: =V22/$V$35 -> 0 | W47: =W22/$W$35 -> 0 | X47: =X22/$X$35 -> 0 | Y47: =Y22/$Y$35 -> 0 | Z47: =Z22/$Z$35 -> 0 | AA47: =AA22/$AA$35 -> 0 | AB47: =AB22/$AB$35 -> 0 | AC47: =AC22/$AC$35 -> 0 | AD47: =AD22/$AD$35 -> 0 | AE47: =AE22/$AE$35 -> 656.96116 | AF47: =AF22/$AF$35 -> 0 | AG47: =AG22/$AG$35 -> 0 | AH47: =SUM(V47:AG47) -> 656.96116
U48: Saxon Agriculture | V48: =V23/$V$35 -> 4518.9884 | W48: =W23/$W$35 -> 2989.7907 | X48: =X23/$X$35 -> 4562.0344 | Y48: =Y23/$Y$35 -> 0 | Z48: =Z23/$Z$35 -> 0 | AA48: =AA23/$AA$35 -> 3256.8153 | AB48: =AB23/$AB$35 -> 0 | AC48: =AC23/$AC$35 -> 0 | AD48: =AD23/$AD$35 -> 0 | AE48: =AE23/$AE$35 -> 0 | AF48: =AF23/$AF$35 -> 0 | AG48: =AG23/$AG$35 -> 0 | AH48: =SUM(V48:AG48) -> 15327.629
U49: Simpsons Malt | V49: =V24/$V$35 -> 0 | W49: =W24/$W$35 -> 0 | X49: =X24/$X$35 -> 0 | Y49: =Y24/$Y$35 -> 0 | Z49: =Z24/$Z$35 -> 0 | AA49: =AA24/$AA$35 -> 1919.8069 | AB49: =AB24/$AB$35 -> 0 | AC49: =AC24/$AC$35 -> 10123.78 | AD49: =AD24/$AD$35 -> 0 | AE49: =AE24/$AE$35 -> 8277.7106 | AF49: =AF24/$AF$35 -> 0 | AG49: =AG24/$AG$35 -> 10091.23 | AH49: =SUM(V49:AG49) -> 30412.528
U50: West Gaines Seeds | V50: =V25/$V$35 -> 0 | W50: =W25/$W$35 -> 923.05852 | X50: =X25/$X$35 -> 0 | Y50: =Y25/$Y$35 -> 0 | Z50: =Z25/$Z$35 -> 0 | AA50: =AA25/$AA$35 -> 3353.2829 | AB50: =AB25/$AB$35 -> 0 | AC50: =AC25/$AC$35 -> 0 | AD50: =AD25/$AD$35 -> 0 | AE50: =AE25/$AE$35 -> 3265.4281 | AF50: =AF25/$AF$35 -> 3397.4527 | AG50: =AG25/$AG$35 -> 0 | AH50: =SUM(V50:AG50) -> 10939.222
U51: Wynnstay Group | V51: =V26/$V$35 -> 0 | W51: =W26/$W$35 -> 0 | X51: =X26/$X$35 -> 0 | Y51: =Y26/$Y$35 -> 0 | Z51: =Z26/$Z$35 -> 413.32652 | AA51: =AA26/$AA$35 -> 0 | AB51: =AB26/$AB$35 -> 0 | AC51: =AC26/$AC$35 -> 0 | AD51: =AD26/$AD$35 -> 0 | AE51: =AE26/$AE$35 -> 0 | AF51: =AF26/$AF$35 -> 0 | AG51: =AG26/$AG$35 -> 0 | AH51: =SUM(V51:AG51) -> 413.32652
AH53: =SUM(AH37:AH52) -> 93858.738

Sheet PS data
A1: Journal Entry | B1: Series | C1: TRX Date | D1: Month | E1: Account Number | F1: Account Description | G1: Currency ID | H1: Reference | I1: Exchange Rate | J1: Debit Amount | K1: Credit Amount | L1: Balance | M1: Currency Index | N1: Originating Debit Amount | O1: Originating Credit Amount | P1: Originating Control Number | Q1: Originating Document Number | R1: Originating Master ID | S1: Originating Posted Date | T1: Originating Source | U1: Source Document | V1: TRX Source | W1: Description | X1: User Who Posted | Y1: Originating Master Name
A2: 101098 | B2: Financial | C2: 45658 | D2: =TEXT(C2,"MMMM") -> January | E2: 5010-10-5-454 | F2: Service Revenue - Initiatives | G2: Z-GBP | H2: December WIP | I2: 0 | J2: 2332 | K2: 0 | L2: =J2-K2 -> 2332 | M2: 1062 | N2: 8790.18 | O2: 0 | S2: 45693 | U2: GJ | V2: GLTRX00026624 | X2: sdoroshenko | Y2: DL Seeds
A3: 101098 | B3: Financial | C3: 45658 | D3: =TEXT(C3,"MMMM") -> January | E3: 5010-10-5-604 | F3: Service Revenue - Mid Market | G3: Z-GBP | H3: December WIP | I3: 0 | J3: 1525.33 | K3: 0 | L3: =J3-K3 -> 1525.33 | M3: 1062 | N3: 18693.69 | O3: 0 | S3: 45693 | U3: GJ | V3: GLTRX00026624 | X3: sdoroshenko | Y3: Glasson Grain
A4: 101098 | B4: Financial | C4: 45658 | D4: =TEXT(C4,"MMMM") -> January | E4: 5010-10-5-604 | F4: Service Revenue - Mid Market | G4: Z-GBP | H4: December WIP | I4: 0 | J4: 15871.95 | K4: 0 | L4: =J4-K4 -> 15871.95 | M4: 1062 | N4: 18693.69 | O4: 0 | S4: 45693 | U4: GJ | V4: GLTRX00026624 | X4: sdoroshenko | Y4: Simpsons Malt
A5: 101098 | B5: Financial | C5: 45658 | D5: =TEXT(C5,"MMMM") -> January | E5: 5010-10-5-604 | F5: Service Revenue - Mid Market | G5: Z-GBP | H5: December WIP | I5: 0 | J5: 1296.41 | K5: 0 | L5: =J5-K5 -> 1296.41 | M5: 1062 | N5: 18693.69 | O5: 0 | S5: 45693 | U5: GJ | V5: GLTRX00026624 | X5: sdoroshenko | Y5: Simpsons Malt
A6: 101098 | B6: Financial | C6: 45658 | D6: =TEXT(C6,"MMMM") -> January | E6: 5010-10-5-454 | F6: Service Revenue - Initiatives | G6: Z-GBP | H6: December WIP | I6: 0 | J6: 6458.18 | K6: 0 | L6: =J6-K6 -> 6458.18 | M6: 1062 | N6: 8790.18 | O6: 0 | S6: 45693 | U6: GJ | V6: GLTRX00026624 | X6: sdoroshenko | Y6: West Gaines Seeds
A7: 101035 | B7: Sales | C7: 45679 | D7: =TEXT(C7,"MMMM") -> January | E7: 5010-46-5-604 | F7: Service Revenue - Non Policy - Mid Market | G7: Z-GBP | H7: SML 3rd party Warehouse Integr | I7: 0 | J7: 0 | K7: 15871.95 | L7: =J7-K7 -> -15871.95 | M7: 1062 | N7: 0 | O7: 15871.95 | P7: DQ25010003 | Q7: DQ25010003 | R7: 4135 | S7: 45686 | T7: RMSLS | U7: SJ | V7: GLTRX00026572 | W7: Sales | X7: sdoroshenko | Y7: Simpsons Malt
A8: 101103 | B8: Financial | C8: 45688 | D8: =TEXT(C8,"MMMM") -> January | E8: 5010-10-5-604 | F8: Service Revenue - Mid Market | G8: Z-GBP | H8: Correct WIP Jan | I8: 0 | J8: 0 | K8: 1763.67 | L8: =J8-K8 -> -1763.67 | M8: 1062 | N8: 0 | O8: 11622.69 | S8: 45693 | U8: GJ | V8: GLTRX00026629 | X8: jkiernan | Y8: COFCO International
A9: 101103 | B9: Financial | C9: 45688 | D9: =TEXT(C9,"MMMM") -> January | E9: 5010-10-5-454 | F9: Service Revenue - Initiatives | G9: Z-GBP | H9: Correct WIP Jan | I9: 0 | J9: 0 | K9: 2332 | L9: =J9-K9 -> -2332 | M9: 1062 | N9: 0 | O9: 8790.18 | S9: 45693 | U9: GJ | V9: GLTRX00026629 | X9: jkiernan | Y9: DL Seeds
A10: 101103 | B10: Financial | C10: 45688 | D10: =TEXT(C10,"MMMM") -> January | E10: 5010-10-5-604 | F10: Service Revenue - Mid Market | G10: Z-GBP | H10: Correct WIP Jan | I10: 0 | J10: 0 | K10: 1525.33 | L10: =J10-K10 -> -1525.33 | M10: 1062 | N10: 0 | O10: 11622.69 | S10: 45693 | U10: GJ | V10: GLTRX00026629 | X10: jkiernan | Y10: Glasson Grain
A11: 101103 | B11: Financial | C11: 45688 | D11: =TEXT(C11,"MMMM") -> January | E11: 5010-10-5-604 | F11: Service Revenue - Mid Market | G11: Z-GBP | H11: Correct WIP Jan | I11: 0 | J11: 0 | K11: 3009.96 | L11: =J11-K11 -> -3009.96 | M11: 1062 | N11: 0 | O11: 11622.69 | S11: 45693 | U11: GJ | V11: GLTRX00026629 | X11: jkiernan | Y11: Openfield
A12: 101103 | B12: Financial | C12: 45688 | D12: =TEXT(C12,"MMMM") -> January | E12: 5010-10-5-604 | F12: Service Revenue - Mid Market | G12: Z-GBP | H12: Correct WIP Jan | I12: 0 | J12: 0 | K12: 3541.32 | L12: =J12-K12 -> -3541.32 | M12: 1062 | N12: 0 | O12: 11622.69 | S12: 45693 | U12: GJ | V12: GLTRX00026629 | X12: jkiernan | Y12: Openfield
A13: 101083 | B13: Sales | C13: 45688 | D13: =TEXT(C13,"MMMM") -> January | E13: 5010-46-5-604 | F13: Service Revenue - Non Policy - Mid Market | G13: Z-GBP | H13: Automate the Bagged Seed Repor | I13: 0 | J13: 0 | K13: 1430 | L13: =J13-K13 -> -1430 | M13: 1062 | N13: 0 | O13: 1430 | P13: DQ25010008 | Q13: DQ25010008 | R13: 892 | S13: 45691 | T13: RMSLS | U13: SJ | V13: GLTRX00026609 | W13: Sales | X13: sdoroshenko | Y13: Saxon Agriculture
A14: 101103 | B14: Financial | C14: 45688 | D14: =TEXT(C14,"MMMM") -> January | E14: 5010-10-5-604 | F14: Service Revenue - Mid Market | G14: Z-GBP | H14: Correct WIP Jan | I14: 0 | J14: 0 | K14: 1782.41 | L14: =J14-K14 -> -1782.41 | M14: 1062 | N14: 0 | O14: 11622.69 | S14: 45693 | U14: GJ | V14: GLTRX00026629 | X14: jkiernan | Y14: Simpsons Malt
A15: 101098 | B15: Financial | C15: 45688 | D15: =TEXT(C15,"MMMM") -> January | E15: 5010-10-5-454 | F15: Service Revenue - Initiatives | G15: Z-GBP | H15: Correct WIP Jan | I15: 0 | J15: 0 | K15: 6458.18 | L15: =J15-K15 -> -6458.18 | M15: 1062 | N15: 8790.18 | O15: 0 | S15: 45693 | U15: GJ | V15: GLTRX00026624 | X15: sdoroshenko | Y15: West Gaines Seeds
A16: 101103 | B16: Financial | C16: 45689 | D16: =TEXT(C16,"MMMM") -> February | E16: 5010-10-5-604 | F16: Service Revenue - Mid Market | G16: Z-GBP | H16: Correct WIP Jan | I16: 0 | J16: 1763.67 | K16: 0 | L16: =J16-K16 -> 1763.67 | M16: 1062 | N16: 0 | O16: 11622.69 | S16: 45693 | U16: GJ | V16: GLTRX00026629 | X16: jkiernan | Y16: COFCO International
A17: 101103 | B17: Financial | C17: 45689 | D17: =TEXT(C17,"MMMM") -> February | E17: 5010-10-5-454 | F17: Service Revenue - Initiatives | G17: Z-GBP | H17: Correct WIP Jan | I17: 0 | J17: 2332 | K17: 0 | L17: =J17-K17 -> 2332 | M17: 1062 | N17: 0 | O17: 8790.18 | S17: 45693 | U17: GJ | V17: GLTRX00026629 | X17: jkiernan | Y17: DL Seeds
A18: 101103 | B18: Financial | C18: 45689 | D18: =TEXT(C18,"MMMM") -> February | E18: 5010-10-5-604 | F18: Service Revenue - Mid Market | G18: Z-GBP | H18: Correct WIP Jan | I18: 0 | J18: 1525.33 | K18: 0 | L18: =J18-K18 -> 1525.33 | M18: 1062 | N18: 0 | O18: 11622.69 | S18: 45693 | U18: GJ | V18: GLTRX00026629 | X18: jkiernan | Y18: Glasson Grain
A19: 101103 | B19: Financial | C19: 45689 | D19: =TEXT(C19,"MMMM") -> February | E19: 5010-10-5-604 | F19: Service Revenue - Mid Market | G19: Z-GBP | H19: Correct WIP Jan | I19: 0 | J19: 3009.96 | K19: 0 | L19: =J19-K19 -> 3009.96 | M19: 1062 | N19: 0 | O19: 11622.69 | S19: 45693 | U19: GJ | V19: GLTRX00026629 | X19: jkiernan | Y19: Openfield
A20: 101103 | B20: Financial | C20: 45689 | D20: =TEXT(C20,"MMMM") -> February | E20: 5010-10-5-604 | F20: Service Revenue - Mid Market | G20: Z-GBP | H20: Correct WIP Jan | I20: 0 | J20: 3541.32 | K20: 0 | L20: =J20-K20 -> 3541.32 | M20: 1062 | N20: 0 | O20: 11622.69 | S20: 45693 | U20: GJ | V20: GLTRX00026629 | X20: jkiernan | Y20: Openfield
A21: 101103 | B21: Financial | C21: 45689 | D21: =TEXT(C21,"MMMM") -> February | E21: 5010-10-5-604 | F21: Service Revenue - Mid Market | G21: Z-GBP | H21: Correct WIP Jan | I21: 0 | J21: 1782.41 | K21: 0 | L21: =J21-K21 -> 1782.41 | M21: 1062 | N21: 0 | O21: 11622.69 | S21: 45693 | U21: GJ | V21: GLTRX00026629 | X21: jkiernan | Y21: Simpsons Malt
A22: 101103 | B22: Financial | C22: 45689 | D22: =TEXT(C22,"MMMM") -> February | E22: 5010-10-5-604 | F22: Service Revenue - Mid Market | G22: Z-GBP | H22: Correct WIP Jan | I22: 0 | J22: 6458.18 | K22: 0 | L22: =J22-K22 -> 6458.18 | M22: 1062 | N22: 0 | O22: 11622.69 | S22: 45693 | U22: GJ | V22: GLTRX00026629 | X22: jkiernan | Y22: West Gaines Seeds
A23: 101257 | B23: Sales | C23: 45698 | D23: =TEXT(C23,"MMMM") -> February | E23: 5010-46-5-604 | F23: Service Revenue - Non Policy - Mid Market | G23: Z-GBP | H23: Add Parent Account Column | I23: 0 | J23: 0 | K23: 3159 | L23: =J23-K23 -> -3159 | M23: 1062 | N23: 0 | O23: 3159 | P23: DQ25020014 | Q23: DQ25020014 | R23: 4067 | S23: 45706 | T23: RMSLS | U23: SJ | V23: GLTRX00026667 | W23: Sales | X23: sdoroshenko | Y23: Openfield
A24: 101256 | B24: Sales | C24: 45698 | D24: =TEXT(C24,"MMMM") -> February | E24: 5010-46-5-604 | F24: Service Revenue - Non Policy - Mid Market | G24: Z-GBP | H24: WheatDNA Trace Changes | I24: 0 | J24: 0 | K24: 1822.5 | L24: =J24-K24 -> -1822.5 | M24: 1062 | N24: 0 | O24: 1822.5 | P24: DQ25020013 | Q24: DQ25020013 | R24: 4135 | S24: 45706 | T24: RMSLS | U24: SJ | V24: GLTRX00026667 | W24: Sales | X24: sdoroshenko | Y24: Simpsons Malt
A25: 101280 | B25: Sales | C25: 45707 | D25: =TEXT(C25,"MMMM") -> February | E25: 5010-46-5-454 | F25: Service Revenue - Non Policy - Gen NA | G25: Z-GBP | H25: Incorporate ProductID in Barco | I25: 0 | J25: 0 | K25: 2509.34 | L25: =J25-K25 -> -2509.34 | M25: 1062 | N25: 0 | O25: 2509.34 | P25: DQ25020024 | Q25: DQ25020024 | R25: 9990 | S25: 45709 | T25: RMSLS | U25: SJ | V25: GLTRX00026683 | W25: Sales | X25: sdoroshenko | Y25: Canterra Seeds
A26: 101279 | B26: Sales | C26: 45707 | D26: =TEXT(C26,"MMMM") -> February | E26: 5010-46-5-454 | F26: Service Revenue - Non Policy - Gen NA | G26: Z-GBP | H26: PETL Data Enhancement for Stoc | I26: 0 | J26: 0 | K26: 1672.9 | L26: =J26-K26 -> -1672.9 | M26: 1062 | N26: 0 | O26: 1672.9 | P26: DQ25020023 | Q26: DQ25020023 | R26: 9990 | S26: 45709 | T26: RMSLS | U26: SJ | V26: GLTRX00026683 | W26: Sales | X26: sdoroshenko | Y26: Canterra Seeds
A27: 101281 | B27: Sales | C27: 45708 | D27: =TEXT(C27,"MMMM") -> February | E27: 5010-46-5-604 | F27: Service Revenue - Non Policy - Mid Market | G27: Z-GBP | H27: Technical Incident Points | I27: 0 | J27: 0 | K27: 1950 | L27: =J27-K27 -> -1950 | M27: 1062 | N27: 0 | O27: 1950 | P27: DQ25020025 | Q27: DQ25020025 | R27: 4058 | S27: 45709 | T27: RMSLS | U27: SJ | V27: GLTRX00026684 | W27: Sales | X27: sdoroshenko | Y27: J Stobart & Sons
A28: 101339 | B28: Financial | C28: 45716 | D28: =TEXT(C28,"MMMM") -> February | E28: 5010-10-5-604 | F28: Service Revenue - Mid Market | G28: Z-GBP | H28: WIP February | I28: 0 | J28: 0 | K28: 1763.67 | L28: =J28-K28 -> -1763.67 | M28: 1062 | N28: 0 | O28: 18792.61 | S28: 45720 | U28: GJ | V28: GLTRX00026727 | X28: sdoroshenko | Y28: COFCO International
A29: 101339 | B29: Financial | C29: 45716 | D29: =TEXT(C29,"MMMM") -> February | E29: 5010-10-5-454 | F29: Service Revenue - Initiatives | G29: Z-GBP | H29: WIP February | I29: 0 | J29: 0 | K29: 2332 | L29: =J29-K29 -> -2332 | M29: 1062 | N29: 0 | O29: 9073.02 | S29: 45720 | U29: GJ | V29: GLTRX00026727 | X29: sdoroshenko | Y29: DL Seeds
A30: 101339 | B30: Financial | C30: 45716 | D30: =TEXT(C30,"MMMM") -> February | E30: 5010-10-5-604 | F30: Service Revenue - Mid Market | G30: Z-GBP | H30: WIP February | I30: 0 | J30: 0 | K30: 715 | L30: =J30-K30 -> -715 | M30: 1062 | N30: 0 | O30: 18792.61 | S30: 45720 | U30: GJ | V30: GLTRX00026727 | X30: sdoroshenko | Y30: Grainco
A31: 101311 | B31: Sales | C31: 45716 | D31: =TEXT(C31,"MMMM") -> February | E31: 5010-46-5-604 | F31: Service Revenue - Non Policy - Mid Market | G31: Z-GBP | H31: Changes to Multiple Crystal Re | I31: 0 | J31: 0 | K31: 1480 | L31: =J31-K31 -> -1480 | M31: 1062 | N31: 0 | O31: 1480 | P31: DQ25020028 | Q31: DQ25020028 | R31: 4136 | S31: 45719 | T31: RMSLS | U31: SJ | V31: GLTRX00026705 | W31: DQ25020028 | X31: sdoroshenko | Y31: H J Lea
A32: 101312 | B32: Sales | C32: 45716 | D32: =TEXT(C32,"MMMM") -> February | E32: 5010-46-5-604 | F32: Service Revenue - Non Policy - Mid Market | G32: Z-GBP | H32: Training / Consultancy 2024 | I32: 0 | J32: 0 | K32: 2145 | L32: =J32-K32 -> -2145 | M32: 1062 | N32: 0 | O32: 2145 | P32: DQ25020029 | Q32: DQ25020029 | R32: 4136 | S32: 45719 | T32: RMSLS | U32: SJ | V32: GLTRX00026705 | W32: DQ25020029 | X32: sdoroshenko | Y32: H J Lea
A33: 101339 | B33: Financial | C33: 45716 | D33: =TEXT(C33,"MMMM") -> February | E33: 5010-10-5-604 | F33: Service Revenue - Mid Market | G33: Z-GBP | H33: WIP February | I33: 0 | J33: 0 | K33: 14983.38 | L33: =J33-K33 -> -14983.38 | M33: 1062 | N33: 0 | O33: 18792.61 | S33: 45720 | U33: GJ | V33: GLTRX00026727 | X33: sdoroshenko | Y33: Openfield
A34: 101316 | B34: Sales | C34: 45716 | D34: =TEXT(C34,"MMMM") -> February | E34: 5010-46-5-604 | F34: Service Revenue - Non Policy - Mid Market | G34: Z-GBP | H34: SAX - Saxon WebCRM Enhancement | I34: 0 | J34: 0 | K34: 7770 | L34: =J34-K34 -> -7770 | M34: 1062 | N34: 0 | O34: 7770 | P34: DQ25030033 | Q34: DQ25030033 | R34: 892 | S34: 45719 | T34: RMSLS | U34: SJ | V34: GLTRX00026705 | W34: DQ25030033 | X34: sdoroshenko | Y34: Saxon Agriculture
A35: 101315 | B35: Sales | C35: 45716 | D35: =TEXT(C35,"MMMM") -> February | E35: 5010-46-5-604 | F35: Service Revenue - Non Policy - Mid Market | G35: Z-GBP | H35: Saxon - Multiple Stock Lots / | I35: 0 | J35: 0 | K35: 2220 | L35: =J35-K35 -> -2220 | M35: 1062 | N35: 0 | O35: 2220 | P35: DQ25030032 | Q35: DQ25030032 | R35: 892 | S35: 45719 | T35: RMSLS | U35: SJ | V35: GLTRX00026705 | W35: DQ25030032 | X35: sdoroshenko | Y35: Saxon Agriculture
A36: 101339 | B36: Financial | C36: 45716 | D36: =TEXT(C36,"MMMM") -> February | E36: 5010-10-5-604 | F36: Service Revenue - Mid Market | G36: Z-GBP | H36: WIP February | I36: 0 | J36: 0 | K36: 1330.56 | L36: =J36-K36 -> -1330.56 | M36: 1062 | N36: 0 | O36: 18792.61 | S36: 45720 | U36: GJ | V36: GLTRX00026727 | X36: sdoroshenko | Y36: Simpsons Malt
A37: 101339 | B37: Financial | C37: 45716 | D37: =TEXT(C37,"MMMM") -> February | E37: 5010-10-5-454 | F37: Service Revenue - Initiatives | G37: Z-GBP | H37: WIP February | I37: 0 | J37: 0 | K37: 6741.02 | L37: =J37-K37 -> -6741.02 | M37: 1062 | N37: 0 | O37: 9073.02 | S37: 45720 | U37: GJ | V37: GLTRX00026727 | X37: sdoroshenko | Y37: West Gaines Seeds
A38: 101339 | B38: Financial | C38: 45717 | D38: =TEXT(C38,"MMMM") -> March | E38: 5010-10-5-604 | F38: Service Revenue - Mid Market | G38: Z-GBP | H38: WIP February | I38: 0 | J38: 1763.67 | K38: 0 | L38: =J38-K38 -> 1763.67 | M38: 1062 | N38: 0 | O38: 18792.61 | S38: 45720 | U38: GJ | V38: GLTRX00026727 | X38: sdoroshenko | Y38: COFCO International
A39: 101339 | B39: Financial | C39: 45717 | D39: =TEXT(C39,"MMMM") -> March | E39: 5010-10-5-454 | F39: Service Revenue - Initiatives | G39: Z-GBP | H39: WIP February | I39: 0 | J39: 2332 | K39: 0 | L39: =J39-K39 -> 2332 | M39: 1062 | N39: 0 | O39: 9073.02 | S39: 45720 | U39: GJ | V39: GLTRX00026727 | X39: sdoroshenko | Y39: DL Seeds
A40: 101339 | B40: Financial | C40: 45717 | D40: =TEXT(C40,"MMMM") -> March | E40: 5010-10-5-604 | F40: Service Revenue - Mid Market | G40: Z-GBP | H40: WIP February | I40: 0 | J40: 715 | K40: 0 | L40: =J40-K40 -> 715 | M40: 1062 | N40: 0 | O40: 18792.61 | S40: 45720 | U40: GJ | V40: GLTRX00026727 | X40: sdoroshenko | Y40: Grainco
A41: 101339 | B41: Financial | C41: 45717 | D41: =TEXT(C41,"MMMM") -> March | E41: 5010-10-5-604 | F41: Service Revenue - Mid Market | G41: Z-GBP | H41: WIP February | I41: 0 | J41: 14983.38 | K41: 0 | L41: =J41-K41 -> 14983.38 | M41: 1062 | N41: 0 | O41: 18792.61 | S41: 45720 | U41: GJ | V41: GLTRX00026727 | X41: sdoroshenko | Y41: Openfield
A42: 101339 | B42: Financial | C42: 45717 | D42: =TEXT(C42,"MMMM") -> March | E42: 5010-10-5-604 | F42: Service Revenue - Mid Market | G42: Z-GBP | H42: WIP February | I42: 0 | J42: 1330.56 | K42: 0 | L42: =J42-K42 -> 1330.56 | M42: 1062 | N42: 0 | O42: 18792.61 | S42: 45720 | U42: GJ | V42: GLTRX00026727 | X42: sdoroshenko | Y42: Simpsons Malt
A43: 101339 | B43: Financial | C43: 45717 | D43: =TEXT(C43,"MMMM") -> March | E43: 5010-10-5-454 | F43: Service Revenue - Initiatives | G43: Z-GBP | H43: WIP February | I43: 0 | J43: 6741.02 | K43: 0 | L43: =J43-K43 -> 6741.02 | M43: 1062 | N43: 0 | O43: 9073.02 | S43: 45720 | U43: GJ | V43: GLTRX00026727 | X43: sdoroshenko | Y43: West Gaines Seeds
A44: 101546 | B44: Sales | C44: 45726 | D44: =TEXT(C44,"MMMM") -> March | E44: 5010-46-5-604 | F44: Service Revenue - Non Policy - Mid Market | G44: Z-GBP | H44: Gold Version Of Monthly Sales | I44: 0 | J44: 0 | K44: 18565.2 | L44: =J44-K44 -> -18565.2 | M44: 1062 | N44: 0 | O44: 18565.2 | P44: DQ25030035 | Q44: DQ25030035 | R44: 4067 | S44: 45735 | T44: RMSLS | U44: SJ | V44: GLTRX00026778 | W44: DQ25030035 | X44: sdoroshenko | Y44: Openfield
A45: 101545 | B45: Sales | C45: 45730 | D45: =TEXT(C45,"MMMM") -> March | E45: 5010-46-5-604 | F45: Service Revenue - Non Policy - Mid Market | G45: Z-GBP | H45: GrainCo - Escone Consultancy ( | I45: 0 | J45: 0 | K45: 715 | L45: =J45-K45 -> -715 | M45: 1062 | N45: 0 | O45: 715 | P45: DQ25020027 | Q45: DQ25020027 | R45: 4117 | S45: 45735 | T45: RMSLS | U45: SJ | V45: GLTRX00026778 | W45: DQ25020027 | X45: sdoroshenko | Y45: Grainco
A46: 101610 | B46: Sales | C46: 45741 | D46: =TEXT(C46,"MMMM") -> March | E46: 5010-46-5-474 | F46: Service Revenue - Non Policy - Methven | G46: Z-GBP | H46: Cofco KIT & GP Upgrade 2023 | I46: 0 | J46: 0 | K46: 6849.7 | L46: =J46-K46 -> -6849.7 | M46: 1062 | N46: 0 | O46: 6849.7 | P46: DQ25030053 | Q46: DQ25030053 | R46: 9017 | S46: 45747 | T46: RMSLS | U46: SJ | V46: GLTRX00026806 | W46: DQ25030053 | X46: sdoroshenko | Y46: COFCO International
A47: 101641 | B47: Sales | C47: 45747 | D47: =TEXT(C47,"MMMM") -> March | E47: 5010-46-5-454 | F47: Service Revenue - Non Policy - Gen NA | G47: Z-GBP | H47: PETL - Add OrderID to Direct D | I47: 0 | J47: 0 | K47: 412.2 | L47: =J47-K47 -> -412.2 | M47: 1062 | N47: 0 | O47: 412.2 | P47: DQ25040055 | Q47: DQ25040055 | R47: 9990 | S47: 45749 | T47: RMSLS | U47: SJ | V47: GLTRX00026831 | W47: Sales | X47: sdoroshenko | Y47: Canterra Seeds
A48: 101643 | B48: Financial | C48: 45747 | D48: =TEXT(C48,"MMMM") -> March | E48: 5010-10-5-454 | F48: Service Revenue - Initiatives | G48: Z-GBP | H48: March WIP | I48: 0 | J48: 0 | K48: 2215.4 | L48: =J48-K48 -> -2215.4 | M48: 1062 | N48: 0 | O48: 9632.7 | S48: 45749 | U48: GJ | V48: GLTRX00026833 | X48: sdoroshenko | Y48: DL Seeds
A49: 101643 | B49: Financial | C49: 45747 | D49: =TEXT(C49,"MMMM") -> March | E49: 5010-10-5-604 | F49: Service Revenue - Mid Market | G49: Z-GBP | H49: March WIP | I49: 0 | J49: 0 | K49: 5821.3333 | L49: =J49-K49 -> -5821.3333 | M49: 1062 | N49: 0 | O49: 28216 | S49: 45749 | U49: GJ | V49: GLTRX00026833 | X49: sdoroshenko | Y49: Grainco
A50: 101643 | B50: Financial | C50: 45747 | D50: =TEXT(C50,"MMMM") -> March | E50: 5010-10-5-604 | F50: Service Revenue - Mid Market | G50: Z-GBP | H50: March WIP | I50: 0 | J50: 0 | K50: 729 | L50: =J50-K50 -> -729 | M50: 1062 | N50: 0 | O50: 28216 | S50: 45749 | U50: GJ | V50: GLTRX00026833 | X50: sdoroshenko | Y50: Openfield
A51: 101643 | B51: Financial | C51: 45747 | D51: =TEXT(C51,"MMMM") -> March | E51: 5010-10-5-604 | F51: Service Revenue - Mid Market | G51: Z-GBP | H51: March WIP | I51: 0 | J51: 0 | K51: 2148.12 | L51: =J51-K51 -> -2148.12 | M51: 1062 | N51: 0 | O51: 28216 | S51: 45749 | U51: GJ | V51: GLTRX00026833 | X51: sdoroshenko | Y51: Openfield
A52: 101643 | B52: Financial | C52: 45747 | D52: =TEXT(C52,"MMMM") -> March | E52: 5010-10-5-604 | F52: Service Revenue - Mid Market | G52: Z-GBP | H52: March WIP | I52: 0 | J52: 0 | K52: 5821.3333 | L52: =J52-K52 -> -5821.3333 | M52: 1062 | N52: 0 | O52: 28216 | S52: 45749 | U52: GJ | V52: GLTRX00026833 | X52: sdoroshenko | Y52: Saxon Agriculture
A53: 101643 | B53: Financial | C53: 45747 | D53: =TEXT(C53,"MMMM") -> March | E53: 5010-10-5-604 | F53: Service Revenue - Mid Market | G53: Z-GBP | H53: March WIP | I53: 0 | J53: 0 | K53: 5016.2133 | L53: =J53-K53 -> -5016.2133 | M53: 1062 | N53: 0 | O53: 28216 | S53: 45749 | U53: GJ | V53: GLTRX00026833 | X53: sdoroshenko | Y53: Saxon Agriculture
A54: 101643 | B54: Financial | C54: 45747 | D54: =TEXT(C54,"MMMM") -> March | E54: 5010-10-5-604 | F54: Service Revenue - Mid Market | G54: Z-GBP | H54: March WIP | I54: 0 | J54: 0 | K54: 2762.6667 | L54: =J54-K54 -> -2762.6667 | M54: 1062 | N54: 0 | O54: 28216 | S54: 45749 | U54: GJ | V54: GLTRX00026833 | X54: sdoroshenko | Y54: Saxon Agriculture
A55: 101643 | B55: Financial | C55: 45747 | D55: =TEXT(C55,"MMMM") -> March | E55: 5010-10-5-604 | F55: Service Revenue - Mid Market | G55: Z-GBP | H55: March WIP | I55: 0 | J55: 0 | K55: 1381.3333 | L55: =J55-K55 -> -1381.3333 | M55: 1062 | N55: 0 | O55: 28216 | S55: 45749 | U55: GJ | V55: GLTRX00026833 | X55: sdoroshenko | Y55: Saxon Agriculture
A56: 101642 | B56: Sales | C56: 45747 | D56: =TEXT(C56,"MMMM") -> March | E56: 5010-46-5-604 | F56: Service Revenue - Non Policy - Mid Market | G56: Z-GBP | H56: Importing Stock Lot Cost Updat | I56: 0 | J56: 0 | K56: 2835 | L56: =J56-K56 -> -2835 | M56: 1062 | N56: 0 | O56: 2835 | P56: DQ25040056 | Q56: DQ25040056 | R56: 4135 | S56: 45749 | T56: RMSLS | U56: SJ | V56: GLTRX00026831 | W56: Sales | X56: sdoroshenko | Y56: Simpsons Malt
A57: 101643 | B57: Financial | C57: 45747 | D57: =TEXT(C57,"MMMM") -> March | E57: 5010-10-5-604 | F57: Service Revenue - Mid Market | G57: Z-GBP | H57: March WIP | I57: 0 | J57: 0 | K57: 4536 | L57: =J57-K57 -> -4536 | M57: 1062 | N57: 0 | O57: 28216 | S57: 45749 | U57: GJ | V57: GLTRX00026833 | X57: sdoroshenko | Y57: Simpsons Malt
A58: 101657 | B58: Financial | C58: 45747 | D58: =TEXT(C58,"MMMM") -> March | E58: 5010-10-5-604 | F58: Service Revenue - Mid Market | G58: Z-GBP | H58: Stonegate 50% Provision | I58: 0 | J58: 2145 | K58: 0 | L58: =J58-K58 -> 2145 | M58: 1062 | N58: 2145 | O58: 0 | S58: 45750 | U58: GJ | V58: GLTRX00026846 | X58: jkiernan | Y58: Stonegate
A59: 101643 | B59: Financial | C59: 45747 | D59: =TEXT(C59,"MMMM") -> March | E59: 5010-10-5-454 | F59: Service Revenue - Initiatives | G59: Z-GBP | H59: March WIP | I59: 0 | J59: 0 | K59: 6741.02 | L59: =J59-K59 -> -6741.02 | M59: 1062 | N59: 0 | O59: 9632.7 | S59: 45749 | U59: GJ | V59: GLTRX00026833 | X59: sdoroshenko | Y59: West Gaines Seeds
A60: 101643 | B60: Financial | C60: 45748 | D60: =TEXT(C60,"MMMM") -> April | E60: 5010-10-5-454 | F60: Service Revenue - Initiatives | G60: Z-GBP | H60: March WIP | I60: 0 | J60: 2215.4 | K60: 0 | L60: =J60-K60 -> 2215.4 | M60: 1062 | N60: 0 | O60: 9632.7 | S60: 45749 | U60: GJ | V60: GLTRX00026833 | X60: sdoroshenko | Y60: DL Seeds
A61: 101643 | B61: Financial | C61: 45748 | D61: =TEXT(C61,"MMMM") -> April | E61: 5010-10-5-604 | F61: Service Revenue - Mid Market | G61: Z-GBP | H61: March WIP | I61: 0 | J61: 5821.3333 | K61: 0 | L61: =J61-K61 -> 5821.3333 | M61: 1062 | N61: 0 | O61: 28216 | S61: 45749 | U61: GJ | V61: GLTRX00026833 | X61: sdoroshenko | Y61: Grainco
A62: 101643 | B62: Financial | C62: 45748 | D62: =TEXT(C62,"MMMM") -> April | E62: 5010-10-5-604 | F62: Service Revenue - Mid Market | G62: Z-GBP | H62: March WIP | I62: 0 | J62: 729 | K62: 0 | L62: =J62-K62 -> 729 | M62: 1062 | N62: 0 | O62: 28216 | S62: 45749 | U62: GJ | V62: GLTRX00026833 | X62: sdoroshenko | Y62: Openfield
A63: 101643 | B63: Financial | C63: 45748 | D63: =TEXT(C63,"MMMM") -> April | E63: 5010-10-5-604 | F63: Service Revenue - Mid Market | G63: Z-GBP | H63: March WIP | I63: 0 | J63: 2148.12 | K63: 0 | L63: =J63-K63 -> 2148.12 | M63: 1062 | N63: 0 | O63: 28216 | S63: 45749 | U63: GJ | V63: GLTRX00026833 | X63: sdoroshenko | Y63: Openfield
A64: 101643 | B64: Financial | C64: 45748 | D64: =TEXT(C64,"MMMM") -> April | E64: 5010-10-5-604 | F64: Service Revenue - Mid Market | G64: Z-GBP | H64: March WIP | I64: 0 | J64: 5821.3333 | K64: 0 | L64: =J64-K64 -> 5821.3333 | M64: 1062 | N64: 0 | O64: 28216 | S64: 45749 | U64: GJ | V64: GLTRX00026833 | X64: sdoroshenko | Y64: Saxon Agriculture
A65: 101643 | B65: Financial | C65: 45748 | D65: =TEXT(C65,"MMMM") -> April | E65: 5010-10-5-604 | F65: Service Revenue - Mid Market | G65: Z-GBP | H65: March WIP | I65: 0 | J65: 5016.2133 | K65: 0 | L65: =J65-K65 -> 5016.2133 | M65: 1062 | N65: 0 | O65: 28216 | S65: 45749 | U65: GJ | V65: GLTRX00026833 | X65: sdoroshenko | Y65: Saxon Agriculture
A66: 101643 | B66: Financial | C66: 45748 | D66: =TEXT(C66,"MMMM") -> April | E66: 5010-10-5-604 | F66: Service Revenue - Mid Market | G66: Z-GBP | H66: March WIP | I66: 0 | J66: 2762.6667 | K66: 0 | L66: =J66-K66 -> 2762.6667 | M66: 1062 | N66: 0 | O66: 28216 | S66: 45749 | U66: GJ | V66: GLTRX00026833 | X66: sdoroshenko | Y66: Saxon Agriculture
A67: 101643 | B67: Financial | C67: 45748 | D67: =TEXT(C67,"MMMM") -> April | E67: 5010-10-5-604 | F67: Service Revenue - Mid Market | G67: Z-GBP | H67: March WIP | I67: 0 | J67: 1381.3333 | K67: 0 | L67: =J67-K67 -> 1381.3333 | M67: 1062 | N67: 0 | O67: 28216 | S67: 45749 | U67: GJ | V67: GLTRX00026833 | X67: sdoroshenko | Y67: Saxon Agriculture
A68: 101643 | B68: Financial | C68: 45748 | D68: =TEXT(C68,"MMMM") -> April | E68: 5010-10-5-604 | F68: Service Revenue - Mid Market | G68: Z-GBP | H68: March WIP | I68: 0 | J68: 4536 | K68: 0 | L68: =J68-K68 -> 4536 | M68: 1062 | N68: 0 | O68: 28216 | S68: 45749 | U68: GJ | V68: GLTRX00026833 | X68: sdoroshenko | Y68: Simpsons Malt
A69: 101643 | B69: Financial | C69: 45748 | D69: =TEXT(C69,"MMMM") -> April | E69: 5010-10-5-454 | F69: Service Revenue - Initiatives | G69: Z-GBP | H69: March WIP | I69: 0 | J69: 6741.02 | K69: 0 | L69: =J69-K69 -> 6741.02 | M69: 1062 | N69: 0 | O69: 9632.7 | S69: 45749 | U69: GJ | V69: GLTRX00026833 | X69: sdoroshenko | Y69: West Gaines Seeds
A70: 101883 | B70: Sales | C70: 45762 | D70: =TEXT(C70,"MMMM") -> April | E70: 5010-46-5-454 | F70: Service Revenue - Non Policy - Gen NA | G70: Z-GBP | H70: ProductID & Alt Batch on Docum | I70: 0 | J70: 0 | K70: 1073.3 | L70: =J70-K70 -> -1073.3 | M70: 1062 | N70: 0 | O70: 1073.3 | P70: DQ25040062 | Q70: DQ25040062 | R70: 9990 | S70: 45777 | T70: RMSLS | U70: SJ | V70: GLTRX00026934 | W70: Sales | X70: sdoroshenko | Y70: Canterra Seeds
A71: 101904 | B71: Financial | C71: 45777 | D71: =TEXT(C71,"MMMM") -> April | E71: 5010-10-5-604 | F71: Service Revenue - Mid Market | G71: Z-GBP | H71: WIP April | I71: 0 | J71: 0 | K71: 2543.49 | L71: =J71-K71 -> -2543.49 | M71: 1062 | N71: 0 | O71: 26014.02 | S71: 45779 | U71: GJ | V71: GLTRX00026948 | X71: sdoroshenko | Y71: Dugdale Nutrition
A72: 101886 | B72: Sales | C72: 45777 | D72: =TEXT(C72,"MMMM") -> April | E72: 5010-10-5-604 | F72: Service Revenue - Mid Market | G72: Z-GBP | H72: Server MIgration | I72: 0 | J72: 0 | K72: 4144 | L72: =J72-K72 -> -4144 | M72: 1062 | N72: 0 | O72: 4144 | P72: DQ25050067 | Q72: DQ25050067 | R72: 4138 | S72: 45778 | T72: RMSLS | U72: SJ | V72: GLTRX00026937 | W72: Sales | X72: jkiernan | Y72: G Williams Seeds
A73: 101904 | B73: Financial | C73: 45777 | D73: =TEXT(C73,"MMMM") -> April | E73: 5010-10-5-604 | F73: Service Revenue - Mid Market | G73: Z-GBP | H73: WIP April | I73: 0 | J73: 0 | K73: 5821.33 | L73: =J73-K73 -> -5821.33 | M73: 1062 | N73: 0 | O73: 26014.02 | S73: 45779 | U73: GJ | V73: GLTRX00026948 | X73: sdoroshenko | Y73: Grainco
A74: 101904 | B74: Financial | C74: 45777 | D74: =TEXT(C74,"MMMM") -> April | E74: 5010-10-5-604 | F74: Service Revenue - Mid Market | G74: Z-GBP | H74: WIP April | I74: 0 | J74: 0 | K74: 197.33 | L74: =J74-K74 -> -197.33 | M74: 1062 | N74: 0 | O74: 26014.02 | S74: 45779 | U74: GJ | V74: GLTRX00026948 | X74: sdoroshenko | Y74: Grainco
A75: 101887 | B75: Sales | C75: 45777 | D75: =TEXT(C75,"MMMM") -> April | E75: 5010-10-5-604 | F75: Service Revenue - Mid Market | G75: Z-GBP | H75: Pool Area Update for Stores | I75: 0 | J75: 0 | K75: 850.5 | L75: =J75-K75 -> -850.5 | M75: 1062 | N75: 0 | O75: 850.5 | P75: DQ25050068 | Q75: DQ25050068 | R75: 4067 | S75: 45778 | T75: RMSLS | U75: SJ | V75: GLTRX00026937 | W75: Sales | X75: jkiernan | Y75: Openfield
A76: 101888 | B76: Sales | C76: 45777 | D76: =TEXT(C76,"MMMM") -> April | E76: 5010-10-5-604 | F76: Service Revenue - Mid Market | G76: Z-GBP | H76: Haulage Position - Multi Selec | I76: 0 | J76: 0 | K76: 1197 | L76: =J76-K76 -> -1197 | M76: 1062 | N76: 0 | O76: 1197 | P76: DQ25050069 | Q76: DQ25050069 | R76: 4067 | S76: 45778 | T76: RMSLS | U76: SJ | V76: GLTRX00026937 | W76: Sales | X76: jkiernan | Y76: Openfield
A77: 101889 | B77: Sales | C77: 45777 | D77: =TEXT(C77,"MMMM") -> April | E77: 5010-10-5-604 | F77: Service Revenue - Mid Market | G77: Z-GBP | H77: Pool Valuation Enquiry - Add p | I77: 0 | J77: 0 | K77: 630 | L77: =J77-K77 -> -630 | M77: 1062 | N77: 0 | O77: 630 | P77: DQ25050070 | Q77: DQ25050070 | R77: 4067 | S77: 45778 | T77: RMSLS | U77: SJ | V77: GLTRX00026937 | W77: Sales | X77: jkiernan | Y77: Openfield
A78: 101892 | B78: Sales | C78: 45777 | D78: =TEXT(C78,"MMMM") -> April | E78: 5010-10-5-604 | F78: Service Revenue - Mid Market | G78: Z-GBP | H78: Purchase Balance in Sales Volu | I78: 0 | J78: 0 | K78: 6427.35 | L78: =J78-K78 -> -6427.35 | M78: 1062 | N78: 0 | O78: 6427.35 | P78: DQ25050073 | Q78: DQ25050073 | R78: 4067 | S78: 45778 | T78: RMSLS | U78: SJ | V78: GLTRX00026937 | W78: Sales | X78: jkiernan | Y78: Openfield
A79: 101890 | B79: Sales | C79: 45777 | D79: =TEXT(C79,"MMMM") -> April | E79: 5010-10-5-604 | F79: Service Revenue - Mid Market | G79: Z-GBP | H79: Stock Lot Rent Details | I79: 0 | J79: 0 | K79: 5920 | L79: =J79-K79 -> -5920 | M79: 1062 | N79: 0 | O79: 5920 | P79: DQ25050071 | Q79: DQ25050071 | R79: 892 | S79: 45778 | T79: RMSLS | U79: SJ | V79: GLTRX00026937 | W79: Sales | X79: jkiernan | Y79: Saxon Agriculture
A80: 101891 | B80: Sales | C80: 45777 | D80: =TEXT(C80,"MMMM") -> April | E80: 5010-10-5-604 | F80: Service Revenue - Mid Market | G80: Z-GBP | H80: M2M Conventional Carry Adjustm | I80: 0 | J80: 0 | K80: 1776 | L80: =J80-K80 -> -1776 | M80: 1062 | N80: 0 | O80: 1776 | P80: DQ25050072 | Q80: DQ25050072 | R80: 892 | S80: 45778 | T80: RMSLS | U80: SJ | V80: GLTRX00026937 | W80: Sales | X80: jkiernan | Y80: Saxon Agriculture
A81: 101904 | B81: Financial | C81: 45777 | D81: =TEXT(C81,"MMMM") -> April | E81: 5010-10-5-604 | F81: Service Revenue - Mid Market | G81: Z-GBP | H81: WIP April | I81: 0 | J81: 0 | K81: 6512 | L81: =J81-K81 -> -6512 | M81: 1062 | N81: 0 | O81: 26014.02 | S81: 45779 | U81: GJ | V81: GLTRX00026948 | X81: sdoroshenko | Y81: Saxon Agriculture
A82: 101904 | B82: Financial | C82: 45777 | D82: =TEXT(C82,"MMMM") -> April | E82: 5010-10-5-604 | F82: Service Revenue - Mid Market | G82: Z-GBP | H82: WIP April | I82: 0 | J82: 0 | K82: 2877.12 | L82: =J82-K82 -> -2877.12 | M82: 1062 | N82: 0 | O82: 26014.02 | S82: 45779 | U82: GJ | V82: GLTRX00026948 | X82: sdoroshenko | Y82: Saxon Agriculture
A83: 101904 | B83: Financial | C83: 45777 | D83: =TEXT(C83,"MMMM") -> April | E83: 5010-10-5-604 | F83: Service Revenue - Mid Market | G83: Z-GBP | H83: WIP April | I83: 0 | J83: 0 | K83: 4536 | L83: =J83-K83 -> -4536 | M83: 1062 | N83: 0 | O83: 26014.02 | S83: 45779 | U83: GJ | V83: GLTRX00026948 | X83: sdoroshenko | Y83: Simpsons Malt
A84: 101894 | B84: Sales | C84: 45777 | D84: =TEXT(C84,"MMMM") -> April | E84: 5010-10-5-454 | F84: Service Revenue - Initiatives | G84: Z-GBP | H84: WGS GenSCOUT Build | I84: 0 | J84: 0 | K84: 7410 | L84: =J84-K84 -> -7410 | M84: 1062 | N84: 0 | O84: 7410 | P84: DQ25040061 | Q84: DQ25040061 | R84: 9995 | S84: 45778 | T84: RMSLS | U84: SJ | V84: GLTRX00026939 | W84: Sales | X84: jkiernan | Y84: West Gaines Seeds
A85: 101904 | B85: Financial | C85: 45778 | D85: =TEXT(C85,"MMMM") -> May | E85: 5010-10-5-604 | F85: Service Revenue - Mid Market | G85: Z-GBP | H85: WIP April | I85: 0 | J85: 2543.49 | K85: 0 | L85: =J85-K85 -> 2543.49 | M85: 1062 | N85: 0 | O85: 26014.02 | S85: 45779 | U85: GJ | V85: GLTRX00026948 | X85: sdoroshenko | Y85: Dugdale Nutrition
A86: 101904 | B86: Financial | C86: 45778 | D86: =TEXT(C86,"MMMM") -> May | E86: 5010-10-5-604 | F86: Service Revenue - Mid Market | G86: Z-GBP | H86: WIP April | I86: 0 | J86: 5821.33 | K86: 0 | L86: =J86-K86 -> 5821.33 | M86: 1062 | N86: 0 | O86: 26014.02 | S86: 45779 | U86: GJ | V86: GLTRX00026948 | X86: sdoroshenko | Y86: Grainco
A87: 101904 | B87: Financial | C87: 45778 | D87: =TEXT(C87,"MMMM") -> May | E87: 5010-10-5-604 | F87: Service Revenue - Mid Market | G87: Z-GBP | H87: WIP April | I87: 0 | J87: 197.33 | K87: 0 | L87: =J87-K87 -> 197.33 | M87: 1062 | N87: 0 | O87: 26014.02 | S87: 45779 | U87: GJ | V87: GLTRX00026948 | X87: sdoroshenko | Y87: Grainco
A88: 101904 | B88: Financial | C88: 45778 | D88: =TEXT(C88,"MMMM") -> May | E88: 5010-10-5-604 | F88: Service Revenue - Mid Market | G88: Z-GBP | H88: WIP April | I88: 0 | J88: 6512 | K88: 0 | L88: =J88-K88 -> 6512 | M88: 1062 | N88: 0 | O88: 26014.02 | S88: 45779 | U88: GJ | V88: GLTRX00026948 | X88: sdoroshenko | Y88: Saxon Agriculture
A89: 101904 | B89: Financial | C89: 45778 | D89: =TEXT(C89,"MMMM") -> May | E89: 5010-10-5-604 | F89: Service Revenue - Mid Market | G89: Z-GBP | H89: WIP April | I89: 0 | J89: 2877.12 | K89: 0 | L89: =J89-K89 -> 2877.12 | M89: 1062 | N89: 0 | O89: 26014.02 | S89: 45779 | U89: GJ | V89: GLTRX00026948 | X89: sdoroshenko | Y89: Saxon Agriculture
A90: 101904 | B90: Financial | C90: 45778 | D90: =TEXT(C90,"MMMM") -> May | E90: 5010-10-5-604 | F90: Service Revenue - Mid Market | G90: Z-GBP | H90: WIP April | I90: 0 | J90: 4536 | K90: 0 | L90: =J90-K90 -> 4536 | M90: 1062 | N90: 0 | O90: 26014.02 | S90: 45779 | U90: GJ | V90: GLTRX00026948 | X90: sdoroshenko | Y90: Simpsons Malt
A91: 102117 | B91: Sales | C91: 45790 | D91: =TEXT(C91,"MMMM") -> May | E91: 5010-46-5-604 | F91: Service Revenue - Non Policy - Mid Market | G91: Z-GBP | H91: G Williams Server Migration (E | I91: 0 | J91: 0 | K91: 3700 | L91: =J91-K91 -> -3700 | M91: 1062 | N91: 0 | O91: 3700 | P91: DQ25050075 | Q91: DQ25050075 | R91: 4138 | S91: 45804 | T91: RMSLS | U91: SJ | V91: GLTRX00027022 | W91: DQ25050075 | X91: sdoroshenko | Y91: G Williams Seeds
A92: 102116 | B92: Sales | C92: 45790 | D92: =TEXT(C92,"MMMM") -> May | E92: 5010-46-5-604 | F92: Service Revenue - Non Policy - Mid Market | G92: Z-GBP | H92: GrainCo - Integration Project | I92: 0 | J92: 0 | K92: 5920 | L92: =J92-K92 -> -5920 | M92: 1062 | N92: 0 | O92: 5920 | P92: DQ25050074 | Q92: DQ25050074 | R92: 4117 | S92: 45804 | T92: RMSLS | U92: SJ | V92: GLTRX00027022 | W92: DQ25050074 | X92: sdoroshenko | Y92: Grainco
A93: 102119 | B93: Sales | C93: 45791 | D93: =TEXT(C93,"MMMM") -> May | E93: 5010-46-5-604 | F93: Service Revenue - Non Policy - Mid Market | G93: Z-GBP | H93: Dugdales Server Migration | I93: 0 | J93: 0 | K93: 5148 | L93: =J93-K93 -> -5148 | M93: 1062 | N93: 0 | O93: 5148 | P93: DQ25050079 | Q93: DQ25050079 | R93: 4112 | S93: 45804 | T93: RMSLS | U93: SJ | V93: GLTRX00027022 | W93: DQ25050079 | X93: sdoroshenko | Y93: Dugdale Nutrition
A94: 102223 | B94: Financial | C94: 45808 | D94: =TEXT(C94,"MMMM") -> May | E94: 5010-10-5-604 | F94: Service Revenue - Mid Market | G94: Z-GBP | H94: Adam & Howling Ltd move | I94: 0 | J94: 0 | K94: 2960 | L94: =J94-K94 -> -2960 | M94: 1062 | N94: 0 | O94: 2960 | S94: 45811 | U94: GJ | V94: GLTRX00027081 | X94: sdoroshenko | Y94: Adams & Howling
A95: 102225 | B95: Sales | C95: 45808 | D95: =TEXT(C95,"MMMM") -> May | E95: 5010-46-5-454 | F95: Service Revenue - Non Policy - Gen NA | G95: Z-GBP | H95: DLS -GP Upgrade 2023 | I95: 0 | J95: 0 | K95: 4359.07 | L95: =J95-K95 -> -4359.07 | M95: 1062 | N95: 0 | O95: 4359.07 | P95: DQ25060089 | Q95: DQ25060089 | R95: 9092 | S95: 45811 | T95: RMSLS | U95: SJ | V95: GLTRX00027083 | W95: Sales | X95: sdoroshenko | Y95: DL Seeds
A96: 102224 | B96: Financial | C96: 45808 | D96: =TEXT(C96,"MMMM") -> May | E96: 5010-10-5-604 | F96: Service Revenue - Mid Market | G96: Z-GBP | H96: WIP May | I96: 0 | J96: 0 | K96: 197.33 | L96: =J96-K96 -> -197.33 | M96: 1062 | N96: 0 | O96: 13207.57 | S96: 45811 | U96: GJ | V96: GLTRX00027082 | X96: sdoroshenko | Y96: Grainco
A97: 102224 | B97: Financial | C97: 45808 | D97: =TEXT(C97,"MMMM") -> May | E97: 5010-10-5-604 | F97: Service Revenue - Mid Market | G97: Z-GBP | H97: WIP May | I97: 0 | J97: 0 | K97: 2417.33 | L97: =J97-K97 -> -2417.33 | M97: 1062 | N97: 0 | O97: 13207.57 | S97: 45811 | U97: GJ | V97: GLTRX00027082 | X97: sdoroshenko | Y97: Grainco
A98: 102224 | B98: Financial | C98: 45808 | D98: =TEXT(C98,"MMMM") -> May | E98: 5010-10-5-604 | F98: Service Revenue - Mid Market | G98: Z-GBP | H98: WIP May | I98: 0 | J98: 0 | K98: 714 | L98: =J98-K98 -> -714 | M98: 1062 | N98: 0 | O98: 13207.57 | S98: 45811 | U98: GJ | V98: GLTRX00027082 | X98: sdoroshenko | Y98: Openfield
A99: 102224 | B99: Financial | C99: 45808 | D99: =TEXT(C99,"MMMM") -> May | E99: 5010-10-5-604 | F99: Service Revenue - Mid Market | G99: Z-GBP | H99: WIP May | I99: 0 | J99: 0 | K99: 4356.24 | L99: =J99-K99 -> -4356.24 | M99: 1062 | N99: 0 | O99: 13207.57 | S99: 45811 | U99: GJ | V99: GLTRX00027082 | X99: sdoroshenko | Y99: Openfield
A100: 102224 | B100: Financial | C100: 45808 | D100: =TEXT(C100,"MMMM") -> May | E100: 5010-10-5-604 | F100: Service Revenue - Mid Market | G100: Z-GBP | H100: WIP May | I100: 0 | J100: 0 | K100: 986.67 | L100: =J100-K100 -> -986.67 | M100: 1062 | N100: 0 | O100: 13207.57 | S100: 45811 | U100: GJ | V100: GLTRX00027082 | X100: sdoroshenko | Y100: Robin Appel
...

Sheet PS Pivot
B4: Sum of Balance | C4: Column Labels
B5: Row Labels | C5: January | D5: February | E5: March | F5: April | G5: May | H5: June | I5: July | J5: August | K5: September | L5: October | M5: November | N5: December | O5: Grand Total
B6: Adams & Howling | G6: -2960 | O6: -2960
B7: Banff & Moray Grain (Marketing) Ltd | J7: -1864.8 | K7: -754.8 | O7: -2619.6
B8: Canterra Seeds | D8: -4182.24 | E8: -412.2 | F8: -1073.3 | I8: -3808.72 | J8: -484.575 | K8: -9621.1059 | L8: -58.1391 | O8: -19640.28
B9: COFCO International | C9: -1763.67 | D9: 0 | E9: -5086.03 | O9: -6849.7
B10: Confluence Genetics | J10: -4340.9195 | K10: -15328.239 | L10: 0 | M10: -6543.455 | N10: 0 | O10: -26212.614
B11: Cope Seeds | N11: -2520 | O11: -2520
B12: Denholm Fish Selling Ltd | J12: -1282.6667 | K12: 0 | L12: 5318.75 | M12: -197.33333 | N12: 10498.75 | O12: 14337.5
B13: DL Seeds | C13: 0 | D13: 0 | E13: 116.6 | F13: 2215.4 | G13: -4359.07 | O13: -2027.07
B14: Dugdale Nutrition | F14: -2543.49 | G14: -2604.51 | I14: -1480 | O14: -6628
B15: Fram Farmers | K15: -296 | L15: 0 | M15: 0 | N15: 0 | O15: -296
B16: G Williams Seeds | F16: -4144 | G16: -3700 | O16: -7844
B17: Glasson Grain | C17: 0 | D17: 1525.33 | H17: -3236.27 | I17: -1627.9967 | J17: -5870.6667 | K17: -5969.3333 | L17: -1332 | M17: -5525.3333 | N17: -1973.3333 | O17: -24009.603
B18: Grainco | D18: -715 | E18: -5821.3333 | F18: -197.32667 | G18: -2516 | H18: -744.94 | O18: -9994.6
B19: H J Lea | D19: -3625 | M19: -690.66667 | N19: -49.333333 | O19: -4365
B20: J Stobart & Sons | D20: -1950 | O20: -1950
B21: North Herts Farmers | H21: -1287.6 | O21: -1287.6
B22: Openfield | C22: -6551.28 | D22: -11591.1 | E22: -6458.94 | F22: -6227.73 | G22: -5070.24 | H22: -6420.12 | I22: -2593.92 | J22: -905.95 | K22: -21738.77 | L22: -1486.8 | M22: -3459.12 | N22: -6620.88 | O22: -79124.85
B23: Robin Appel | G23: -986.67 | H23: 0 | I23: 0.0033333333 | J23: -1973.3333 | O23: -2960
B24: Saxon Agriculture | C24: -1430 | D24: -9990 | E24: -14981.547 | F24: -2103.5733 | G24: -9110.88 | H24: -2072 | I24: -2368 | J24: -5520.4 | K24: -6512 | M24: -5920 | N24: -10261.333 | O24: -70269.733
B25: Simpsons Malt | C25: -486 | D25: -1370.65 | E25: -6040.44 | F25: 0 | G25: 0 | H25: -8967.84 | I25: -10083.36 | J25: -5880 | K25: -1793.55 | L25: -1890 | M25: -2037 | N25: -3112.2 | O25: -41661.04
B26: Stonegate | E26: 2145 | I26: -7298.65 | J26: -2145 | O26: -7298.65
B27: West Gaines Seeds | C27: 0 | D27: -282.84 | E27: 0 | F27: -668.98 | H27: -4153.73 | J27: -2055.81 | O27: -7161.36
B28: Grand Total | C28: -10230.95 | D28: -32181.5 | E28: -36538.89 | F28: -14743 | G28: -31307.37 | H28: -26882.5 | I28: -29260.643 | J28: -32324.121 | K28: -62013.799 | L28: 551.8109 | M28: -24372.908 | N28: -14038.33 | O28: -313342.2
C29: 10231 | D29: 32182 | E29: 36539 | F29: 14743 | G29: 31307 | H29: 26882 | I29: 29261 | J29: 32324 | K29: 62014 | L29: 552 | M29: 24373 | N29: 14038
C30: =C29+C28 -> 0.05 | D30: =D29+D28 -> 0.5 | E30: =E29+E28 -> 0.11 | F30: =F29+F28 -> 0 | G30: =G29+G28 -> -0.37 | H30: =H29+H28 -> -0.5 | I30: =I29+I28 -> 0.35666667 | J30: =J29+J28 -> -0.12118667 | K30: =K29+K28 -> 0.20146 | L30: =L29-L28 -> 0.1891 | M30: =M29+M28 -> 0.091626667 | N30: =N29+N28 -> -0.33
B33: FX RATE | C33: 0.80549 | D33: 0.79437 | E33: 0.77312 | F33: 0.74848 | G33: 0.74348 | H33: 0.72924 | I33: 0.75575 | J33: 0.74083 | K33: 0.744 | L33: 0.76108 | M33: 0.75609 | N33: 0.74322
B35: Adams & Howling | C35: =C6/$C$33 -> 0 | D35: =D6/$D$33 -> 0 | E35: =E6/$E$33 -> 0 | F35: =F6/$F$33 -> 0 | G35: =G6/$G$33 -> -3981.2772 | H35: =H6/$H$33 -> 0 | I35: =I6/$I$33 -> 0 | J35: =J6/$J$33 -> 0 | K35: =K6/$K$33 -> 0 | L35: =L6/$L$33 -> 0 | M35: =M6/$M$33 -> 0 | N35: =N6/$N$33 -> 0 | O35: =SUM(C35:N35) -> -3981.2772
B36: Banff & Moray Grain (Marketing) Ltd | C36: =C7/$C$33 -> 0 | D36: =D7/$D$33 -> 0 | E36: =E7/$E$33 -> 0 | F36: =F7/$F$33 -> 0 | G36: =G7/$G$33 -> 0 | H36: =H7/$H$33 -> 0 | I36: =I7/$I$33 -> 0 | J36: =J7/$J$33 -> -2517.1767 | K36: =K7/$K$33 -> -1014.5161 | L36: =L7/$L$33 -> 0 | M36: =M7/$M$33 -> 0 | N36: =N7/$N$33 -> 0 | O36: =SUM(C36:N36) -> -3531.6928
B37: Canterra Seeds | C37: =C8/$C$33 -> 0 | D37: =D8/$D$33 -> -5264.8514 | E37: =E8/$E$33 -> -533.16432 | F37: =F8/$F$33 -> -1433.9729 | G37: =G8/$G$33 -> 0 | H37: =H8/$H$33 -> 0 | I37: =I8/$I$33 -> -5039.656 | J37: =J8/$J$33 -> -654.09743 | K37: =K8/$K$33 -> -12931.594 | L37: =L8/$L$33 -> -76.390261 | M37: =M8/$M$33 -> 0 | N37: =N8/$N$33 -> 0 | O37: =SUM(C37:N37) -> -25933.726
B38: COFCO International | C38: =C9/$C$33 -> -2189.5616 | D38: =D9/$D$33 -> 0 | E38: =E9/$E$33 -> -6578.5777 | F38: =F9/$F$33 -> 0 | G38: =G9/$G$33 -> 0 | H38: =H9/$H$33 -> 0 | I38: =I9/$I$33 -> 0 | J38: =J9/$J$33 -> 0 | K38: =K9/$K$33 -> 0 | L38: =L9/$L$33 -> 0 | M38: =M9/$M$33 -> 0 | N38: =N9/$N$33 -> 0 | O38: =SUM(C38:N38) -> -8768.1393
B39: Confluence Genetics | C39: =C10/$C$33 -> 0 | D39: =D10/$D$33 -> 0 | E39: =E10/$E$33 -> 0 | F39: =F10/$F$33 -> 0 | G39: =G10/$G$33 -> 0 | H39: =H10/$H$33 -> 0 | I39: =I10/$I$33 -> 0 | J39: =J10/$J$33 -> -5859.5353 | K39: =K10/$K$33 -> -20602.472 | L39: =L10/$L$33 -> 0 | M39: =M10/$M$33 -> -8654.3335 | N39: =N10/$N$33 -> 0 | O39: =SUM(C39:N39) -> -35116.341
B40: Cope Seeds | C40: =C11/$C$33 -> 0 | D40: =D11/$D$33 -> 0 | E40: =E11/$E$33 -> 0 | F40: =F11/$F$33 -> 0 | G40: =G11/$G$33 -> 0 | H40: =H11/$H$33 -> 0 | I40: =I11/$I$33 -> 0 | J40: =J11/$J$33 -> 0 | K40: =K11/$K$33 -> 0 | L40: =L11/$L$33 -> 0 | M40: =M11/$M$33 -> 0 | N40: =N11/$N$33 -> -3390.6515 | O40: =SUM(C40:N40) -> -3390.6515
B41: Denholm Fish Selling Ltd | C41: =C12/$C$33 -> 0 | D41: =D12/$D$33 -> 0 | E41: =E12/$E$33 -> 0 | F41: =F12/$F$33 -> 0 | G41: =G12/$G$33 -> 0 | H41: =H12/$H$33 -> 0 | I41: =I12/$I$33 -> 0 | J41: =J12/$J$33 -> -1731.3914 | K41: =K12/$K$33 -> 0 | L41: =L12/$L$33 -> 6988.4243 | M41: =M12/$M$33 -> -260.99186 | N41: =N12/$N$33 -> 14126.033 | O41: =SUM(C41:N41) -> 19122.074
B42: DL Seeds | C42: =C13/$C$33 -> 0 | D42: =D13/$D$33 -> 0 | E42: =E13/$E$33 -> 150.81747 | F42: =F13/$F$33 -> 2959.8653 | G42: =G13/$G$33 -> -5863.0629 | H42: =H13/$H$33 -> 0 | I42: =I13/$I$33 -> 0 | J42: =J13/$J$33 -> 0 | K42: =K13/$K$33 -> 0 | L42: =L13/$L$33 -> 0 | M42: =M13/$M$33 -> 0 | N42: =N13/$N$33 -> 0 | O42: =SUM(C42:N42) -> -2752.3801
B43: Dugdale Nutrition | C43: =C14/$C$33 -> 0 | D43: =D14/$D$33 -> 0 | E43: =E14/$E$33 -> 0 | F43: =F14/$F$33 -> -3398.207 | G43: =G14/$G$33 -> -3503.1339 | H43: =H14/$H$33 -> 0 | I43: =I14/$I$33 -> -1958.3196 | J43: =J14/$J$33 -> 0 | K43: =K14/$K$33 -> 0 | L43: =L14/$L$33 -> 0 | M43: =M14/$M$33 -> 0 | N43: =N14/$N$33 -> 0 | O43: =SUM(C43:N43) -> -8859.6605
B44: Fram Farmers | C44: =C15/$C$33 -> 0 | D44: =D15/$D$33 -> 0 | E44: =E15/$E$33 -> 0 | F44: =F15/$F$33 -> 0 | G44: =G15/$G$33 -> 0 | H44: =H15/$H$33 -> 0 | I44: =I15/$I$33 -> 0 | J44: =J15/$J$33 -> 0 | K44: =K15/$K$33 -> -397.84946 | L44: =L15/$L$33 -> 0 | M44: =M15/$M$33 -> 0 | N44: =N15/$N$33 -> 0 | O44: =SUM(C44:N44) -> -397.84946
B45: G Williams Seeds | C45: =C16/$C$33 -> 0 | D45: =D16/$D$33 -> 0 | E45: =E16/$E$33 -> 0 | F45: =F16/$F$33 -> -5536.5541 | G45: =G16/$G$33 -> -4976.5965 | H45: =H16/$H$33 -> 0 | I45: =I16/$I$33 -> 0 | J45: =J16/$J$33 -> 0 | K45: =K16/$K$33 -> 0 | L45: =L16/$L$33 -> 0 | M45: =M16/$M$33 -> 0 | N45: =N16/$N$33 -> 0 | O45: =SUM(C45:N45) -> -10513.151
B46: Glasson Grain | C46: =C17/$C$33 -> 0 | D46: =D17/$D$33 -> 1920.1757 | E46: =E17/$E$33 -> 0 | F46: =F17/$F$33 -> 0 | G46: =G17/$G$33 -> 0 | H46: =H17/$H$33 -> -4437.8668 | I46: =I17/$I$33 -> -2154.1471 | J46: =J17/$J$33 -> -7924.4451 | K46: =K17/$K$33 -> -8023.2975 | L46: =L17/$L$33 -> -1750.1445 | M46: =M17/$M$33 -> -7307.772 | N46: =N17/$N$33 -> -2655.1133 | O46: =SUM(C46:N46) -> -32332.611
... B56: West Gaines Seeds | C56: =C27/$C$33 -> 0 | D56: =D27/$D$33 -> -356.05574 | E56: =E27/$E$33 -> 0 | F56: =F27/$F$33 -> -893.78474 | G56: =G27/$G$33 -> 0 | H56: =H27/$H$33 -> -5695.9711 | I56: =I27/$I$33 -> 0 | J56: =J27/$J$33 -> -2775.0091 | K56: =K27/$K$33 -> 0 | L56: =L27/$L$33 -> 0 | M56: =M27/$M$33 -> 0 | N56: =N27/$N$33 -> 0 | O56: =SUM(C56:N56) -> -9720.8207
O58: =SUM(O35:O57) -> -415245.8

Sheet Licenses
A3: Row Labels | B3: Sum of Jan-25 | C3: Sum of Feb-25 | D3: Sum of Mar-25 | E3: Sum of Apr-25 | F3: Sum of May-25 | G3: Sum of Jun-25 | H3: Sum of Jul-25 | I3: Sum of Aug-25 | J3: Sum of Sep-25 | K3: Sum of Oct-25 | L3: Sum of Nov-25 | M3: Sum of Dec-25 | N3: Sum of Total Income 2025
A4: Barenbrug | B4: 448.37 | N4: 448.37
A5: Canterra Seeds | F5: 2206.62 | K5: 3406.29 | L5: 6474.47 | M5: 1929.21 | N5: 14016.59
A6: COFCO International | N6: 0
A7: Confluence Genetics | L7: 8404.03 | N7: 8404.03
A8: Denholm Fish Selling Ltd | G8: 6109.5 | N8: 6109.5
A9: DL Seeds | F9: 4604.18 | N9: 4604.18
A10: Dugdale Nutrition | I10: 553.82 | N10: 553.82
A11: Fram Farmers | L11: 3796.28 | N11: 3796.28
A12: G Williams Seeds | E12: 786.47 | N12: 786.47
A13: Glasson Grain | G13: 4258.77 | N13: 4258.77
A14: Grainco | B14: 1890.35 | J14: 5620.42 | N14: 7510.77
A15: J Stobart & Sons | J15: 545.41 | N15: 545.41
A16: Morning Foods | B16: 2489.66 | N16: 2489.66
A17: North Herts Farmers | E17: 399.37 | N17: 399.37
A18: Openfield | K18: 847.45 | L18: 37255.6 | N18: 38103.05
A19: Robin Appel | M19: 513.31 | N19: 513.31
A20: Saxon Agriculture | B20: 5075 | D20: 575.39 | H20: 5298.3 | N20: 10948.69
A21: Simpsons Malt | B21: 0 | G21: 3806.31 | N21: 3806.31
A22: West Gaines Seeds | D22: 2531.9 | J22: 6597.09 | L22: 10885.81 | N22: 20014.8
A23: Grand Total | B23: 9903.38 | D23: 3107.29 | E23: 1185.84 | F23: 6810.8 | G23: 14174.58 | H23: 5298.3 | I23: 553.82 | J23: 12762.92 | K23: 4253.74 | L23: 66816.19 | M23: 2442.52 | N23: 127309.38
B25: 9904 | C25: 0 | D25: 3107 | E25: 1186 | F25: 6811 | G25: 14175 | H25: 5298 | I25: 554 | J25: 12763 | K25: 4253 | L25: 66817 | M25: 2442
B27: =GETPIVOTDATA("Sum of Jan-25",$A$3)-B25 -> -0.62 | C27: =C25 -> 0 | D27: =D25-GETPIVOTDATA("Sum of Mar-25",$A$3) -> -0.29 | E27: =E25-GETPIVOTDATA("Sum of Apr-25",$A$3) -> 0.16 | F27: =F25-GETPIVOTDATA("Sum of May-25",$A$3) -> 0.2 | G27: =G25-GETPIVOTDATA("Sum of Jun-25",$A$3) -> 0.42 | H27: =H25-H23 -> -0.3 | I27: =I25-I23 -> 0.18 | J27: =J25-J23 -> 0.08 | K27: =K25-K23 -> -0.74 | L27: =L25-L23 -> 0.81 | M27: =M25-M23 -> -0.52
A33: FX RATE | B33: 0.80549 | C33: 0.79437 | D33: 0.77312 | E33: 0.74848 | F33: 0.74348 | G33: 0.72924 | H33: 0.75575 | I33: 0.74083 | J33: 0.744 | K33: 0.76108 | L33: 0.75609 | M33: 0.74322
A35: Barenbrug | B35: =B4/$B$33 -> 556.64254 | C35: =C4/$C$33 -> 0 | D35: =D4/$D$33 -> 0 | E35: =E4/$E$33 -> 0 | F35: =F4/$F$33 -> 0 | G35: =G4/$G$33 -> 0 | H35: =H4/$H$33 -> 0 | I35: =I4/$I$33 -> 0 | J35: =J4/$J$33 -> 0 | K35: =K4/$K$33 -> 0 | L35: =L4/$L$33 -> 0 | M35: =M4/$M$33 -> 0 | N35: =SUM(B35:M35) -> 556.64254
A36: Canterra Seeds | B36: =B5/$B$33 -> 0 | C36: =C5/$C$33 -> 0 | D36: =D5/$D$33 -> 0 | E36: =E5/$E$33 -> 0 | F36: =F5/$F$33 -> 2967.9615 | G36: =G5/$G$33 -> 0 | H36: =H5/$H$33 -> 0 | I36: =I5/$I$33 -> 0 | J36: =J5/$J$33 -> 0 | K36: =K5/$K$33 -> 4475.6005 | L36: =L5/$L$33 -> 8563.0943 | M36: =M5/$M$33 -> 2595.7455 | N36: =SUM(B36:M36) -> 18602.402
A37: COFCO International | B37: =B6/$B$33 -> 0 | C37: =C6/$C$33 -> 0 | D37: =D6/$D$33 -> 0 | E37: =E6/$E$33 -> 0 | F37: =F6/$F$33 -> 0 | G37: =G6/$G$33 -> 0 | H37: =H6/$H$33 -> 0 | I37: =I6/$I$33 -> 0 | J37: =J6/$J$33 -> 0 | K37: =K6/$K$33 -> 0 | L37: =L6/$L$33 -> 0 | M37: =M6/$M$33 -> 0 | N37: =SUM(B37:M37) -> 0
A38: Confluence Genetics | B38: =B7/$B$33 -> 0 | C38: =C7/$C$33 -> 0 | D38: =D7/$D$33 -> 0 | E38: =E7/$E$33 -> 0 | F38: =F7/$F$33 -> 0 | G38: =G7/$G$33 -> 0 | H38: =H7/$H$33 -> 0 | I38: =I7/$I$33 -> 0 | J38: =J7/$J$33 -> 0 | K38: =K7/$K$33 -> 0 | L38: =L7/$L$33 -> 11115.119 | M38: =M7/$M$33 -> 0 | N38: =SUM(B38:M38) -> 11115.119
A39: Denholm Fish Selling Ltd | B39: =B8/$B$33 -> 0 | C39: =C8/$C$33 -> 0 | D39: =D8/$D$33 -> 0 | E39: =E8/$E$33 -> 0 | F39: =F8/$F$33 -> 0 | G39: =G8/$G$33 -> 8377.9003 | H39: =H8/$H$33 -> 0 | I39: =I8/$I$33 -> 0 | J39: =J8/$J$33 -> 0 | K39: =K8/$K$33 -> 0 | L39: =L8/$L$33 -> 0 | M39: =M8/$M$33 -> 0 | N39: =SUM(B39:M39) -> 8377.9003
A40: DL Seeds | B40: =B9/$B$33 -> 0 | C40: =C9/$C$33 -> 0 | D40: =D9/$D$33 -> 0 | E40: =E9/$E$33 -> 0 | F40: =F9/$F$33 -> 6192.7422 | G40: =G9/$G$33 -> 0 | H40: =H9/$H$33 -> 0 | I40: =I9/$I$33 -> 0 | J40: =J9/$J$33 -> 0 | K40: =K9/$K$33 -> 0 | L40: =L9/$L$33 -> 0 | M40: =M9/$M$33 -> 0 | N40: =SUM(B40:M40) -> 6192.7422
A41: Dugdale Nutrition | B41: =B10/$B$33 -> 0 | C41: =C10/$C$33 -> 0 | D41: =D10/$D$33 -> 0 | E41: =E10/$E$33 -> 0 | F41: =F10/$F$33 -> 0 | G41: =G10/$G$33 -> 0 | H41: =H10/$H$33 -> 0 | I41: =I10/$I$33 -> 747.56692 | J41: =J10/$J$33 -> 0 | K41: =K10/$K$33 -> 0 | L41: =L10/$L$33 -> 0 | M41: =M10/$M$33 -> 0 | N41: =SUM(B41:M41) -> 747.56692
A42: Fram Farmers | B42: =B11/$B$33 -> 0 | C42: =C11/$C$33 -> 0 | D42: =D11/$D$33 -> 0 | E42: =E11/$E$33 -> 0 | F42: =F11/$F$33 -> 0 | G42: =G11/$G$33 -> 0 | H42: =H11/$H$33 -> 0 | I42: =I11/$I$33 -> 0 | J42: =J11/$J$33 -> 0 | K42: =K11/$K$33 -> 0 | L42: =L11/$L$33 -> 5020.9367 | M42: =M11/$M$33 -> 0 | N42: =SUM(B42:M42) -> 5020.9367
A43: G Williams Seeds | B43: =B12/$B$33 -> 0 | C43: =C12/$C$33 -> 0 | D43: =D12/$D$33 -> 0 | E43: =E12/$E$33 -> 1050.7562 | F43: =F12/$F$33 -> 0 | G43: =G12/$G$33 -> 0 | H43: =H12/$H$33 -> 0 | I43: =I12/$I$33 -> 0 | J43: =J12/$J$33 -> 0 | K43: =K12/$K$33 -> 0 | L43: =L12/$L$33 -> 0 | M43: =M12/$M$33 -> 0 | N43: =SUM(B43:M43) -> 1050.7562
A44: Glasson Grain | B44: =B13/$B$33 -> 0 | C44: =C13/$C$33 -> 0 | D44: =D13/$D$33 -> 0 | E44: =E13/$E$33 -> 0 | F44: =F13/$F$33 -> 0 | G44: =G13/$G$33 -> 5840.0115 | H44: =H13/$H$33 -> 0 | I44: =I13/$I$33 -> 0 | J44: =J13/$J$33 -> 0 | K44: =K13/$K$33 -> 0 | L44: =L13/$L$33 -> 0 | M44: =M13/$M$33 -> 0 | N44: =SUM(B44:M44) -> 5840.0115
A45: Grainco | B45: =B14/$B$33 -> 2346.8324 | C45: =C14/$C$33 -> 0 | D45: =D14/$D$33 -> 0 | E45: =E14/$E$33 -> 0 | F45: =F14/$F$33 -> 0 | G45: =G14/$G$33 -> 0 | H45: =H14/$H$33 -> 0 | I45: =I14/$I$33 -> 0 | J45: =J14/$J$33 -> 7554.328 | K45: =K14/$K$33 -> 0 | L45: =L14/$L$33 -> 0 | M45: =M14/$M$33 -> 0 | N45: =SUM(B45:M45) -> 9901.1603
A46: J Stobart & Sons | B46: =B15/$B$33 -> 0 | C46: =C15/$C$33 -> 0 | D46: =D15/$D$33 -> 0 | E46: =E15/$E$33 -> 0 | F46: =F15/$F$33 -> 0 | G46: =G15/$G$33 -> 0 | H46: =H15/$H$33 -> 0 | I46: =I15/$I$33 -> 0 | J46: =J15/$J$33 -> 733.07796 | K46: =K15/$K$33 -> 0 | L46: =L15/$L$33 -> 0 | M46: =M15/$M$33 -> 0 | N46: =SUM(B46:M46) -> 733.07796
... A53: West Gaines Seeds | B53: =B22/$B$33 -> 0 | C53: =C22/$C$33 -> 0 | D53: =D22/$D$33 -> 3274.912 | E53: =E22/$E$33 -> 0 | F53: =F22/$F$33 -> 0 | G53: =G22/$G$33 -> 0 | H53: =H22/$H$33 -> 0 | I53: =I22/$I$33 -> 0 | J53: =J22/$J$33 -> 8867.0565 | K53: =K22/$K$33 -> 0 | L53: =L22/$L$33 -> 14397.506 | M53: =M22/$M$33 -> 0 | N53: =SUM(B53:M53) -> 26539.474
N55: =SUM(N35:N54) -> 168655.36

Sheet Annual Maintenance
A1: Customer | B1: Location | C1: Annual Maintenance GBP | E1: Third Party Maintenance GBP | G1: Total Annual Maintenance GBP | J1: Own-authored Maintenance USD | L1: Third Party Maintenance USD | N1: Total Maintenance USD
A2: AB Agri | B2: UK | C2: =IFERROR(VLOOKUP(A2,'Own-Auth Maint'!$A$1:$N$34,14,FALSE),0) -> 86882.937 | D2: =IFERROR(VLOOKUP(B2,#REF!,8,FALSE),0) -> 0 | E2: =IFERROR(VLOOKUP(A2,'3rd Party Maint'!$A$2:$N$36,14,FALSE),0) -> 0 | G2: =E2+C2 -> 86882.937 | J2: =IFERROR(VLOOKUP(A2,'Own-Auth Maint'!$A$48:$N$80,14,FALSE),0) -> 114783.73 | L2: =IFERROR(VLOOKUP(A2,'3rd Party Maint'!$A$46:$N$79,14,FALSE),0) -> 0 | N2: =SUM(J2:L2) -> 114783.73
A3: Adams & Howling | B3: UK | C3: =IFERROR(VLOOKUP(A3,'Own-Auth Maint'!$A$1:$N$34,14,FALSE),0) -> 30682.274 | E3: =IFERROR(VLOOKUP(A3,'3rd Party Maint'!$A$2:$N$36,14,FALSE),0) -> 3969.0418 | G3: =E3+C3 -> 34651.316 | J3: =IFERROR(VLOOKUP(A3,'Own-Auth Maint'!$A$48:$N$80,14,FALSE),0) -> 40527.546 | L3: =IFERROR(VLOOKUP(A3,'3rd Party Maint'!$A$46:$N$79,14,FALSE),0) -> 5243.6805 | N3: =SUM(J3:L3) -> 45771.226
A4: ADM Direct | B4: UK | C4: =IFERROR(VLOOKUP(A4,'Own-Auth Maint'!$A$1:$N$34,14,FALSE),0) -> 24683.533 | E4: =IFERROR(VLOOKUP(A4,'3rd Party Maint'!$A$2:$N$36,14,FALSE),0) -> 0 | G4: =E4+C4 -> 24683.533 | J4: =IFERROR(VLOOKUP(A4,'Own-Auth Maint'!$A$48:$N$80,14,FALSE),0) -> 32178.468 | L4: =IFERROR(VLOOKUP(A4,'3rd Party Maint'!$A$46:$N$79,14,FALSE),0) -> 0 | N4: =SUM(J4:L4) -> 32178.468
A5: Banff & Moray Grain (Marketing) Ltd | B5: UK | C5: =IFERROR(VLOOKUP(A5,'Own-Auth Maint'!$A$1:$N$34,14,FALSE),0) -> 11904.123 | E5: =IFERROR(VLOOKUP(A5,'3rd Party Maint'!$A$2:$N$36,14,FALSE),0) -> 1232.98 | G5: =E5+C5 -> 13137.103 | J5: =IFERROR(VLOOKUP(A5,'Own-Auth Maint'!$A$48:$N$80,14,FALSE),0) -> 15724.28 | L5: =IFERROR(VLOOKUP(A5,'3rd Party Maint'!$A$46:$N$79,14,FALSE),0) -> 1628.6396 | N5: =SUM(J5:L5) -> 17352.92
A6: Barenbrug | B6: UK | C6: =IFERROR(VLOOKUP(A6,'Own-Auth Maint'!$A$1:$N$34,14,FALSE),0) -> 46946.94 | E6: =IFERROR(VLOOKUP(A6,'3rd Party Maint'!$A$2:$N$36,14,FALSE),0) -> 12144.93 | G6: =E6+C6 -> 59091.87 | J6: =IFERROR(VLOOKUP(A6,'Own-Auth Maint'!$A$48:$N$80,14,FALSE),0) -> 62002.612 | L6: =IFERROR(VLOOKUP(A6,'3rd Party Maint'!$A$46:$N$79,14,FALSE),0) -> 16039.536 | N6: =SUM(J6:L6) -> 78042.149
A7: Canterra Seeds | B7: Canada | C7: =IFERROR(VLOOKUP(A7,'Own-Auth Maint'!$A$1:$N$34,14,FALSE),0) -> 57590.68 | E7: =IFERROR(VLOOKUP(A7,'3rd Party Maint'!$A$2:$N$36,14,FALSE),0) -> 4504.5321 | G7: =E7+C7 -> 62095.212 | J7: =IFERROR(VLOOKUP(A7,'Own-Auth Maint'!$A$48:$N$80,14,FALSE),0) -> 76080.909 | L7: =IFERROR(VLOOKUP(A7,'3rd Party Maint'!$A$46:$N$79,14,FALSE),0) -> 5943.6282 | N7: =SUM(J7:L7) -> 82024.538
A8: COFCO International | B8: UK | C8: =IFERROR(VLOOKUP(A8,'Own-Auth Maint'!$A$1:$N$34,14,FALSE),0) -> 47578.364 | E8: =IFERROR(VLOOKUP(A8,'3rd Party Maint'!$A$2:$N$36,14,FALSE),0) -> 14951.252 | G8: =E8+C8 -> 62529.616 | J8: =IFERROR(VLOOKUP(A8,'Own-Auth Maint'!$A$48:$N$80,14,FALSE),0) -> 62837.171 | L8: =IFERROR(VLOOKUP(A8,'3rd Party Maint'!$A$46:$N$79,14,FALSE),0) -> 19742.815 | N8: =SUM(J8:L8) -> 82579.986
A9: Denholm Fish Selling Ltd | B9: UK | C9: =IFERROR(VLOOKUP(A9,'Own-Auth Maint'!$A$1:$N$34,14,FALSE),0) -> 54643.369 | E9: =IFERROR(VLOOKUP(A9,'3rd Party Maint'!$A$2:$N$36,14,FALSE),0) -> 909.95438 | G9: =E9+C9 -> 55553.323 | J9: =IFERROR(VLOOKUP(A9,'Own-Auth Maint'!$A$48:$N$80,14,FALSE),0) -> 72194.428 | L9: =IFERROR(VLOOKUP(A9,'3rd Party Maint'!$A$46:$N$79,14,FALSE),0) -> 1189.6497 | N9: =SUM(J9:L9) -> 73384.077
A10: DL Seeds | B10: Canada | C10: =IFERROR(VLOOKUP(A10,'Own-Auth Maint'!$A$1:$N$34,14,FALSE),0) -> 6370.3005 | E10: =IFERROR(VLOOKUP(A10,'3rd Party Maint'!$A$2:$N$36,14,FALSE),0) -> 2638.0638 | G10: =E10+C10 -> 9008.3644 | J10: =IFERROR(VLOOKUP(A10,'Own-Auth Maint'!$A$48:$N$80,14,FALSE),0) -> 8212.1165 | L10: =IFERROR(VLOOKUP(A10,'3rd Party Maint'!$A$46:$N$79,14,FALSE),0) -> 3486.2254 | N10: =SUM(J10:L10) -> 11698.342
A11: Dugdale Nutrition | B11: UK | C11: =IFERROR(VLOOKUP(A11,'Own-Auth Maint'!$A$1:$N$34,14,FALSE),0) -> 53749.571 | E11: =IFERROR(VLOOKUP(A11,'3rd Party Maint'!$A$2:$N$36,14,FALSE),0) -> 10604.899 | G11: =E11+C11 -> 64354.47 | J11: =IFERROR(VLOOKUP(A11,'Own-Auth Maint'!$A$48:$N$80,14,FALSE),0) -> 71000.327 | L11: =IFERROR(VLOOKUP(A11,'3rd Party Maint'!$A$46:$N$79,14,FALSE),0) -> 14005.139 | N11: =SUM(J11:L11) -> 85005.466
A12: E B Bradshaws | B12: UK | C12: =IFERROR(VLOOKUP(A12,'Own-Auth Maint'!$A$1:$N$34,14,FALSE),0) -> 0 | E12: =IFERROR(VLOOKUP(A12,'3rd Party Maint'!$A$2:$N$36,14,FALSE),0) -> 0 | G12: =E12+C12 -> 0 | J12: =IFERROR(VLOOKUP(A12,'Own-Auth Maint'!$A$48:$N$80,14,FALSE),0) -> 0 | L12: =IFERROR(VLOOKUP(A12,'3rd Party Maint'!$A$46:$N$79,14,FALSE),0) -> 0 | N12: =SUM(J12:L12) -> 0
A13: Elevator | B13: UK | C13: =IFERROR(VLOOKUP(A13,'Own-Auth Maint'!$A$1:$N$34,14,FALSE),0) -> 896.41646 | E13: =IFERROR(VLOOKUP(A13,'3rd Party Maint'!$A$2:$N$36,14,FALSE),0) -> 9986.0364 | G13: =E13+C13 -> 10882.453 | J13: =IFERROR(VLOOKUP(A13,'Own-Auth Maint'!$A$48:$N$80,14,FALSE),0) -> 1183.974 | L13: =IFERROR(VLOOKUP(A13,'3rd Party Maint'!$A$46:$N$79,14,FALSE),0) -> 13187.673 | N13: =SUM(J13:L13) -> 14371.647
A14: Fengrain Ltd | B14: UK | C14: =IFERROR(VLOOKUP(A14,'Own-Auth Maint'!$A$1:$N$34,14,FALSE),0) -> 0 | E14: =IFERROR(VLOOKUP(A14,'3rd Party Maint'!$A$2:$N$36,14,FALSE),0) -> 0 | G14: =E14+C14 -> 0 | J14: =IFERROR(VLOOKUP(A14,'Own-Auth Maint'!$A$48:$N$80,14,FALSE),0) -> 0 | L14: =IFERROR(VLOOKUP(A14,'3rd Party Maint'!$A$46:$N$79,14,FALSE),0) -> 0 | N14: =SUM(J14:L14) -> 0
... A41: Wynnstay Group | B41: UK | C41: =IFERROR(VLOOKUP(A41,'Own-Auth Maint'!$A$1:$N$34,14,FALSE),0) -> 59073.484 | E41: =IFERROR(VLOOKUP(A41,'3rd Party Maint'!$A$2:$N$36,14,FALSE),0) -> 109630.69 | G41: =E41+C41 -> 168704.17 | J41: =IFERROR(VLOOKUP(A41,'Own-Auth Maint'!$A$48:$N$80,14,FALSE),0) -> 77980.481 | L41: =IFERROR(VLOOKUP(A41,'3rd Party Maint'!$A$46:$N$79,14,FALSE),0) -> 144804.27 | N41: =SUM(J41:L41) -> 222784.75
E42: =IFERROR(VLOOKUP(A42,'3rd Party Maint'!#REF!,8,FALSE),0) -> 0 | J42: =IFERROR(VLOOKUP(A42,'Own-Auth Maint'!$A$48:$N$80,14,FALSE),0) -> 0
C43: =SUM(C2:C42) -> 4240482.9 | D43: =SUM(D2:D42) -> 0 | E43: =SUM(E2:E42) -> 708933.64 | G43: =SUM(G2:G42) -> 4949416.5 | J43: =SUM(J2:J42) -> 5600423.2 | L43: =SUM(L2:L42) -> 936381.74 | N43: =SUM(N2:N42) -> 6536804.9

Sheet Own-Auth Maint
A1: Row Labels | B1: Sum of Jan-25 | C1: Sum of Feb-25 | D1: Sum of Mar-25 | E1: Sum of Apr-25 | F1: Sum of May-25 | G1: Sum of Jun-25 | H1: Sum of Jul-25 | I1: Sum of Aug-25 | J1: Sum of Sep-25 | K1: Sum of Oct-25 | L1: Sum of Nov-25 | M1: Sum of Dec-25 | N1: Sum of Total Income 2025
A2: AB Agri | B2: 7147.8356 | C2: 6456.1096 | D2: 7407.6069 | E2: 7185.9692 | F2: 7425.5015 | G2: 7185.9692 | H2: 7425.5015 | I2: 7425.5015 | J2: 7185.9692 | K2: 7425.5015 | L2: 7185.9692 | M2: 7425.5015 | N2: 86882.937
A3: Adams & Howling | B3: 2546.1237 | C3: 2299.7246 | D3: 2546.1237 | E3: 2463.9907 | F3: 2546.1237 | G3: 2381.86 | H3: 2678.5226 | I3: 2678.5226 | J3: 2592.1187 | K3: 2678.5226 | L3: 2592.1187 | M3: 2678.5226 | N3: 30682.274
A4: ADM Direct | B4: 4227.5662 | C4: 3818.4469 | D4: 4227.5662 | E4: 4091.1931 | F4: 8318.76 | N4: 24683.533
A5: Banff & Moray Grain (Marketing) Ltd | B5: 983.65385 | C5: 888.46154 | D5: 983.65385 | E5: 951.92308 | F5: 983.65385 | G5: 951.92308 | H5: 983.65385 | I5: 951.92 | J5: 1019.8451 | K5: 1080.0922 | L5: 1045.2505 | M5: 1080.0922 | N5: 11904.123
A6: Barenbrug | B6: 3833.9 | C6: 3833.9 | D6: 3833.9 | E6: 3833.9 | F6: 3833.9 | G6: 3833.9 | H6: 3990.59 | I6: 3990.59 | J6: 3990.59 | K6: 3990.59 | L6: 3990.59 | M6: 3990.59 | N6: 46946.94
A7: Canterra Seeds | B7: 4764.6477 | C7: 4307.7636 | D7: 4822.5847 | E7: 4684.6434 | F7: 4850.1902 | G7: 4693.7324 | H7: 4852.2527 | I7: 4914.1285 | J7: 4755.6083 | K7: 4919.9554 | L7: 4930.4131 | M7: 5094.7603 | N7: 57590.68
A8: COFCO International | B8: 4004.2921 | C8: 3616.78 | D8: 4004.2921 | E8: 3875.1214 | F8: 4004.2921 | G8: 3875.1214 | H8: 4004.2921 | I8: 4004.2921 | J8: 3745.95 | K8: 4193.0634 | L8: 4057.8033 | M8: 4193.0634 | N8: 47578.364
A9: Denholm Fish Selling Ltd | B9: 4514.6325 | C9: 4077.7326 | D9: 4519.8505 | E9: 4525.5157 | F9: 4676.3662 | G9: 4525.5157 | H9: 4676.3662 | I9: 4676.3662 | J9: 4525.5157 | K9: 4676.3662 | L9: 4525.5157 | M9: 4723.6257 | N9: 54643.369
A10: DL Seeds | B10: 1473.7272 | C10: 1331.1085 | D10: 1473.7272 | E10: 1426.1876 | F10: 665.55 | N10: 6370.3005
A11: Dugdale Nutrition | B11: 4418.6972 | C11: 4123.4823 | D11: 4565.284 | E11: 4418.0168 | F11: 4565.284 | G11: 4418.0168 | H11: 4572.4204 | I11: 4592.9376 | J11: 4444.7783 | K11: 4592.9376 | L11: 4444.7783 | M11: 4592.9376 | N11: 53749.571
A12: Elevator | B12: 76.025797 | C12: 68.668462 | D12: 76.025797 | E12: 73.573352 | F12: 76.025797 | G12: 73.573352 | H12: 76.025797 | I12: 76.025797 | J12: 73.573352 | K12: 76.025797 | L12: 71.350495 | M12: 79.522665 | N12: 896.41646
A13: Fram Farmers | B13: 2268.5766 | C13: 2049.0369 | D13: 2268.5766 | E13: 2195.3967 | F13: 2268.5766 | G13: 2123.26 | H13: 2539.302 | I13: 2539.302 | J13: 2457.389 | K13: 2539.302 | L13: 2457.389 | M13: 2539.302 | N13: 28245.409
A14: Frontier Agriculture | B14: 125277.13 | C14: 112293.32 | D14: 124324.75 | E14: 120314.27 | F14: 124324.75 | G14: 120314.27 | H14: 124324.75 | I14: 124324.75 | J14: 120314.27 | K14: 124324.75 | L14: 120314.27 | M14: 119361.89 | N14: 1459813.2
A15: G Williams Seeds | B15: 1451.2034 | C15: 1310.7644 | D15: 1451.2034 | E15: 1435.3057 | F15: 1507.5768 | G15: 1458.9453 | H15: 1507.5768 | I15: 1507.5768 | J15: 1458.9453 | K15: 1507.5768 | L15: 1458.9453 | M15: 1507.5768 | N15: 17563.197
A16: Glasson Grain | B16: 6850.3237 | C16: 6187.3892 | D16: 6850.3237 | E16: 6629.3455 | F16: 6850.3237 | G16: 6629.3455 | H16: 6850.3237 | I16: 7665.09 | J16: 6784.8824 | K16: 7011.0452 | L16: 6784.8824 | M16: 7011.0452 | N16: 82104.32
A17: Gover Horowitz | B17: 717.04533 | C17: 647.65385 | D17: 717.04533 | E17: 693.91484 | F17: 717.04533 | G17: 672.26132 | H17: 739.99044 | I17: 739.99044 | J17: 716.11978 | K17: 739.99044 | L17: 716.11978 | M17: 739.99044 | N17: 8557.1673
A18: Grainco | B18: 6619.4777 | C18: 5978.8831 | D18: 6619.4777 | E18: 6405.9462 | F18: 6619.4777 | G18: 6413.0827 | H18: 6663.724 | I18: 6663.724 | J18: 6448.7652 | K18: 6643.0232 | L18: 6492.435 | M18: 6518.9256 | N18: 78086.942
A19: H J Lea | B19: 6433.2571 | C19: 5810.6838 | D19: 6433.2571 | E19: 6225.7327 | F19: 6433.2571 | G19: 6225.7327 | H19: 6433.2571 | I19: 6433.2571 | J19: 1444.8958 | K19: 6714.7209 | L19: 6498.117 | M19: 6718.7351 | N19: 71804.904
A20: Harlow Agriculture | B20: 6532.7404 | C20: 5900.5397 | D20: 6532.7404 | E20: 6322.0068 | F20: 6532.7404 | G20: 6322.0068 | H20: 6629.9863 | I20: 6963.381 | J20: 6738.7558 | K20: 6963.381 | L20: 6738.7558 | M20: 6963.381 | N20: 79140.415
A21: Humphrey Feeds | E21: 9496.9286 | F21: 2453.3732 | G21: 2374.2321 | H21: 2453.3732 | I21: 2453.3732 | J21: 2374.2321 | K21: 2453.3732 | L21: 2374.2321 | M21: 2374.23 | N21: 28807.348
A22: J Stobart & Sons | B22: 864.28341 | C22: 752.76 | D22: 895.16673 | E22: 866.29038 | F22: 895.16673 | G22: 866.29038 | H22: 895.16673 | I22: 895.16673 | J22: 866.29038 | K22: 895.16673 | L22: 866.29038 | M22: 895.16673 | N22: 10453.205
A23: London Metals Ltd | B23: 1824.1473 | C23: 1647.6169 | D23: 1824.1473 | E23: 1765.3038 | F23: 1824.1473 | G23: 1765.3038 | H23: 1824.1473 | I23: 1824.1473 | J23: 1709.288 | K23: 1911.707 | L23: 1850.039 | M23: 1911.707 | N23: 21681.702
A24: North Herts Farmers | B24: 1286.9693 | C24: 1162.4238 | D24: 1286.9693 | E24: 1232.9617 | F24: 1334.3243 | G24: 1291.2816 | H24: 1334.3243 | I24: 1334.3243 | J24: 1291.2816 | K24: 1334.3243 | L24: 1291.2816 | M24: 1334.3243 | N24: 15514.79
A25: Openfield | B25: 61026.317 | C25: 55161.118 | D25: 61332.838 | E25: 59469.671 | F25: 61639.552 | G25: 59556.911 | H25: 59996.768 | I25: 63788.117 | J25: 61810.401 | K25: 63982.621 | L25: 62295.947 | M25: 64445.924 | N25: 734506.18
A26: Oxbow Coal | B26: 14019.169 | C26: 12662.475 | D26: 14019.169 | E26: 13566.938 | F26: 14019.169 | G26: 13566.938 | H26: 14019.169 | I26: 14019.169 | J26: 13566.938 | K26: 14019.169 | L26: 13566.938 | M26: 13566.94 | N26: 164612.18
A27: Pearce Seeds | B27: 1318.68 | C27: 1318.68 | D27: 1318.68 | E27: 1318.68 | F27: 1318.68 | G27: 1318.68 | H27: 1318.68 | N27: 9230.76
A28: Robin Appel | B28: 3597.6865 | C28: 3422.9746 | D28: 3789.7219 | E28: 3667.4728 | F28: 3789.7219 | G28: 3667.4728 | H28: 3733.2854 | I28: 3736.7448 | J28: 3640.3761 | K28: 3761.7219 | L28: 3640.3761 | M28: 3761.7219 | N28: 44209.277
A29: Saxon Agriculture | B29: 8549.9262 | C29: 7752.6103 | D29: 8864.3166 | E29: 8947.0624 | F29: 9388.0949 | G29: 9377.9524 | H29: 9701.2837 | I29: 9701.2837 | J29: 9463.6702 | K29: 9868.0884 | L29: 9549.763 | M29: 9868.0884 | N29: 111032.14
A30: Scott & Newman | B30: 1144.0686 | C30: 1033.3523 | D30: 1140.9993 | E30: 1146.2069 | F30: 1184.4138 | G30: 1146.2069 | H30: 1184.4138 | I30: 1184.4138 | J30: 1146.2069 | K30: 1184.4138 | L30: 1146.2069 | M30: 1184.4138 | N30: 13825.317
A31: Simpsons Malt | B31: 21793.55 | C31: 19774.111 | D31: 21905.88 | E31: 21225.791 | F31: 21933.318 | G31: 21227.809 | H31: 21995.871 | I31: 22030.914 | J31: 21423.406 | K31: 22203.904 | L31: 21630.426 | M31: 22480.535 | N31: 259625.52
A32: WCF | B32: 5358.9862 | C32: 4840.3746 | D32: 5186.1168 | E32: 5186.1157 | F32: 5358.9862 | G32: 5186.1157 | H32: 5358.9862 | I32: 5358.9862 | J32: 5186.1157 | K32: 5358.9862 | L32: 5186.1157 | M32: 5358.9862 | N32: 62924.871
A33: West Gaines Seeds | B33: 39159.455 | C33: 35369.83 | D33: 39159.455 | E33: 37969.249 | F33: 38033.12 | G33: 37504.49 | H33: 38819.507 | I33: 38819.507 | J33: 37607.14 | K33: 38851.203 | L33: 37597.938 | M33: 38851.203 | N33: 457742.1
A34: Wynnstay Group | B34: 5189.3968 | C34: 4719.8248 | D34: 5140.7513 | E34: 4802.5648 | F34: 4962.6503 | G34: 4802.5648 | H34: 4962.6503 | I34: 4962.6503 | J34: 4802.5648 | K34: 4962.6503 | L34: 4802.5648 | M34: 4962.6503 | N34: 59073.484
A35: Grand Total | B35: 359273.49 | C35: 324618.6 | D35: 359522.2 | E35: 358413.19 | F35: 365334.11 | G35: 345750.77 | H35: 356546.16 | I35: 360256.15 | J35: 343585.88 | K35: 360864.17 | L35: 350102.82 | M35: 356215.35 | N35: 4240482.9
B36: 359273 | C36: 324619 | D36: 359522 | E36: 358413 | F36: 365334 | G36: 345751 | H36: 356546 | I36: 360256 | J36: 343586 | K36: 360864 | L36: 350103 | M36: 356215
B37: =B36-GETPIVOTDATA("Sum of Jan-25",$A$1) -> -0.4932039 | C37: =C36-GETPIVOTDATA("Sum of Feb-25",$A$1) -> 0.39905961 | D37: =D36-GETPIVOTDATA("Sum of Mar-25",$A$1) -> -0.19749881 | E37: =E36-GETPIVOTDATA("Sum of Apr-25",$A$1) -> -0.19021944 | F37: =F36-GETPIVOTDATA("Sum of May-25",$A$1) -> -0.10967225 | G37: =G36-GETPIVOTDATA("Sum of Jun-25",$A$1) -> 0.23400374 | H37: =H36-GETPIVOTDATA("Sum of Jul-25",$A$1) -> -0.15887566 | I37: =I36-GETPIVOTDATA("Sum of Aug-25",$A$1) -> -0.14985063 | J37: =J36-GETPIVOTDATA("Sum of Sep-25",$A$1) -> 0.11505362 | K37: =K36-GETPIVOTDATA("Sum of Oct-25",$A$1) -> -0.16978617 | L37: =L36-GETPIVOTDATA("Sum of Nov-25",$A$1) -> 0.1757258 | M37: =M36-GETPIVOTDATA("Sum of Dec-25",$A$1) -> -0.35339139
A46: FX RATE | B46: 0.80549 | C46: 0.79437 | D46: 0.77312 | E46: 0.74848 | F46: 0.74348 | G46: 0.72924 | H46: 0.75575 | I46: 0.74083 | J46: 0.744 | K46: 0.76108 | L46: 0.75609 | M46: 0.74322
A48: AB Agri | B48: =B2/$B$46 -> 8873.8974 | C48: =C2/$C$46 -> 8127.3331 | D48: =D2/$D$46 -> 9581.4452 | E48: =E2/$E$46 -> 9600.7498 | F48: =F2/$F$46 -> 9987.4933 | G48: =G2/$G$46 -> 9854.0525 | H48: =H2/$H$46 -> 9825.3411 | I48: =I2/$I$46 -> 10023.219 | J48: =J2/$J$46 -> 9658.5608 | K48: =K2/$K$46 -> 9756.5322 | L48: =L2/$L$46 -> 9504.1189 | M48: =M2/$M$46 -> 9990.9872 | N48: =SUM(B48:M48) -> 114783.73
A49: Adams & Howling | B49: =B3/$B$46 -> 3160.9625 | C49: =C3/$C$46 -> 2895.0295 | D49: =D3/$D$46 -> 3293.3098 | E49: =E3/$E$46 -> 3291.9927 | F49: =F3/$F$46 -> 3424.6028 | G49: =G3/$G$46 -> 3266.2224 | H49: =H3/$H$46 -> 3544.1914 | I49: =I3/$I$46 -> 3615.5699 | J49: =J3/$J$46 -> 3484.0305 | K49: =K3/$K$46 -> 3519.3707 | L49: =L3/$L$46 -> 3428.3203 | M49: =M3/$M$46 -> 3603.9432 | N49: =SUM(B49:M49) -> 40527.546
A50: ADM Direct | B50: =B4/$B$46 -> 5248.4404 | C50: =C4/$C$46 -> 4806.8871 | D50: =D4/$D$46 -> 5468.1889 | E50: =E4/$E$46 -> 5466.0019 | F50: =F4/$F$46 -> 11188.949 | G50: =G4/$G$46 -> 0 | H50: =H4/$H$46 -> 0 | I50: =I4/$I$46 -> 0 | J50: =J4/$J$46 -> 0 | K50: =K4/$K$46 -> 0 | L50: =L4/$L$46 -> 0 | M50: =M4/$M$46 -> 0 | N50: =SUM(B50:M50) -> 32178.468
A51: Banff & Moray Grain (Marketing) Ltd | B51: =B5/$B$46 -> 1221.1869 | C51: =C5/$C$46 -> 1118.448 | D51: =D5/$D$46 -> 1272.3172 | E51: =E5/$E$46 -> 1271.8083 | F51: =F5/$F$46 -> 1323.0401 | G51: =G5/$G$46 -> 1305.3632 | H51: =H5/$H$46 -> 1301.5598 | I51: =I5/$I$46 -> 1284.9372 | J51: =J5/$J$46 -> 1370.7596 | K51: =K5/$K$46 -> 1419.1573 | L51: =L5/$L$46 -> 1382.442 | M51: =M5/$M$46 -> 1453.2604 | N51: =SUM(B51:M51) -> 15724.28
A52: Barenbrug | B52: =B6/$B$46 -> 4759.7115 | C52: =C6/$C$46 -> 4826.3404 | D52: =D6/$D$46 -> 4958.9973 | E52: =E6/$E$46 -> 5122.2478 | F52: =F6/$F$46 -> 5156.6955 | G52: =G6/$G$46 -> 5257.3913 | H52: =H6/$H$46 -> 5280.3043 | I52: =I6/$I$46 -> 5386.6474 | J52: =J6/$J$46 -> 5363.6962 | K52: =K6/$K$46 -> 5243.3253 | L52: =L6/$L$46 -> 5277.9299 | M52: =M6/$M$46 -> 5369.3254 | N52: =SUM(B52:M52) -> 62002.612
A53: Canterra Seeds | B53: =B7/$B$46 -> 5915.2164 | C53: =C7/$C$46 -> 5422.868 | D53: =D7/$D$46 -> 6237.8217 | E53: =E7/$E$46 -> 6258.8758 | F53: =F7/$F$46 -> 6523.6323 | G53: =G7/$G$46 -> 6436.4714 | H53: =H7/$H$46 -> 6420.4468 | I53: =I7/$I$46 -> 6633.2742 | J53: =J7/$J$46 -> 6391.9466 | K53: =K7/$K$46 -> 6464.4392 | L53: =L7/$L$46 -> 6520.9342 | M53: =M7/$M$46 -> 6854.9827 | N53: =SUM(B53:M53) -> 76080.909
A54: COFCO International | B54: =B8/$B$46 -> 4971.25 | C54: =C8/$C$46 -> 4553.0169 | D54: =D8/$D$46 -> 5179.3928 | E54: =E8/$E$46 -> 5177.3213 | F54: =F8/$F$46 -> 5385.8774 | G54: =G8/$G$46 -> 5313.9178 | H54: =H8/$H$46 -> 5298.4349 | I54: =I8/$I$46 -> 5405.1431 | J54: =J8/$J$46 -> 5034.879 | K54: =K8/$K$46 -> 5509.3596 | L54: =L8/$L$46 -> 5366.8258 | M54: =M8/$M$46 -> 5641.7527 | N54: =SUM(B54:M54) -> 62837.171
A55: Denholm Fish Selling Ltd | B55: =B9/$B$46 -> 5604.8275 | C55: =C9/$C$46 -> 5133.2912 | D55: =D9/$D$46 -> 5846.2471 | E55: =E9/$E$46 -> 6046.2747 | F55: =F9/$F$46 -> 6289.8345 | G55: =G9/$G$46 -> 6205.7973 | H55: =H9/$H$46 -> 6187.7158 | I55: =I9/$I$46 -> 6312.3337 | J55: =J9/$J$46 -> 6082.6823 | K55: =K9/$K$46 -> 6144.3819 | L55: =L9/$L$46 -> 5985.4193 | M55: =M9/$M$46 -> 6355.6225 | N55: =SUM(B55:M55) -> 72194.428
A56: DL Seeds | B56: =B10/$B$46 -> 1829.6034 | C56: =C10/$C$46 -> 1675.6782 | D56: =D10/$D$46 -> 1906.2076 | E56: =E10/$E$46 -> 1905.4452 | F56: =F10/$F$46 -> 895.18212 | G56: =G10/$G$46 -> 0 | H56: =H10/$H$46 -> 0 | I56: =I10/$I$46 -> 0 | J56: =J10/$J$46 -> 0 | K56: =K10/$K$46 -> 0 | L56: =L10/$L$46 -> 0 | M56: =M10/$M$46 -> 0 | N56: =SUM(B56:M56) -> 8212.1165
A57: Dugdale Nutrition | B57: =B11/$B$46 -> 5485.7257 | C57: =C11/$C$46 -> 5190.8837 | D57: =D11/$D$46 -> 5905.0134 | E57: =E11/$E$46 -> 5902.6517 | F57: =F11/$F$46 -> 6140.4261 | G57: =G11/$G$46 -> 6058.3851 | H57: =H11/$H$46 -> 6050.1759 | I57: =I11/$I$46 -> 6199.7187 | J57: =J11/$J$46 -> 5974.1644 | K57: =K11/$K$46 -> 6034.7633 | L57: =L11/$L$46 -> 5878.6366 | M57: =M11/$M$46 -> 6179.782 | N57: =SUM(B57:M57) -> 71000.327
A58: Elevator | B58: =B12/$B$46 -> 94.384532 | C58: =C12/$C$46 -> 86.443926 | D58: =D12/$D$46 -> 98.336347 | E58: =E12/$E$46 -> 98.297017 | F58: =F12/$F$46 -> 102.25668 | G58: =G12/$G$46 -> 100.89045 | H58: =H12/$H$46 -> 100.59649 | I58: =I12/$I$46 -> 102.62246 | J58: =J12/$J$46 -> 98.888914 | K58: =K12/$K$46 -> 99.891991 | L58: =L12/$L$46 -> 94.367727 | M58: =M12/$M$46 -> 106.99748 | N58: =SUM(B58:M58) -> 1183.974
A59: Fram Farmers | B59: =B13/$B$46 -> 2816.3932 | C59: =C13/$C$46 -> 2579.449 | D59: =D13/$D$46 -> 2934.3137 | E59: =E13/$E$46 -> 2933.1401 | F59: =F13/$F$46 -> 3051.2947 | G59: =G13/$G$46 -> 2911.6066 | H59: =H13/$H$46 -> 3359.9762 | I59: =I13/$I$46 -> 3427.6446 | J59: =J13/$J$46 -> 3302.9422 | K59: =K13/$K$46 -> 3336.4455 | L59: =L13/$L$46 -> 3250.1276 | M59: =M13/$M$46 -> 3416.6222 | N59: =SUM(B59:M59) -> 37319.956
... A80: Wynnstay Group | B80: =B34/$B$46 -> 6442.5341 | C80: =C34/$C$46 -> 5941.595 | D80: =D34/$D$46 -> 6649.3576 | E80: =E34/$E$46 -> 6416.4237 | F80: =F34/$F$46 -> 6674.8942 | G80: =G34/$G$46 -> 6585.7123 | H80: =H34/$H$46 -> 6566.5238 | I80: =I34/$I$46 -> 6698.7707 | J80: =J34/$J$46 -> 6455.0603 | K80: =K34/$K$46 -> 6520.537 | L80: =L34/$L$46 -> 6351.8428 | M80: =M34/$M$46 -> 6677.2293 | N80: =SUM(B80:M80) -> 77980.481
A81: =A35 -> Grand Total | B81: =B35/$B$46 -> 446030.98 | C81: =C35/$C$46 -> 408649.12 | D81: =D35/$D$46 -> 465027.68 | E81: =E35/$E$46 -> 478854.73 | F81: =F35/$F$46 -> 491383.91 | G81: =G35/$G$46 -> 474124.8 | H81: =H35/$H$46 -> 471777.91 | I81: =I35/$I$46 -> 486287.2 | J81: =J35/J$46 -> 461808.99 | K81: =K35/$K$46 -> 474147.49 | L81: =L35/$L$46 -> 463043.85 | M81: =SUM(B81:L81) -> 5121136.7
N82: =SUM(N48:N81) -> 5600423.2

Sheet 3rd Party Maint
A1: Row Labels | B1: Sum of Jan-25 | C1: Sum of Feb-25 | D1: Sum of Mar-25 | E1: Sum of Apr-25 | F1: Sum of May-25 | G1: Sum of Jun-25 | H1: Sum of Jul-25 | I1: Sum of Aug-25 | J1: Sum of Sep-25 | K1: Sum of Oct-25 | L1: Sum of Nov-25 | M1: Sum of Dec-25 | N1: Sum of Total Income 2025
A2: Adams & Howling | B2: 329.31538 | C2: 308.06923 | D2: 308.07 | E2: 329.84588 | F2: 340.84074 | G2: 329.84588 | H2: 340.84074 | I2: 340.84074 | J2: 329.84588 | K2: 340.84074 | L2: 329.84588 | M2: 340.84074 | N2: 3969.0418
A3: Banff & Moray Grain (Marketing) Ltd | B3: 102.4533 | C3: 95.843407 | D3: 102.4533 | E3: 93.3675 | F3: 106.14179 | G3: 102.71786 | H3: 106.14179 | I3: 106.14179 | J3: 102.71786 | K3: 106.14179 | L3: 102.71786 | M3: 106.14179 | N3: 1232.98
A4: Barenbrug | B4: 999.78931 | C4: 960.2147 | D4: 1026.4364 | E4: 993.32555 | F4: 1026.4364 | G4: 993.32555 | H4: 1026.4364 | I4: 1026.4364 | J4: 956.57786 | K4: 1056.6793 | L4: 1022.5929 | M4: 1056.6793 | N4: 12144.93
A5: Canterra Seeds | B5: 436.15956 | C5: 352.18747 | D5: 376.47626 | E5: 364.33187 | F5: 376.47626 | G5: 364.33187 | H5: 376.47626 | I5: 376.47626 | J5: 364.33187 | K5: 376.47626 | L5: 364.33187 | M5: 376.47626 | N5: 4504.5321
A6: COFCO International | B6: 1258.0584 | C6: 1176.8933 | D6: 1258.0584 | E6: 1217.4758 | F6: 1258.0584 | G6: 1217.4758 | H6: 1258.0584 | I6: 1258.0584 | J6: 1136.31 | K6: 1318.4453 | L6: 1275.9148 | M6: 1318.4453 | N6: 14951.252
A7: Confluence Genetics | N7: 0
A8: Denholm Fish Selling Ltd | B8: 155.84932 | C8: 145.79452 | D8: 155.84932 | E8: 150.82192 | F8: 155.84932 | G8: 145.79 | N8: 909.95438
A9: DL Seeds | B9: 258.72645 | C9: 242.03442 | D9: 258.72645 | E9: 70.737418 | F9: 9.5023562 | G9: 547.8526 | H9: 210.6794 | I9: 210.6794 | J9: 203.88329 | K9: 210.6794 | L9: 203.88329 | M9: 210.6794 | N9: 2638.0638
A10: Dugdale Nutrition | B10: 886.52732 | C10: 833.3511 | D10: 890.82359 | E10: 862.08735 | F10: 886.71255 | G10: 864.56482 | H10: 893.38365 | I10: 876.65027 | J10: 887.90136 | K10: 917.49807 | L10: 887.90136 | M10: 917.49807 | N10: 10604.899
A11: Elevator | B11: 846.92681 | C11: 792.28637 | D11: 846.92681 | E11: 819.60659 | F11: 846.92681 | G11: 819.60659 | H11: 846.92681 | I11: 846.92681 | J11: 819.60659 | K11: 846.92681 | L11: 767.4839 | M11: 885.88547 | N11: 9986.0364
A12: Fram Farmers | B12: 103.28621 | C12: 96.622582 | D12: 103.28621 | E12: 99.954396 | F12: 103.28621 | G12: 99.954396 | H12: 103.28621 | I12: 103.28621 | J12: 99.954396 | K12: 103.28621 | L12: 99.954396 | M12: 98.724615 | N12: 1214.882
A13: Frontier Agriculture | B13: 16167.758 | C13: 15164.099 | D13: 15231.226 | E13: 16509.087 | F13: 17059.389 | G13: 16509.087 | H13: 17059.389 | I13: 17059.389 | J13: 16509.08 | K13: 17059.39 | L13: 16509.08 | M13: 17059.39 | N13: 197896.37
A14: G Williams Seeds | B14: 267.2481 | C14: 250.00629 | D14: 267.2481 | E14: 241.11022 | F14: 276.86918 | G14: 267.93791 | H14: 276.86918 | I14: 276.86918 | J14: 267.93791 | K14: 276.86918 | L14: 267.93791 | M14: 276.86918 | N14: 3213.7723
A15: Glasson Grain | B15: 1347.8738 | C15: 1260.9142 | D15: 1347.8738 | E15: 1304.394 | F15: 1347.8738 | G15: 1199.311 | H15: 1406.2423 | I15: 1405.3215 | J15: 1347.0305 | K15: 1391.9315 | L15: 1342.763 | M15: 1396.5773 | N15: 16098.107
A16: Gover Horowitz | B16: 152.05967 | C16: 142.24937 | D16: 152.05967 | E16: 147.15452 | F16: 152.05967 | G16: 142.67216 | H16: 158.59855 | I16: 158.59855 | J16: 153.48247 | K16: 158.59855 | L16: 153.48247 | M16: 158.59855 | N16: 1829.6142
A17: Grainco | B17: 1391.1071 | C17: 1301.3583 | D17: 1391.1071 | E17: 1346.2327 | F17: 1391.1071 | G17: 1346.2327 | H17: 1382.2803 | I17: 1397.4059 | J17: 1337.3273 | K17: 1418.8751 | L17: 1373.1049 | M17: 1367.0176 | N17: 16443.156
A18: H J Lea | B18: 852.74698 | C18: 797.73104 | D18: 852.74698 | E18: 825.23901 | F18: 852.74698 | G18: 825.23901 | H18: 807.63659 | I18: 891.12055 | J18: 862.37473 | K18: 891.12055 | L18: 862.37473 | M18: 891.12055 | N18: 10212.198
A19: Harlow Agriculture | B19: 1105.4438 | C19: 1034.1249 | D19: 1105.4438 | E19: 1069.7843 | F19: 1105.4438 | G19: 1069.7843 | H19: 1057.9298 | I19: 1094.5972 | J19: 1059.2876 | K19: 1091.672 | L19: 1061.7626 | M19: 1097.1547 | N19: 12952.429
A20: Humphrey Feeds | B20: 640.55003 | C20: 572.75239 | D20: 664.79074 | E20: 643.34588 | F20: 664.79074 | G20: 643.34588 | H20: 664.79074 | I20: 664.79074 | J20: 643.34588 | K20: 664.79074 | L20: 643.34588 | M20: 664.79074 | N20: 7775.4304
A21: Integra Petrochemicals | B21: 1062.6936 | C21: 994.13275 | D21: 1062.6936 | E21: 1028.4132 | F21: 1062.6936 | G21: 171.4 | H21: 1932.5947 | I21: 1109.4525 | J21: 1073.6637 | K21: 1109.4525 | L21: 1073.6637 | M21: 1109.4525 | N21: 12790.307
A22: J E Porter | B22: 10.295577 | C22: 9.6313462 | D22: 10.295577 | E22: 9.9634615 | F22: 8.3 | N22: 48.485962
A23: J Stobart & Sons | B23: 692.91813 | C23: 648.21374 | D23: 692.91813 | E23: 670.56593 | F23: 692.91813 | G23: 670.56593 | H23: 692.91813 | I23: 692.91813 | J23: 654.1189 | K23: 693.88396 | L23: 702.75247 | M23: 726.17755 | N23: 8230.8691
A24: London Metals Ltd | B24: 620.10475 | C24: 580.09799 | D24: 620.10475 | E24: 600.10137 | F24: 620.10475 | G24: 600.10137 | H24: 620.10475 | I24: 620.10475 | J24: 600.10137 | K24: 620.10475 | L24: 577.57681 | M24: 648.62901 | N24: 7327.2365
A25: North Herts Farmers | B25: 375.11959 | C25: 350.91832 | D25: 375.11959 | E25: 401.42319 | F25: 388.62418 | G25: 376.08791 | H25: 388.62418 | I25: 388.62418 | J25: 376.08791 | K25: 388.62418 | L25: 376.08791 | M25: 388.62418 | N25: 4573.9653
A26: Openfield | B26: 7988.6446 | C26: 7473.2482 | D26: 7988.6446 | E26: 7766.0499 | F26: 7997.8586 | G26: 7739.8632 | H26: 7997.8586 | I26: 7997.8586 | J26: 7475.3366 | K26: 8299.3004 | L26: 7937.8622 | M26: 8366.1241 | N26: 95028.65
A27: Oxbow Coal | B27: 2315.7332 | C27: 2166.3311 | D27: 2315.7332 | E27: 2241.0321 | F27: 2315.7332 | G27: 2241.0321 | H27: 2315.7332 | I27: 2315.7332 | J27: 2238.0758 | K27: 2317.933 | L27: 2243.161 | M27: 2171.4847 | N27: 27197.716
A28: Pearce Seeds | B28: 102.12201 | C28: 95.533489 | D28: 102.12201 | E28: 98.827747 | F28: 96.875165 | G28: 102.18791 | H28: 105.59418 | I28: 105.59418 | J28: 102.18791 | K28: 105.59418 | L28: 102.18791 | M28: 105.59418 | N28: 1224.4209
A29: Robin Appel | B29: 463.69698 | C29: 433.78104 | D29: 463.69698 | E29: 448.73901 | F29: 463.69698 | G29: 448.73901 | H29: 463.69698 | I29: 463.69698 | J29: 448.73901 | K29: 465.22038 | L29: 459.50104 | M29: 485.64907 | N29: 5508.8535
A30: Saxon Agriculture | B30: 1874.9234 | C30: 1753.9606 | D30: 1766.6596 | E30: 1877.9481 | F30: 1940.5463 | G30: 1877.9481 | H30: 1940.5463 | I30: 1940.5463 | J30: 1877.9481 | K30: 1940.5463 | L30: 1877.9481 | M30: 1940.5463 | N30: 22610.068
A31: Scott & Newman | B31: 346.06105 | C31: 415.15916 | D31: 332.8202 | E31: 313.04376 | F31: 323.47856 | G31: 313.04376 | H31: 323.47856 | I31: 323.47856 | J31: 313.04376 | K31: 323.47856 | L31: 313.04376 | M31: 323.47856 | N31: 3963.6082
A32: Simpsons Malt | B32: 5000.3928 | C32: 4677.7868 | D32: 4768.1176 | E32: 5008.458 | F32: 5175.4066 | G32: 5008.458 | H32: 5175.4066 | I32: 5175.4066 | J32: 5008.458 | K32: 5175.4066 | L32: 5008.458 | M32: 5175.4066 | N32: 60357.162
A33: WCF | B33: 819.71297 | C33: 804.92687 | D33: 860.43907 | E33: 832.68297 | F33: 860.43907 | G33: 832.68297 | H33: 860.43907 | I33: 855.10261 | J33: 836.36456 | K33: 864.24338 | L33: 836.36456 | M33: 864.24338 | N33: 10127.641
A34: West Gaines Seeds | B34: 952.99901 | C34: 891.5152 | D34: 952.99901 | E34: 922.25711 | F34: 894.84901 | G34: 998.37033 | H34: 1031.6493 | I34: 1031.6493 | J34: 998.37033 | K34: 1031.6493 | L34: 998.37033 | M34: 1031.6493 | N34: 11736.328
... A36: Grand Total | B36: 59060.988 | C36: 55366.189 | D36: 57785.657 | E36: 58006.649 | F36: 60180.44 | G36: 57945.431 | H36: 61203.015 | I36: 60492.16 | J36: 58159.366 | K36: 60944.063 | L36: 58851.331 | M36: 60938.353 | N36: 708933.64
B37: 59061 | C37: 55366 | D37: 57786 | E37: 58007 | F37: 60180 | G37: 57945 | H37: 61203 | I37: 60492 | J37: 58159 | K37: 60944 | L37: 58851 | M37: 60938
B39: =B37-GETPIVOTDATA("Sum of Jan-25",$A$1) -> 0.012459569 | C39: =C37-GETPIVOTDATA("Sum of Feb-25",$A$1) -> -0.18902744 | D39: =D37-GETPIVOTDATA("Sum of Mar-25",$A$1) -> 0.34294203 | E39: =E37-GETPIVOTDATA("Sum of Apr-25",$A$1) -> 0.35109289 | F39: =F37-GETPIVOTDATA("Sum of May-25",$A$1) -> -0.43987996 | G39: =G37-GETPIVOTDATA("Sum of Jun-25",$A$1) -> -0.43052656 | H39: =H37-GETPIVOTDATA("Sum of Jul-25",$A$1) -> -0.0153838 | I39: =I37-GETPIVOTDATA("Sum of Aug-25",$A$1) -> -0.15950918 | J39: =J37-GETPIVOTDATA("Sum of Sep-25",$A$1) -> -0.36642594 | K39: =K37-GETPIVOTDATA("Sum of Oct-25",$A$1) -> -0.063355336 | L39: =L37-GETPIVOTDATA("Sum of Nov-25",$A$1) -> -0.33065671 | M39: =M37-GETPIVOTDATA("Sum of Dec-25",$A$1) -> -0.35330039
B40: frontier
B44: 0.80549 | C44: 0.79437 | D44: 0.77312 | E44: 0.74848 | F44: 0.74348 | G44: 0.72924 | H44: 0.75575 | I44: 0.74083 | J44: 0.744 | K44: 0.76108 | L44: 0.75609 | M44: 0.74322
A46: Adams & Howling | B46: =B2/$B$44 -> 408.83858 | C46: =C2/$C$44 -> 387.81579 | D46: =D2/$D$44 -> 398.4763 | E46: =E2/$E$44 -> 440.68763 | F46: =F2/$F$44 -> 458.43969 | G46: =G2/$G$44 -> 452.31457 | H46: =H2/$H$44 -> 450.99668 | I46: =I2/$I$44 -> 460.07956 | J46: =J2/$J$44 -> 443.34124 | K46: =K2/$K$44 -> 447.83826 | L46: =L2/$L$44 -> 436.25214 | M46: =M2/$M$44 -> 458.60007 | N46: =SUM(B46:M46) -> 5243.6805
A47: Banff & Moray Grain (Marketing) Ltd | B47: =B3/$B$44 -> 127.19375 | C47: =C3/$C$44 -> 120.65336 | D47: =D3/$D$44 -> 132.51927 | E47: =E3/$E$44 -> 124.74281 | F47: =F3/$F$44 -> 142.76347 | G47: =G3/$G$44 -> 140.85604 | H47: =H3/$H$44 -> 140.44563 | I47: =I3/$I$44 -> 143.27415 | J47: =J3/$J$44 -> 138.06164 | K47: =K3/$K$44 -> 139.46206 | L47: =L3/$L$44 -> 135.85401 | M47: =M3/$M$44 -> 142.81341 | N47: =SUM(B47:M47) -> 1628.6396
A48: Barenbrug | B48: =B4/$B$44 -> 1241.2188 | C48: =C4/$C$44 -> 1208.7751 | D48: =D4/$D$44 -> 1327.6547 | E48: =E4/$E$44 -> 1327.1237 | F48: =F4/$F$44 -> 1380.5837 | G48: =G4/$G$44 -> 1362.138 | H48: =H4/$H$44 -> 1358.1692 | I48: =I4/$I$44 -> 1385.5222 | J48: =J4/$J$44 -> 1285.7229 | K48: =K4/$K$44 -> 1388.3945 | L48: =L4/$L$44 -> 1352.475 | M48: =M4/$M$44 -> 1421.7584 | N48: =SUM(B48:M48) -> 16039.536
A49: Canterra Seeds | B49: =B5/$B$44 -> 541.48352 | C49: =C5/$C$44 -> 443.35445 | D49: =D5/$D$44 -> 486.95709 | E49: =E5/$E$44 -> 486.76233 | F49: =F5/$F$44 -> 506.3704 | G49: =G5/$G$44 -> 499.60489 | H49: =H5/$H$44 -> 498.14921 | I49: =I5/$I$44 -> 508.18172 | J49: =J5/$J$44 -> 489.69337 | K49: =K5/$K$44 -> 494.66057 | L49: =L5/$L$44 -> 481.8631 | M49: =M5/$M$44 -> 506.54754 | N49: =SUM(B49:M49) -> 5943.6282
A50: COFCO International | B50: =B6/$B$44 -> 1561.8547 | C50: =C6/$C$44 -> 1481.543 | D50: =D6/$D$44 -> 1627.2485 | E50: =E6/$E$44 -> 1626.5977 | F50: =F6/$F$44 -> 1692.1213 | G50: =G6/$G$44 -> 1669.5132 | H50: =H6/$H$44 -> 1664.6488 | I50: =I6/$I$44 -> 1698.1741 | J50: =J6/$J$44 -> 1527.2984 | K50: =K6/$K$44 -> 1732.3347 | L50: =L6/$L$44 -> 1687.5171 | M50: =M6/$M$44 -> 1773.9637 | N50: =SUM(B50:M50) -> 19742.815
A51: Confluence Genetics | B51: =B7/$B$44 -> 0 | C51: =C7/$C$44 -> 0 | D51: =D7/$D$44 -> 0 | E51: =E7/$E$44 -> 0 | F51: =F7/$F$44 -> 0 | G51: =G7/$G$44 -> 0 | H51: =H7/$H$44 -> 0 | I51: =I7/$I$44 -> 0 | J51: =J7/$J$44 -> 0 | K51: =K7/$K$44 -> 0 | L51: =L7/$L$44 -> 0 | M51: =M7/$M$44 -> 0 | N51: =SUM(B51:M51) -> 0
A52: Denholm Fish Selling Ltd | B52: =B8/$B$44 -> 193.48386 | C52: =C8/$C$44 -> 183.53478 | D52: =D8/$D$44 -> 201.5849 | E52: =E8/$E$44 -> 201.50427 | F52: =F8/$F$44 -> 209.6214 | G52: =G8/$G$44 -> 199.92047 | H52: =H8/$H$44 -> 0 | I52: =I8/$I$44 -> 0 | J52: =J8/$J$44 -> 0 | K52: =K8/$K$44 -> 0 | L52: =L8/$L$44 -> 0 | M52: =M8/$M$44 -> 0 | N52: =SUM(B52:M52) -> 1189.6497
A53: DL Seeds | B53: =B9/$B$44 -> 321.2038 | C53: =C9/$C$44 -> 304.68726 | D53: =D9/$D$44 -> 334.65238 | E53: =E9/$E$44 -> 94.508093 | F53: =F9/$F$44 -> 12.780917 | G53: =G9/$G$44 -> 751.26516 | H53: =H9/$H$44 -> 278.76864 | I53: =I9/$I$44 -> 284.38292 | J53: =J9/$J$44 -> 274.03668 | K53: =K9/$K$44 -> 276.81636 | L53: =L9/$L$44 -> 269.65479 | M53: =M9/$M$44 -> 283.46842 | N53: =SUM(B53:M53) -> 3486.2254
A54: Dugdale Nutrition | B54: =B10/$B$44 -> 1100.6062 | C54: =C10/$C$44 -> 1049.0717 | D54: =D10/$D$44 -> 1152.2449 | E54: =E10/$E$44 -> 1151.7841 | F54: =F10/$F$44 -> 1192.6515 | G54: =G10/$G$44 -> 1185.5697 | H54: =H10/$H$44 -> 1182.1153 | I54: =I10/$I$44 -> 1183.3353 | J54: =J10/$J$44 -> 1193.4158 | K54: =K10/$K$44 -> 1205.5212 | L54: =L10/$L$44 -> 1174.3329 | M54: =M10/$M$44 -> 1234.4906 | N54: =SUM(B54:M54) -> 14005.139
A55: Elevator | B55: =B11/$B$44 -> 1051.443 | C55: =C11/$C$44 -> 997.37701 | D55: =D11/$D$44 -> 1095.4662 | E55: =E11/$E$44 -> 1095.028 | F55: =F11/$F$44 -> 1139.1387 | G55: =G11/$G$44 -> 1123.9189 | H55: =H11/$H$44 -> 1120.6441 | I55: =I11/$I$44 -> 1143.2134 | J55: =J11/$J$44 -> 1101.6218 | K55: =K11/$K$44 -> 1112.796 | L55: =L11/$L$44 -> 1015.0695 | M55: =M11/$M$44 -> 1191.9559 | N55: =SUM(B55:M55) -> 13187.673
A56: Fram Farmers | B56: =B12/$B$44 -> 128.2278 | C56: =C12/$C$44 -> 121.63423 | D56: =D12/$D$44 -> 133.59661 | E56: =E12/$E$44 -> 133.54317 | F56: =F12/$F$44 -> 138.92265 | G56: =G12/$G$44 -> 137.06653 | H56: =H12/$H$44 -> 136.66716 | I56: =I12/$I$44 -> 139.41958 | J56: =J12/$J$44 -> 134.34731 | K56: =K12/$K$44 -> 135.71006 | L56: =L12/$L$44 -> 132.19907 | M56: =M12/$M$44 -> 132.83364 | N56: =SUM(B56:M56) -> 1604.1678
A57: Frontier Agriculture | B57: =B13/$B$44 -> 20071.954 | C57: =C13/$C$44 -> 19089.466 | D57: =D13/$D$44 -> 19700.986 | E57: =E13/$E$44 -> 22056.817 | F57: =F13/$F$44 -> 22945.324 | G57: =G13/$G$44 -> 22638.756 | H57: =H13/$H$44 -> 22572.794 | I57: =I13/$I$44 -> 23027.401 | J57: =J13/$J$44 -> 22189.624 | K57: =K13/$K$44 -> 22414.713 | L57: =L13/$L$44 -> 21834.808 | M57: =M13/$M$44 -> 22953.352 | N57: =SUM(B57:M57) -> 261496
... A79: Wynnstay Group | B79: =B35/$B$44 -> 11339.297 | C79: =C35/$C$44 -> 10756.221 | D79: =D35/$D$44 -> 11814.065 | E79: =E35/$E$44 -> 11622.544 | F79: =F35/$F$44 -> 12614.198 | G79: =G35/$G$44 -> 12445.663 | H79: =H35/$H$44 -> 12409.4 | I79: =I35/$I$44 -> 12659.32 | J79: =J35/$J$44 -> 12198.757 | K79: =K35/$K$44 -> 12322.495 | L79: =L35/$L$44 -> 12003.697 | M79: =M35/$M$44 -> 12618.611 | N79: =SUM(B79:M79) -> 144804.27
N81: =SUM(N46:N80) -> 936381.74
