Workbook

Sheet BPC Check
A1: Revenue Type | B1: Amount | C1: BPC | D1: Variance
A2: Maintenance | B2: ='Deferred Maintenance'!AA51 -> 2739365.1 | C2: 2133853.4 | D2: =B2-C2 -> 605511.73
A3: 3rd Party Maint | B3: ='3rd Party Maintenance'!AA45 -> 178875.82 | C3: 130966.08 | D3: =B3-C3 -> 47909.736
A4: Hosting | B4: =Hosting!AA38 -> 591425.97 | C4: 460483.53 | D4: =B4-C4 -> 130942.44
A5: PS | B5: =PS!AA53 -> 711077.97 | C5: =374650.81+469779.47 -> 844430.28 | D5: =B5-C5 -> -133352.31
A6: License | B6: =Licence!AA52 -> 241612.42 | C6: 209063.37 | D6: =B6-C6 -> 32549.048
A7: Hardware/Flowthrough | B7: 375.72 | C7: 375.72 | D7: =B7-C7 -> 0
A8: Total Revs 2021 | B8: =SUM(B2:B7) -> 4462733 | C8: =SUM(C2:C7) -> 3779172.4 | D8: =SUM(D2:D7) -> 683560.65
A11: Ireland | B11: =C8-B12 -> #REF!
A12: UK | B12: =GETPIVOTDATA("Amount",'Consolidated Revenue'!$D$2,"Customer","Denis Brinicombe")+GETPIVOTDATA("Amount",'Consolidated Revenue'!$D$2,"Customer","Denis Brinicombe Group")+GETPIVOTDATA("Amount",'Consolidated Revenue'!$D$2,"Customer","East Coast Viners")+GETPIVOTDATA("Amount",'Consolidated Revenue'!$D$2,"Customer","OMSCO") -> #REF!
A14: Total | B14: =SUM(B11:B13) -> #REF!

Sheet Customers sorted by Revs 22
A1: Customer | B1: Amount
A2: Glanbia | B2: 506750.97
A3: Heat Merchants | B3: 279561.24
A4: Aurivo Co-Op Society | B4: 196069.76
A5: Arrabawn Co-Op Society | B5: 190597.76
A6: East Coast Viners | B6: 175401.07
A7: Dairygold Co-Op | B7: 167267.15
A8: Lakeland Dairies | B8: 147268.71
A9: Drinagh Co-Op | B9: 141864.45
A10: Bandon Co-Op | B10: 137071.36
A11: Lisavaird Co-Op | B11: 134300.56
A12: North Cork Co-Op | B12: 130824.86
A13: M.D O'Shea | B13: 127732.93
... A47: Newmarket Co-Op | B47: 1153.3541

Sheet Consolidated Revenue
A1: Customer | B1: Amount
A2: Arrabawn Co-Op Society | B2: 13380.452 | D2: Row Labels | E2: Sum of Amount
A3: Aurivo Co-Op Society | B3: 2100.0703 | D3: Arrabawn Co-Op Society | E3: 190597.76
A4: Aurivo Co-Op Society | B4: 0 | D4: Aurivo Co-Op Society | E4: 196069.76
A5: BallyJamesDuff Co-Op | B5: 0 | D5: BallyJamesDuff Co-Op | E5: 17701.797
A6: Bandon Co-Op | B6: 5555.9744 | D6: Bandon Co-Op | E6: 137071.36
A7: Bandon Vale Cheese | B7: 2551.7331 | D7: Bandon Vale Cheese | E7: 15688.142
A8: Barryroe Co-Op | B8: 0 | D8: Barryroe Co-Op | E8: 102327.43
A9: Brett Brothers | B9: 845.48721 | D9: Brett Brothers | E9: 51317.681
A10: Callan Co-Op | B10: 5185.6009 | D10: Callan Co-Op | E10: 30175.774
A11: Carbery | B11: 0 | D11: Carbery | E11: 43355.952
A12: Centenary Thurles Co-Op | B12: 0 | D12: Centenary Thurles Co-Op | E12: 52194.313
A13: Centenary Thurles Feed & Grain | B13: 0 | D13: Centenary Thurles Feed & Grain | E13: 16778.728
A14: Centenary Thurles Fresh Milk | B14: 0 | D14: Centenary Thurles Fresh Milk | E14: 8933.2532
... A52: Arrabawn Co-Op Society | B52: 44205.374 | D52: Grand Total | E52: 3779172.4
A53: Aurivo Co-Op Society | B53: 25410.286
A54: Aurivo Co-Op Society | B54: 0
A55: BallyJamesDuff Co-Op | B55: 0
A56: Bandon Co-Op | B56: 14208.375
A57: Bandon Vale Cheese | B57: 134.07354
A58: Barryroe Co-Op | B58: 11532.682
A59: Brett Brothers | B59: 1039.717
A60: Callan Co-Op | B60: 2747.579
A61: Carbery | B61: 25816.401
A62: Centenary Thurles Co-Op | B62: 13132.502
A63: Centenary Thurles Feed & Grain | B63: 1004.0161
A64: Centenary Thurles Fresh Milk | B64: 0
... A224: East Coast Viners | B224: 375.72

Sheet Recurring Revenue Euros
A1: 3rd Party Maint | D1: Maintenance | G1: Hosting
A3: Row Labels | B3: Sum of Consolidated Eur | D3: Row Labels | E3: Sum of Cons EUR | G3: Row Labels | H3: Sum of Consildated Eur | K3: Customer | L3: Amount
A4: Arrabawn | B4: 9651.45 | D4: Arrabawn | E4: 139228.06 | G4: Arrabawn | H4: 10567.26 | K4: (blank) | L4: 2423519.2
A5: Aurivo | B5: 19128.44 | D5: Aurivo | E5: 170337.22 | G5: BallyJamesDuff | H5: 8074.24 | K5: Adj | L5: -0.5 | N5: Row Labels | O5: Sum of Amount
A6: Aurivo NI | B6: 387.73 | D6: Aurivo NI | E6: 7666.1 | G6: Bandon Co-Op | H6: 30534.76 | K6: Adj | L6: 0 | N6: Arrabawn | O6: 159446.77
A7: BallyJamesDuff | B7: 516.95 | D7: BallyJamesDuff | E7: 11829.446 | G7: Barryroe Co-Op | H7: 28225.96 | K7: Arrabawn | L7: 9651.45 | N7: Aurivo | O7: 197519.47
A8: Bandon Co-Op | B8: 5817.83 | D8: Bandon Co-Op | E8: 98598.38 | G8: Brett Brothers | H8: 8380.75 | K8: Arrabawn | L8: 139228.06 | N8: BallyJamesDuff | O8: 20420.636
A9: Bandon Vale Cheese | B9: 260.11 | D9: Bandon Vale Cheese | E9: 14425.44 | G9: Callan Co-Op | H9: 5828.88 | K9: Arrabawn | L9: 10567.26 | N9: Bandon Co-Op | O9: 134950.97
A10: Barryroe Co-op | B10: 4404.83 | D10: Barryroe Co-Op | E10: 73404.02 | G10: Carbery | H10: 6899.14 | K10: Aurivo | L10: 19128.44 | N10: Bandon Vale Cheese | O10: 14685.55
A11: Callan Co-Op | B11: 639.1 | D11: Brett Brothers | E11: 48255.92 | G11: Centenary Thurles Co-Op | H11: 6852.29 | K11: Aurivo | L11: 170337.2 | N11: Barryroe Co-op | O11: 106034.81
A12: Carbery | B12: 778.09 | D12: Callan Co-Op | E12: 29512.68 | G12: Dan O'Connor | H12: 1663.48 | K12: Aurivo | L12: 387.73 | N12: Brett Brothers | O12: 56636.67
A13: Centenary Thurles Co-Op | B13: 1691.89 | D13: Carbery | E13: 17409.4 | G13: Denis Brinicombe | H13: 19633.03 | K13: Aurivo | L13: 7666.1 | N13: Callan Co-Op | O13: 35980.66
A14: Centenary Thurles Stores | B14: 4931.43 | D14: Centenary Thurles Co-Op | E14: 37525.12 | G14: Drinagh Co-Op | H14: 25977.19 | K14: BallyJamesDuff | L14: 516.95 | N14: Carbery | O14: 7677.23
A15: Dan O'Connor | B15: 88.69 | D15: Centenary Thurles Feed & Grain | E15: 17695.96 | G15: Drinagh Dairies | H15: 1647.01 | K15: BallyJamesDuff | L15: 11829.446 | N15: Carbery | O15: 17409.4
A16: Denis Brinicombe | B16: 1869.56 | D16: Centenary Thurles Fresh Milk | E16: 10021.24 | G16: Heat Merchants | H16: 123019.94 | K16: BallyJamesDuff | L16: 8074.24 | N16: Centenary Thurles Co-Op | O16: 46069.3
A17: Drinagh Co-Op | B17: 5882.16 | D17: Centenary Thurles Stores | E17: 41181.34 | G17: Hopkins | H17: 6899.14 | K17: Bandon Co-Op | L17: 5817.83 | N17: Centenary Thurles Feed & Grain | O17: 17695.96
... A40: Strathroy Dairy | B40: 641.41 | D40: Morris DIY | E40: 43950.24 | G40: Grand Total | H40: 523479.21 | K40: Centenary Thurles Stores | L40: 41181.34 | N40: McDonnell Bros | O40: 55308.31
A41: T&A Building | B41: 881.19 | D41: North Cork | E41: 78296.98 | K41: Dan O'Connor | L41: 88.69 | N41: McDonogh | O41: 36230.68
A42: Tirlan | B42: 33235.04 | D42: Organic Herd | E42: 21375.12 | K42: Dan O'Connor | L42: 38313.1 | N42: Morris DIY | O42: 46324
A43: Wallaces | B43: 1603.68 | D43: Peter Curran | E43: 31446.02 | K43: Dan O'Connor | L43: 1663.48 | N43: North Cork | O43: 91347.04
A44: Brett Brother | B44: 2805.91 | D44: Richard Boyle | E44: 64598.7 | K44: Denis Brinicombe | L44: 1869.56 | N44: Organic Herd | O44: 44671.04
A45: Kiernan Milling | B45: 3192.0011 | D45: Smiths Building | E45: 15550.88 | K45: Denis Brinicombe | L45: 31133.3 | N45: Peter Curran | O45: 42624.75
A46: Grand Total | B46: 158131.04 | D46: Smiths Tools | E46: 1434.19 | K46: Denis Brinicombe | L46: 19633.03 | N46: Richard Boyle | O46: 84269.66
D47: Strathroy Dairy | E47: 13958.33 | K47: Drinagh Co-Op | L47: 5882.16 | N47: Smiths Building | O47: 28457.79
D48: T&A Building | E48: 20778.08 | K48: Drinagh Co-Op | L48: 111777.58 | N48: Smiths Tools | O48: 2182.95
D49: Tirlan | E49: 349646.53 | K49: Drinagh Co-Op | L49: 25977.19 | N49: Strathroy Dairy | O49: 20779
D50: Wallaces | E50: 58557.1 | K50: Drinagh Dairies | L50: 33319.5 | N50: T&A Building | O50: 30843.56
D51: Kiernan Milling | E51: 12300 | K51: Drinagh Dairies | L51: 1647.01 | N51: Tirlan | O51: 400710.64
D52: Adj | E52: 0 | K52: East Coast Viners | L52: 3203.43 | N52: Adj | O52: -0.5
D53: Grand Total | E53: 2423519.2 | K53: East Coast Viners | L53: 31047.49 | N53: Brett Brother | O53: 2805.91
K54: Heat Merchants | L54: 13788.91 | N54: Kiernan Milling | O54: 15492.001
K55: Heat Merchants | L55: 161591.86 | N55: Wallaces Homevalue Hardware | O55: 60599.11
K56: Heat Merchants | L56: 123019.94 | N56: Grand Total | O56: 3105129.4
K57: Hopkins | L57: 359.48
K58: Hopkins | L58: 17595.65
K59: Hopkins | L59: 6899.14
K60: ICMSA | L60: 3247.59
K61: ICMSA | L61: 8660.24
K62: Irish International Traders | L62: 1133
K63: Irish International Traders | L63: 10594.79
K64: J.McKenna | L64: 1395.73
K65: J.McKenna | L65: 34478.249
K66: J.McKenna | L66: 7305.52
K67: John McCarthy | L67: 1521
K68: John McCarthy | L68: 21380.096
... K131: Wallaces Homevalue Hardware | L131: 438.34
L132: =SUBTOTAL(9,L5:L131) -> 3105129.4

Sheet Recurring Revenue Data
A1: Customer | B1: Amount
A2: Bandon Co-Op | B2: 111426.79
A3: Barryroe Co-Op | B3: 82954.448
A4: Brett Brothers | B4: 54554.246
A5: Callan Co-Op | B5: 33579.615 | G5: Row Labels | H5: Sum of Amount
A6: Centenary Thurles Feed & Grain | B6: 19993.023 | G6: Arrabawn | H6: 180331.79 | M6: Tirlan | N6: 452741.11
A7: Centenary Thurles Fresh Milk | B7: 11322.069 | G7: Aurivo | H7: 223189.75 | M7: Heat Merchants | N7: 337224.14
A8: Centenary Thurles Stores | B8: 46526.973 | G8: Bandon Co-Op | H8: 152509.13 | M8: Aurivo | N8: 223189.75
A9: Denis Brinicombe | B9: 35213.125 | G9: Drinagh Co-Op | H9: 162333.46 | M9: Arrabawn | N9: 180331.79
A10: Drinagh Co-Op | B10: 126328.56 | G10: Heat Merchants | H10: 337224.14 | M10: Drinagh Co-Op | N10: 162333.46
A11: Drinagh Dairies | B11: 37654.623 | G11: Kiernan Milling | H11: 18081.747 | M11: Bandon Co-Op | N11: 152509.13
A12: Heat Merchants | B12: 182616.2 | G12: Lakeland Dairies | H12: 150259.19 | M12: Lakeland Dairies | N12: 150259.19
A13: J.McKenna | B13: 38950.359 | G13: Lisavaird | H13: 136329.13 | M13: Lisavaird | N13: 136329.13
A14: John McCarthy | B14: 24161.494 | G14: M.D O'Shea | H14: 131225.21 | M14: M.D O'Shea | N14: 131225.21
A15: M.D O'Shea | B15: 111418.84 | G15: Tirlan | H15: 452741.11 | M15: Kiernan Milling | N15: 18081.747
A16: Peter Curran | B16: 35527.939 | G16: Grand Total | H16: 1944224.7
A17: Smiths Tools | B17: 1483.0263
A18: T&A Building | B18: 23472.853
A19: BallyJamesDuff | B19: 13364.833
A20: Centenary Thurles Co-Op | B20: 42396.15
A21: Dan O'Connor | B21: 43297.929
A22: Hopkins | B22: 19879.657
A23: ICMSA | B23: 3670.1264
A24: Lee Strand | B24: 47235.868
A25: Lisavaird | B25: 106593.97
A26: Morris DIY | B26: 49655.296
A27: North Cork | B27: 88460.49
A28: Richard Boyle | B28: 72984.075
... A126: Kiernan Milling | B126: 3737.0849

Sheet Revenue Consolidated
A1: Customer | B1: Revenue | U1: 151266.33
A2: Bandon Co-Op | B2: 6574.7744 | T2: Customer | U2: Hosting Revenue | V2: % | W2: Hosting COGs
A3: Barryroe Co-op | B3: 4977.9323 | T3: Tirlan | U3: =_xlfn.XLOOKUP(T3,Summary!$G$40:$G$73,Summary!$H$40:$H$73) -> #N/A | V3: =U3/Summary!$H$75 -> #N/A | W3: =$U$1*V3 -> #N/A
A4: Callan Co-Op | B4: 722.25183 | T4: Heat Merchants | U4: =_xlfn.XLOOKUP(T4,Summary!$G$40:$G$73,Summary!$H$40:$H$73) -> #N/A | V4: =U4/Summary!$H$75 -> #N/A | W4: =$U$1*V4 -> #N/A
A5: Centenary Thurles Stores | B5: 5573.047 | D5: Row Labels | E5: Sum of Revenue | H5: Customer | I5: Amount | J5: Country | K5: 3rd Party COGS | L5: Hosting COGS | M5: Net Revenue | T5: Aurivo Co-Op | U5: 0 | V5: =U5/Summary!$H$75 -> #DIV/0! | W5: =$U$1*V5 -> #DIV/0!
A6: Denis Brinicombe Group | B6: 2112.8041 | D6: AIB Merchant Services | E6: 3975.549 | H6: Tirlan | I6: 601656.03 | J6: Ireland | K6: 1941.0089 | L6: 5043.7386 | M6: =I6-K6-L6 -> 594671.28 | T6: Drinagh Co-Op | U6: =_xlfn.XLOOKUP(T6,Summary!$G$40:$G$73,Summary!$H$40:$H$73) -> #N/A | V6: =U6/Summary!$H$75 -> #N/A | W6: =$U$1*V6 -> #N/A
A7: Drinagh Co-Op | B7: 6647.8783 | D7: Arrabawn Co-Op Society | E7: 333622.81 | H7: Heat Merchants Group | I7: 399481.19 | J7: Ireland | K7: 820.94353 | L7: 34956.537 | M7: =I7-K7-L7 -> 363703.71 | T7: Arrabawn | U7: =_xlfn.XLOOKUP(T7,Summary!$G$40:$G$73,Summary!$H$40:$H$73) -> #N/A | V7: =U7/Summary!$H$75 -> #N/A | W7: =$U$1*V7 -> #N/A
A8: Heat Merchants Group | B8: 15582.953 | D8: Aurivo Co-Op | E8: 249690.63 | H8: Arrabawn Co-Op Society | I8: 333622.81 | J8: Ireland | K8: 1126.0137 | L8: 0 | M8: =I8-K8-L8 -> 332496.79 | T8: Lakeland Dairies | U8: =_xlfn.XLOOKUP(T8,Summary!$G$40:$G$73,Summary!$H$40:$H$73) -> #N/A | V8: =U8/Summary!$H$75 -> #N/A | W8: =$U$1*V8 -> #N/A
A9: J. McKenna Ltd | B9: 1577.3252 | D9: BallyJamesDuff Co-Op | E9: 23073.803 | H9: Aurivo Co-Op | I9: 249690.63 | J9: Ireland | K9: 345.80922 | L9: 7491.3712 | M9: =I9-K9-L9 -> 241853.45 | T9: M.D O'Shea | U9: =_xlfn.XLOOKUP(T9,Summary!$G$40:$G$73,Summary!$H$40:$H$73) -> #N/A | V9: =U9/Summary!$H$75 -> #N/A | W9: =$U$1*V9 -> #N/A
A10: John R. McCarthy | B10: 1718.8938 | D10: Bandon Co-Op | E10: 165745.69 | H10: Kiernan Milling | I10: 234100.25 | J10: Ireland | K10: 529.60411 | L10: 3047.409 | M10: =I10-K10-L10 -> 230523.24 | T10: Bandon Co-Op | U10: =_xlfn.XLOOKUP(T10,Summary!$G$40:$G$73,Summary!$H$40:$H$73) -> #N/A | V10: =U10/Summary!$H$75 -> #N/A | W10: =$U$1*V10 -> #N/A
A11: M.D O'Shea & Sons Ltd | B11: 10723.294 | D11: Bandon Vale Cheese | E11: 16596.253 | H11: Lisavaird Co-Op | I11: 184226.11 | J11: Ireland | K11: 153.21331 | L11: 2641.5506 | M11: =I11-K11-L11 -> 181431.34 | T11: Lisavaird | U11: =_xlfn.XLOOKUP(T11,Summary!$G$40:$G$73,Summary!$H$40:$H$73) -> #N/A | V11: =U11/Summary!$H$75 -> #N/A | W11: =$U$1*V11 -> #N/A
A12: McDonnell Bros Ltd | B12: 2705.2126 | D12: Barryroe Co-op | E12: 126603.07 | H12: Drinagh Co-Op | I12: 179057.25 | J12: Ireland | K12: 513.16291 | L12: 2317.828 | M12: =I12-K12-L12 -> 176226.26 | T12: Barryroe Co-op | U12: =_xlfn.XLOOKUP(T12,Summary!$G$40:$G$73,Summary!$H$40:$H$73) -> #N/A | V12: =U12/Summary!$H$75 -> #N/A | W12: =$U$1*V12 -> #N/A
A13: Peter Curran Electrical | B13: 2001.2173 | D13: Brett Brothers | E13: 85104.007 | H13: Bandon Co-Op | I13: 165745.69 | J13: Ireland | K13: 341.36579 | L13: 8805.6934 | M13: =I13-K13-L13 -> 156598.63
A14: Smith's Tool Hire | B14: 846.17943 | D14: Callan Co-Op | E14: 88253.787 | H14: M.D O'Shea & Sons Ltd | I14: 165195.93 | J14: Ireland | K14: 162.47915 | L14: 6755.4099 | M14: =I14-K14-L14 -> 158278.04
A15: T&A Building | B15: 995.8396 | D15: Carbery Group | E15: 32026.795 | H15: Lakeland Dairies | I15: 160704.37 | J15: Ireland | K15: 262.24797 | L15: 8139.8767 | M15: =I15-K15-L15 -> 152302.25 | U15: 9023.58
A16: BallyJamesDuff Co-Op | B16: 584.20917 | D16: Centenary Thurles Co-Op | E16: 54023.376 | H16: Barryroe Co-op | I16: 126603.07 | J16: Ireland
A17: Centenary Thurles Co-Op | B17: 1912.0179 | D17: Centenary Thurles Feed & Grain | E17: 19993.023 | H17: North Cork Co-Op | I17: 116155.05 | J17: Ireland | T17: Tirlan | U17: 31652.42 | V17: =U17/$T$29 -> 0.21510409 | W17: =$U$15*V17 -> 1941.0089
A18: Dan O'Connor Feeds | B18: 100.22925 | D18: Centenary Thurles Fresh Milk | E18: 11322.069 | H18: Wallaces Homevalue Hardware | I18: 113688.17 | J18: Ireland | T18: Heat Merchants | U18: 13387.29 | V18: =U18/$T$29 -> 0.090977587 | W18: =$U$15*V18 -> 820.94353
A19: East Coast Viners | B19: 3621.295 | D19: Centenary Thurles Stores | E19: 53082.918 | H19: Richard Boyle & Sons Ltd | I19: 96907.329 | J19: Ireland | T19: Aurivo Co-Op | U19: 18362.13 | V19: =U19/$T$29 -> 0.12478569 | W19: =$U$15*V19 -> 1126.0137
A20: Hopkins Homevalue Hardware | B20: 406.28262 | D20: Dan O'Connor Feeds | E20: 45350.946 | H20: Denis Brinicombe Group | I20: 92025.601 | J20: UK | T20: Drinagh Co-Op | U20: 5639.18 | V20: =U20/$T$29 -> 0.038322841 | W20: =$U$15*V20 -> 345.80922
A21: Lee Strand Dairies | B21: 895.74596 | D21: Denis Brinicombe Group | E21: 92025.601 | H21: Callan Co-Op | I21: 88253.787 | J21: Ireland | T21: Arrabawn | U21: 8636.36 | V21: =U21/$T$29 -> 0.058691131 | W21: =$U$15*V21 -> 529.60411
A22: Lisavaird Co-Op | B22: 3262.2018 | D22: Drinagh Co-Op | E22: 179057.25 | H22: Brett Brothers | I22: 85104.007 | J22: Ireland | T22: Lakeland Dairies | U22: 2498.48 | V22: =U22/$T$29 -> 0.016979215 | W22: =$U$15*V22 -> 153.21331
A23: Morris DIY & Building | B23: 2682.6044 | D23: Drinagh Dairies | E23: 39515.922 | H23: Kerry Agribusiness | I23: 78930.962 | J23: Ireland | T23: M.D O'Shea | U23: 8368.25 | V23: =U23/$T$29 -> 0.056869104 | W23: =$U$15*V23 -> 513.16291
A24: North Cork Co-Op | B24: 4615.5971 | D24: East Coast Viners | E24: 66059.099 | H24: East Coast Viners | I24: 66059.099 | J24: UK | T24: Bandon Co-Op | U24: 5566.72 | V24: =U24/$T$29 -> 0.037830416 | W24: =$U$15*V24 -> 341.36579
A25: Richard Boyle & Sons Ltd | B25: 4313.3046 | D25: Heat Merchants Group | E25: 399481.19 | H25: McDonnell Bros Ltd | I25: 65824.662 | J25: Ireland | T25: Lisavaird | U25: 2649.58 | V25: =U25/$T$29 -> 0.018006064 | W25: =$U$15*V25 -> 162.47915
A26: Wallaces Homevalue Hardware | B26: 1811.417 | D26: Hopkins Homevalue Hardware | E26: 28082.711 | H26: Lee Strand Dairies | I26: 61078.842 | J26: Ireland | T26: Barryroe Co-op | U26: 4276.53 | V26: =U26/$T$29 -> 0.02906252 | W26: =$U$15*V26 -> 262.24797
A27: Arrabawn Co-Op Society | B27: 10930.289 | D27: ICMSA | E27: 13457.13 | H27: Morris DIY & Building | I27: 57942.364 | J27: Ireland
A28: Aurivo Co-Op | B28: 21620.609 | D28: Irish International Traders | E28: 13690.924 | H28: Organic Herd | I28: 54033.221 | J28: UK
A29: Aurivo Co-Op | B29: 438.17665 | D29: J. McKenna Ltd | E29: 48783.708 | H29: Centenary Thurles Co-Op | I29: 54023.376 | J29: Ireland | T29: 147149.32
A30: Bandon Vale Cheese | B30: 293.95231 | D30: John R. McCarthy | E30: 33624.146 | H30: Centenary Thurles Stores | I30: 53082.918 | J30: Ireland
A31: Carbery Group | B31: 879.32549 | D31: Joyce Hardware | E31: 0 | H31: J. McKenna Ltd | I31: 48783.708 | J31: Ireland
A32: Irish International Traders | B32: 1280.412 | D32: Kellihers Mills | E32: 12933.315 | H32: Peter Curran Electrical | I32: 48685.313 | J32: Ireland
A33: Kellihers Mills | B33: 541.4798 | D33: Kerry Agribusiness | E33: 78930.962 | H33: Lacpatrick Dairies | I33: 48656.88 | J33: Ireland
A34: Lacpatrick Dairies | B34: 3050.3189 | D34: Kiernan Milling | E34: 234100.25 | H34: Dan O'Connor Feeds | I34: 45350.946 | J34: Ireland
A35: Lakeland Dairies | B35: 1674.1076 | D35: Lacpatrick Dairies | E35: 48656.88 | H35: McDonogh Trade Centre Ltd | I35: 43031.373 | J35: Ireland
A36: Lakeland Dairies | B36: 1234.1567 | D36: Lakeland Dairies | E36: 160704.37 | H36: Drinagh Dairies | I36: 39515.922 | J36: Ireland
A37: McDonogh Trade Centre Ltd | B37: 1639.1647 | D37: Lee Strand Dairies | E37: 61078.842 | H37: T&A Building | I37: 34847.896 | J37: Ireland
A38: Organic Herd | B38: 1705.4342 | D38: Lisavaird Co-Op | E38: 184226.11 | H38: John R. McCarthy | I38: 33624.146 | J38: Ireland
A39: Smith's Building supplies | B39: 1431.7786 | D39: M.D O'Shea & Sons Ltd | E39: 165195.93 | H39: Smith's Building supplies | I39: 32153.92 | J39: Ireland
A40: Strathroy Dairies | B40: 724.86237 | D40: McDonnell Bros Ltd | E40: 65824.662 | H40: Carbery Group | I40: 32026.795 | J40: Ireland | L40: Row Labels | M40: Sum of Amount
A41: Tirlan | B41: 37559.174 | D41: McDonogh Trade Centre Ltd | E41: 43031.373 | H41: Hopkins Homevalue Hardware | I41: 28082.711 | J41: Ireland | L41: Ireland | M41: 4223205.7
A42: Brett Brothers | B42: 3170.9805 | D42: Mole Avon Town | E42: 1741.796 | H42: Strathroy Dairies | I42: 23482.508 | J42: UK | L42: UK | M42: 239297.67
A43: Kiernan Milling | B43: 3737.0849 | D43: Morris DIY & Building | E43: 57942.364 | H43: BallyJamesDuff Co-Op | I43: 23073.803 | J43: Ireland | L43: (blank)
A44: Bandon Co-Op | B44: 111426.79 | D44: NewMarket Co-Op Creameries Ltd | E44: 0 | H44: Centenary Thurles Feed & Grain | I44: 19993.023 | J44: Ireland | L44: Grand Total | M44: 4462503.4
A45: Barryroe Co-Op | B45: 82954.448 | D45: North Cork Co-Op | E45: 116155.05 | H45: Bandon Vale Cheese | I45: 16596.253 | J45: Ireland
A46: Brett Brothers | B46: 54554.246 | D46: Organic Herd | E46: 54033.221 | H46: Irish International Traders | I46: 13690.924 | J46: Ireland
A47: Callan Co-Op | B47: 33579.615 | D47: Peter Curran Electrical | E47: 48685.313 | H47: ICMSA | I47: 13457.13 | J47: Ireland
A48: Centenary Thurles Feed & Grain | B48: 19993.023 | D48: Richard Boyle & Sons Ltd | E48: 96907.329 | H48: Kellihers Mills | I48: 12933.315 | J48: Ireland
A49: Centenary Thurles Fresh Milk | B49: 11322.069 | D49: Smith's Building supplies | E49: 32153.92 | H49: Centenary Thurles Fresh Milk | I49: 11322.069 | J49: Ireland
A50: Centenary Thurles Stores | B50: 46526.973 | D50: Smith's Tool Hire | E50: 2329.2057 | H50: AIB Merchant Services | I50: 3975.549 | J50: Ireland
A51: Denis Brinicombe Group | B51: 35213.125 | D51: Strathroy Dairies | E51: 23482.508 | H51: Smith's Tool Hire | I51: 2329.2057 | J51: Ireland
A52: Drinagh Co-Op | B52: 126328.56 | D52: T&A Building | E52: 34847.896 | H52: Wolseley | I52: 1955.4489 | J52: UK
A53: Drinagh Dairies | B53: 37654.623 | D53: Tirlan | E53: 601656.03 | H53: Mole Avon Town | I53: 1741.796 | J53: UK
A54: Heat Merchants Group | B54: 182616.2 | D54: Wallaces Homevalue Hardware | E54: 113688.17
A55: J. McKenna Ltd | B55: 38950.359 | D55: Wolseley | E55: 1955.4489
A56: John R. McCarthy | B56: 24161.494 | D56: Grand Total | E56: 4462503.4
A57: M.D O'Shea & Sons Ltd | B57: 111418.84
A58: Peter Curran Electrical | B58: 35527.939
A59: Smith's Tool Hire | B59: 1483.0263 | I59: =SUM(I6:I58) -> 4462503.4
A60: T&A Building | B60: 23472.853
A61: BallyJamesDuff Co-Op | B61: 13364.833
A62: Centenary Thurles Co-Op | B62: 42396.15 | H62: UK | I62: =SUMIF(J:J,H62,I:I) -> 239297.67
A63: Dan O'Connor Feeds | B63: 43297.929 | H63: Ireland | I63: =SUMIF(J:J,H63,I:I) -> 4223205.7
A64: Hopkins Homevalue Hardware | B64: 19879.657
A65: ICMSA | B65: 3670.1264
A66: Lee Strand Dairies | B66: 47235.868
A67: Lisavaird Co-Op | B67: 106593.97
A68: Morris DIY & Building | B68: 49655.296
A69: North Cork Co-Op | B69: 88460.49
A70: Richard Boyle & Sons Ltd | B70: 72984.075
A71: Wallaces Homevalue Hardware | B71: 66174.611
A72: Arrabawn Co-Op Society | B72: 157459.35
A73: Aurivo Co-Op | B73: 192467.44
A74: Aurivo Co-Op | B74: 8663.5186
A75: Bandon Vale Cheese | B75: 16302.301
... A218: Organic Herd | B218: 0
A219: AIB Merchant Services
A220: Tirlan | B220: 0
A221: T&A Building | B221: 0
A222: AIB Merchant Services | B222: 3383.4459
A223: Kiernan Milling | B223: 146.07
B225: =SUM(B2:B223) -> 4462503.4

Sheet Summary
A1: 3rd Party Maint | D1: Maintenance | G1: Hosting | J1: PS | M1: License
A3: Row Labels | B3: Sum of Consol USD | D3: Row Labels | E3: Sum of Consol USD | G3: Row Labels | H3: Sum of Consol USD | J3: Row Labels | K3: Sum of Consol USD | M3: Row Labels | N3: Sum of CONSOL USD
A4: Bandon Co-Op | B4: 6574.7744 | D4: Bandon Co-Op | E4: 111426.79 | G4: Bandon Co-Op | H4: 34507.567 | J4: Arrabawn Co-Op Society | K4: 80968.525 | M4: Arrabawn Co-Op Society | N4: 72322.498
A5: Barryroe Co-op | B5: 4977.9323 | D5: Barryroe Co-Op | E5: 82954.448 | G5: Barryroe Co-Op | H5: 31898.374 | J5: Aurivo Co-Op | K5: 11726.547 | M5: BallyJamesDuff Co-Op | N5: 0
A6: Callan Co-Op | B6: 722.25183 | D6: Brett Brothers | E6: 54554.246 | G6: Brett Brothers | H6: 9471.15 | J6: BallyJamesDuff Co-Op | K6: 0 | M6: Bandon Co-Op | N6: 0
A7: Centenary Thurles Stores | B7: 5573.047 | D7: Callan Co-Op | E7: 33579.615 | G7: Callan Co-Op | H7: 6587.2621 | J7: Bandon Co-Op | K7: 13236.562 | M7: Bandon Vale Cheese | N7: 0
A8: Denis Brinicombe | B8: 2112.8041 | D8: Centenary Thurles Feed & Grain | E8: 19993.023 | G8: Carbery | H8: 7796.7712 | J8: Bandon Vale Cheese | K8: 0 | M8: Barryroe Co-Op | N8: 0
A9: Drinagh Co-Op | B9: 6647.8783 | D9: Centenary Thurles Fresh Milk | E9: 11322.069 | G9: Denis Brinicombe | H9: 22010.503 | J9: Barryroe Co-Op | K9: 6772.3186 | M9: Brett Brothers | N9: 11816.467
A10: Heat Merchants | B10: 15582.953 | D10: Centenary Thurles Stores | E10: 46526.973 | G10: Drinagh Co-Op | H10: 29357.022 | J10: Brett Brothers | K10: 6091.1639 | M10: Callan Co-Op | N10: 28795.07
A11: J.McKenna | B11: 1577.3252 | D11: Denis Brinicombe | E11: 35213.125 | G11: Drinagh Dairies | H11: 1861.2987 | J11: Callan Co-Op | K11: 18569.589 | M11: Carbery Group | N11: 0
A12: John McCarthy | B12: 1718.8938 | D12: Drinagh Co-Op | E12: 126328.56 | G12: Heat Merchants | H12: 139024.99 | J12: Carbery Group | K12: 3676.2018 | M12: Centenary Thurles Co-Op | N12: 0
A13: M.D O'Shea | B13: 10723.294 | D13: Drinagh Dairies | E13: 37654.623 | G13: J.McKenna | H13: 8256.0243 | J13: Centenary Thurles Co-Op | K13: 1971.3829 | M13: Centenary Thurles Feed & Grain | N13: 0
A14: McDonnell Bros | B14: 2705.2126 | D14: Heat Merchants | E14: 182616.2 | G14: John McCarthy | H14: 7743.7578 | J14: Centenary Thurles Feed & Grain | K14: 0 | M14: Centenary Thurles Fresh Milk | N14: 0
A15: Peter Curran | B15: 2001.2173 | D15: J.McKenna | E15: 38950.359 | G15: Lakeland Dairies | H15: 10351.673 | J15: Centenary Thurles Fresh Milk | K15: 0 | M15: Centenary Thurles Stores | N15: 0
... A38: Lakeland Dairies NI | B38: 1234.1567 | D38: Irish International Traders | E38: 11973.254 | G38: Wallaces Homevalue Hardware | H38: 511.21835 | J38: McDonogh Trade Centre Ltd | K38: 2080.7851 | M38: Smith's Building supplies | N38: 0
A39: McDonogh | B39: 1639.1647 | D39: Kelliher Mills | E39: 5036.8461 | G39: (blank) | J39: Mole Avon Town | K39: 1741.796 | M39: Smith's Tool Hire | N39: 0
A40: Organic Herd | B40: 1705.4342 | D40: Kerry | E40: 50281.249 | G40: Grand Total | H40: 591425.97 | J40: Morris DIY & Building | K40: 2975.0049 | M40: Strathroy Dairies | N40: 0
A41: Smiths Building | B41: 1431.7786 | D41: Lacpatrick Dairies | E41: 43704.813 | J41: North Cork Co-Op | K41: 12946.587 | M41: Wallaces Homevalue Hardware | N41: 10982.202
A42: Strathroy Dairy | B42: 724.86237 | D42: Lacpatrick Dairies NI | E42: 1377.5327 | J42: Organic Herd | K42: 3550.135 | M42: Aurivo Co-Op | N42: 14774.338
A43: Tirlan | B43: 37559.174 | D43: Lakeland Dairies | E43: 65443.519 | J43: Peter Curran Electrical | K43: 524.20515 | M43: Lacpatrick | N43: 0
A44: Brett Brother | B44: 3170.9805 | D44: Lakeland Dairies NI | E44: 61204.056 | J44: Richard Boyle & Sons Ltd | K44: 1692.951 | M44: Lakeland | N44: 0
A45: Kiernan Milling | B45: 3737.0849 | D45: McDonnell | E45: 46142.557 | J45: Smith's Building supplies | K45: 0 | M45: ICMSA | N45: 0
A46: Grand Total | B46: 178875.82 | D46: McDonogh | E46: 26741.631 | J46: Smith's Tool Hire | K46: 0 | M46: Kiernan | N46: 37631.882
D47: Organic Herd | E47: 24156.188 | J47: Strathroy Dairies | K47: 0 | M47: Organic Herd | N47: 0
D48: Smiths Building | E48: 17567.721 | J48: Wallaces Homevalue Hardware | K48: 34208.723 | M48: Discount
D49: Strathroy Dairy | E49: 15774.416 | J49: Wolseley | K49: 1955.4489 | M49: AIB Merchant Services | N49: 3383.4459
D50: Tirlan | E50: 395033.16 | J50: AIB Merchant Services | K50: 592.10304 | M50: Tirlan | N50: 0
D51: Kiernan Milling | E51: 14344.662 | J51: Tirlan | K51: 148914.92 | M51: T&A Building | N51: 0
D52: Adj | E52: 0 | J52: Adj | K52: 0 | M52: Grand Total | N52: 241612.42
D53: Grand Total | E53: 2739365.1 | J53: T&A Building | K53: 0
J54: Grand Total | K54: 711077.97

Sheet Deferred Maintenance
A1: Customer | B1: January | C1: February | D1: March | E1: April | F1: May | G1: June | H1: July | I1: August | J1: September | K1: October | L1: November | M1: December | N1: Cons EUR | O1: USD January | P1: USD February | Q1: USD March | R1: USD April | S1: USD May | T1: USD June | U1: USD July | V1: USD August | W1: USD September | X1: USD October | Y1: USD November | Z1: USD December | AA1: Consol USD
A2: Arrabawn | B2: 11498.217 | C2: 10385.486 | D2: 11498.217 | E2: 11127.307 | F2: 11930.951 | G2: 11546.082 | H2: 11967.596 | I2: 12009.806 | J2: 11622.393 | K2: 12009.806 | L2: 11622.393 | M2: 12009.806 | N2: =SUM(B2:M2) -> 139228.06 | O2: =B2/$B$57 -> 11896.389 | P2: =C2/$C$57 -> 10812.245 | Q2: =D2/$D$57 -> 12399.539 | R2: =E2/$E$57 -> 12500.204 | S2: =F2/$F$57 -> 13455.91 | T2: =G2/$G$57 -> 13300.865 | U2: =H2/$H$57 -> 13985.737 | V2: =I2/$I$57 -> 13988.15 | W2: =J2/$J$57 -> 13633.625 | X2: =K2/$K$57 -> 13984.078 | Y2: =L2/$L$57 -> 13435.982 | Z2: =M2/$M$57 -> 14066.629 | AA2: =SUM(O2:Z2) -> 157459.35
A3: Aurivo | B3: 14407.711 | C3: 13188.63 | D3: =14601.6913905693+0.01 -> 14601.701 | E3: 14130.669 | F3: 14601.691 | G3: 14130.669 | H3: 14367.176 | I3: 14367.176 | J3: 13903.719 | K3: 14367.176 | L3: 13903.719 | M3: 14367.176 | N3: =SUM(B3:M3) -> 170337.22 | O3: =B3/$B$57 -> 14906.636 | P3: =C3/$C$57 -> 13730.576 | Q3: =D3/$D$57 -> 15746.3 | R3: =E3/$E$57 -> 15874.124 | S3: =F3/$F$57 -> 16468.011 | T3: =G3/$G$57 -> 16278.26 | U3: =H3/$H$57 -> 16789.969 | V3: =I3/$I$57 -> 16733.844 | W3: =J3/$J$57 -> 16309.73 | X3: =K3/$K$57 -> 16728.973 | Y3: =L3/$L$57 -> 16073.292 | Z3: =M3/$M$57 -> 16827.726 | AA3: =SUM(O3:Z3) -> 192467.44
A4: Aurivo NI | B4: 651.09342 | C4: 588.08438 | D4: 651.09342 | E4: 630.09041 | F4: 651.09342 | G4: 630.09041 | H4: 651.09342 | I4: 651.09342 | J4: 630.09041 | K4: 651.09342 | L4: 630.09041 | M4: 651.09342 | N4: =SUM(B4:M4) -> 7666.1 | O4: =B4/$B$57 -> 673.64016 | P4: =C4/$C$57 -> 612.24989 | Q4: =D4/$D$57 -> 702.13135 | R4: =E4/$E$57 -> 707.83155 | S4: =F4/$F$57 -> 734.31313 | T4: =G4/$G$57 -> 725.85208 | U4: =H4/$H$57 -> 760.88983 | V4: =I4/$I$57 -> 758.34635 | W4: =J4/$J$57 -> 739.12633 | X4: =K4/$K$57 -> 758.1256 | Y4: =L4/$L$57 -> 728.41138 | Z4: =M4/$M$57 -> 762.60093 | AA4: =SUM(O4:Z4) -> 8663.5186
A5: BallyJamesDuff | B5: 1013.6315 | C5: 915.53812 | D5: 1013.6315 | E5: 980.9337 | F5: 1013.6315 | G5: 974.28 | H5: 997.10489 | I5: 997.10489 | J5: 964.94022 | K5: 997.10489 | L5: =964.940217391304-0.5 -> 964.44022 | M5: 997.10489 | N5: =SUM(B5:M5) -> 11829.446 | O5: =B5/$B$57 -> 1048.7326 | P5: =C5/$C$57 -> 953.15932 | Q5: =D5/$D$57 -> 1093.0881 | R5: =E5/$E$57 -> 1101.9622 | S5: =F5/$F$57 -> 1143.1891 | T5: =G5/$G$57 -> 1122.3519 | U5: =H5/$H$57 -> 1165.2505 | V5: =I5/$I$57 -> 1161.3554 | W5: =J5/$J$57 -> 1131.9212 | X5: =K5/$K$57 -> 1161.0173 | Y5: =L5/$L$57 -> 1114.934 | Z5: =M5/$M$57 -> 1167.871 | AA5: =SUM(O5:Z5) -> 13364.833
A6: Bandon Co-Op | B6: 8374.109 | C6: 7563.7113 | D6: 8374.109 | E6: 8103.9764 | F6: 8374.109 | G6: 8103.9764 | H6: 8374.109 | I6: 8374.109 | J6: 8103.9764 | K6: 8374.109 | L6: 8103.9764 | M6: 8374.109 | N6: =SUM(B6:M6) -> 98598.38 | O6: =B6/$B$57 -> 8664.0963 | P6: =C6/$C$57 -> 7874.5186 | Q6: =D6/$D$57 -> 9030.5389 | R6: =E6/$E$57 -> 9103.8526 | S6: =F6/$F$57 -> 9444.4483 | T6: =G6/$G$57 -> 9335.6255 | U6: =H6/$H$57 -> 9786.2674 | V6: =I6/$I$57 -> 9753.5541 | W6: =J6/$J$57 -> 9506.3537 | X6: =K6/$K$57 -> 9750.7149 | Y6: =L6/$L$57 -> 9368.5423 | Z6: =M6/$M$57 -> 9808.2749 | AA6: =SUM(O6:Z6) -> 111426.79
A7: Bandon Vale Cheese | B7: 1225.1744 | C7: 1106.6091 | D7: 1225.1744 | E7: 1185.6526 | F7: 1225.1744 | G7: 1185.6526 | H7: 1225.1744 | I7: 1225.1744 | J7: 1185.6526 | K7: 1225.1744 | L7: 1185.6526 | M7: 1225.1744 | N7: =SUM(B7:M7) -> 14425.44 | O7: =B7/$B$57 -> 1267.601 | P7: =C7/$C$57 -> 1152.0818 | Q7: =D7/$D$57 -> 1321.2134 | R7: =E7/$E$57 -> 1331.9395 | S7: =F7/$F$57 -> 1381.7704 | T7: =G7/$G$57 -> 1365.8491 | U7: =H7/$H$57 -> 1431.7802 | V7: =I7/$I$57 -> 1426.9941 | W7: =J7/$J$57 -> 1390.8275 | X7: =K7/$K$57 -> 1426.5787 | Y7: =L7/$L$57 -> 1370.665 | Z7: =M7/$M$57 -> 1435.0001 | AA7: =SUM(O7:Z7) -> 16302.301
A8: Barryroe Co-Op | B8: 6234.314 | C8: 5630.9933 | D8: 6234.314 | E8: 6033.2071 | F8: 6234.314 | G8: 6033.2071 | H8: 6234.314 | I8: 6234.314 | J8: 6033.2071 | K8: 6234.314 | L8: 6033.2071 | M8: 6234.314 | N8: =SUM(B8:M8) -> 73404.02 | O8: =B8/$B$57 -> 6450.2023 | P8: =C8/$C$57 -> 5862.3815 | Q8: =D8/$D$57 -> 6723.0096 | R8: =E8/$E$57 -> 6777.5898 | S8: =F8/$F$57 -> 7031.1548 | T8: =G8/$G$57 -> 6950.139 | U8: =H8/$H$57 -> 7285.6305 | V8: =I8/$I$57 -> 7261.2763 | W8: =J8/$J$57 -> 7077.2418 | X8: =K8/$K$57 -> 7259.1626 | Y8: =L8/$L$57 -> 6974.6447 | Z8: =M8/$M$57 -> 7302.0146 | AA8: =SUM(O8:Z8) -> 82954.448
A9: Brett Brothers | B9: 4014.2248 | C9: 3664.1743 | D9: 4056.7644 | E9: 3925.9011 | F9: 4124.247 | G9: 3991.2068 | H9: 4124.247 | I9: 4124.247 | J9: 3991.2068 | K9: 4124.247 | L9: 3991.2068 | M9: 4124.247 | N9: =SUM(B9:M9) -> 48255.92 | O9: =B9/$B$57 -> 4153.2335 | P9: =C9/$C$57 -> 3814.7422 | Q9: =D9/$D$57 -> 4374.7662 | R9: =E9/$E$57 -> 4410.2824 | S9: =F9/$F$57 -> 4651.3889 | T9: =G9/$G$57 -> 4597.7937 | U9: =H9/$H$57 -> 4819.7347 | V9: =I9/$I$57 -> 4803.6235 | W9: =J9/$J$57 -> 4681.8773 | X9: =K9/$K$57 -> 4802.2252 | Y9: =L9/$L$57 -> 4614.0052 | Z9: =M9/$M$57 -> 4830.5735 | AA9: =SUM(O9:Z9) -> 54554.246
A10: Callan Co-Op | B10: 1772.6063 | C10: 1601.0638 | D10: 1772.6063 | E10: 2533.6073 | F10: 2753.0273 | G10: 2664.22 | H10: 2753.0273 | I10: 2753.0273 | J10: 2664.22 | K10: 2753.0273 | L10: 2664.22 | M10: 2828.0273 | N10: =SUM(B10:M10) -> 29512.68 | O10: =B10/$B$57 -> 1833.99 | P10: =C10/$C$57 -> 1666.8545 | Q10: =D10/$D$57 -> 1911.5574 | R10: =E10/$E$57 -> 2846.2061 | S10: =F10/$F$57 -> 3104.9063 | T10: =G10/$G$57 -> 3069.1303 | U10: =H10/$H$57 -> 3217.2809 | V10: =I10/$I$57 -> 3206.5263 | W10: =J10/$J$57 -> 3125.258 | X10: =K10/$K$57 -> 3205.5929 | Y10: =L10/$L$57 -> 3079.9519 | Z10: =M10/$M$57 -> 3312.3607 | AA10: =SUM(O10:Z10) -> 33579.615
A11: Carbery | B11: 1478.6066 | C11: 1335.5156 | D11: 1478.6066 | E11: 1430.9096 | F11: 1478.6066 | G11: 1430.9096 | H11: 1478.6066 | I11: 1478.6066 | J11: 1430.9096 | K11: 1478.6066 | L11: 1430.9096 | M11: 1478.6066 | N11: =SUM(B11:M11) -> 17409.4 | O11: =B11/$B$57 -> 1529.8093 | P11: =C11/$C$57 -> 1390.3945 | Q11: =D11/$D$57 -> 1594.5116 | R11: =E11/$E$57 -> 1607.4565 | S11: =F11/$F$57 -> 1667.5951 | T11: =G11/$G$57 -> 1648.3804 | U11: =H11/$H$57 -> 1727.9497 | V11: =I11/$I$57 -> 1722.1736 | W11: =J11/$J$57 -> 1678.5257 | X11: =K11/$K$57 -> 1721.6723 | Y11: =L11/$L$57 -> 1654.1925 | Z11: =M11/$M$57 -> 1731.8356 | AA11: =SUM(O11:Z11) -> 19674.497
A12: Centenary Thurles Co-Op | B12: 3213.4771 | C12: 2902.4955 | D12: 3213.4771 | E12: 3109.8166 | F12: 3213.4771 | G12: 3109.8166 | H12: 3161.0835 | I12: 3161.0835 | J12: 3059.113 | K12: 3161.0835 | L12: 3059.113 | M12: 3161.0835 | N12: =SUM(B12:M12) -> 37525.12 | O12: =B12/$B$57 -> 3324.7567 | P12: =C12/$C$57 -> 3021.7645 | Q12: =D12/$D$57 -> 3465.3753 | R12: =E12/$E$57 -> 3493.5086 | S12: =F12/$F$57 -> 3624.2087 | T12: =G12/$G$57 -> 3582.4491 | U12: =H12/$H$57 -> 3694.1492 | V12: =I12/$I$57 -> 3681.8005 | W12: =J12/$J$57 -> 3588.4866 | X12: =K12/$K$57 -> 3680.7288 | Y12: =L12/$L$57 -> 3536.4651 | Z12: =M12/$M$57 -> 3702.4567 | AA12: =SUM(O12:Z12) -> 42396.15
A13: Centenary Thurles Feed & Grain | B13: 1515.3999 | C13: 1368.7483 | D13: 1515.3999 | E13: 1466.516 | F13: 1515.3999 | G13: 1466.516 | H13: 1490.6923 | I13: 1490.6923 | J13: 1442.6054 | K13: 1490.6923 | L13: 1442.6054 | M13: 1490.6923 | N13: =SUM(B13:M13) -> 17695.96 | O13: =B13/$B$57 -> 1567.8767 | P13: =C13/$C$57 -> 1424.9928 | Q13: =D13/$D$57 -> 1634.1891 | R13: =E13/$E$57 -> 1647.4561 | S13: =F13/$F$57 -> 1709.0912 | T13: =G13/$G$57 -> 1689.3983 | U13: =H13/$H$57 -> 1742.0735 | V13: =I13/$I$57 -> 1736.2501 | W13: =J13/$J$57 -> 1692.2455 | X13: =K13/$K$57 -> 1735.7447 | Y13: =L13/$L$57 -> 1667.7134 | Z13: =M13/$M$57 -> 1745.9911 | AA13: =SUM(O13:Z13) -> 19993.023
A14: Centenary Thurles Fresh Milk | B14: 858.17249 | C14: 775.12354 | D14: 858.17249 | E14: 830.4895 | F14: 858.17249 | G14: 830.4895 | H14: 844.18054 | I14: 844.18054 | J14: 816.94891 | K14: 844.18054 | L14: 816.94891 | M14: 844.18054 | N14: =SUM(B14:M14) -> 10021.24 | O14: =B14/$B$57 -> 887.89017 | P14: =C14/$C$57 -> 806.97483 | Q14: =D14/$D$57 -> 925.44293 | R14: =E14/$E$57 -> 932.95607 | S14: =F14/$F$57 -> 967.86007 | T14: =G14/$G$57 -> 956.70799 | U14: =H14/$H$57 -> 986.53797 | V14: =I14/$I$57 -> 983.24021 | W14: =J14/$J$57 -> 958.32033 | X14: =K14/$K$57 -> 982.95399 | Y14: =L14/$L$57 -> 944.42777 | Z14: =M14/$M$57 -> 988.75652 | AA14: =SUM(O14:Z14) -> 11322.069
A15: Centenary Thurles Stores | B15: 3526.5788 | C15: 3185.297 | D15: 3526.5788 | E15: 3412.8182 | F15: 3526.5788 | G15: 3412.8182 | H15: 3469.0803 | I15: 3469.0803 | J15: 3357.1745 | K15: 3469.0803 | L15: 3357.1745 | M15: 3469.0803 | N15: =SUM(B15:M15) -> 41181.34 | O15: =B15/$B$57 -> 3648.7009 | P15: =C15/$C$57 -> 3316.1869 | Q15: =D15/$D$57 -> 3803.0204 | R15: =E15/$E$57 -> 3833.8949 | S15: =F15/$F$57 -> 3977.3296 | T15: =G15/$G$57 -> 3931.5012 | U15: =H15/$H$57 -> 4054.0847 | V15: =I15/$I$57 -> 4040.5328 | W15: =J15/$J$57 -> 3938.1269 | X15: =K15/$K$57 -> 4039.3566 | Y15: =L15/$L$57 -> 3881.0368 | Z15: =M15/$M$57 -> 4063.2016 | AA15: =SUM(O15:Z15) -> 46526.973
A16: Dan O'Connor | B16: 3253.9893 | C16: 2939.0871 | D16: 3253.9893 | E16: 3149.0219 | F16: 3253.9893 | G16: 3149.0219 | H16: 3253.9893 | I16: 3253.9893 | J16: 3149.0219 | K16: 3253.9893 | L16: 3149.0219 | M16: 3253.9893 | N16: =SUM(B16:M16) -> 38313.1 | O16: =B16/$B$57 -> 3366.6718 | P16: =C16/$C$57 -> 3059.8598 | Q16: =D16/$D$57 -> 3509.0631 | R16: =E16/$E$57 -> 3537.5512 | S16: =F16/$F$57 -> 3669.899 | T16: =G16/$G$57 -> 3627.6129 | U16: =H16/$H$57 -> 3802.7221 | V16: =I16/$I$57 -> 3790.0105 | W16: =J16/$J$57 -> 3693.954 | X16: =K16/$K$57 -> 3788.9072 | Y16: =L16/$L$57 -> 3640.4036 | Z16: =M16/$M$57 -> 3811.2738 | AA16: =SUM(O16:Z16) -> 43297.929
A17: Denis Brinicombe | B17: 2547.7252 | C17: 2301.1712 | D17: 2547.7252 | E17: 2589.4558 | F17: 2675.771 | G17: 2589.4558 | H17: 2675.771 | I17: 2675.771 | J17: 2589.4558 | K17: 2675.771 | L17: 2589.4558 | M17: 2675.771 | N17: =SUM(B17:M17) -> 31133.3 | O17: =B17/$B$57 -> 2635.9505 | P17: =C17/$C$57 -> 2395.7307 | Q17: =D17/$D$57 -> 2747.4364 | R17: =E17/$E$57 -> 2908.9453 | S17: =F17/$F$57 -> 3017.7755 | T17: =G17/$G$57 -> 2983.0035 | U17: =H17/$H$57 -> 3126.9966 | V17: =I17/$I$57 -> 3116.5438 | W17: =J17/$J$57 -> 3037.5561 | X17: =K17/$K$57 -> 3115.6366 | Y17: =L17/$L$57 -> 2993.5213 | Z17: =M17/$M$57 -> 3134.0287 | AA17: =SUM(O17:Z17) -> 35213.125
... A21: ECV | B21: 2557.2868 | C21: 2309.8075 | D21: 2557.2868 | E21: 2474.7937 | F21: 2557.2868 | G21: 2597.4573 | H21: 2684.0392 | I21: 2696.7026 | J21: 2609.7122 | K21: 2696.7026 | L21: 2609.7122 | M21: 2696.7026 | N21: =SUM(B21:M21) -> 31047.49 | O21: =B21/$B$57 -> 2645.8432 | P21: =C21/$C$57 -> 2404.7218 | Q21: =D21/$D$57 -> 2757.7475 | R21: =E21/$E$57 -> 2780.136 | S21: =F21/$F$57 -> 2884.1472 | T21: =G21/$G$57 -> 2992.221 | U21: =H21/$H$57 -> 3136.6591 | V21: =I21/$I$57 -> 3140.9233 | W21: =J21/$J$57 -> 3061.3177 | X21: =K21/$K$57 -> 3140.009 | Y21: =L21/$L$57 -> 3016.9385 | Z21: =M21/$M$57 -> 3158.545 | AA21: =SUM(O21:Z21) -> 35119.209
A22: Hopkins | B22: 1506.8809 | C22: 1361.0537 | D22: 1506.8809 | E22: 1458.2718 | F22: 1506.8809 | G22: 1458.2718 | H22: 1482.3122 | I22: 1482.3122 | J22: 1434.4957 | K22: 1482.3122 | L22: 1434.4957 | M22: =1482.31217391304-0.83 -> 1481.4822 | N22: =SUM(B22:M22) -> 17595.65 | O22: =B22/$B$57 -> 1559.0627 | P22: =C22/$C$57 -> 1416.982 | Q22: =D22/$D$57 -> 1625.0023 | R22: =E22/$E$57 -> 1638.1948 | S22: =F22/$F$57 -> 1699.4833 | T22: =G22/$G$57 -> 1679.9012 | U22: =H22/$H$57 -> 1732.2802 | V22: =I22/$I$57 -> 1726.4896 | W22: =J22/$J$57 -> 1682.7323 | X22: =K22/$K$57 -> 1725.987 | Y22: =L22/$L$57 -> 1658.3381 | Z22: =M22/$M$57 -> 1735.2037 | AA22: =SUM(O22:Z22) -> 19879.657
A23: ICMSA | B23: 275.82271 | C23: 249.13019 | D23: 275.82271 | E23: 266.92521 | F23: 275.82271 | G23: 266.92521 | H23: 275.82271 | I23: 275.82271 | J23: 266.92521 | K23: 275.82271 | L23: 266.92521 | M23: 275.82271 | N23: =SUM(B23:M23) -> 3247.59 | O23: =B23/$B$57 -> 285.37419 | P23: =C23/$C$57 -> 259.36742 | Q23: =D23/$D$57 -> 297.44391 | R23: =E23/$E$57 -> 299.85868 | S23: =F23/$F$57 -> 311.07708 | T23: =G23/$G$57 -> 307.49272 | U23: =H23/$H$57 -> 322.33576 | V23: =I23/$I$57 -> 321.25827 | W23: =J23/$J$57 -> 313.11609 | X23: =K23/$K$57 -> 321.16475 | Y23: =L23/$L$57 -> 308.57692 | Z23: =M23/$M$57 -> 323.06064 | AA23: =SUM(O23:Z23) -> 3670.1264
A24: Irish International Traders | B24: 899.83148 | C24: 812.75101 | D24: 899.83148 | E24: 870.80466 | F24: 899.83148 | G24: 870.80466 | H24: 899.83148 | I24: 899.83148 | J24: 870.80466 | K24: 899.83148 | L24: 870.80466 | M24: 899.83148 | N24: =SUM(B24:M24) -> 10594.79 | O24: =B24/$B$57 -> 930.99177 | P24: =C24/$C$57 -> 846.14849 | Q24: =D24/$D$57 -> 970.36749 | R24: =E24/$E$57 -> 978.24534 | S24: =F24/$F$57 -> 1014.8437 | T24: =G24/$G$57 -> 1003.1503 | U24: =H24/$H$57 -> 1051.5735 | V24: =I24/$I$57 -> 1048.0584 | W24: =J24/$J$57 -> 1021.4957 | X24: =K24/$K$57 -> 1047.7533 | Y24: =L24/$L$57 -> 1006.6873 | Z24: =M24/$M$57 -> 1053.9383 | AA24: =SUM(O24:Z24) -> 11973.254
A25: J.McKenna | B25: 2978.6247 | C25: =2690.37-39.09 -> 2651.28 | D25: 2978.6247 | E25: 2850.8637 | F25: 2945.8925 | G25: 2850.8637 | H25: =2913.87195652174-36.57 -> 2877.302 | I25: 2913.872 | J25: 2819.8761 | K25: 2913.872 | L25: 2819.8761 | M25: =2913.87195652174-36.57 -> 2877.302 | N25: =SUM(B25:M25) -> 34478.249 | O25: =B25/$B$57 -> 3081.7716 | P25: =C25/$C$57 -> 2760.2261 | Q25: =D25/$D$57 -> 3212.1132 | R25: =E25/$E$57 -> 3202.6059 | S25: =F25/$F$57 -> 3322.4227 | T25: =G25/$G$57 -> 3284.1404 | U25: =H25/$H$57 -> 3362.5125 | V25: =I25/$I$57 -> 3393.8665 | W25: =J25/$J$57 -> 3307.8501 | X25: =K25/$K$57 -> 3392.8786 | Y25: =L25/$L$57 -> 3259.897 | Z25: =M25/$M$57 -> 3370.0742 | AA25: =SUM(O25:Z25) -> 38950.359
A26: John McCarthy | B26: 1818.9501 | C26: =1642.92263013699-0.54 -> 1642.3826 | D26: 1818.9501 | E26: 1723.7 | F26: 1818.9501 | G26: 1760.2742 | H26: 1818.9501 | I26: 1818.9501 | J26: 1760.2742 | K26: 1818.9501 | L26: 1760.2742 | M26: 1818.9501 | N26: =SUM(B26:M26) -> 21379.556 | O26: =B26/$B$57 -> 1881.9385 | P26: =C26/$C$57 -> 1709.8712 | Q26: =D26/$D$57 -> 1961.534 | R26: =E26/$E$57 -> 1936.3717 | S26: =F26/$F$57 -> 2051.4397 | T26: =G26/$G$57 -> 2027.8022 | U26: =H26/$H$57 -> 2125.6866 | V26: =I26/$I$57 -> 2118.581 | W26: =J26/$J$57 -> 2064.8863 | X26: =K26/$K$57 -> 2117.9642 | Y26: =L26/$L$57 -> 2034.9521 | Z26: =M26/$M$57 -> 2130.4669 | AA26: =SUM(O26:Z26) -> 24161.494
A27: Kelliher Mills | B27: 383.94189 | C27: 346.78622 | D27: 383.94189 | E27: 367.47363 | F27: 379.72275 | G27: 367.47363 | H27: 375.59533 | I27: 375.59533 | J27: =363.479347826087-0.08 -> 363.39935 | K27: 375.59533 | L27: 363.47935 | M27: 375.59533 | N27: =SUM(B27:M27) -> 4458.6 | O27: =B27/$B$57 -> 397.23743 | P27: =C27/$C$57 -> 361.03633 | Q27: =D27/$D$57 -> 414.03834 | R27: =E27/$E$57 -> 412.81286 | S27: =F27/$F$57 -> 428.25713 | T27: =G27/$G$57 -> 423.32257 | U27: =H27/$H$57 -> 438.93342 | V27: =I27/$I$57 -> 437.46617 | W27: =J27/$J$57 -> 426.2849 | X27: =K27/$K$57 -> 437.33882 | Y27: =L27/$L$57 -> 420.19762 | Z27: =M27/$M$57 -> 439.9205 | AA27: =SUM(O27:Z27) -> 5036.8461
A28: Kerry | B28: 3778.81 | C28: 3413.1187 | D28: 3778.81 | E28: 3656.9129 | F28: 3778.81 | G28: 3656.9129 | H28: 3778.81 | I28: 3778.81 | J28: 3656.9129 | K28: 3778.81 | L28: 3656.9129 | M28: 3778.81 | N28: =SUM(B28:M28) -> 44492.44 | O28: =B28/$B$57 -> 3909.6665 | P28: =C28/$C$57 -> 3553.3702 | Q28: =D28/$D$57 -> 4075.0234 | R28: =E28/$E$57 -> 4108.1062 | S28: =F28/$F$57 -> 4261.7997 | T28: =G28/$G$57 -> 4212.6935 | U28: =H28/$H$57 -> 4416.0453 | V28: =I28/$I$57 -> 4401.2835 | W28: =J28/$J$57 -> 4289.7345 | X28: =K28/$K$57 -> 4400.0023 | Y28: =L28/$L$57 -> 4227.5472 | Z28: =M28/$M$57 -> 4425.9762 | AA28: =SUM(O28:Z28) -> 50281.249
A29: Kiernan Milling | J29: 3012.2951 | K29: 3112.7049 | L29: 3012.2951 | M29: 3162.7049 | N29: =SUM(B29:M29) -> 12300 | O29: =B29/$B$57 -> 0 | P29: =C29/$C$57 -> 0 | Q29: =D29/$D$57 -> 0 | R29: =E29/$E$57 -> 0 | S29: =F29/$F$57 -> 0 | T29: =G29/$G$57 -> 0 | U29: =H29/$H$57 -> 0 | V29: =I29/$I$57 -> 0 | W29: =J29/$J$57 -> 3533.5669 | X29: =K29/$K$57 -> 3624.3973 | Y29: =L29/$L$57 -> 3482.3415 | Z29: =M29/$M$57 -> 3704.3558 | AA29: =SUM(O29:Z29) -> 14344.662
A30: Lacpatrick Dairies | B30: 2985.2587 | C30: 2696.3627 | D30: 2985.2587 | E30: 3289.0154 | F30: 3398.6492 | G30: 3289.0154 | H30: 3361.7074 | I30: 3361.7074 | J30: 3253.2652 | K30: 3361.7074 | L30: 3253.2652 | M30: 3361.7074 | N30: =SUM(B30:M30) -> 38596.92 | O30: =B30/$B$57 -> 3088.6353 | P30: =C30/$C$57 -> 2807.1613 | Q30: =D30/$D$57 -> 3219.2672 | R30: =E30/$E$57 -> 3694.8172 | S30: =F30/$F$57 -> 3833.0486 | T30: =G30/$G$57 -> 3788.8827 | U30: =H30/$H$57 -> 3928.6051 | V30: =I30/$I$57 -> 3915.4727 | W30: =J30/$J$57 -> 3816.2364 | X30: =K30/$K$57 -> 3914.3329 | Y30: =L30/$L$57 -> 3760.9133 | Z30: =M30/$M$57 -> 3937.4398 | AA30: =SUM(O30:Z30) -> 43704.813
A31: Lakeland Dairies | B31: 4918.3071 | C31: 4442.3419 | D31: 4918.3071 | E31: 4759.6521 | F31: 4918.3071 | G31: 4759.6521 | H31: 4918.3071 | I31: 4918.3071 | J31: 4759.6521 | K31: 4918.3071 | L31: 4759.6521 | M31: 4918.3071 | N31: =SUM(B31:M31) -> 57909.1 | O31: =B31/$B$57 -> 5088.6233 | P31: =C31/$C$57 -> 4624.8862 | Q31: =D31/$D$57 -> 5303.8435 | R31: =E31/$E$57 -> 5346.9023 | S31: =F31/$F$57 -> 5546.9421 | T31: =G31/$G$57 -> 5483.0279 | U31: =H31/$H$57 -> 5747.7003 | V31: =I31/$I$57 -> 5728.487 | W31: =J31/$J$57 -> 5583.3006 | X31: =K31/$K$57 -> 5726.8195 | Y31: =L31/$L$57 -> 5502.3607 | Z31: =M31/$M$57 -> 5760.6258 | AA31: =SUM(O31:Z31) -> 65443.519
A32: Lacpatrick Dairies NI | B32: 451.15333 | C32: 407.49333 | D32: 451.15333 | M32: 0 | N32: =SUM(B32:M32) -> 1309.8 | O32: =B32/$B$57 -> 466.77634 | P32: =C32/$C$57 -> 424.23801 | Q32: =D32/$D$57 -> 486.51835 | R32: =E32/$E$57 -> 0 | S32: =F32/$F$57 -> 0 | T32: =G32/$G$57 -> 0 | U32: =H32/$H$57 -> 0 | V32: =I32/$I$57 -> 0 | W32: =J32/$J$57 -> 0 | X32: =K32/$K$57 -> 0 | Y32: =L32/$L$57 -> 0 | Z32: =M32/$M$57 -> 0 | AA32: =SUM(O32:Z32) -> 1377.5327
A33: Lakeland Dairies NI | B33: 4599.6968 | C33: 4154.5648 | D33: 4599.6968 | E33: 4451.3195 | F33: 4599.6968 | G33: 4451.3195 | H33: 4599.6968 | I33: 4599.6968 | J33: 4451.3195 | K33: 4599.6968 | L33: 4451.3195 | M33: 4599.6968 | N33: =SUM(B33:M33) -> 54157.72 | O33: =B33/$B$57 -> 4758.9798 | P33: =C33/$C$57 -> 4325.2838 | Q33: =D33/$D$57 -> 4960.2579 | R33: =E33/$E$57 -> 5000.5274 | S33: =F33/$F$57 -> 5187.6084 | T33: =G33/$G$57 -> 5127.8347 | U33: =H33/$H$57 -> 5375.3614 | V33: =I33/$I$57 -> 5357.3928 | W33: =J33/$J$57 -> 5221.6116 | X33: =K33/$K$57 -> 5355.8333 | Y33: =L33/$L$57 -> 5145.9151 | Z33: =M33/$M$57 -> 5387.4497 | AA33: =SUM(O33:Z33) -> 61204.056
A34: Lee Strand | B34: 3549.9391 | C34: 3206.3966 | D34: 3549.9391 | E34: 3435.4249 | F34: 3549.9391 | G34: 3435.4249 | H34: 3549.9391 | I34: 3549.9391 | J34: 3435.4249 | K34: 3549.9391 | L34: 3435.4249 | M34: 3549.9391 | N34: =SUM(B34:M34) -> 41797.67 | O34: =B34/$B$57 -> 3672.8701 | P34: =C34/$C$57 -> 3338.1535 | Q34: =D34/$D$57 -> 3828.2118 | R34: =E34/$E$57 -> 3859.2908 | S34: =F34/$F$57 -> 4003.6757 | T34: =G34/$G$57 -> 3957.5437 | U34: =H34/$H$57 -> 4148.5791 | V34: =I34/$I$57 -> 4134.7113 | W34: =J34/$J$57 -> 4029.9185 | X34: =K34/$K$57 -> 4133.5077 | Y34: =L34/$L$57 -> 3971.4977 | Z34: =M34/$M$57 -> 4157.9085 | AA34: =SUM(O34:Z34) -> 47235.868
A35: Lisavaird | B35: 7861.6493 | C35: 7100.8445 | D35: 7976.8862 | E35: 7755.5673 | F35: 8014.0862 | G35: 7791.5491 | H35: 8051.2674 | I35: 8051.2674 | J35: 7791.5491 | K35: 8051.2674 | L35: 7791.5491 | M35: 8051.2674 | N35: =SUM(B35:M35) -> 94288.75 | O35: =B35/$B$57 -> 8133.8906 | P35: =C35/$C$57 -> 7392.6317 | Q35: =D35/$D$57 -> 8602.1785 | R35: =E35/$E$57 -> 8712.4564 | S35: =F35/$F$57 -> 9038.4091 | T35: =G35/$G$57 -> 8975.7152 | U35: =H35/$H$57 -> 9408.9837 | V35: =I35/$I$57 -> 9377.5317 | W35: =J35/$J$57 -> 9139.8614 | X35: =K35/$K$57 -> 9374.8019 | Y35: =L35/$L$57 -> 9007.3629 | Z35: =M35/$M$57 -> 9430.1428 | AA35: =SUM(O35:Z35) -> 106593.97
A36: M.D O'Shea | B36: 8301.1283 | C36: =7497.79-0.06 -> 7497.73 | D36: 8301.1283 | E36: 7945.0714 | F36: 8209.9071 | G36: 8043.2023 | H36: 8425.9296 | I36: 8425.9296 | J36: =8154.12540633889-0.86 -> 8153.2654 | K36: =8510.16871698496-0.06 -> 8510.1087 | L36: 8235.6471 | M36: 8510.1687 | N36: =SUM(B36:M36) -> 98559.217 | O36: =B36/$B$57 -> 8588.5884 | P36: =C36/$C$57 -> 7805.826 | Q36: =D36/$D$57 -> 8951.8374 | R36: =E36/$E$57 -> 8925.3417 | S36: =F36/$F$57 -> 9259.259 | T36: =G36/$G$57 -> 9265.6148 | U36: =H36/$H$57 -> 9846.8267 | V36: =I36/$I$57 -> 9813.911 | W36: =J36/$J$57 -> 9564.1721 | X36: =K36/$K$57 -> 9909.0714 | Y36: =L36/$L$57 -> 9520.7592 | Z36: =M36/$M$57 -> 9967.6365 | AA36: =SUM(O36:Z36) -> 111418.84
A37: McDonnell | B37: 3467.773 | C37: 3132.182 | D37: 3467.773 | E37: 3355.9093 | F37: 3467.773 | G37: 3355.9093 | H37: 3467.773 | I37: 3467.773 | J37: 3355.9093 | K37: 3467.773 | L37: 3355.9093 | M37: 3467.773 | N37: =SUM(B37:M37) -> 40830.23 | O37: =B37/$B$57 -> 3587.8586 | P37: =C37/$C$57 -> 3260.8893 | Q37: =D37/$D$57 -> 3739.6048 | R37: =E37/$E$57 -> 3769.9645 | S37: =F37/$F$57 -> 3911.0074 | T37: =G37/$G$57 -> 3865.9432 | U37: =H37/$H$57 -> 4052.5569 | V37: =I37/$I$57 -> 4039.0102 | W37: =J37/$J$57 -> 3936.6429 | X37: =K37/$K$57 -> 4037.8344 | Y37: =L37/$L$57 -> 3879.5742 | Z37: =M37/$M$57 -> 4061.6704 | AA37: =SUM(O37:Z37) -> 46142.557
A38: McDonogh | B38: 1995.1184 | C38: 1802.0424 | D38: 1995.1184 | E38: 1930.7597 | F38: 1995.1184 | G38: 1930.7597 | H38: 1995.1184 | I38: 1995.1184 | J38: 1971.7442 | K38: 2037.469 | L38: 1971.7442 | M38: 2037.469 | N38: =SUM(B38:M38) -> 23657.58 | O38: =B38/$B$57 -> 2064.2074 | P38: =C38/$C$57 -> 1876.0918 | Q38: =D38/$D$57 -> 2151.5118 | R38: =E38/$E$57 -> 2168.9787 | S38: =F38/$F$57 -> 2250.1251 | T38: =G38/$G$57 -> 2224.1982 | U38: =H38/$H$57 -> 2331.5629 | V38: =I38/$I$57 -> 2323.769 | W38: =J38/$J$57 -> 2312.9506 | X38: =K38/$K$57 -> 2372.4051 | Y38: =L38/$L$57 -> 2279.4203 | Z38: =M38/$M$57 -> 2386.4098 | AA38: =SUM(O38:Z38) -> 26741.631
A39: Morris DIY | B39: 3763.6946 | C39: 3399.4661 | D39: 3763.6946 | E39: 3642.2851 | F39: 3763.6946 | G39: 3642.2851 | H39: 3702.33 | I39: 3702.33 | J39: 3582.9 | K39: 3702.33 | L39: 3582.9 | M39: 3702.33 | N39: =SUM(B39:M39) -> 43950.24 | O39: =B39/$B$57 -> 3894.0277 | P39: =C39/$C$57 -> 3539.1566 | Q39: =D39/$D$57 -> 4058.7232 | R39: =E39/$E$57 -> 4091.6736 | S39: =F39/$F$57 -> 4244.7524 | T39: =G39/$G$57 -> 4195.8426 | U39: =H39/$H$57 -> 4326.6682 | V39: =I39/$I$57 -> 4312.2052 | W39: =J39/$J$57 -> 4202.9139 | X39: =K39/$K$57 -> 4310.9499 | Y39: =L39/$L$57 -> 4141.9852 | Z39: =M39/$M$57 -> 4336.3981 | AA39: =SUM(O39:Z39) -> 49655.296
A40: North Cork | B40: 6704.99 | C40: 6056.12 | D40: 6704.99 | E40: 6488.7 | F40: 6704.99 | G40: 6488.7 | H40: 6595.6695 | I40: 6595.6695 | J40: 6382.906 | K40: 6595.6695 | L40: 6382.906 | M40: 6595.6695 | N40: =SUM(B40:M40) -> 78296.98 | O40: =B40/$B$57 -> 6937.1773 | P40: =C40/$C$57 -> 6304.9775 | Q40: =D40/$D$57 -> 7230.5809 | R40: =E40/$E$57 -> 7289.2818 | S40: =F40/$F$57 -> 7561.9904 | T40: =G40/$G$57 -> 7474.858 | U40: =H40/$H$57 -> 7707.9228 | V40: =I40/$I$57 -> 7682.157 | W40: =J40/$J$57 -> 7487.4554 | X40: =K40/$K$57 -> 7679.9207 | Y40: =L40/$L$57 -> 7378.9114 | Z40: =M40/$M$57 -> 7725.2565 | AA40: =SUM(O40:Z40) -> 88460.49
A41: Organic Herd | B41: 1815.4212 | C41: 1639.7352 | D41: 1815.4212 | E41: 1756.8592 | F41: 1815.4212 | G41: 1756.8592 | H41: 1815.4212 | I41: 1815.4212 | J41: 1756.8592 | K41: 1815.4212 | L41: 1756.8592 | M41: 1815.4212 | N41: =SUM(B41:M41) -> 21375.12 | O41: =B41/$B$57 -> 1878.2874 | P41: =C41/$C$57 -> 1707.1151 | Q41: =D41/$D$57 -> 1957.7284 | R41: =E41/$E$57 -> 1973.6221 | S41: =F41/$F$57 -> 2047.4598 | T41: =G41/$G$57 -> 2023.8681 | U41: =H41/$H$57 -> 2121.5626 | V41: =I41/$I$57 -> 2114.4707 | W41: =J41/$J$57 -> 2060.8802 | X41: =K41/$K$57 -> 2113.8552 | Y41: =L41/$L$57 -> 2031.0041 | Z41: =M41/$M$57 -> 2126.3337 | AA41: =SUM(O41:Z41) -> 24156.188
A42: Peter Curran | B42: 2692.8912 | C42: 2432.2888 | D42: 2692.8912 | E42: 2606.0238 | F42: 2692.8912 | G42: 2606.0238 | H42: 2648.9854 | I42: 2648.9854 | J42: 2563.5342 | K42: 2648.9854 | L42: 2563.5342 | M42: 2648.9854 | N42: =SUM(B42:M42) -> 31446.02 | O42: =B42/$B$57 -> 2786.1434 | P42: =C42/$C$57 -> 2532.2362 | Q42: =D42/$D$57 -> 2903.9816 | R42: =E42/$E$57 -> 2927.5574 | S42: =F42/$F$57 -> 3037.0839 | T42: =G42/$G$57 -> 3002.0894 | U42: =H42/$H$57 -> 3095.694 | V42: =I42/$I$57 -> 3085.3458 | W42: =J42/$J$57 -> 3007.1488 | X42: =K42/$K$57 -> 3084.4477 | Y42: =L42/$L$57 -> 2963.5549 | Z42: =M42/$M$57 -> 3102.6557 | AA42: =SUM(O42:Z42) -> 35527.939
A43: Richard Boyle | B43: 5531.9329 | C43: 4996.5845 | D43: 5531.9329 | E43: 5353.4834 | F43: 5531.9329 | G43: 5353.4834 | H43: 5441.7383 | I43: 5441.7383 | J43: 5266.1984 | K43: 5441.7383 | L43: 5266.1984 | M43: 5441.7383 | N43: =SUM(B43:M43) -> 64598.7 | O43: =B43/$B$57 -> 5723.4984 | P43: =C43/$C$57 -> 5201.9037 | Q43: =D43/$D$57 -> 5965.5702 | R43: =E43/$E$57 -> 6014.0012 | S43: =F43/$F$57 -> 6238.9986 | T43: =G43/$G$57 -> 6167.1103 | U43: =H43/$H$57 -> 6359.3997 | V43: =I43/$I$57 -> 6338.1417 | W43: =J43/$J$57 -> 6177.5037 | X43: =K43/$K$57 -> 6336.2967 | Y43: =L43/$L$57 -> 6087.9498 | Z43: =M43/$M$57 -> 6373.7009 | AA43: =SUM(O43:Z43) -> 72984.075
A44: Smiths Building | B44: 1339.1036 | C44: 1209.5129 | D44: 1339.1036 | E44: 1281.6659 | F44: 1324.3881 | G44: 1281.6659 | H44: 1309.9926 | I44: 1309.9926 | J44: 1267.7348 | K44: 1309.9926 | L44: 1267.7348 | M44: 1309.9926 | N44: =SUM(B44:M44) -> 15550.88 | O44: =B44/$B$57 -> 1385.4754 | P44: =C44/$C$57 -> 1259.2141 | Q44: =D44/$D$57 -> 1444.0732 | R44: =E44/$E$57 -> 1439.7991 | S44: =F44/$F$57 -> 1493.6652 | T44: =G44/$G$57 -> 1476.4546 | U44: =H44/$H$57 -> 1530.9017 | V44: =I44/$I$57 -> 1525.7843 | W44: =J44/$J$57 -> 1487.1138 | X44: =K44/$K$57 -> 1525.3401 | Y44: =L44/$L$57 -> 1465.5555 | Z44: =M44/$M$57 -> 1534.3445 | AA44: =SUM(O44:Z44) -> 17567.721
A45: Smiths Tools | B45: 493.99878 | C45: 446.19244 | D45: 493.99878 | E45: 472.80989 | F45: 488.57022 | G45: -961.38011 | H45: 0 | I45: 0 | J45: 0 | K45: 0 | L45: 0 | M45: 0 | N45: =SUM(B45:M45) -> 1434.19 | O45: =B45/$B$57 -> 511.10548 | P45: =C45/$C$57 -> 464.52734 | Q45: =D45/$D$57 -> 532.72237 | R45: =E45/$E$57 -> 531.14561 | S45: =F45/$F$57 -> 551.01697 | T45: =G45/$G$57 -> -1107.4915 | U45: =H45/$H$57 -> 0 | V45: =I45/$I$57 -> 0 | W45: =J45/$J$57 -> 0 | X45: =K45/$K$57 -> 0 | Y45: =L45/$L$57 -> 0 | Z45: =M45/$M$57 -> 0 | AA45: =SUM(O45:Z45) -> 1483.0263
A46: Strathroy Dairy | B46: 1185.502 | C46: 1070.776 | D46: 1185.502 | E46: 1147.26 | F46: 1185.502 | G46: 1147.26 | H46: 1185.502 | I46: 1185.502 | J46: 1147.26 | K46: 1185.502 | L46: 1147.26 | M46: 1185.502 | N46: =SUM(B46:M46) -> 13958.33 | O46: =B46/$B$57 -> 1226.5548 | P46: =C46/$C$57 -> 1114.7762 | Q46: =D46/$D$57 -> 1278.4312 | R46: =E46/$E$57 -> 1288.81 | S46: =F46/$F$57 -> 1337.0273 | T46: =G46/$G$57 -> 1321.6215 | U46: =H46/$H$57 -> 1385.4178 | V46: =I46/$I$57 -> 1380.7867 | W46: =J46/$J$57 -> 1345.7911 | X46: =K46/$K$57 -> 1380.3847 | Y46: =L46/$L$57 -> 1326.2815 | Z46: =M46/$M$57 -> 1388.5333 | AA46: =SUM(O46:Z46) -> 15774.416
A47: T&A Building | B47: 1789.2236 | C47: 1616.0729 | D47: 1789.2236 | E47: 1712.4791 | F47: 1769.5618 | G47: 1712.4791 | H47: 1750.3274 | I47: 1750.3274 | J47: 1693.8652 | K47: 1750.3274 | L47: 1693.8652 | M47: 1750.3274 | N47: =SUM(B47:M47) -> 20778.08 | O47: =B47/$B$57 -> 1851.1826 | P47: =C47/$C$57 -> 1682.4804 | Q47: =D47/$D$57 -> 1929.4773 | R47: =E47/$E$57 -> 1923.7664 | S47: =F47/$F$57 -> 1995.7388 | T47: =G47/$G$57 -> 1972.7431 | U47: =H47/$H$57 -> 2045.4919 | V47: =I47/$I$57 -> 2038.6543 | W47: =J47/$J$57 -> 1986.9853 | X47: =K47/$K$57 -> 2038.0608 | Y47: =L47/$L$57 -> 1958.1804 | Z47: =M47/$M$57 -> 2050.0918 | AA47: =SUM(O47:Z47) -> 23472.853
A48: Tirlan | B48: 29942.105 | C48: =27044.4822099448 -> 27044.482 | D48: 29942.105 | E48: 28976.231 | F48: 29942.105 | G48: 28976.231 | H48: 29453.919 | I48: =29453.9188043478+0.01 -> 29453.929 | J48: =28503.7923913043 -> 28503.792 | K48: 29453.919 | L48: 28503.792 | M48: 29453.919 | N48: =SUM(B48:M48) -> 349646.53 | O48: =B48/$B$57 -> 30978.971 | P48: =C48/$C$57 -> 28155.791 | Q48: =D48/$D$57 -> 32289.208 | R48: =E48/$E$57 -> 32551.345 | S48: =F48/$F$57 -> 33769.165 | T48: =G48/$G$57 -> 33380.063 | U48: =H48/$H$57 -> 34420.847 | V48: =I48/$I$57 -> 34305.798 | W48: =J48/$J$57 -> 33436.318 | X48: =K48/$K$57 -> 34295.8 | Y48: =L48/$L$57 -> 32951.599 | Z48: =M48/$M$57 -> 34498.253 | AA48: =SUM(O48:Z48) -> 395033.16
A49: Wallaces | B49: 5094.8271 | C49: 4601.7793 | D49: 4668.1506 | E49: 4788.2523 | F49: 4947.8607 | G49: 4788.2523 | H49: 4947.8607 | I49: 4947.8607 | J49: =4788.25232876712+0.01 -> 4788.2623 | K49: 5048.9477 | L49: 4886.0784 | M49: 5048.9677 | N49: =SUM(B49:M49) -> 58557.1 | O49: =B49/$B$57 -> 5271.256 | P49: =C49/$C$57 -> 4790.8751 | Q49: =D49/$D$57 -> 5034.0777 | R49: =E49/$E$57 -> 5379.0313 | S49: =F49/$F$57 -> 5580.2731 | T49: =G49/$G$57 -> 5515.9749 | U49: =H49/$H$57 -> 5782.2376 | V49: =I49/$I$57 -> 5762.909 | W49: =J49/$J$57 -> 5616.8618 | X49: =K49/$K$57 -> 5878.9359 | Y49: =L49/$L$57 -> 5648.515 | Z49: =M49/$M$57 -> 5913.6636 | AA49: =SUM(O49:Z49) -> 66174.611
A50: Adj | B50: 0 | E50: 0 | F50: 0 | G50: 0 | H50: 0 | K50: 0 | L50: 0 | M50: 0 | N50: =SUM(B50:M50) -> 0 | O50: =B50/$B$57 -> 0 | P50: =C50/$C$57 -> 0 | Q50: =D50/$D$57 -> 0 | R50: =E50/$E$57 -> 0 | S50: =F50/$F$57 -> 0 | T50: =G50/$G$57 -> 0 | U50: =H50/$H$57 -> 0 | V50: =I50/$I$57 -> 0 | W50: =J50/$J$57 -> 0 | X50: =K50/$K$57 -> 0 | Y50: =L50/$L$57 -> 0 | Z50: =M50/$M$57 -> 0 | AA50: =SUM(O50:Z50) -> 0
B51: =SUM(B2:B50) -> 204296.63 | C51: =SUM(C2:C50) -> 184699.93 | D51: =SUM(D2:D50) -> 204221.72 | E51: =SUM(E2:E50) -> 198647.02 | F51: =SUM(F2:F50) -> 205941.56 | G51: =SUM(G2:G50) -> 198114.22 | H51: =SUM(H2:H50) -> 204509.13 | I51: =SUM(I2:I50) -> 204600.58 | ... AA51: =SUM(AA2:AA50) -> 2739365.1
A53: GP CHECK | B53: 204296.63 | C53: 184699.93 | D53: 204221.72 | E53: 198647.02 | F53: 205941.56 | G53: 198114.22 | H53: 204509.13 | I53: 204600.58 | J53: 201052.9 | K53: 207940.89 | L53: 201347.44 | M53: 208147.16
A55: Variance | B55: =B51-B53 -> 0 | C55: =C51-C53 -> 4.0258077e-05 | D55: =D51-D53 -> -0.00043225382 | E55: =E51-E53 -> 0 | F55: =F51-F53 -> 0 | G55: =G51-G53 -> 0 | H55: =H51-H53 -> 0 | I55: =I51-I53 -> 0 | ... M55: =M51-M53 -> 0 | O55: =B53/B57 -> 211371.22 | P55: =C53/C57 -> 192289.6 | Q55: =D53/D57 -> 220230.26 | R55: =E53/E57 -> 223156.27 | S55: =F53/F57 -> 232264.05 | T55: =G53/G57 -> 228223.78 | U55: =H53/H57 -> 238996.29 | V55: =I53/I57 -> 238303.9 | ... Z55: =M53/M57 -> 243794.84
A57: Monthly Avg Rate 25 | B57: 0.96653 | C57: 0.96053 | D57: 0.92731 | E57: 0.89017 | F57: 0.88667 | G57: 0.86807 | H57: 0.8557 | I57: 0.85857 | J57: 0.85248 | K57: 0.85882 | L57: 0.86502 | M57: 0.85378 | O57: =O51-O55 -> 0 | P57: =P51-P55 -> 4.1912397e-05 | Q57: =Q51-Q55 -> -0.00046613725 | R57: =R51-R55 -> 0 | S57: =S51-S55 -> 0 | T57: =T51-T55 -> 0 | U57: =U51-U55 -> 0 | V57: =V51-V55 -> 0 | ... Z57: =Z51-Z55 -> 0
K59: Total | L59: =SUM(B51:M51) -> 2423519.2 | M59: =AA51 -> 2739365.1
K60: BPC
K61: Variance | L61: =L59-L60 -> 2423519.2 | M61: =M59-M60 -> 2739365.1

Sheet Hosting
A1: Customer | B1: January | C1: February | D1: March | E1: April | F1: May | G1: June | H1: July | I1: August | J1: September | K1: October | L1: November | M1: December | N1: Consildated Eur | O1: Jan USD | P1: Feb USD | Q1: March USD | R1: Apr USD | S1: May USD | T1: June USD | U1: July USD | V1: August USD | W1: Sept USD | X1: Oct USD | Y1: Nov USD | Z1: Dec USD | AA1: Consol USD
A2: Arrabawn | B2: 897.49332 | C2: 810.63912 | D2: 897.49332 | E2: 868.54192 | F2: 897.49332 | G2: 868.54192 | H2: 897.49332 | I2: 897.49332 | J2: 868.54192 | K2: 897.49332 | L2: 868.54192 | M2: 897.49332 | N2: =SUM(B2:M2) -> 10567.26 | O2: =B2/$B$44 -> 928.57264 | P2: =C2/$C$44 -> 843.94982 | Q2: =D2/$D$44 -> 967.84604 | R2: =E2/$E$44 -> 975.70342 | S2: =F2/$F$44 -> 1012.2067 | T2: =G2/$G$44 -> 1000.5436 | U2: =H2/$H$44 -> 1048.8411 | V2: =I2/$I$44 -> 1045.3351 | W2: =J2/$J$44 -> 1018.8414 | X2: =K2/$K$44 -> 1045.0308 | Y2: =L2/$L$44 -> 1004.0715 | Z2: =M2/$M$44 -> 1051.1997 | AA2: =SUM(O2:Z2) -> 11942.142 | AD2: 868.97235 | AE2: =AD2/0.95474 -> 910.16648 | AF2: =AE2-Z2 -> -141.03326
A3: BallyJamesDuff | B3: 685.75737 | C3: 619.39375 | D3: 685.75737 | E3: 663.63616 | F3: 685.75737 | G3: 663.63616 | H3: 685.75737 | I3: 685.75737 | J3: 663.63616 | K3: 685.75737 | L3: 663.63616 | M3: 685.75737 | N3: =SUM(B3:M3) -> 8074.24 | O3: =B3/$B$44 -> 709.50448 | P3: =C3/$C$44 -> 644.84582 | Q3: =D3/$D$44 -> 739.51254 | R3: =E3/$E$44 -> 745.51621 | S3: =F3/$F$44 -> 773.40766 | T3: =G3/$G$44 -> 764.49614 | U3: =H3/$H$44 -> 801.39929 | V3: =I3/$I$44 -> 798.7204 | W3: =J3/$J$44 -> 778.47711 | X3: =K3/$K$44 -> 798.48789 | Y3: =L3/$L$44 -> 767.1917 | Z3: =M3/$M$44 -> 803.20149 | AA3: =SUM(O3:Z3) -> 9124.7607 | AD3: 663.96495 | AE3: =AD3/0.95474 -> 695.44059 | AF3: =AE3-Z3 -> -107.76091
A4: Bandon Co-Op | B4: 2593.3632 | C4: 2342.3925 | D4: 2593.3632 | E4: 2509.7063 | F4: 2593.3632 | G4: 2509.7063 | H4: 2593.3632 | I4: 2593.3632 | J4: 2509.7063 | K4: 2593.3632 | L4: 2509.7063 | M4: 2593.3632 | N4: =SUM(B4:M4) -> 30534.76 | O4: =B4/$B$44 -> 2683.1688 | P4: =C4/$C$44 -> 2438.6459 | Q4: =D4/$D$44 -> 2796.6518 | R4: =E4/$E$44 -> 2819.3562 | S4: =F4/$F$44 -> 2924.8347 | T4: =G4/$G$44 -> 2891.1336 | U4: =H4/$H$44 -> 3030.692 | V4: =I4/$I$44 -> 3020.5611 | W4: =J4/$J$44 -> 2944.0061 | X4: =K4/$K$44 -> 3019.6819 | Y4: =L4/$L$44 -> 2901.3275 | Z4: =M4/$M$44 -> 3037.5075 | AA4: =SUM(O4:Z4) -> 34507.567 | AD4: 2510.9492 | AE4: =AD4/0.95474 -> 2629.9822 | AF4: =AE4-Z4 -> -407.52536
A5: Barryroe Co-Op | B5: 2397.2733 | C5: 2165.2791 | D5: 2397.2733 | E5: 2319.9419 | F5: 2397.2733 | G5: 2319.9419 | H5: 2397.2733 | I5: 2397.2733 | J5: 2319.9419 | K5: 2397.2733 | L5: 2319.9419 | M5: 2397.2733 | N5: =SUM(B5:M5) -> 28225.96 | O5: =B5/$B$44 -> 2480.2886 | P5: =C5/$C$44 -> 2254.2546 | Q5: =D5/$D$44 -> 2585.1908 | R5: =E5/$E$44 -> 2606.1785 | S5: =F5/$F$44 -> 2703.6815 | T5: =G5/$G$44 -> 2672.5286 | U5: =H5/$H$44 -> 2801.5348 | V5: =I5/$I$44 -> 2792.1699 | W5: =J5/$J$44 -> 2721.4033 | X5: =K5/$K$44 -> 2791.3571 | Y5: =L5/$L$44 -> 2681.9518 | Z5: =M5/$M$44 -> 2807.8349 | AA5: =SUM(O5:Z5) -> 31898.374 | AD5: 2321.0903 | AE5: =AD5/0.95474 -> 2431.1229 | AF5: =AE5-Z5 -> -376.71204
A6: Brett Brothers | B6: 711.78973 | C6: 642.90685 | D6: 711.78973 | E6: 688.82877 | F6: 711.78973 | G6: 688.82877 | H6: 711.78973 | I6: 711.78973 | J6: 688.82877 | K6: 711.78973 | L6: 688.82877 | M6: 711.78973 | N6: =SUM(B6:M6) -> 8380.75 | O6: =B6/$B$44 -> 736.43832 | P6: =C6/$C$44 -> 669.32511 | Q6: =D6/$D$44 -> 767.58552 | R6: =E6/$E$44 -> 773.8171 | S6: =F6/$F$44 -> 802.76735 | T6: =G6/$G$44 -> 793.51754 | U6: =H6/$H$44 -> 831.82158 | V6: =I6/$I$44 -> 829.04099 | W6: =J6/$J$44 -> 808.02924 | X6: =K6/$K$44 -> 828.79966 | Y6: =L6/$L$44 -> 796.31542 | Z6: =M6/$M$44 -> 833.6922 | AA6: =SUM(O6:Z6) -> 9471.15 | AD6: 689.16981 | AE6: =AD6/0.95474 -> 721.8403 | AF6: =AE6-Z6 -> -111.8519
A7: Callan Co-Op | B7: 495.05556 | C7: 447.14696 | D7: 495.05556 | E7: 479.08603 | F7: 495.05556 | G7: 479.08603 | H7: 495.05556 | I7: 495.05556 | J7: 479.08603 | K7: 495.05556 | L7: 479.08603 | M7: 495.05556 | N7: =SUM(B7:M7) -> 5828.88 | O7: =B7/$B$44 -> 512.19886 | P7: =C7/$C$44 -> 465.52108 | Q7: =D7/$D$44 -> 533.86199 | R7: =E7/$E$44 -> 538.19611 | S7: =F7/$F$44 -> 558.33124 | T7: =G7/$G$44 -> 551.89792 | U7: =H7/$H$44 -> 578.5387 | V7: =I7/$I$44 -> 576.60477 | W7: =J7/$J$44 -> 561.99093 | X7: =K7/$K$44 -> 576.43693 | Y7: =L7/$L$44 -> 553.84387 | Z7: =M7/$M$44 -> 579.83973 | AA7: =SUM(O7:Z7) -> 6587.2621 | AD7: 479.32352 | AE7: =AD7/0.95474 -> 502.04613 | AF7: =AE7-Z7 -> -77.793594
A8: Carbery | B8: 585.95436 | C8: 529.2491 | D8: 585.95436 | E8: 567.0526 | F8: 585.95436 | G8: 567.0526 | H8: 585.95436 | I8: 585.95436 | J8: 567.0526 | K8: 585.95436 | L8: 567.0526 | M8: 585.95436 | N8: =SUM(B8:M8) -> 6899.14 | O8: =B8/$B$44 -> 606.24539 | P8: =C8/$C$44 -> 550.99695 | Q8: =D8/$D$44 -> 631.88616 | R8: =E8/$E$44 -> 637.01608 | S8: =F8/$F$44 -> 660.84829 | T8: =G8/$G$44 -> 653.23373 | U8: =H8/$H$44 -> 684.76611 | V8: =I8/$I$44 -> 682.47709 | W8: =J8/$J$44 -> 665.17995 | X8: =K8/$K$44 -> 682.27842 | Y8: =L8/$L$44 -> 655.53698 | Z8: =M8/$M$44 -> 686.30602 | AA8: =SUM(O8:Z8) -> 7796.7712 | AD8: 567.33303 | AE8: =AD8/0.95474 -> 594.22778 | AF8: =AE8-Z8 -> -92.078241
A9: Centenary Thurles Co-Op | B9: 581.97532 | C9: 525.65512 | D9: 581.97532 | E9: 563.20192 | F9: 581.97532 | G9: 563.20192 | H9: 581.97532 | I9: 581.97532 | J9: 563.20192 | K9: 581.97532 | L9: 563.20192 | M9: 581.97532 | N9: =SUM(B9:M9) -> 6852.29 | O9: =B9/$B$44 -> 602.12856 | P9: =C9/$C$44 -> 547.25529 | Q9: =D9/$D$44 -> 627.59521 | R9: =E9/$E$44 -> 632.69029 | S9: =F9/$F$44 -> 656.36067 | T9: =G9/$G$44 -> 648.79781 | U9: =H9/$H$44 -> 680.11606 | V9: =I9/$I$44 -> 677.84259 | W9: =J9/$J$44 -> 660.66291 | X9: =K9/$K$44 -> 677.64527 | Y9: =L9/$L$44 -> 651.08543 | Z9: =M9/$M$44 -> 681.64552 | AA9: =SUM(O9:Z9) -> 7743.8256 | AD9: 563.4809 | AE9: =AD9/0.95474 -> 590.19304 | AF9: =AE9-Z9 -> -91.452485
A10: Dan O'Connor | B10: 141.28186 | C10: 127.60942 | D10: 141.28186 | E10: 136.72438 | F10: 141.28186 | G10: 136.72438 | H10: 141.28186 | I10: 141.28186 | J10: 136.72438 | K10: 141.28186 | L10: 136.72438 | M10: 141.28186 | N10: =SUM(B10:M10) -> 1663.48 | O10: =B10/$B$44 -> 146.17432 | P10: =C10/$C$44 -> 132.85314 | Q10: =D10/$D$44 -> 152.35667 | R10: =E10/$E$44 -> 153.59356 | S10: =F10/$F$44 -> 159.33985 | T10: =G10/$G$44 -> 157.50387 | U10: =H10/$H$44 -> 165.10677 | V10: =I10/$I$44 -> 164.55486 | W10: =J10/$J$44 -> 160.38427 | X10: =K10/$K$44 -> 164.50695 | Y10: =L10/$L$44 -> 158.05922 | Z10: =M10/$M$44 -> 165.47807 | AA10: =SUM(O10:Z10) -> 1879.9115 | AD10: 136.79216 | AE10: =AD10/0.95474 -> 143.27687 | AF10: =AE10-Z10 -> -22.201196
A11: Denis Brinicombe | B11: 2069.4267 | C11: 1869.1596 | D11: 2069.4267 | E11: 2002.671 | F11: 2069.4267 | G11: 2002.671 | H11: -679.48732 | I11: 1667.4628 | J11: 1613.6737 | K11: 1667.4628 | L11: 1613.6737 | M11: 1667.4628 | N11: =SUM(B11:M11) -> 19633.03 | O11: =B11/$B$44 -> 2141.0889 | P11: =C11/$C$44 -> 1945.9669 | Q11: =D11/$D$44 -> 2231.6449 | R11: =E11/$E$44 -> 2249.7624 | S11: =F11/$F$44 -> 2333.9311 | T11: =G11/$G$44 -> 2307.0386 | U11: =H11/$H$44 -> -794.07189 | V11: =I11/$I$44 -> 1942.1396 | W11: =J11/$J$44 -> 1892.9168 | X11: =K11/$K$44 -> 1941.5743 | Y11: =L11/$L$44 -> 1865.4756 | Z11: =M11/$M$44 -> 1953.0357 | AA11: =SUM(O11:Z11) -> 22010.503 | AD11: 1914.1238 | AE11: =AD11/0.95474 -> 2004.8639 | AF11: =AE11-Z11 -> 51.828237
A12: Drinagh Co-Op | B12: 2206.2819 | C12: 1992.7707 | D12: 2206.2819 | E12: 2135.1115 | F12: 2206.2819 | G12: 2135.1115 | H12: 2206.2819 | I12: 2206.2819 | J12: 2135.1115 | K12: 2206.2819 | L12: 2135.1115 | M12: 2206.2819 | N12: =SUM(B12:M12) -> 25977.19 | O12: =B12/$B$44 -> 2282.6833 | P12: =C12/$C$44 -> 2074.6575 | Q12: =D12/$D$44 -> 2379.228 | R12: =E12/$E$44 -> 2398.5435 | S12: =F12/$F$44 -> 2488.2785 | T12: =G12/$G$44 -> 2459.6075 | U12: =H12/$H$44 -> 2578.3357 | V12: =I12/$I$44 -> 2569.717 | W12: =J12/$J$44 -> 2504.5884 | X12: =K12/$K$44 -> 2568.9689 | Y12: =L12/$L$44 -> 2468.2799 | Z12: =M12/$M$44 -> 2584.134 | AA12: =SUM(O12:Z12) -> 29357.022 | AD12: 135.43781 | AE12: =AD12/0.95474 -> 141.85832 | AF12: =AE12-Z12 -> -2442.2756
A13: Drinagh Dairies | B13: 139.88304 | C13: 126.34597 | D13: 139.88304 | E13: 135.37068 | F13: 139.88304 | G13: 135.37068 | H13: 139.88304 | I13: 139.88304 | J13: 135.37068 | K13: 139.88304 | L13: 135.37068 | M13: 139.88304 | N13: =SUM(B13:M13) -> 1647.01 | O13: =B13/$B$44 -> 144.72706 | P13: =C13/$C$44 -> 131.53777 | Q13: =D13/$D$44 -> 150.8482 | R13: =E13/$E$44 -> 152.07285 | S13: =F13/$F$44 -> 157.76224 | T13: =G13/$G$44 -> 155.94443 | U13: =H13/$H$44 -> 163.47206 | V13: =I13/$I$44 -> 162.92561 | W13: =J13/$J$44 -> 158.79632 | X13: =K13/$K$44 -> 162.87818 | Y13: =L13/$L$44 -> 156.49428 | Z13: =M13/$M$44 -> 163.83968 | AA13: =SUM(O13:Z13) -> 1861.2987 | AD13: 10704.238 | AE13: =AD13/0.95474 -> 11211.679 | AF13: =AE13-Z13 -> 11047.839
... A15: Hopkins | B15: 585.95436 | C15: 529.2491 | D15: 585.95436 | E15: 567.0526 | F15: 585.95436 | G15: 567.0526 | H15: 585.95436 | I15: 585.95436 | J15: 567.0526 | K15: 585.95436 | L15: 567.0526 | M15: 585.95436 | N15: =SUM(B15:M15) -> 6899.14 | O15: =B15/$B$44 -> 606.24539 | P15: =C15/$C$44 -> 550.99695 | Q15: =D15/$D$44 -> 631.88616 | R15: =E15/$E$44 -> 637.01608 | S15: =F15/$F$44 -> 660.84829 | T15: =G15/$G$44 -> 653.23373 | U15: =H15/$H$44 -> 684.76611 | V15: =I15/$I$44 -> 682.47709 | W15: =J15/$J$44 -> 665.17995 | X15: =K15/$K$44 -> 682.27842 | Y15: =L15/$L$44 -> 655.53698 | Z15: =M15/$M$44 -> 686.30602 | AA15: =SUM(O15:Z15) -> 7796.7712 | AD15: 600.7512 | AE15: =AD15/0.95474 -> 629.23016 | AF15: =AE15-Z15 -> -57.075864
A16: ICMSA | B16: 735.52723 | C16: 664.34718 | D16: 735.52723 | E16: 711.80055 | F16: 735.52723 | G16: 711.80055 | H16: 735.52723 | I16: 735.52723 | J16: 711.80055 | K16: 735.52723 | L16: 711.80055 | M16: 735.52723 | N16: =SUM(B16:M16) -> 8660.24 | O16: =B16/$B$44 -> 760.99783 | P16: =C16/$C$44 -> 691.64646 | Q16: =D16/$D$44 -> 793.18376 | R16: =E16/$E$44 -> 799.62316 | S16: =F16/$F$44 -> 829.53887 | T16: =G16/$G$44 -> 819.98059 | U16: =H16/$H$44 -> 859.56203 | V16: =I16/$I$44 -> 856.68872 | W16: =J16/$J$44 -> 834.97624 | X16: =K16/$K$44 -> 856.43934 | Y16: =L16/$L$44 -> 822.87178 | Z16: =M16/$M$44 -> 861.49504 | AA16: =SUM(O16:Z16) -> 9787.0038
A17: J.McKenna | B17: 620.46882 | C17: 560.42345 | D17: 620.46882 | E17: 600.4537 | F17: 620.46882 | G17: 600.4537 | H17: 620.46882 | I17: 620.46882 | J17: 600.4537 | K17: 620.46882 | L17: 600.4537 | M17: 620.46882 | N17: =SUM(B17:M17) -> 7305.52 | O17: =B17/$B$44 -> 641.95506 | P17: =C17/$C$44 -> 583.45231 | Q17: =D17/$D$44 -> 669.10615 | R17: =E17/$E$44 -> 674.53823 | S17: =F17/$F$44 -> 699.77424 | T17: =G17/$G$44 -> 691.71115 | U17: =H17/$H$44 -> 725.10088 | V17: =I17/$I$44 -> 722.67703 | W17: =J17/$J$44 -> 704.36104 | X17: =K17/$K$44 -> 722.46667 | Y17: =L17/$L$44 -> 694.15008 | Z17: =M17/$M$44 -> 726.7315 | AA17: =SUM(O17:Z17) -> 8256.0243
A18: John McCarthy | B18: 581.97022 | C18: 525.65052 | D18: 581.97022 | E18: 563.19699 | F18: 581.97022 | G18: 563.19699 | H18: 581.97022 | I18: 581.97022 | J18: 563.19699 | K18: 581.97022 | L18: 563.19699 | M18: 581.97022 | N18: =SUM(B18:M18) -> 6852.23 | O18: =B18/$B$44 -> 602.12329 | P18: =C18/$C$44 -> 547.2505 | Q18: =D18/$D$44 -> 627.58972 | R18: =E18/$E$44 -> 632.68475 | S18: =F18/$F$44 -> 656.35492 | T18: =G18/$G$44 -> 648.79213 | U18: =H18/$H$44 -> 680.11011 | V18: =I18/$I$44 -> 677.83666 | W18: =J18/$J$44 -> 660.65713 | X18: =K18/$K$44 -> 677.63934 | Y18: =L18/$L$44 -> 651.07973 | Z18: =M18/$M$44 -> 681.63955 | AA18: =SUM(O18:Z18) -> 7743.7578
A19: Kelliher Mills | B19: 691.51658 | C19: 624.59562 | D19: 691.51658 | E19: 669.20959 | F19: 691.51658 | G19: 669.20959 | H19: 691.51658 | I19: 691.51658 | J19: 669.20959 | K19: 691.51658 | L19: 669.20959 | M19: 691.51658 | N19: =SUM(B19:M19) -> 8142.05 | O19: =B19/$B$44 -> 715.46313 | P19: =C19/$C$44 -> 650.26144 | Q19: =D19/$D$44 -> 745.72319 | R19: =E19/$E$44 -> 751.77729 | S19: =F19/$F$44 -> 779.90298 | T19: =G19/$G$44 -> 770.91662 | U19: =H19/$H$44 -> 808.12969 | V19: =I19/$I$44 -> 805.4283 | W19: =J19/$J$44 -> 785.015 | X19: =K19/$K$44 -> 805.19384 | Y19: =L19/$L$44 -> 773.63482 | Z19: =M19/$M$44 -> 809.94703 | AA19: =SUM(O19:Z19) -> 9201.3933
A20: Kerry | B20: 1946.4305 | C20: 1758.0663 | D20: 1946.4305 | E20: 1883.6425 | F20: 1946.4305 | G20: 1883.6425 | H20: 1946.4305 | I20: 1946.4305 | J20: 1883.6425 | K20: 1946.4305 | L20: 1883.6425 | M20: 1946.4305 | N20: =SUM(B20:M20) -> 22917.65 | O20: =B20/$B$44 -> 2013.8336 | P20: =C20/$C$44 -> 1830.3086 | Q20: =D20/$D$44 -> 2099.0074 | R20: =E20/$E$44 -> 2116.048 | S20: =F20/$F$44 -> 2195.2142 | T20: =G20/$G$44 -> 2169.92 | U20: =H20/$H$44 -> 2274.6647 | V20: =I20/$I$44 -> 2267.061 | W20: =J20/$J$44 -> 2209.6031 | X20: =K20/$K$44 -> 2266.401 | Y20: =L20/$L$44 -> 2177.571 | Z20: =M20/$M$44 -> 2279.78 | AA20: =SUM(O20:Z20) -> 25899.413
A21: Lakeland Dairies | B21: 777.96411 | C21: 702.67726 | D21: 777.96411 | E21: 752.86849 | F21: 777.96411 | G21: 752.86849 | H21: 777.96411 | I21: 777.96411 | J21: 752.86849 | K21: 777.96411 | L21: 752.86849 | M21: 777.96411 | N21: =SUM(B21:M21) -> 9159.9 | O21: =B21/$B$44 -> 804.90426 | P21: =C21/$C$44 -> 731.5516 | Q21: =D21/$D$44 -> 838.94718 | R21: =E21/$E$44 -> 845.75811 | S21: =F21/$F$44 -> 877.39983 | T21: =G21/$G$44 -> 867.29007 | U21: =H21/$H$44 -> 909.15521 | V21: =I21/$I$44 -> 906.11611 | W21: =J21/$J$44 -> 883.15092 | X21: =K21/$K$44 -> 905.85234 | Y21: =L21/$L$44 -> 870.34808 | Z21: =M21/$M$44 -> 911.19973 | AA21: =SUM(O21:Z21) -> 10351.673
A22: Lakeland Dairies NI | B22: 777.96411 | C22: 702.67726 | D22: 777.96411 | E22: 752.86849 | F22: 777.96411 | G22: 752.86849 | H22: 777.96411 | I22: 777.96411 | J22: 752.86849 | K22: 777.96411 | L22: 752.86849 | M22: 777.96411 | N22: =SUM(B22:M22) -> 9159.9 | O22: =B22/$B$44 -> 804.90426 | P22: =C22/$C$44 -> 731.5516 | Q22: =D22/$D$44 -> 838.94718 | R22: =E22/$E$44 -> 845.75811 | S22: =F22/$F$44 -> 877.39983 | T22: =G22/$G$44 -> 867.29007 | U22: =H22/$H$44 -> 909.15521 | V22: =I22/$I$44 -> 906.11611 | W22: =J22/$J$44 -> 883.15092 | X22: =K22/$K$44 -> 905.85234 | Y22: =L22/$L$44 -> 870.34808 | Z22: =M22/$M$44 -> 911.19973 | AA22: =SUM(O22:Z22) -> 10351.673 | AD22: 563.47582 | AE22: =AD22/0.95474 -> 590.18772 | AF22: =AE22-Z22 -> -321.01202
A23: Lee Strand | B23: 944.66342 | C23: 853.24438 | D23: 944.66342 | E23: 914.19041 | F23: 944.66342 | G23: 914.19041 | H23: 944.66342 | I23: 944.66342 | J23: 914.19041 | K23: 944.66342 | L23: 914.19041 | M23: 944.66342 | N23: =SUM(B23:M23) -> 11122.65 | O23: =B23/$B$44 -> 977.37621 | P23: =C23/$C$44 -> 888.30581 | Q23: =D23/$D$44 -> 1018.7137 | R23: =E23/$E$44 -> 1026.9841 | S23: =F23/$F$44 -> 1065.4059 | T23: =G23/$G$44 -> 1053.1298 | U23: =H23/$H$44 -> 1103.9657 | V23: =I23/$I$44 -> 1100.2754 | W23: =J23/$J$44 -> 1072.3893 | X23: =K23/$K$44 -> 1099.9551 | Y23: =L23/$L$44 -> 1056.8431 | Z23: =M23/$M$44 -> 1106.4483 | AA23: =SUM(O23:Z23) -> 12569.792 | AD23: 669.54071 | AE23: =AD23/0.95474 -> 701.28067 | AF23: =AE23-Z23 -> -405.16762
A24: Lisavaird | B24: 1989.535 | C24: 1796.9993 | D24: 1989.535 | E24: 1925.3564 | F24: 1989.535 | G24: 1925.3564 | H24: 1989.535 | I24: 1989.535 | J24: 1925.3564 | K24: 1989.535 | L24: 1925.3564 | M24: 1989.535 | N24: =SUM(B24:M24) -> 23425.17 | O24: =B24/$B$44 -> 2058.4307 | P24: =C24/$C$44 -> 1870.8415 | Q24: =D24/$D$44 -> 2145.4907 | R24: =E24/$E$44 -> 2162.9087 | S24: =F24/$F$44 -> 2243.828 | T24: =G24/$G$44 -> 2217.9737 | U24: =H24/$H$44 -> 2325.038 | V24: =I24/$I$44 -> 2317.2659 | W24: =J24/$J$44 -> 2258.5356 | X24: =K24/$K$44 -> 2316.5914 | Y24: =L24/$L$44 -> 2225.7941 | Z24: =M24/$M$44 -> 2330.2666 | AA24: =SUM(O24:Z24) -> 26472.965 | AD24: 1884.5755 | AE24: =AD24/0.95474 -> 1973.9149 | AF24: =AE24-Z24 -> -356.35163
A25: M.D O'Shea | B25: 682.62425 | C25: 616.56384 | D25: 682.62425 | E25: 660.60411 | F25: 682.62425 | G25: 660.60411 | H25: 682.62425 | I25: 682.62425 | J25: 660.60411 | K25: 682.62425 | L25: 660.60411 | M25: 682.62425 | N25: =SUM(B25:M25) -> 8037.35 | O25: =B25/$B$44 -> 706.26286 | P25: =C25/$C$44 -> 641.89961 | Q25: =D25/$D$44 -> 736.13381 | R25: =E25/$E$44 -> 742.11006 | S25: =F25/$F$44 -> 769.87408 | T25: =G25/$G$44 -> 761.00327 | U25: =H25/$H$44 -> 797.73781 | V25: =I25/$I$44 -> 795.07116 | W25: =J25/$J$44 -> 774.92036 | X25: =K25/$K$44 -> 794.83972 | Y25: =L25/$L$44 -> 763.68652 | Z25: =M25/$M$44 -> 799.53178 | AA25: =SUM(O25:Z25) -> 9083.071 | AD25: 753.24156 | AE25: =AD25/0.95474 -> 788.94941 | AF25: =AE25-Z25 -> -10.582376
A26: McDonnell | B26: 1026.4024 | C26: 927.0731 | D26: 1026.4024 | E26: 993.2926 | F26: 1026.4024 | G26: 993.2926 | H26: 1026.4024 | I26: 1026.4024 | J26: 993.2926 | K26: 1026.4024 | L26: 993.2926 | M26: 1026.4024 | N26: =SUM(B26:M26) -> 12085.06 | O26: =B26/$B$44 -> 1061.9457 | P26: =C26/$C$44 -> 965.16829 | Q26: =D26/$D$44 -> 1106.86 | R26: =E26/$E$44 -> 1115.846 | S26: =F26/$F$44 -> 1157.5923 | T26: =G26/$G$44 -> 1144.254 | U26: =H26/$H$44 -> 1199.4886 | V26: =I26/$I$44 -> 1195.4789 | W26: =J26/$J$44 -> 1165.1799 | X26: =K26/$K$44 -> 1195.1309 | Y26: =L26/$L$44 -> 1148.2886 | Z26: =M26/$M$44 -> 1202.186 | AA26: =SUM(O26:Z26) -> 13657.419
A27: McDonogh | B27: 944.66342 | C27: 853.24438 | D27: 944.66342 | E27: 914.19041 | F27: 944.66342 | G27: 914.19041 | H27: 944.66342 | I27: 944.66342 | J27: 914.19041 | K27: 944.66342 | L27: 914.19041 | M27: 944.66342 | N27: =SUM(B27:M27) -> 11122.65 | O27: =B27/$B$44 -> 977.37621 | P27: =C27/$C$44 -> 888.30581 | Q27: =D27/$D$44 -> 1018.7137 | R27: =E27/$E$44 -> 1026.9841 | S27: =F27/$F$44 -> 1065.4059 | T27: =G27/$G$44 -> 1053.1298 | U27: =H27/$H$44 -> 1103.9657 | V27: =I27/$I$44 -> 1100.2754 | W27: =J27/$J$44 -> 1072.3893 | X27: =K27/$K$44 -> 1099.9551 | Y27: =L27/$L$44 -> 1056.8431 | Z27: =M27/$M$44 -> 1106.4483 | AA27: =SUM(O27:Z27) -> 12569.792 | AD27: 753.24156 | AE27: =AD27/0.95474 -> 788.94941 | AF27: =AE27-Z27 -> -317.49889
A28: North Cork | B28: 761.48315 | C28: 687.79123 | D28: 761.48315 | E28: 736.91918 | F28: 761.48315 | G28: 736.91918 | H28: 761.48315 | I28: 761.48315 | J28: 736.91918 | K28: 761.48315 | L28: 736.91918 | M28: 761.48315 | N28: =SUM(B28:M28) -> 8965.85 | O28: =B28/$B$44 -> 787.85258 | P28: =C28/$C$44 -> 716.05388 | Q28: =D28/$D$44 -> 821.17431 | R28: =E28/$E$44 -> 827.84095 | S28: =F28/$F$44 -> 858.81235 | T28: =G28/$G$44 -> 848.91677 | U28: =H28/$H$44 -> 889.895 | V28: =I28/$I$44 -> 886.92029 | W28: =J28/$J$44 -> 864.4416 | X28: =K28/$K$44 -> 886.66211 | Y28: =L28/$L$44 -> 851.90999 | Z28: =M28/$M$44 -> 891.89622 | AA28: =SUM(O28:Z28) -> 10132.376 | AD28: 1926.3095 | AE28: =AD28/0.95474 -> 2017.6273 | AF28: =AE28-Z28 -> 1125.7311
A29: Organic Herd | B29: 1850.3883 | C29: 1671.3185 | D29: 1850.3883 | E29: 1790.6984 | F29: 1850.3883 | G29: 1790.6984 | H29: 1850.3883 | I29: 1850.3883 | J29: 1790.6984 | K29: 1850.3883 | L29: 1790.6984 | M29: 1850.3883 | N29: =SUM(B29:M29) -> 21786.83 | O29: =B29/$B$44 -> 1914.4655 | P29: =C29/$C$44 -> 1739.9961 | Q29: =D29/$D$44 -> 1995.4366 | R29: =E29/$E$44 -> 2011.6364 | S29: =F29/$F$44 -> 2086.8963 | T29: =G29/$G$44 -> 2062.8502 | U29: =H29/$H$44 -> 2162.4264 | V29: =I29/$I$44 -> 2155.1979 | W29: =J29/$J$44 -> 2100.5752 | X29: =K29/$K$44 -> 2154.5706 | Y29: =L29/$L$44 -> 2070.1236 | Z29: =M29/$M$44 -> 2167.2894 | AA29: =SUM(O29:Z29) -> 24621.464 | AD29: 660.93101 | AE29: =AD29/0.95474 -> 692.26283 | AF29: =AE29-Z29 -> -1475.0265
A30: Peter Curran | B30: 799.02797 | C30: 721.70268 | D30: 799.02797 | E30: 773.25288 | F30: 799.02797 | G30: 773.25288 | H30: 799.02797 | I30: 799.02797 | J30: 773.25288 | K30: 799.02797 | L30: 773.25288 | M30: 799.02797 | N30: =SUM(B30:M30) -> 9407.91 | O30: =B30/$B$44 -> 826.69754 | P30: =C30/$C$44 -> 751.35882 | Q30: =D30/$D$44 -> 861.6622 | R30: =E30/$E$44 -> 868.65753 | S30: =F30/$F$44 -> 901.15598 | T30: =G30/$G$44 -> 890.77249 | U30: =H30/$H$44 -> 933.77115 | V30: =I30/$I$44 -> 930.64977 | W30: =J30/$J$44 -> 907.06278 | X30: =K30/$K$44 -> 930.37886 | Y30: =L30/$L$44 -> 893.91329 | Z30: =M30/$M$44 -> 935.87104 | AA30: =SUM(O30:Z30) -> 10631.951 | AD30: 993.78462 | AE30: =AD30/0.95474 -> 1040.8956 | AF30: =AE30-Z30 -> 105.02451
A31: Richard Boyle | B31: 1346.5245 | C31: 1216.2157 | D31: 1346.5245 | E31: 1303.0882 | F31: 1346.5245 | G31: 1303.0882 | H31: 1346.5245 | I31: 1346.5245 | J31: 1303.0882 | K31: 1346.5245 | L31: 1303.0882 | M31: 1346.5245 | N31: =SUM(B31:M31) -> 15854.24 | O31: =B31/$B$44 -> 1393.1533 | P31: =C31/$C$44 -> 1266.1923 | Q31: =D31/$D$44 -> 1452.0759 | R31: =E31/$E$44 -> 1463.8645 | S31: =F31/$F$44 -> 1518.6309 | T31: =G31/$G$44 -> 1501.1326 | U31: =H31/$H$44 -> 1573.5941 | V31: =I31/$I$44 -> 1568.334 | W31: =J31/$J$44 -> 1528.5851 | X31: =K31/$K$44 -> 1567.8774 | Y31: =L31/$L$44 -> 1506.4255 | Z31: =M31/$M$44 -> 1577.1329 | AA31: =SUM(O31:Z31) -> 17916.999 | AD31: 914.64314 | AE31: =AD31/0.95474 -> 958.00233 | AF31: =AE31-Z31 -> -619.13053
A32: Smiths Building | B32: 988.60019 | C32: 892.92921 | D32: 988.60019 | E32: 956.70986 | F32: 988.60019 | G32: 956.70986 | H32: 988.60019 | I32: 988.60019 | J32: 956.70986 | K32: 988.60019 | L32: 956.70986 | M32: 988.60019 | N32: =SUM(B32:M32) -> 11639.97 | O32: =B32/$B$44 -> 1022.8345 | P32: =C32/$C$44 -> 929.62136 | Q32: =D32/$D$44 -> 1066.0946 | R32: =E32/$E$44 -> 1074.7496 | S32: =F32/$F$44 -> 1114.9584 | T32: =G32/$G$44 -> 1102.1114 | U32: =H32/$H$44 -> 1155.3117 | V32: =I32/$I$44 -> 1151.4497 | W32: =J32/$J$44 -> 1122.2666 | X32: =K32/$K$44 -> 1151.1145 | Y32: =L32/$L$44 -> 1105.9974 | Z32: =M32/$M$44 -> 1157.9098 | AA32: =SUM(O32:Z32) -> 13154.42 | AD32: 737.28418 | AE32: =AD32/0.95474 -> 772.23556 | AF32: =AE32-Z32 -> -385.67419
A33: Strathroy Dairy | B33: 524.81386 | C33: 474.02542 | D33: 524.81386 | E33: 507.88438 | F33: 524.81386 | G33: 507.88438 | H33: 524.81386 | I33: 524.81386 | J33: 507.88438 | K33: 524.81386 | L33: 507.88438 | M33: 524.81386 | N33: =SUM(B33:M33) -> 6179.26 | O33: =B33/$B$44 -> 542.98766 | P33: =C33/$C$44 -> 493.50403 | Q33: =D33/$D$44 -> 565.95299 | R33: =E33/$E$44 -> 570.54763 | S33: =F33/$F$44 -> 591.89311 | T33: =G33/$G$44 -> 585.07307 | U33: =H33/$H$44 -> 613.31525 | V33: =I33/$I$44 -> 611.26508 | W33: =J33/$J$44 -> 595.77278 | X33: =K33/$K$44 -> 611.08715 | Y33: =L33/$L$44 -> 587.136 | Z33: =M33/$M$44 -> 614.69449 | AA33: =SUM(O33:Z33) -> 6983.2292 | AD33: 1791.5849 | AE33: =AD33/0.95474 -> 1876.516 | AF33: =AE33-Z33 -> 1261.8215
A34: T&A Building | B34: 780.11712 | C34: 704.62192 | D34: 780.11712 | E34: 754.95205 | F34: 780.11712 | G34: 754.95205 | H34: 780.11712 | I34: =780.117123287671-0.96 -> 779.15712 | J34: 754.95205 | K34: 780.11712 | L34: 754.95205 | M34: 780.11712 | N34: =SUM(B34:M34) -> 9184.29 | O34: =B34/$B$44 -> 807.13183 | P34: =C34/$C$44 -> 733.57617 | Q34: =D34/$D$44 -> 841.26896 | R34: =E34/$E$44 -> 848.09874 | S34: =F34/$F$44 -> 879.82803 | T34: =G34/$G$44 -> 869.6903 | U34: =H34/$H$44 -> 911.67129 | V34: =I34/$I$44 -> 907.50565 | W34: =J34/$J$44 -> 885.59503 | X34: =K34/$K$44 -> 908.35929 | Y34: =L34/$L$44 -> 872.75676 | Z34: =M34/$M$44 -> 913.72148 | AA34: =SUM(O34:Z34) -> 10379.204 | AD34: 773.63549 | AE34: =AD34/0.95474 -> 810.31013 | AF34: =AE34-Z34 -> -103.41135
A35: Tirlan | B35: 1514.2506 | C35: 1367.7102 | D35: 1514.2506 | E35: 1465.4038 | F35: 1514.2506 | G35: 1465.4038 | H35: 1514.2506 | I35: 1514.2506 | J35: 1465.4038 | K35: 1514.2506 | L35: 1465.4038 | M35: 1514.2506 | N35: =SUM(B35:M35) -> 17829.08 | O35: =B35/$B$44 -> 1566.6877 | P35: =C35/$C$44 -> 1423.9121 | Q35: =D35/$D$44 -> 1632.9497 | R35: =E35/$E$44 -> 1646.2067 | S35: =F35/$F$44 -> 1707.795 | T35: =G35/$G$44 -> 1688.1171 | U35: =H35/$H$44 -> 1769.6046 | V35: =I35/$I$44 -> 1763.6892 | W35: =J35/$J$44 -> 1718.9891 | X35: =K35/$K$44 -> 1763.1758 | Y35: =L35/$L$44 -> 1694.0693 | Z35: =M35/$M$44 -> 1773.5841 | AA35: =SUM(O35:Z35) -> 20148.78 | AD35: 1303.7338 | AE35: =AD35/0.95474 -> 1365.538 | AF35: =AE35-Z35 -> -408.04605
A36: Wallaces Homevalue Hardware | D36: -11.66 | K36: 151.63043 | L36: 146.73913 | M36: 151.63043 | N36: =SUM(B36:M36) -> 438.34 | O36: =B36/$B$44 -> 0 | P36: =C36/$C$44 -> 0 | Q36: =D36/$D$44 -> -12.574004 | R36: =E36/$E$44 -> 0 | S36: =F36/$F$44 -> 0 | T36: =G36/$G$44 -> 0 | U36: =H36/$H$44 -> 0 | V36: =I36/$I$44 -> 0 | W36: =J36/$J$44 -> 0 | X36: =K36/$K$44 -> 176.55671 | Y36: =L36/$L$44 -> 169.63669 | Z36: =M36/$M$44 -> 177.59895 | AA36: =SUM(O36:Z36) -> 511.21835 | AD36: 957.18344 | AE36: =AD36/0.95474 -> 1002.5593 | AF36: =AE36-Z36 -> 824.96032
N37: =SUM(B37:M37) -> 0 | O37: =B37/$B$44 -> 0 | P37: =C37/$C$44 -> 0 | Q37: =D37/$D$44 -> 0 | R37: =E37/$E$44 -> 0 | S37: =F37/$F$44 -> 0 | T37: =G37/$G$44 -> 0 | U37: =H37/$H$44 -> 0 | V37: =I37/$I$44 -> 0 | W37: =J37/$J$44 -> 0 | X37: =K37/$K$44 -> 0 | Y37: =L37/$L$44 -> 0 | Z37: =M37/$M$44 -> 0
B38: =SUM(B2:B37) -> 44824.695 | C38: =SUM(C2:C37) -> 40486.821 | D38: =SUM(D2:D37) -> 44813.035 | E38: =SUM(E2:E37) -> 43378.737 | F38: =SUM(F2:F37) -> 44824.695 | G38: =SUM(G2:G37) -> 43378.737 | H38: =SUM(H2:H37) -> 42075.781 | I38: =SUM(I2:I37) -> 44955.836 | ... R38: =SUM(R2:R37) -> 48730.845 | S38: =SUM(S2:S36) -> 50553.977 | T38: =SUM(T2:T36) -> 49971.473 | U38: =SUM(U2:U36) -> 49171.182 | V38: =SUM(V2:V36) -> 52361.294 | W38: =SUM(W2:W36) -> 50274.977 | X38: =SUM(X2:X36) -> 51743.854 | Y38: =SUM(Y2:Y36) -> 49715.789 | Z38: =SUM(Z2:Z37) -> 52049.303 | AA38: =SUM(AA2:AA36) -> 591425.97
A40: GP CHECK | B40: 44824.695 | C40: 40486.821 | D40: 44813.035 | E40: 43378.737 | F40: 44824.695 | G40: 43378.737 | H40: 42075.781 | I40: 44955.836 | J40: 42858.413 | K40: 44438.657 | L40: 43005.152 | M40: 44438.654 | N40: =SUM(B40:M40) -> 523479.21 | O40: =B40/B44 -> 46376.93 | P40: =C40/C44 -> 42150.501 | Q40: =D40/D44 -> 48325.84 | R40: =E40/E44 -> 48730.845 | S40: =F40/F44 -> 50553.977 | T40: =G40/G44 -> 49971.473 | U40: =H40/H44 -> 49171.182 | V40: =I40/I44 -> 52361.294 | ... Z40: =M40/M44 -> 52049.303
A42: Variance | B42: =B38-B40 -> 0 | C42: =C38-C40 -> 0 | D42: =D38-D40 -> 0 | E42: =E38-E40 -> 0 | F42: =F38-F40 -> 0 | G42: =G38-G40 -> 0 | H42: =H38-H40 -> 0 | I42: =I38-I40 -> 0 | ... M42: =M38-M40 -> 0 | O42: =O38-O40 -> 0 | P42: =P38-P40 -> 0 | Q42: =Q38-Q40 -> 0 | R42: =R38-R40 -> 0 | S42: =S38-S40 -> 0 | T42: =T38-T40 -> 0 | U42: =U38-U40 -> 0 | V42: =V38-V40 -> 0 | ... Z42: =Z38-Z40 -> 0
A44: Monthly Avg Rate 25 | B44: 0.96653 | C44: 0.96053 | D44: 0.92731 | E44: 0.89017 | F44: 0.88667 | G44: 0.86807 | H44: 0.8557 | I44: 0.85857 | J44: 0.85248 | K44: 0.85882 | L44: 0.86502 | M44: 0.85378
L46: Total | M46: =SUM(B38:M38) -> 523479.21 | O46: =SUM(O38:Z38) -> 591425.97
L47: BPC
L48: Variance | M48: =M46-M47 -> 523479.21 | O48: =O46-O47 -> 591425.97

Sheet 3rd Party Maintenance
A1: Customer | B1: January | C1: February | D1: March | E1: April | F1: May | G1: June | H1: July | I1: August | J1: September | K1: October | L1: November | M1: December | N1: Consolidated Eur | O1: Jan USD | P1: Feb USD | Q1: March USD | R1: April USD | S1: May USD | T1: June USD | U1: July USD | V1: August USD | W1: September USD | X1: October USD | Y1: November USD | Z1: December USD | AA1: Consol USD
A2: Arrabawn | B2: 755.50397 | C2: 682.39068 | D2: 755.50397 | E2: 731.13288 | F2: 837.49581 | G2: 810.47982 | H2: 855.69146 | I2: 855.69146 | J2: 828.08851 | K2: 855.69146 | L2: 828.08851 | M2: 855.69146 | N2: =SUM(B2:M2) -> 9651.45 | O2: =B2/$B$51 -> 781.66635 | P2: =C2/$C$51 -> 710.43141 | Q2: =D2/$D$51 -> 814.72644 | R2: =E2/$E$51 -> 821.34073 | S2: =F2/$F$51 -> 944.54059 | T2: =G2/$G$51 -> 933.65721 | U2: =H2/$H$51 -> 999.99002 | V2: =I2/$I$51 -> 996.64729 | W2: =J2/$J$51 -> 971.38761 | X2: =K2/$K$51 -> 996.35717 | Y2: =L2/$L$51 -> 957.30562 | Z2: =M2/$M$51 -> 1002.2388 | AA2: =SUM(O2:Z2) -> 10930.289
A3: Aurivo | B3: 1591.9069 | C3: 1470.1285 | D3: 1627.6423 | E3: 1575.1377 | F3: 1627.6423 | G3: 1575.1377 | H3: 1627.6423 | I3: 1627.6423 | J3: 1575.1377 | K3: 1627.6423 | L3: 1575.1377 | M3: 1627.6423 | N3: =SUM(B3:M3) -> 19128.44 | O3: =B3/$B$51 -> 1647.0331 | P3: =C3/$C$51 -> 1530.5389 | Q3: =D3/$D$51 -> 1755.23 | R3: =E3/$E$51 -> 1769.4797 | S3: =F3/$F$51 -> 1835.6799 | T3: =G3/$G$51 -> 1814.5284 | U3: =H3/$H$51 -> 1902.1179 | V3: =I3/$I$51 -> 1895.7596 | W3: =J3/$J$51 -> 1847.7122 | X3: =K3/$K$51 -> 1895.2077 | Y3: =L3/$L$51 -> 1820.9263 | Z3: =M3/$M$51 -> 1906.3954 | AA3: =SUM(O3:Z3) -> 21620.609
A4: Aurivo NI | B4: 32.930493 | C4: 29.743671 | D4: 32.930493 | E4: 31.868219 | F4: 32.930493 | G4: 31.868219 | H4: 32.930493 | I4: 32.930493 | J4: 31.868219 | K4: 32.930493 | L4: 31.868219 | M4: 32.930493 | N4: =SUM(B4:M4) -> 387.73 | O4: =B4/$B$51 -> 34.070844 | P4: =C4/$C$51 -> 30.965895 | Q4: =D4/$D$51 -> 35.511849 | R4: =E4/$E$51 -> 35.80015 | S4: =F4/$F$51 -> 37.139514 | T4: =G4/$G$51 -> 36.711578 | U4: =H4/$H$51 -> 38.48369 | V4: =I4/$I$51 -> 38.355048 | W4: =J4/$J$51 -> 37.382952 | X4: =K4/$K$51 -> 38.343882 | Y4: =L4/$L$51 -> 36.84102 | Z4: =M4/$M$51 -> 38.570233 | AA4: =SUM(O4:Z4) -> 438.17665
A5: BallyJamesDuff | B5: 43.905342 | C5: 39.656438 | D5: 43.905342 | E5: 42.489041 | F5: 43.905342 | G5: 42.489041 | H5: 43.905342 | I5: 43.905342 | J5: 42.489041 | K5: 43.905342 | L5: 42.489041 | M5: 43.905342 | N5: =SUM(B5:M5) -> 516.95 | O5: =B5/$B$51 -> 45.425742 | P5: =C5/$C$51 -> 41.285997 | Q5: =D5/$D$51 -> 47.346996 | R5: =E5/$E$51 -> 47.731378 | S5: =F5/$F$51 -> 49.517117 | T5: =G5/$G$51 -> 48.946561 | U5: =H5/$H$51 -> 51.30927 | V5: =I5/$I$51 -> 51.137755 | W5: =J5/$J$51 -> 49.841687 | X5: =K5/$K$51 -> 51.122869 | Y5: =L5/$L$51 -> 49.119143 | Z5: =M5/$M$51 -> 51.424656 | AA5: =SUM(O5:Z5) -> 584.20917
A6: Bandon Co-Op | B6: 494.11707 | C6: 446.29929 | D6: 494.11707 | E6: 478.17781 | F6: 494.11707 | G6: 478.17781 | H6: 494.11707 | I6: 494.11707 | J6: 478.17781 | K6: 494.11707 | L6: 478.17781 | M6: 494.11707 | N6: =SUM(B6:M6) -> 5817.83 | O6: =B6/$B$51 -> 511.22787 | P6: =C6/$C$51 -> 464.63857 | Q6: =D6/$D$51 -> 532.84993 | R6: =E6/$E$51 -> 537.17583 | S6: =F6/$F$51 -> 557.27279 | T6: =G6/$G$51 -> 550.85167 | U6: =H6/$H$51 -> 577.44194 | V6: =I6/$I$51 -> 575.51169 | W6: =J6/$J$51 -> 560.92554 | X6: =K6/$K$51 -> 575.34416 | Y6: =L6/$L$51 -> 552.79393 | Z6: =M6/$M$51 -> 578.74051 | AA6: =SUM(O6:Z6) -> 6574.7744
A7: Bandon Vale Cheese | B7: 22.091534 | C7: 19.953644 | D7: 22.091534 | E7: 21.378904 | F7: 22.091534 | G7: 21.378904 | H7: 22.091534 | I7: 22.091534 | J7: 21.378904 | K7: 22.091534 | L7: 21.378904 | M7: 22.091534 | N7: =SUM(B7:M7) -> 260.11 | O7: =B7/$B$51 -> 22.856543 | P7: =C7/$C$51 -> 20.773577 | Q7: =D7/$D$51 -> 23.823246 | R7: =E7/$E$51 -> 24.016653 | S7: =F7/$F$51 -> 24.915171 | T7: =G7/$G$51 -> 24.628088 | U7: =H7/$H$51 -> 25.816915 | V7: =I7/$I$51 -> 25.730615 | W7: =J7/$J$51 -> 25.078482 | X7: =K7/$K$51 -> 25.723125 | Y7: =L7/$L$51 -> 24.714925 | Z7: =M7/$M$51 -> 25.874973 | AA7: =SUM(O7:Z7) -> 293.95231
A8: Barryroe Co-op | B8: 374.10885 | C8: 337.90477 | D8: 374.10885 | E8: 362.04082 | F8: 374.10885 | G8: 362.04082 | H8: 374.10885 | I8: 374.10885 | J8: 362.04082 | K8: 374.10885 | L8: 362.04082 | M8: 374.10885 | N8: =SUM(B8:M8) -> 4404.83 | O8: =B8/$B$51 -> 387.06388 | P8: =C8/$C$51 -> 351.78992 | Q8: =D8/$D$51 -> 403.4345 | R8: =E8/$E$51 -> 406.70975 | S8: =F8/$F$51 -> 421.92569 | T8: =G8/$G$51 -> 417.06409 | U8: =H8/$H$51 -> 437.19627 | V8: =I8/$I$51 -> 435.73483 | W8: =J8/$J$51 -> 424.69128 | X8: =K8/$K$51 -> 435.60798 | Y8: =L8/$L$51 -> 418.53463 | Z8: =M8/$M$51 -> 438.17945 | AA8: =SUM(O8:Z8) -> 4977.9323
A9: Brett Brother | B9: 238.31016 | C9: 215.24789 | D9: 238.31016 | E9: 230.62274 | F9: 238.31016 | G9: 230.62274 | H9: 238.31016 | I9: 238.31016 | J9: 230.62274 | K9: 238.31016 | L9: 230.62274 | M9: 238.31016 | N9: =SUM(B9:M9) -> 2805.91 | O9: =B9/$B$51 -> 246.56262 | P9: =C9/$C$51 -> 224.09283 | Q9: =D9/$D$51 -> 256.99083 | R9: =E9/$E$51 -> 259.07719 | S9: =F9/$F$51 -> 268.76985 | T9: =G9/$G$51 -> 265.67298 | U9: =H9/$H$51 -> 278.49733 | V9: =I9/$I$51 -> 277.56638 | W9: =J9/$J$51 -> 270.53155 | X9: =K9/$K$51 -> 277.48558 | Y9: =L9/$L$51 -> 266.60972 | Z9: =M9/$M$51 -> 279.12362 | AA9: =SUM(O9:Z9) -> 3170.9805
A10: Callan Co-Op | B10: 54.279726 | C10: 49.026849 | D10: 54.279726 | E10: 52.528767 | F10: 54.279726 | G10: 52.528767 | H10: 54.279726 | I10: 54.279726 | J10: 52.528767 | K10: 54.279726 | L10: 52.528767 | M10: 54.279726 | N10: =SUM(B10:M10) -> 639.1 | O10: =B10/$B$51 -> 56.15938 | P10: =C10/$C$51 -> 51.041456 | Q10: =D10/$D$51 -> 58.534607 | R10: =E10/$E$51 -> 59.009815 | S10: =F10/$F$51 -> 61.217506 | T10: =G10/$G$51 -> 60.512133 | U10: =H10/$H$51 -> 63.433126 | V10: =I10/$I$51 -> 63.221084 | W10: =J10/$J$51 -> 61.618768 | X10: =K10/$K$51 -> 63.20268 | Y10: =L10/$L$51 -> 60.725494 | Z10: =M10/$M$51 -> 63.575776 | AA10: =SUM(O10:Z10) -> 722.25183
A11: Carbery | B11: 66.084356 | C11: 59.689096 | D11: 66.084356 | E11: 63.952603 | F11: 66.084356 | G11: 63.952603 | H11: 66.084356 | I11: 66.084356 | J11: 63.952603 | K11: 66.084356 | L11: 63.952603 | M11: 66.084356 | N11: =SUM(B11:M11) -> 778.09 | O11: =B11/$B$51 -> 68.372794 | P11: =C11/$C$51 -> 62.141834 | Q11: =D11/$D$51 -> 71.264578 | R11: =E11/$E$51 -> 71.843134 | S11: =F11/$F$51 -> 74.530949 | T11: =G11/$G$51 -> 73.672172 | U11: =H11/$H$51 -> 77.228417 | V11: =I11/$I$51 -> 76.97026 | W11: =J11/$J$51 -> 75.019476 | X11: =K11/$K$51 -> 76.947854 | Y11: =L11/$L$51 -> 73.931935 | Z11: =M11/$M$51 -> 77.40209 | AA11: =SUM(O11:Z11) -> 879.32549
A12: Centenary Thurles Co-Op | B12: 143.69477 | C12: 129.78882 | D12: 143.69477 | E12: 139.05945 | F12: 143.69477 | G12: 139.05945 | H12: 143.69477 | I12: 143.69477 | J12: 139.05945 | K12: 143.69477 | L12: 139.05945 | M12: 143.69477 | N12: =SUM(B12:M12) -> 1691.89 | O12: =B12/$B$51 -> 148.67078 | P12: =C12/$C$51 -> 135.12209 | Q12: =D12/$D$51 -> 154.95872 | R12: =E12/$E$51 -> 156.21674 | S12: =F12/$F$51 -> 162.06116 | T12: =G12/$G$51 -> 160.19382 | U12: =H12/$H$51 -> 167.92657 | V12: =I12/$I$51 -> 167.36523 | W12: =J12/$J$51 -> 163.12342 | X12: =K12/$K$51 -> 167.31651 | Y12: =L12/$L$51 -> 160.75866 | Z12: =M12/$M$51 -> 168.30421 | AA12: =SUM(O12:Z12) -> 1912.0179
A13: Centenary Thurles Stores | B13: 418.83378 | C13: 378.30148 | D13: 418.83378 | E13: 405.32301 | F13: 418.83378 | G13: 405.32301 | H13: 418.83378 | I13: 418.83378 | J13: 405.32301 | K13: 418.83378 | L13: 405.32301 | M13: 418.83378 | N13: =SUM(B13:M13) -> 4931.43 | O13: =B13/$B$51 -> 433.33759 | P13: =C13/$C$51 -> 393.8466 | Q13: =D13/$D$51 -> 451.66533 | R13: =E13/$E$51 -> 455.33214 | S13: =F13/$F$51 -> 472.36715 | T13: =G13/$G$51 -> 466.92434 | U13: =H13/$H$51 -> 489.46334 | V13: =I13/$I$51 -> 487.82718 | W13: =J13/$J$51 -> 475.46337 | X13: =K13/$K$51 -> 487.68517 | Y13: =L13/$L$51 -> 468.57068 | Z13: =M13/$M$51 -> 490.56406 | AA13: =SUM(O13:Z13) -> 5573.047
... A18: Heat Merchants | B18: 1171.1129 | C18: 1057.7794 | D18: 1171.1129 | E18: 1133.3351 | F18: 1171.1129 | G18: 1133.3351 | H18: 1171.1129 | I18: 1171.1129 | J18: 1133.3351 | K18: 1171.1129 | L18: 1133.3351 | M18: 1171.1129 | N18: =SUM(B18:M18) -> 13788.91 | O18: =B18/$B$51 -> 1211.6674 | P18: =C18/$C$51 -> 1101.2456 | Q18: =D18/$D$51 -> 1262.9141 | R18: =E18/$E$51 -> 1273.167 | S18: =F18/$F$51 -> 1320.7991 | T18: =G18/$G$51 -> 1305.5803 | U18: =H18/$H$51 -> 1368.6022 | V18: =I18/$I$51 -> 1364.0273 | W18: =J18/$J$51 -> 1329.4565 | X18: =K18/$K$51 -> 1363.6302 | Y18: =L18/$L$51 -> 1310.1837 | Z18: =M18/$M$51 -> 1371.6799 | AA18: =SUM(O18:Z18) -> 15582.953
A19: Hopkins | B19: =30.5592054794521-0.33 -> 30.229205 | C19: 27.601863 | D19: 30.559205 | E19: 29.573425 | F19: 30.559205 | G19: 29.573425 | H19: 30.559205 | I19: 30.559205 | J19: 29.573425 | K19: 30.559205 | L19: 29.573425 | M19: 30.559205 | N19: =SUM(B19:M19) -> 359.48 | O19: =B19/$B$51 -> 31.276014 | P19: =C19/$C$51 -> 28.736076 | Q19: =D19/$D$51 -> 32.954681 | R19: =E19/$E$51 -> 33.222221 | S19: =F19/$F$51 -> 34.46514 | T19: =G19/$G$51 -> 34.068018 | U19: =H19/$H$51 -> 35.712522 | V19: =I19/$I$51 -> 35.593144 | W19: =J19/$J$51 -> 34.691048 | X19: =K19/$K$51 -> 35.582783 | Y19: =L19/$L$51 -> 34.18814 | Z19: =M19/$M$51 -> 35.792834 | AA19: =SUM(O19:Z19) -> 406.28262
A20: Irish International Traders | B20: 96.227397 | C20: 86.915068 | D20: 96.227397 | E20: 93.123288 | F20: 96.227397 | G20: 93.123288 | H20: 96.227397 | I20: 96.227397 | J20: 93.123288 | K20: 96.227397 | L20: 93.123288 | M20: 96.227397 | N20: =SUM(B20:M20) -> 1133 | O20: =B20/$B$51 -> 99.559659 | P20: =C20/$C$51 -> 90.486574 | Q20: =D20/$D$51 -> 103.77047 | R20: =E20/$E$51 -> 104.61293 | S20: =F20/$F$51 -> 108.52673 | T20: =G20/$G$51 -> 107.27624 | U20: =H20/$H$51 -> 112.4546 | V20: =I20/$I$51 -> 112.07869 | W20: =J20/$J$51 -> 109.23809 | X20: =K20/$K$51 -> 112.04606 | Y20: =L20/$L$51 -> 107.65449 | Z20: =M20/$M$51 -> 112.70749 | AA20: =SUM(O20:Z20) -> 1280.412
A21: J.McKenna | B21: 118.54145 | C21: 107.0697 | D21: 118.54145 | E21: 114.71753 | F21: 118.54145 | G21: 114.71753 | H21: 118.54145 | I21: 118.54145 | J21: 114.71753 | K21: 118.54145 | L21: 114.71753 | M21: 118.54145 | N21: =SUM(B21:M21) -> 1395.73 | O21: =B21/$B$51 -> 122.64643 | P21: =C21/$C$51 -> 111.4694 | Q21: =D21/$D$51 -> 127.83368 | R21: =E21/$E$51 -> 128.87149 | S21: =F21/$F$51 -> 133.69286 | T21: =G21/$G$51 -> 132.1524 | U21: =H21/$H$51 -> 138.53156 | V21: =I21/$I$51 -> 138.06848 | W21: =J21/$J$51 -> 134.56918 | X21: =K21/$K$51 -> 138.02829 | Y21: =L21/$L$51 -> 132.61836 | Z21: =M21/$M$51 -> 138.84309 | AA21: =SUM(O21:Z21) -> 1577.3252
A22: John McCarthy | B22: 129.18082 | C22: 116.67945 | D22: 129.18082 | E22: 125.0137 | F22: 129.18082 | G22: 125.0137 | H22: 129.18082 | I22: 129.18082 | J22: 125.0137 | K22: 129.18082 | L22: 125.0137 | M22: 129.18082 | N22: =SUM(B22:M22) -> 1521 | O22: =B22/$B$51 -> 133.65423 | P22: =C22/$C$51 -> 121.47403 | Q22: =D22/$D$51 -> 139.30705 | R22: =E22/$E$51 -> 140.438 | S22: =F22/$F$51 -> 145.69211 | T22: =G22/$G$51 -> 144.01338 | U22: =H22/$H$51 -> 150.96508 | V22: =I22/$I$51 -> 150.46044 | W22: =J22/$J$51 -> 146.64708 | X22: =K22/$K$51 -> 150.41664 | Y22: =L22/$L$51 -> 144.52117 | Z22: =M22/$M$51 -> 151.30458 | AA22: =SUM(O22:Z22) -> 1718.8938
A23: Kiernan Milling | J23: 2376 | K23: 269.8022 | L23: 261.0989 | M23: 285.1 | N23: =SUM(B23:M23) -> 3192.0011 | O23: =B23/$B$51 -> 0 | P23: =C23/$C$51 -> 0 | Q23: =D23/$D$51 -> 0 | R23: =E23/$E$51 -> 0 | S23: =F23/$F$51 -> 0 | T23: =G23/$G$51 -> 0 | U23: =H23/$H$51 -> 0 | V23: =I23/$I$51 -> 0 | W23: =J23/$J$51 -> 2787.1622 | X23: =K23/$K$51 -> 314.15454 | Y23: =L23/$L$51 -> 301.84146 | Z23: =M23/$M$51 -> 333.92677 | AA23: =SUM(O23:Z23) -> 3737.0849
A24: Kelliher Mills | B24: 40.694082 | C24: 36.755945 | D24: 40.694082 | E24: 39.38137 | F24: 40.694082 | G24: 39.38137 | H24: 40.694082 | I24: 40.694082 | J24: 39.38137 | K24: 40.694082 | L24: 39.38137 | M24: 40.694082 | N24: =SUM(B24:M24) -> 479.14 | O24: =B24/$B$51 -> 42.103279 | P24: =C24/$C$51 -> 38.266317 | Q24: =D24/$D$51 -> 43.884011 | R24: =E24/$E$51 -> 44.24028 | S24: =F24/$F$51 -> 45.895409 | T24: =G24/$G$51 -> 45.366583 | U24: =H24/$H$51 -> 47.556483 | V24: =I24/$I$51 -> 47.397512 | W24: =J24/$J$51 -> 46.196239 | X24: =K24/$K$51 -> 47.383715 | Y24: =L24/$L$51 -> 45.526543 | Z24: =M24/$M$51 -> 47.663429 | AA24: =SUM(O24:Z24) -> 541.4798
A25: Lacpatrick Dairies | B25: 229.24203 | C25: 207.05732 | D25: 229.24203 | E25: 221.84712 | F25: 229.24203 | G25: 221.84712 | H25: 229.24203 | I25: 229.24203 | J25: 221.84712 | K25: 229.24203 | L25: 221.84712 | M25: 229.24203 | N25: =SUM(B25:M25) -> 2699.14 | O25: =B25/$B$51 -> 237.18046 | P25: =C25/$C$51 -> 215.56569 | Q25: =D25/$D$51 -> 247.21186 | R25: =E25/$E$51 -> 249.21883 | S25: =F25/$F$51 -> 258.54267 | T25: =G25/$G$51 -> 255.56363 | U25: =H25/$H$51 -> 267.9 | V25: =I25/$I$51 -> 267.00447 | W25: =J25/$J$51 -> 260.23733 | X25: =K25/$K$51 -> 266.92675 | Y25: =L25/$L$51 -> 256.46473 | Z25: =M25/$M$51 -> 268.50246 | AA25: =SUM(O25:Z25) -> 3050.3189
A26: Lakeland Dairies | B26: 125.81499 | C26: 113.63934 | D26: 125.81499 | E26: 121.75644 | F26: 125.81499 | G26: 121.75644 | H26: 125.81499 | I26: 125.81499 | J26: 121.75644 | K26: 125.81499 | L26: 121.75644 | M26: 125.81499 | N26: =SUM(B26:M26) -> 1481.37 | O26: =B26/$B$51 -> 130.17184 | P26: =C26/$C$51 -> 118.309 | Q26: =D26/$D$51 -> 135.67737 | R26: =E26/$E$51 -> 136.77886 | S26: =F26/$F$51 -> 141.89607 | T26: =G26/$G$51 -> 140.26108 | U26: =H26/$H$51 -> 147.03165 | V26: =I26/$I$51 -> 146.54016 | W26: =J26/$J$51 -> 142.82615 | X26: =K26/$K$51 -> 146.4975 | Y26: =L26/$L$51 -> 140.75563 | Z26: =M26/$M$51 -> 147.3623 | AA26: =SUM(O26:Z26) -> 1674.1076
A27: Lakeland Dairies NI | B27: 92.751151 | C27: 83.775233 | D27: 92.751151 | E27: 89.759178 | F27: 92.751151 | G27: 89.759178 | H27: 92.751151 | I27: 92.751151 | J27: 89.759178 | K27: 92.751151 | L27: 89.759178 | M27: 92.751151 | N27: =SUM(B27:M27) -> 1092.07 | O27: =B27/$B$51 -> 95.963033 | P27: =C27/$C$51 -> 87.217716 | Q27: =D27/$D$51 -> 100.02173 | R27: =E27/$E$51 -> 100.83375 | S27: =F27/$F$51 -> 104.60617 | T27: =G27/$G$51 -> 103.40085 | U27: =H27/$H$51 -> 108.39214 | V27: =I27/$I$51 -> 108.02981 | W27: =J27/$J$51 -> 105.29183 | X27: =K27/$K$51 -> 107.99836 | Y27: =L27/$L$51 -> 103.76544 | Z27: =M27/$M$51 -> 108.63589 | AA27: =SUM(O27:Z27) -> 1234.1567
A28: Lee Strand | B28: 67.318411 | C28: 60.803726 | D28: 67.318411 | E28: 65.146849 | F28: 67.318411 | G28: 65.146849 | H28: 67.318411 | I28: 67.318411 | J28: 65.146849 | K28: 67.318411 | L28: 65.146849 | M28: 67.318411 | N28: =SUM(B28:M28) -> 792.62 | O28: =B28/$B$51 -> 69.649582 | P28: =C28/$C$51 -> 63.302266 | Q28: =D28/$D$51 -> 72.595368 | R28: =E28/$E$51 -> 73.184728 | S28: =F28/$F$51 -> 75.922734 | T28: =G28/$G$51 -> 75.047922 | U28: =H28/$H$51 -> 78.670575 | V28: =I28/$I$51 -> 78.407597 | W28: =J28/$J$51 -> 76.420384 | X28: =K28/$K$51 -> 78.384773 | Y28: =L28/$L$51 -> 75.312535 | Z28: =M28/$M$51 -> 78.847491 | AA28: =SUM(O28:Z28) -> 895.74596
A29: Lisavaird | B29: 237.03279 | C29: 214.09414 | D29: 237.03279 | E29: 235.11385 | F29: 242.95098 | G29: 240.83768 | H29: 248.8656 | I29: 248.8656 | J29: 240.83768 | K29: 248.8656 | L29: 240.83768 | M29: 248.8656 | N29: =SUM(B29:M29) -> 2884.2 | O29: =B29/$B$51 -> 245.24101 | P29: =C29/$C$51 -> 222.89167 | Q29: =D29/$D$51 -> 255.61333 | R29: =E29/$E$51 -> 264.12241 | S29: =F29/$F$51 -> 274.00383 | T29: =G29/$G$51 -> 277.44039 | U29: =H29/$H$51 -> 290.83277 | V29: =I29/$I$51 -> 289.86059 | W29: =J29/$J$51 -> 282.51417 | X29: =K29/$K$51 -> 289.77621 | Y29: =L29/$L$51 -> 278.41863 | Z29: =M29/$M$51 -> 291.4868 | AA29: =SUM(O29:Z29) -> 3262.2018
A30: M.D O'Shea | B30: 774.04027 | C30: 699.13315 | D30: 790.92514 | E30: 765.41143 | F30: =790.925143253649-0.68 -> 790.24514 | G30: 765.41143 | H30: 824.6208 | I30: 824.6208 | J30: 798.02012 | K30: 824.6208 | L30: 798.02012 | M30: 824.6208 | N30: =SUM(B30:M30) -> 9479.69 | O30: =B30/$B$51 -> 800.84454 | P30: =C30/$C$51 -> 727.86186 | Q30: =D30/$D$51 -> 852.9242 | R30: =E30/$E$51 -> 859.8486 | S30: =F30/$F$51 -> 891.25057 | T30: =G30/$G$51 -> 881.73929 | U30: =H30/$H$51 -> 963.67979 | V30: =I30/$I$51 -> 960.45843 | W30: =J30/$J$51 -> 936.11595 | X30: =K30/$K$51 -> 960.17884 | Y30: =L30/$L$51 -> 922.54529 | Z30: =M30/$M$51 -> 965.84693 | AA30: =SUM(O30:Z30) -> 10723.294
A31: McDonnell Bros | B31: 201.26134 | C31: 181.78444 | D31: 201.26134 | E31: 194.76904 | F31: 201.26134 | G31: 194.76904 | H31: 201.26134 | I31: 201.26134 | J31: 200.50593 | K31: 207.18946 | L31: 200.50593 | M31: 207.18946 | N31: =SUM(B31:M31) -> 2393.02 | O31: =B31/$B$51 -> 208.23083 | P31: =C31/$C$51 -> 189.25431 | Q31: =D31/$D$51 -> 217.03782 | R31: =E31/$E$51 -> 218.79983 | S31: =F31/$F$51 -> 226.98562 | T31: =G31/$G$51 -> 224.3702 | U31: =H31/$H$51 -> 235.20082 | V31: =I31/$I$51 -> 234.4146 | W31: =J31/$J$51 -> 235.20309 | X31: =K31/$K$51 -> 241.24899 | Y31: =L31/$L$51 -> 231.7934 | Z31: =M31/$M$51 -> 242.67312 | AA31: =SUM(O31:Z31) -> 2705.2126
A32: McDonogh | B32: 123.1889 | C32: 111.2674 | D32: 123.1889 | E32: 119.21507 | F32: 123.1889 | G32: 119.21507 | H32: 123.1889 | I32: 123.1889 | J32: 119.21507 | K32: 123.1889 | L32: 119.21507 | M32: 123.1889 | N32: =SUM(B32:M32) -> 1450.45 | O32: =B32/$B$51 -> 127.45482 | P32: =C32/$C$51 -> 115.83959 | Q32: =D32/$D$51 -> 132.84544 | R32: =E32/$E$51 -> 133.92393 | S32: =F32/$F$51 -> 138.93433 | T32: =G32/$G$51 -> 137.33347 | U32: =H32/$H$51 -> 143.96273 | V32: =I32/$I$51 -> 143.48149 | W32: =J32/$J$51 -> 139.845 | X32: =K32/$K$51 -> 143.43972 | Y32: =L32/$L$51 -> 137.8177 | Z32: =M32/$M$51 -> 144.28647 | AA32: =SUM(O32:Z32) -> 1639.1647
A33: Morris DIY | B33: 201.60701 | C33: 182.09666 | D33: 201.60701 | E33: 195.10356 | F33: 201.60701 | G33: 195.10356 | H33: 201.60701 | I33: 201.60701 | J33: 195.10356 | K33: 201.60701 | L33: 195.10356 | M33: 201.60701 | N33: =SUM(B33:M33) -> 2373.76 | O33: =B33/$B$51 -> 208.58847 | P33: =C33/$C$51 -> 189.57935 | Q33: =D33/$D$51 -> 217.41059 | R33: =E33/$E$51 -> 219.17562 | S33: =F33/$F$51 -> 227.37548 | T33: =G33/$G$51 -> 224.75556 | U33: =H33/$H$51 -> 235.60478 | V33: =I33/$I$51 -> 234.81721 | W33: =J33/$J$51 -> 228.86585 | X33: =K33/$K$51 -> 234.74886 | Y33: =L33/$L$51 -> 225.54804 | Z33: =M33/$M$51 -> 236.13462 | AA33: =SUM(O33:Z33) -> 2682.6044
A34: North Cork | B34: 346.87811 | C34: 313.30926 | D34: 346.87811 | E34: 335.68849 | F34: 346.87811 | G34: 335.68849 | H34: 346.87811 | I34: 346.87811 | J34: 335.68849 | K34: 346.87811 | L34: 335.68849 | M34: 346.87811 | N34: =SUM(B34:M34) -> 4084.21 | O34: =B34/$B$51 -> 358.89016 | P34: =C34/$C$51 -> 326.18373 | Q34: =D34/$D$51 -> 374.0692 | R34: =E34/$E$51 -> 377.10605 | S34: =F34/$F$51 -> 391.21444 | T34: =G34/$G$51 -> 386.70671 | U34: =H34/$H$51 -> 405.37351 | V34: =I34/$I$51 -> 404.01844 | W34: =J34/$J$51 -> 393.77873 | X34: =K34/$K$51 -> 403.90083 | Y34: =L34/$L$51 -> 388.07021 | Z34: =M34/$M$51 -> 406.28512 | AA34: =SUM(O34:Z34) -> 4615.5971
A35: Organic Herd | B35: 128.16929 | C35: 115.76581 | D35: 128.16929 | E35: 124.03479 | F35: 128.16929 | G35: 124.03479 | H35: 128.16929 | I35: 128.16929 | J35: 124.03479 | K35: 128.16929 | L35: 124.03479 | M35: 128.16929 | N35: =SUM(B35:M35) -> 1509.09 | O35: =B35/$B$51 -> 132.60767 | P35: =C35/$C$51 -> 120.52284 | Q35: =D35/$D$51 -> 138.21623 | R35: =E35/$E$51 -> 139.33832 | S35: =F35/$F$51 -> 144.55128 | T35: =G35/$G$51 -> 142.88571 | U35: =H35/$H$51 -> 149.78297 | V35: =I35/$I$51 -> 149.28228 | W35: =J35/$J$51 -> 145.49877 | X35: =K35/$K$51 -> 149.23882 | Y35: =L35/$L$51 -> 143.38951 | Z35: =M35/$M$51 -> 150.11981 | AA35: =SUM(O35:Z35) -> 1705.4342
A36: Peter Curran | B36: 150.39841 | C36: 135.84373 | D36: 150.39841 | E36: 145.54685 | F36: 150.39841 | G36: 145.54685 | H36: 150.39841 | I36: 150.39841 | J36: 145.54685 | K36: 150.39841 | L36: 145.54685 | M36: 150.39841 | N36: =SUM(B36:M36) -> 1770.82 | O36: =B36/$B$51 -> 155.60656 | P36: =C36/$C$51 -> 141.4258 | Q36: =D36/$D$51 -> 162.18785 | R36: =E36/$E$51 -> 163.50455 | S36: =F36/$F$51 -> 169.62163 | T36: =G36/$G$51 -> 167.66718 | U36: =H36/$H$51 -> 175.76068 | V36: =I36/$I$51 -> 175.17315 | W36: =J36/$J$51 -> 170.73345 | X36: =K36/$K$51 -> 175.12216 | Y36: =L36/$L$51 -> 168.25836 | Z36: =M36/$M$51 -> 176.15593 | AA36: =SUM(O36:Z36) -> 2001.2173
A37: Richard Boyle | B37: 324.15978 | C37: 292.78948 | D37: 324.15978 | E37: 313.70301 | F37: 324.15978 | G37: 313.70301 | H37: 324.15978 | I37: 324.15978 | J37: 313.70301 | K37: 324.15978 | L37: 313.70301 | M37: 324.15978 | N37: =SUM(B37:M37) -> 3816.72 | O37: =B37/$B$51 -> 335.38512 | P37: =C37/$C$51 -> 304.82075 | Q37: =D37/$D$51 -> 349.57003 | R37: =E37/$E$51 -> 352.40798 | S37: =F37/$F$51 -> 365.59236 | T37: =G37/$G$51 -> 361.37986 | U37: =H37/$H$51 -> 378.8241 | V37: =I37/$I$51 -> 377.55778 | W37: =J37/$J$51 -> 367.98871 | X37: =K37/$K$51 -> 377.44787 | Y37: =L37/$L$51 -> 362.65406 | Z37: =M37/$M$51 -> 379.67601 | AA37: =SUM(O37:Z37) -> 4313.3046
A38: Smiths Building | B38: 107.60312 | C38: 97.189918 | D38: 107.60312 | E38: 104.13205 | F38: 107.60312 | G38: 104.13205 | H38: 107.60312 | I38: 107.60312 | J38: 104.13205 | K38: 107.60312 | L38: 104.13205 | M38: 107.60312 | N38: =SUM(B38:M38) -> 1266.94 | O38: =B38/$B$51 -> 111.32932 | P38: =C38/$C$51 -> 101.18364 | Q38: =D38/$D$51 -> 116.03792 | R38: =E38/$E$51 -> 116.97996 | S38: =F38/$F$51 -> 121.35645 | T38: =G38/$G$51 -> 119.95813 | U38: =H38/$H$51 -> 125.74865 | V38: =I38/$I$51 -> 125.32831 | W38: =J38/$J$51 -> 122.1519 | X38: =K38/$K$51 -> 125.29182 | Y38: =L38/$L$51 -> 120.38109 | Z38: =M38/$M$51 -> 126.03144 | AA38: =SUM(O38:Z38) -> 1431.7786
A39: Smiths Tools | B39: 63.593315 | C39: 57.439123 | D39: 63.593315 | E39: 61.541918 | F39: 63.593315 | G39: 61.541918 | H39: 63.593315 | I39: 63.593315 | J39: 61.541918 | K39: 63.593315 | L39: 61.541918 | M39: 63.593315 | N39: =SUM(B39:M39) -> 748.76 | O39: =B39/$B$51 -> 65.79549 | P39: =C39/$C$51 -> 59.799406 | Q39: =D39/$D$51 -> 68.578269 | R39: =E39/$E$51 -> 69.135017 | S39: =F39/$F$51 -> 71.721514 | T39: =G39/$G$51 -> 70.89511 | U39: =H39/$H$51 -> 74.317302 | V39: =I39/$I$51 -> 74.068876 | W39: =J39/$J$51 -> 72.191627 | X39: =K39/$K$51 -> 74.047315 | Y39: =L39/$L$51 -> 71.145081 | Z39: =M39/$M$51 -> 74.484428 | AA39: =SUM(O39:Z39) -> 846.17943
A40: Strathroy Dairy | B40: 54.475918 | C40: 49.204055 | D40: 54.475918 | E40: 52.71863 | F40: 54.475918 | G40: 52.71863 | H40: 54.475918 | I40: 54.475918 | J40: 52.71863 | K40: 54.475918 | L40: 52.71863 | M40: 54.475918 | N40: =SUM(B40:M40) -> 641.41 | O40: =B40/$B$51 -> 56.362366 | P40: =C40/$C$51 -> 51.225943 | Q40: =D40/$D$51 -> 58.746177 | R40: =E40/$E$51 -> 59.223104 | S40: =F40/$F$51 -> 61.438774 | T40: =G40/$G$51 -> 60.730851 | U40: =H40/$H$51 -> 63.662402 | V40: =I40/$I$51 -> 63.449594 | W40: =J40/$J$51 -> 61.841486 | X40: =K40/$K$51 -> 63.431124 | Y40: =L40/$L$51 -> 60.944984 | Z40: =M40/$M$51 -> 63.805568 | AA40: =SUM(O40:Z40) -> 724.86237
A41: T&A Building | B41: 74.840795 | C41: 67.598137 | D41: 74.840795 | E41: 72.426575 | F41: 74.840795 | G41: 72.426575 | H41: 74.840795 | I41: 74.840795 | J41: 72.426575 | K41: 74.840795 | L41: 72.426575 | M41: 74.840795 | N41: =SUM(B41:M41) -> 881.19 | O41: =B41/$B$51 -> 77.432459 | P41: =C41/$C$51 -> 70.375873 | Q41: =D41/$D$51 -> 80.707417 | R41: =E41/$E$51 -> 81.362633 | S41: =F41/$F$51 -> 84.406594 | T41: =G41/$G$51 -> 83.434026 | U41: =H41/$H$51 -> 87.461487 | V41: =I41/$I$51 -> 87.169124 | W41: =J41/$J$51 -> 84.959853 | X41: =K41/$K$51 -> 87.143749 | Y41: =L41/$L$51 -> 83.728209 | Z41: =M41/$M$51 -> 87.658173 | AA41: =SUM(O41:Z41) -> 995.8396
A42: Tirlan | B42: 2822.702 | C42: 2549.5373 | D42: 2822.702 | E42: 2731.6471 | F42: 2822.702 | G42: 2731.6471 | H42: 2822.702 | I42: 2822.702 | J42: 2731.6471 | K42: 2822.702 | L42: 2731.6471 | M42: 2822.702 | N42: =SUM(B42:M42) -> 33235.04 | O42: =B42/$B$51 -> 2920.4495 | P42: =C42/$C$51 -> 2654.3026 | Q42: =D42/$D$51 -> 3043.9681 | R42: =E42/$E$51 -> 3068.6803 | S42: =F42/$F$51 -> 3183.4866 | T42: =G42/$G$51 -> 3146.8051 | U42: =H42/$H$51 -> 3298.7052 | V42: =I42/$I$51 -> 3287.6784 | W42: =J42/$J$51 -> 3204.3533 | X42: =K42/$K$51 -> 3286.7213 | Y42: =L42/$L$51 -> 3157.9005 | Z42: =M42/$M$51 -> 3306.1234 | AA42: =SUM(O42:Z42) -> 37559.174
A43: Wallaces | B43: 139.22907 | C43: 125.75529 | D43: =127.568520547945+11.66 -> 139.22852 | E43: 130.85096 | F43: 135.21266 | G43: 130.85096 | H43: 135.21266 | I43: 135.21266 | J43: 130.85096 | K43: 135.21266 | L43: 130.85096 | M43: 135.21266 | N43: =SUM(B43:M43) -> 1603.68 | O43: =B43/$B$51 -> 144.05044 | P43: =C43/$C$51 -> 130.92281 | Q43: =D43/$D$51 -> 150.14237 | R43: =E43/$E$51 -> 146.99547 | S43: =F43/$F$51 -> 152.49491 | T43: =G43/$G$51 -> 150.7378 | U43: =H43/$H$51 -> 158.01409 | V43: =I43/$I$51 -> 157.48589 | W43: =J43/$J$51 -> 153.49446 | X43: =K43/$K$51 -> 157.44004 | Y43: =L43/$L$51 -> 151.26929 | Z43: =M43/$M$51 -> 158.36944 | AA43: =SUM(O43:Z43) -> 1811.417
B45: =SUM(B2:B44) -> 13020.462 | C45: =SUM(C2:C44) -> 11792.993 | D45: =SUM(D2:D44) -> 13073.412 | E45: =SUM(E2:E44) -> 12653.53 | F45: =SUM(F2:F44) -> 13156.626 | G45: =SUM(G2:G44) -> 12738.601 | H45: =SUM(H2:H44) -> 13215.112 | I45: =SUM(I2:I44) -> 13221.191 | ... AA45: =SUM(AA2:AA44) -> 178875.82
A47: GP CHECK | B47: 13020.462 | C47: 11792.993 | D47: 13073.412 | E47: 12653.53 | F47: 13156.626 | G47: 12738.601 | H47: 13215.112 | I47: 13221.191 | J47: 15176.438 | K47: 13496.921 | L47: 13067.438 | M47: 13518.316 | O47: =B45/B51 -> 13471.348 | P47: =C45/C51 -> 12277.589 | Q47: =D45/D51 -> 14098.211 | R47: =E45/E51 -> 14214.734 | S47: =F45/F51 -> 14838.245 | T47: =G45/G51 -> 14674.624 | U47: =H45/H51 -> 15443.628 | V47: =I45/I51 -> 15399.083 | ... Z47: =M45/M51 -> 15833.49
A49: Variance | B49: =B45-B47 -> 0 | C49: =C45-C47 -> 0 | D49: =D45-D47 -> 0 | E49: =E45-E47 -> 0 | F49: =F45-F47 -> 0 | G49: =G45-G47 -> 0 | H49: =H45-H47 -> 0 | I49: =I45-I47 -> -2.0008883e-11 | ... M49: =M45-M47 -> 0.0010989011 | O49: =O45-O47 -> 0 | P49: =P45-P47 -> 0 | Q49: =Q45-Q47 -> 0 | R49: =R45-R47 -> 0 | S49: =S45-S47 -> 0 | T49: =T45-T47 -> 0 | U49: =U45-U47 -> 0 | V49: =V45-V47 -> 0 | ... Z49: =Z45-Z47 -> 0
A51: Monthly Avg Rate 25 | B51: 0.96653 | C51: 0.96053 | D51: 0.92731 | E51: 0.89017 | F51: 0.88667 | G51: 0.86807 | H51: 0.8557 | I51: 0.85857 | J51: 0.85248 | K51: 0.85882 | L51: 0.86502 | M51: 0.85378
K54: Total | L54: =SUM(B45:M45) -> 158131.04 | M54: =SUM(O45:Z45) -> 178875.82
K55: BPC
K56: Variance | L56: =L54-L55 -> 158131.04 | M56: =M54-M55 -> 178875.82
B60: 0.86502 | C60: 0.85882 | D60: 0.85248 | E60: 0.85857 | F60: 0.8557 | G60: 0.86807 | H60: 0.88667 | I60: 0.89017 | J60: 0.92731 | K60: 0.96053 | L60: 0.96653

Sheet Hosting COGS
A1: Customer | B1: Amount | C1: Percentage | D1: Hosting Costs
A2: Arrabawn Co-Op | B2: 10555.809 | C2: =B2/$B$38 -> 0.019994816 | D2: =-$A$40*C2 -> -2774.7567
A3: BallyJamesDuff | B3: 8065.4892 | C3: =B3/$B$38 -> 0.015277652 | D3: =-$A$40*C3 -> -2120.1378
A4: Bandon Co-Op | B4: 30501.65 | C4: =B4/$B$38 -> 0.057776233 | D4: =-$A$40*C4 -> -8017.8274
A5: Barryroe Co-Op | B5: 28195.344 | C5: =B5/$B$38 -> 0.053407629 | D5: =-$A$40*C5 -> -7411.5796
A6: Brett Brothers | B6: 8371.6644 | C6: =B6/$B$38 -> 0.015857609 | D6: =-$A$40*C6 -> -2200.6207
A7: Callan Co-Op | B7: 5822.562 | C7: =B7/$B$38 -> 0.011029099 | D7: =-$A$40*C7 -> -1530.5499
A8: Carbery Group | B8: 6891.6555 | C8: =B8/$B$38 -> 0.013054176 | D8: =-$A$40*C8 -> -1811.5776
A9: Centenary Thurles Co-Op | B9: 6844.8653 | C9: =B9/$B$38 -> 0.012965546 | D9: =-$A$40*C9 -> -1799.278
A10: Dan O'Connor | B10: 1661.6767 | C10: =B10/$B$38 -> 0.0031475484 | D10: =-$A$40*C10 -> -436.79726
A11: Denis Brinicombe | B11: 23407.435 | C11: =B11/$B$38 -> 0.044338369 | D11: =-$A$40*C11 -> -6153.0039
A12: Drinagh Co-Op | B12: 25949.022 | C12: =B12/$B$38 -> 0.049152644 | D12: =-$A$40*C12 -> -6821.0991
A13: Drinagh Dairies | B13: 1645.2293 | C13: =B13/$B$38 -> 0.0031163937 | D13: =-$A$40*C13 -> -432.4738
... A36: T&A Building | B36: 9175.2958 | C36: =B36/$B$38 -> 0.017379848 | D36: =-$A$40*C36 -> -2411.8675
B38: =SUM(B2:B37) -> 527927.28 | D38: =SUM(D2:D37) -> -138773.8
A40: 138773.8

Sheet PS
A1: Customer | B1: January | C1: February | D1: March | E1: April | F1: May | G1: June | H1: July | I1: August | J1: September | K1: October | L1: November | M1: December | N1: Consol Eur | O1: Jan USD | P1: Feb USD | Q1: March USD | R1: Apr USD | S1: May | T1: June | U1: July | V1: August | W1: September | X1: October | Y1: November | Z1: December | AA1: Consol USD
A2: Arrabawn Co-Op Society | B2: 210 | C2: =8715+660 -> 9375 | D2: =10150+455 -> 10605 | E2: 15155 | F2: 13895 | G2: 10885 | H2: 210 | I2: 280 | J2: 280 | K2: 3500 | L2: 6895 | M2: =892.5+280 -> 1172.5 | N2: =SUM(B2:M2) -> 72462.5 | O2: =B2/$B$59 -> 217.2721 | P2: =C2/$C$59 -> 9760.2365 | Q2: =D2/$D$59 -> 11436.305 | R2: =E2/$E$59 -> 17024.838 | S2: =F2/$F$59 -> 15670.994 | T2: =G2/$G$59 -> 12539.311 | U2: =H2/$H$59 -> 245.41311 | V2: =I2/$I$59 -> 326.12367 | W2: =J2/$J$59 -> 328.45345 | X2: =K2/$K$59 -> 4075.3592 | Y2: =L2/$L$59 -> 7970.914 | Z2: =M2/$M$59 -> 1373.3046 | AA2: =SUM(O2:Z2) -> 80968.525
A3: AIB Merchant Services | F3: 525 | N3: =SUM(B3:M3) -> 525 | O3: =B3/$B$59 -> 0 | P3: =C3/$C$59 -> 0 | Q3: =D3/$D$59 -> 0 | R3: =E3/$E$59 -> 0 | S3: =F3/$F$59 -> 592.10304 | T3: =G3/$G$59 -> 0 | U3: =H3/$H$59 -> 0 | V3: =I3/$I$59 -> 0 | W3: =J3/$J$59 -> 0 | X3: =K3/$K$59 -> 0 | Y3: =L3/$L$59 -> 0 | Z3: =M3/$M$59 -> 0 | AA3: =SUM(O3:Z3) -> 592.10304
A4: Aurivo Co-Op | C4: =1960+126.67 -> 2086.67 | D4: 2006.67 | E4: =3523.33+253.33 -> 3776.66 | F4: 490.36 | G4: 1050 | H4: 385 | K4: 525 | L4: 280 | N4: =SUM(B4:M4) -> 10600.36 | O4: =B4/$B$59 -> 0 | P4: =C4/$C$59 -> 2172.4152 | Q4: =D4/$D$59 -> 2163.9689 | R4: =E4/$E$59 -> 4242.6278 | S4: =F4/$F$59 -> 553.03551 | T4: =G4/$G$59 -> 1209.5799 | U4: =H4/$H$59 -> 449.92404 | V4: =I4/$I$59 -> 0 | W4: =J4/$J$59 -> 0 | X4: =K4/$K$59 -> 611.30388 | Y4: =L4/$L$59 -> 323.69194 | Z4: =M4/$M$59 -> 0 | AA4: =SUM(O4:Z4) -> 11726.547
A5: BallyJamesDuff Co-Op | N5: =SUM(B5:M5) -> 0 | O5: =B5/$B$59 -> 0 | P5: =C5/$C$59 -> 0 | Q5: =D5/$D$59 -> 0 | R5: =E5/$E$59 -> 0 | S5: =F5/$F$59 -> 0 | T5: =G5/$G$59 -> 0 | U5: =H5/$H$59 -> 0 | V5: =I5/$I$59 -> 0 | W5: =J5/$J$59 -> 0 | X5: =K5/$K$59 -> 0 | Y5: =L5/$L$59 -> 0 | Z5: =M5/$M$59 -> 0 | AA5: =SUM(O5:Z5) -> 0
A6: Bandon Co-Op | B6: 840 | C6: 2078.33 | F6: 1750 | G6: 1137.5 | I6: 805 | J6: =1295+280 -> 1575 | L6: =2800+280 -> 3080 | M6: 490 | N6: =SUM(B6:M6) -> 11755.83 | O6: =B6/$B$59 -> 869.08839 | P6: =C6/$C$59 -> 2163.7325 | Q6: =D6/$D$59 -> 0 | R6: =E6/$E$59 -> 0 | S6: =F6/$F$59 -> 1973.6768 | T6: =G6/$G$59 -> 1310.3782 | U6: =H6/$H$59 -> 0 | V6: =I6/$I$59 -> 937.60555 | W6: =J6/$J$59 -> 1847.5507 | X6: =K6/$K$59 -> 0 | Y6: =L6/$L$59 -> 3560.6113 | Z6: =M6/$M$59 -> 573.91834 | AA6: =SUM(O6:Z6) -> 13236.562
A7: Bandon Vale Cheese | N7: =SUM(B7:M7) -> 0 | O7: =B7/$B$59 -> 0 | P7: =C7/$C$59 -> 0 | Q7: =D7/$D$59 -> 0 | R7: =E7/$E$59 -> 0 | S7: =F7/$F$59 -> 0 | T7: =G7/$G$59 -> 0 | U7: =H7/$H$59 -> 0 | V7: =I7/$I$59 -> 0 | W7: =J7/$J$59 -> 0 | X7: =K7/$K$59 -> 0 | Y7: =L7/$L$59 -> 0 | Z7: =M7/$M$59 -> 0 | AA7: =SUM(O7:Z7) -> 0
A8: Barryroe Co-Op | B8: 525 | C8: 980 | E8: 595 | F8: 1960 | H8: 1645 | K8: 350 | N8: =SUM(B8:M8) -> 6055 | O8: =B8/$B$59 -> 543.18024 | P8: =C8/$C$59 -> 1020.2701 | Q8: =D8/$D$59 -> 0 | R8: =E8/$E$59 -> 668.41165 | S8: =F8/$F$59 -> 2210.518 | T8: =G8/$G$59 -> 0 | U8: =H8/$H$59 -> 1922.4027 | V8: =I8/$I$59 -> 0 | W8: =J8/$J$59 -> 0 | X8: =K8/$K$59 -> 407.53592 | Y8: =L8/$L$59 -> 0 | Z8: =M8/$M$59 -> 0 | AA8: =SUM(O8:Z8) -> 6772.3186
A9: Brett Brothers | C9: =1050+475 -> 1525 | D9: =2730+918.33 -> 3648.33 | E9: 506.67 | N9: =SUM(B9:M9) -> 5680 | O9: =B9/$B$59 -> 0 | P9: =C9/$C$59 -> 1587.6651 | Q9: =D9/$D$59 -> 3934.3154 | R9: =E9/$E$59 -> 569.18341 | S9: =F9/$F$59 -> 0 | T9: =G9/$G$59 -> 0 | U9: =H9/$H$59 -> 0 | V9: =I9/$I$59 -> 0 | W9: =J9/$J$59 -> 0 | X9: =K9/$K$59 -> 0 | Y9: =L9/$L$59 -> 0 | Z9: =M9/$M$59 -> 0 | AA9: =SUM(O9:Z9) -> 6091.1639
A10: Callan Co-Op | B10: 5040 | C10: 4795 | D10: 4340 | E10: 1050 | F10: 70 | G10: 1190 | H10: 70 | K10: 70 | L10: 770 | N10: =SUM(B10:M10) -> 17395 | O10: =B10/$B$59 -> 5214.5303 | P10: =C10/$C$59 -> 4992.0356 | Q10: =D10/$D$59 -> 4680.204 | R10: =E10/$E$59 -> 1179.55 | S10: =F10/$F$59 -> 78.947072 | T10: =G10/$G$59 -> 1370.8572 | U10: =H10/$H$59 -> 81.804371 | V10: =I10/$I$59 -> 0 | W10: =J10/$J$59 -> 0 | X10: =K10/$K$59 -> 81.507184 | Y10: =L10/$L$59 -> 890.15283 | Z10: =M10/$M$59 -> 0 | AA10: =SUM(O10:Z10) -> 18569.589
A11: Carbery Group | J11: 525 | K11: 1680 | L11: 175 | M11: 770 | N11: =SUM(B11:M11) -> 3150 | O11: =B11/$B$59 -> 0 | P11: =C11/$C$59 -> 0 | Q11: =D11/$D$59 -> 0 | R11: =E11/$E$59 -> 0 | S11: =F11/$F$59 -> 0 | T11: =G11/$G$59 -> 0 | U11: =H11/$H$59 -> 0 | V11: =I11/$I$59 -> 0 | W11: =J11/$J$59 -> 615.85023 | X11: =K11/$K$59 -> 1956.1724 | Y11: =L11/$L$59 -> 202.30746 | Z11: =M11/$M$59 -> 901.87168 | AA11: =SUM(O11:Z11) -> 3676.2018
A12: Centenary Thurles Fresh Milk | N12: =SUM(B12:M12) -> 0 | O12: =B12/$B$59 -> 0 | P12: =C12/$C$59 -> 0 | Q12: =D12/$D$59 -> 0 | R12: =E12/$E$59 -> 0 | S12: =F12/$F$59 -> 0 | T12: =G12/$G$59 -> 0 | U12: =H12/$H$59 -> 0 | V12: =I12/$I$59 -> 0 | W12: =J12/$J$59 -> 0 | X12: =K12/$K$59 -> 0 | Y12: =L12/$L$59 -> 0 | Z12: =M12/$M$59 -> 0 | AA12: =SUM(O12:Z12) -> 0
A13: Centenary Thurles Co-Op | B13: 1631.65 | L13: 245 | N13: =SUM(B13:M13) -> 1876.65 | O13: =B13/$B$59 -> 1688.1525 | P13: =C13/$C$59 -> 0 | Q13: =D13/$D$59 -> 0 | R13: =E13/$E$59 -> 0 | S13: =F13/$F$59 -> 0 | T13: =G13/$G$59 -> 0 | U13: =H13/$H$59 -> 0 | V13: =I13/$I$59 -> 0 | W13: =J13/$J$59 -> 0 | X13: =K13/$K$59 -> 0 | Y13: =L13/$L$59 -> 283.23045 | Z13: =M13/$M$59 -> 0 | AA13: =SUM(O13:Z13) -> 1971.3829
A14: Centenary Thurles Stores | B14: 950 | N14: =SUM(B14:M14) -> 950 | O14: =B14/$B$59 -> 982.89758 | P14: =C14/$C$59 -> 0 | Q14: =D14/$D$59 -> 0 | R14: =E14/$E$59 -> 0 | S14: =F14/$F$59 -> 0 | T14: =G14/$G$59 -> 0 | U14: =H14/$H$59 -> 0 | V14: =I14/$I$59 -> 0 | W14: =J14/$J$59 -> 0 | X14: =K14/$K$59 -> 0 | Y14: =L14/$L$59 -> 0 | Z14: =M14/$M$59 -> 0 | AA14: =SUM(O14:Z14) -> 982.89758
A15: Centenary Thurles Feed & Grain | N15: =SUM(B15:M15) -> 0 | O15: =B15/$B$59 -> 0 | P15: =C15/$C$59 -> 0 | Q15: =D15/$D$59 -> 0 | R15: =E15/$E$59 -> 0 | S15: =F15/$F$59 -> 0 | T15: =G15/$G$59 -> 0 | U15: =H15/$H$59 -> 0 | V15: =I15/$I$59 -> 0 | W15: =J15/$J$59 -> 0 | X15: =K15/$K$59 -> 0 | Y15: =L15/$L$59 -> 0 | Z15: =M15/$M$59 -> 0 | AA15: =SUM(O15:Z15) -> 0
A16: Dan O'Connor Feeds | C16: 70 | N16: =SUM(B16:M16) -> 70 | O16: =B16/$B$59 -> 0 | P16: =C16/$C$59 -> 72.876433 | Q16: =D16/$D$59 -> 0 | R16: =E16/$E$59 -> 0 | S16: =F16/$F$59 -> 0 | T16: =G16/$G$59 -> 0 | U16: =H16/$H$59 -> 0 | V16: =I16/$I$59 -> 0 | W16: =J16/$J$59 -> 0 | X16: =K16/$K$59 -> 0 | Y16: =L16/$L$59 -> 0 | Z16: =M16/$M$59 -> 0 | AA16: =SUM(O16:Z16) -> 72.876433
A17: Denis Brinicombe Group | B17: 134.63 | C17: =2977.77+102.15 -> 3079.92 | D17: 6291.13 | I17: 208.04 | K17: 1236.76 | L17: 7180.09 | M17: =10326.96+410.39 -> 10737.35 | N17: =SUM(B17:M17) -> 28867.92 | O17: =B17/$B$59 -> 139.29211 | P17: =C17/$C$59 -> 3206.4798 | Q17: =D17/$D$59 -> 6784.2793 | R17: =E17/$E$59 -> 0 | S17: =F17/$F$59 -> 0 | T17: =G17/$G$59 -> 0 | U17: =H17/$H$59 -> 0 | V17: =I17/$I$59 -> 242.30989 | W17: =J17/$J$59 -> 0 | X17: =K17/$K$59 -> 1440.0689 | Y17: =L17/$L$59 -> 8300.4902 | Z17: =M17/$M$59 -> 12576.249 | AA17: =SUM(O17:Z17) -> 32689.169
A18: Drinagh Co-Op | B18: =105.01+245+140 -> 490.01 | C18: 2438.33 | D18: 4200 | E18: 420 | I18: =1050-2100 -> -1050 | J18: 1190 | K18: =560+910 -> 1470 | L18: 2317 | M18: =-777+(-3937.5) -> -4714.5 | N18: =SUM(B18:M18) -> 6760.84 | O18: =B18/$B$59 -> 506.97857 | P18: =C18/$C$59 -> 2538.5256 | Q18: =D18/$D$59 -> 4529.2297 | R18: =E18/$E$59 -> 471.81999 | S18: =F18/$F$59 -> 0 | T18: =G18/$G$59 -> 0 | U18: =H18/$H$59 -> 0 | V18: =I18/$I$59 -> -1222.9638 | W18: =J18/$J$59 -> 1395.9272 | X18: =K18/$K$59 -> 1711.6509 | Y18: =L18/$L$59 -> 2678.5508 | Z18: =M18/$M$59 -> -5521.9143 | AA18: =SUM(O18:Z18) -> 7087.8046
A19: Drinagh Dairies | N19: =SUM(B19:M19) -> 0 | O19: =B19/$B$59 -> 0 | P19: =C19/$C$59 -> 0 | Q19: =D19/$D$59 -> 0 | R19: =E19/$E$59 -> 0 | S19: =F19/$F$59 -> 0 | T19: =G19/$G$59 -> 0 | U19: =H19/$H$59 -> 0 | V19: =I19/$I$59 -> 0 | W19: =J19/$J$59 -> 0 | X19: =K19/$K$59 -> 0 | Y19: =L19/$L$59 -> 0 | Z19: =M19/$M$59 -> 0 | AA19: =SUM(O19:Z19) -> 0
A20: East Coast Viners | D20: 5635 | E20: 2590 | F20: 175 | H20: 4200 | L20: 1379 | M20: 5166 | N20: =SUM(B20:M20) -> 19145 | O20: =B20/$B$59 -> 0 | P20: =C20/$C$59 -> 0 | Q20: =D20/$D$59 -> 6076.7165 | R20: =E20/$E$59 -> 2909.5566 | S20: =F20/$F$59 -> 197.36768 | T20: =G20/$G$59 -> 0 | U20: =H20/$H$59 -> 4908.2622 | V20: =I20/$I$59 -> 0 | W20: =J20/$J$59 -> 0 | X20: =K20/$K$59 -> 0 | Y20: =L20/$L$59 -> 1594.1828 | Z20: =M20/$M$59 -> 6050.7391 | AA20: =SUM(O20:Z20) -> 21736.825
A21: Tirlan | B21: =4845+2590+7884+4092.5 -> 19411.5 | C21: =3983.33+185+0.01 -> 4168.34 | D21: =6707.5+370 -> 7077.5 | E21: =6320.33+2096.67 -> 8417 | F21: =4110.67+740+0.02 -> 4850.69 | G21: =9180+259 -> 9439 | H21: =5930+370-0.01 -> 6299.99 | I21: =16420.83+215.83-0.02 -> 16636.64 | J21: =11006.67+308.33+0.03 -> 11315.03 | K21: =8445+1646.67+0.01 -> 10091.68 | L21: =12808.33+1350+1715+0.02 -> 15873.35 | M21: =16451.67+70+1361.67-0.01 -> 17883.33 | N21: =SUM(B21:M21) -> 131464.05 | O21: =B21/$B$59 -> 20083.701 | P21: =C21/$C$59 -> 4339.625 | Q21: =D21/$D$59 -> 7632.2913 | R21: =E21/$E$59 -> 9455.4973 | S21: =F21/$F$59 -> 5470.6824 | T21: =G21/$G$59 -> 10873.547 | U21: =H21/$H$59 -> 7362.3817 | V21: =I21/$I$59 -> 19377.15 | W21: =J21/$J$59 -> 13273.074 | X21: =K21/$K$59 -> 11750.635 | Y21: =L21/$L$59 -> 18350.269 | Z21: =M21/$M$59 -> 20946.063 | AA21: =SUM(O21:Z21) -> 148914.92
A22: Heat Merchants Group | B22: 70 | C22: =4375+70 -> 4445 | D22: 3360 | E22: 1015 | F22: =70+2450 -> 2520 | I22: 3780 | K22: 3955 | L22: =18970+525 -> 19495 | M22: 15715 | N22: =SUM(B22:M22) -> 54355 | O22: =B22/$B$59 -> 72.424032 | P22: =C22/$C$59 -> 4627.6535 | Q22: =D22/$D$59 -> 3623.3838 | R22: =E22/$E$59 -> 1140.2316 | S22: =F22/$F$59 -> 2842.0946 | T22: =G22/$G$59 -> 0 | U22: =H22/$H$59 -> 0 | V22: =I22/$I$59 -> 4402.6696 | W22: =J22/$J$59 -> 0 | X22: =K22/$K$59 -> 4605.1559 | Y22: =L22/$L$59 -> 22537.051 | Z22: =M22/$M$59 -> 18406.381 | AA22: =SUM(O22:Z22) -> 62257.045
A23: Hopkins Homevalue Hardware | N23: =SUM(B23:M23) -> 0 | O23: =B23/$B$59 -> 0 | P23: =C23/$C$59 -> 0 | Q23: =D23/$D$59 -> 0 | R23: =E23/$E$59 -> 0 | S23: =F23/$F$59 -> 0 | T23: =G23/$G$59 -> 0 | U23: =H23/$H$59 -> 0 | V23: =I23/$I$59 -> 0 | W23: =J23/$J$59 -> 0 | X23: =K23/$K$59 -> 0 | Y23: =L23/$L$59 -> 0 | Z23: =M23/$M$59 -> 0 | AA23: =SUM(O23:Z23) -> 0
A24: ICMSA | N24: =SUM(B24:M24) -> 0 | O24: =B24/$B$59 -> 0 | P24: =C24/$C$59 -> 0 | Q24: =D24/$D$59 -> 0 | R24: =E24/$E$59 -> 0 | S24: =F24/$F$59 -> 0 | T24: =G24/$G$59 -> 0 | U24: =H24/$H$59 -> 0 | V24: =I24/$I$59 -> 0 | W24: =J24/$J$59 -> 0 | X24: =K24/$K$59 -> 0 | Y24: =L24/$L$59 -> 0 | Z24: =M24/$M$59 -> 0 | AA24: =SUM(O24:Z24) -> 0
A25: Irish International Traders | C25: 420 | N25: =SUM(B25:M25) -> 420 | O25: =B25/$B$59 -> 0 | P25: =C25/$C$59 -> 437.2586 | Q25: =D25/$D$59 -> 0 | R25: =E25/$E$59 -> 0 | S25: =F25/$F$59 -> 0 | T25: =G25/$G$59 -> 0 | U25: =H25/$H$59 -> 0 | V25: =I25/$I$59 -> 0 | W25: =J25/$J$59 -> 0 | X25: =K25/$K$59 -> 0 | Y25: =L25/$L$59 -> 0 | Z25: =M25/$M$59 -> 0 | AA25: =SUM(O25:Z25) -> 437.2586
A26: John R. McCarthy | N26: =SUM(B26:M26) -> 0 | O26: =B26/$B$59 -> 0 | P26: =C26/$C$59 -> 0 | Q26: =D26/$D$59 -> 0 | R26: =E26/$E$59 -> 0 | S26: =F26/$F$59 -> 0 | T26: =G26/$G$59 -> 0 | U26: =H26/$H$59 -> 0 | V26: =I26/$I$59 -> 0 | W26: =J26/$J$59 -> 0 | X26: =K26/$K$59 -> 0 | Y26: =L26/$L$59 -> 0 | Z26: =M26/$M$59 -> 0 | AA26: =SUM(O26:Z26) -> 0
A27: J. McKenna Ltd | N27: =SUM(B27:M27) -> 0 | O27: =B27/$B$59 -> 0 | P27: =C27/$C$59 -> 0 | Q27: =D27/$D$59 -> 0 | R27: =E27/$E$59 -> 0 | S27: =F27/$F$59 -> 0 | T27: =G27/$G$59 -> 0 | U27: =H27/$H$59 -> 0 | V27: =I27/$I$59 -> 0 | W27: =J27/$J$59 -> 0 | X27: =K27/$K$59 -> 0 | Y27: =L27/$L$59 -> 0 | Z27: =M27/$M$59 -> 0 | AA27: =SUM(O27:Z27) -> 0
A28: Joyce Hardware | N28: =SUM(B28:M28) -> 0 | O28: =B28/$B$59 -> 0 | P28: =C28/$C$59 -> 0 | Q28: =D28/$D$59 -> 0 | R28: =E28/$E$59 -> 0 | S28: =F28/$F$59 -> 0 | T28: =G28/$G$59 -> 0 | U28: =H28/$H$59 -> 0 | V28: =I28/$I$59 -> 0 | W28: =J28/$J$59 -> 0 | X28: =K28/$K$59 -> 0 | Y28: =L28/$L$59 -> 0 | Z28: =M28/$M$59 -> 0 | AA28: =SUM(O28:Z28) -> 0
A29: Kellihers Mills | B29: 443.33 | J29: -1965.04 | N29: =SUM(B29:M29) -> -1521.71 | O29: =B29/$B$59 -> 458.68209 | P29: =C29/$C$59 -> 0 | Q29: =D29/$D$59 -> 0 | R29: =E29/$E$59 -> 0 | S29: =F29/$F$59 -> 0 | T29: =G29/$G$59 -> 0 | U29: =H29/$H$59 -> 0 | V29: =I29/$I$59 -> 0 | W29: =J29/$J$59 -> -2305.0863 | X29: =K29/$K$59 -> 0 | Y29: =L29/$L$59 -> 0 | Z29: =M29/$M$59 -> 0 | AA29: =SUM(O29:Z29) -> -1846.4042
A30: Kerry Agribusiness | K30: 1050 | L30: 630 | M30: 682.5 | N30: =SUM(B30:M30) -> 2362.5 | O30: =B30/$B$59 -> 0 | P30: =C30/$C$59 -> 0 | Q30: =D30/$D$59 -> 0 | R30: =E30/$E$59 -> 0 | S30: =F30/$F$59 -> 0 | T30: =G30/$G$59 -> 0 | U30: =H30/$H$59 -> 0 | V30: =I30/$I$59 -> 0 | W30: =J30/$J$59 -> 0 | X30: =K30/$K$59 -> 1222.6078 | Y30: =L30/$L$59 -> 728.30686 | Z30: =M30/$M$59 -> 799.38626 | AA30: =SUM(O30:Z30) -> 2750.3009
A31: Kiernan | B31: =10465+2590+3290 -> 16345 | C31: 22176 | D31: =24823.91+4065.04 -> 28888.95 | E31: 10554.09 | F31: 10654 | G31: 21455 | H31: 11480 | I31: 9275 | J31: 7210 | K31: 11347 | L31: 9803.5 | M31: 1092 | N31: =SUM(B31:M31) -> 160280.54 | O31: =B31/$B$59 -> 16911.012 | P31: =C31/$C$59 -> 23087.254 | Q31: =D31/$D$59 -> 31153.498 | R31: =E31/$E$59 -> 11856.263 | S31: =F31/$F$59 -> 12015.744 | T31: =G31/$G$59 -> 24715.749 | U31: =H31/$H$59 -> 13415.917 | V31: =I31/$I$59 -> 10802.847 | W31: =J31/$J$59 -> 8457.6764 | X31: =K31/$K$59 -> 13212.315 | Y31: =L31/$L$59 -> 11333.264 | Z31: =M31/$M$59 -> 1279.018 | AA31: =SUM(O31:Z31) -> 178240.56
A32: Lacpatrick | B32: 506.67 | N32: =SUM(B32:M32) -> 506.67 | O32: =B32/$B$59 -> 524.21549 | P32: =C32/$C$59 -> 0 | Q32: =D32/$D$59 -> 0 | R32: =E32/$E$59 -> 0 | S32: =F32/$F$59 -> 0 | T32: =G32/$G$59 -> 0 | U32: =H32/$H$59 -> 0 | V32: =I32/$I$59 -> 0 | W32: =J32/$J$59 -> 0 | X32: =K32/$K$59 -> 0 | Y32: =L32/$L$59 -> 0 | Z32: =M32/$M$59 -> 0 | AA32: =SUM(O32:Z32) -> 524.21549
A33: Lakeland | B33: =1015+420 -> 1435 | C33: 700 | D33: 140 | E33: =280+210 -> 490 | G33: 490 | H33: 350 | J33: =-280+420 -> 140 | K33: 210 | L33: 70 | M33: 5180 | N33: =SUM(B33:M33) -> 9205 | O33: =B33/$B$59 -> 1484.6927 | P33: =C33/$C$59 -> 728.76433 | Q33: =D33/$D$59 -> 150.97432 | R33: =E33/$E$59 -> 550.45665 | S33: =F33/$F$59 -> 0 | T33: =G33/$G$59 -> 564.47061 | U33: =H33/$H$59 -> 409.02185 | V33: =I33/$I$59 -> 0 | W33: =J33/$J$59 -> 164.22673 | X33: =K33/$K$59 -> 244.52155 | Y33: =L33/$L$59 -> 80.922984 | Z33: =M33/$M$59 -> 6067.1367 | AA33: =SUM(O33:Z33) -> 10445.188
A34: Lee Strand Dairies | D34: 350 | N34: =SUM(B34:M34) -> 350 | O34: =B34/$B$59 -> 0 | P34: =C34/$C$59 -> 0 | Q34: =D34/$D$59 -> 377.43581 | R34: =E34/$E$59 -> 0 | S34: =F34/$F$59 -> 0 | T34: =G34/$G$59 -> 0 | U34: =H34/$H$59 -> 0 | V34: =I34/$I$59 -> 0 | W34: =J34/$J$59 -> 0 | X34: =K34/$K$59 -> 0 | Y34: =L34/$L$59 -> 0 | Z34: =M34/$M$59 -> 0 | AA34: =SUM(O34:Z34) -> 377.43581
A35: Lisavaird Co-Op | B35: =4095+420 -> 4515 | C35: =805+350 -> 1155 | D35: 1155 | E35: =2100+140 -> 2240 | F35: =1610+560 -> 2170 | G35: =5635+560 -> 6195 | I35: =350+140 -> 490 | J35: 2485 | K35: 140 | L35: =4935+2100 -> 7035 | M35: =-35+770 -> 735 | N35: =SUM(B35:M35) -> 28315 | O35: =B35/$B$59 -> 4671.3501 | P35: =C35/$C$59 -> 1202.4611 | Q35: =D35/$D$59 -> 1245.5382 | R35: =E35/$E$59 -> 2516.3733 | S35: =F35/$F$59 -> 2447.3592 | T35: =G35/$G$59 -> 7136.5212 | U35: =H35/$H$59 -> 0 | V35: =I35/$I$59 -> 570.71642 | W35: =J35/$J$59 -> 2915.0244 | X35: =K35/$K$59 -> 163.01437 | Y35: =L35/$L$59 -> 8132.7599 | Z35: =M35/$M$59 -> 860.87751 | AA35: =SUM(O35:Z35) -> 31861.996
A36: McDonnell Bros Ltd | N36: =SUM(B36:M36) -> 0 | O36: =B36/$B$59 -> 0 | P36: =C36/$C$59 -> 0 | Q36: =D36/$D$59 -> 0 | R36: =E36/$E$59 -> 0 | S36: =F36/$F$59 -> 0 | T36: =G36/$G$59 -> 0 | U36: =H36/$H$59 -> 0 | V36: =I36/$I$59 -> 0 | W36: =J36/$J$59 -> 0 | X36: =K36/$K$59 -> 0 | Y36: =L36/$L$59 -> 0 | Z36: =M36/$M$59 -> 0 | AA36: =SUM(O36:Z36) -> 0
A37: McDonogh Trade Centre Ltd | F37: 1050 | K37: 770 | N37: =SUM(B37:M37) -> 1820 | O37: =B37/$B$59 -> 0 | P37: =C37/$C$59 -> 0 | Q37: =D37/$D$59 -> 0 | R37: =E37/$E$59 -> 0 | S37: =F37/$F$59 -> 1184.2061 | T37: =G37/$G$59 -> 0 | U37: =H37/$H$59 -> 0 | V37: =I37/$I$59 -> 0 | W37: =J37/$J$59 -> 0 | X37: =K37/$K$59 -> 896.57903 | Y37: =L37/$L$59 -> 0 | Z37: =M37/$M$59 -> 0 | AA37: =SUM(O37:Z37) -> 2080.7851
A38: M.D O'Shea & Sons Ltd | B38: 117.42 | C38: =110.08+1120 -> 1230.08 | E38: =1050+700 -> 1750 | F38: =1071.67+253.33 -> 1325 | G38: 1680 | L38: =678.33+1456.67 -> 2135 | N38: =SUM(B38:M38) -> 8237.5 | O38: =B38/$B$59 -> 121.48614 | P38: =C38/$C$59 -> 1280.6263 | Q38: =D38/$D$59 -> 0 | R38: =E38/$E$59 -> 1965.9166 | S38: =F38/$F$59 -> 1494.3553 | T38: =G38/$G$59 -> 1935.3278 | U38: =H38/$H$59 -> 0 | V38: =I38/$I$59 -> 0 | W38: =J38/$J$59 -> 0 | X38: =K38/$K$59 -> 0 | Y38: =L38/$L$59 -> 2468.151 | Z38: =M38/$M$59 -> 0 | AA38: =SUM(O38:Z38) -> 9265.8632
A39: Morris DIY & Building | B39: =305.39+1693.33 -> 1998.72 | C39: =102.94+453.32 -> 556.26 | M39: 280 | N39: =SUM(B39:M39) -> 2834.98 | O39: =B39/$B$59 -> 2067.9337 | P39: =C39/$C$59 -> 579.11778 | Q39: =D39/$D$59 -> 0 | R39: =E39/$E$59 -> 0 | S39: =F39/$F$59 -> 0 | T39: =G39/$G$59 -> 0 | U39: =H39/$H$59 -> 0 | V39: =I39/$I$59 -> 0 | W39: =J39/$J$59 -> 0 | X39: =K39/$K$59 -> 0 | Y39: =L39/$L$59 -> 0 | Z39: =M39/$M$59 -> 327.95334 | AA39: =SUM(O39:Z39) -> 2975.0049
A40: Mole Avon Town | B40: 1120 | C40: 560 | N40: =SUM(B40:M40) -> 1680 | O40: =B40/$B$59 -> 1158.7845 | P40: =C40/$C$59 -> 583.01146 | Q40: =D40/$D$59 -> 0 | R40: =E40/$E$59 -> 0 | S40: =F40/$F$59 -> 0 | T40: =G40/$G$59 -> 0 | U40: =H40/$H$59 -> 0 | V40: =I40/$I$59 -> 0 | W40: =J40/$J$59 -> 0 | X40: =K40/$K$59 -> 0 | Y40: =L40/$L$59 -> 0 | Z40: =M40/$M$59 -> 0 | AA40: =SUM(O40:Z40) -> 1741.796
A41: North Cork Co-Op | B41: 665 | C41: =5775+623.33 -> 6398.33 | D41: 1785 | E41: 315 | F41: 245 | K41: 910 | L41: =1575+140 -> 1715 | N41: =SUM(B41:M41) -> 12033.33 | O41: =B41/$B$59 -> 688.02831 | P41: =C41/$C$59 -> 6661.2495 | Q41: =D41/$D$59 -> 1924.9226 | R41: =E41/$E$59 -> 353.86499 | S41: =F41/$F$59 -> 276.31475 | T41: =G41/$G$59 -> 0 | U41: =H41/$H$59 -> 0 | V41: =I41/$I$59 -> 0 | W41: =J41/$J$59 -> 0 | X41: =K41/$K$59 -> 1059.5934 | Y41: =L41/$L$59 -> 1982.6131 | Z41: =M41/$M$59 -> 0 | AA41: =SUM(O41:Z41) -> 12946.587
A42: Organic Herd | E42: 560 | F42: 2590 | N42: =SUM(B42:M42) -> 3150 | O42: =B42/$B$59 -> 0 | P42: =C42/$C$59 -> 0 | Q42: =D42/$D$59 -> 0 | R42: =E42/$E$59 -> 629.09332 | S42: =F42/$F$59 -> 2921.0417 | T42: =G42/$G$59 -> 0 | U42: =H42/$H$59 -> 0 | V42: =I42/$I$59 -> 0 | W42: =J42/$J$59 -> 0 | X42: =K42/$K$59 -> 0 | Y42: =L42/$L$59 -> 0 | Z42: =M42/$M$59 -> 0 | AA42: =SUM(O42:Z42) -> 3550.135
A43: Peter Curran Electrical | B43: 506.66 | N43: =SUM(B43:M43) -> 506.66 | O43: =B43/$B$59 -> 524.20515 | P43: =C43/$C$59 -> 0 | Q43: =D43/$D$59 -> 0 | R43: =E43/$E$59 -> 0 | S43: =F43/$F$59 -> 0 | T43: =G43/$G$59 -> 0 | U43: =H43/$H$59 -> 0 | V43: =I43/$I$59 -> 0 | W43: =J43/$J$59 -> 0 | X43: =K43/$K$59 -> 0 | Y43: =L43/$L$59 -> 0 | Z43: =M43/$M$59 -> 0 | AA43: =SUM(O43:Z43) -> 524.20515
A44: Richard Boyle & Sons Ltd | C44: 696.66 | G44: 840 | N44: =SUM(B44:M44) -> 1536.66 | O44: =B44/$B$59 -> 0 | P44: =C44/$C$59 -> 725.28708 | Q44: =D44/$D$59 -> 0 | R44: =E44/$E$59 -> 0 | S44: =F44/$F$59 -> 0 | T44: =G44/$G$59 -> 967.6639 | U44: =H44/$H$59 -> 0 | V44: =I44/$I$59 -> 0 | W44: =J44/$J$59 -> 0 | X44: =K44/$K$59 -> 0 | Y44: =L44/$L$59 -> 0 | Z44: =M44/$M$59 -> 0 | AA44: =SUM(O44:Z44) -> 1692.951
A45: Smith's Building supplies | N45: =SUM(B45:M45) -> 0 | O45: =B45/$B$59 -> 0 | P45: =C45/$C$59 -> 0 | Q45: =D45/$D$59 -> 0 | R45: =E45/$E$59 -> 0 | S45: =F45/$F$59 -> 0 | T45: =G45/$G$59 -> 0 | U45: =H45/$H$59 -> 0 | V45: =I45/$I$59 -> 0 | W45: =J45/$J$59 -> 0 | X45: =K45/$K$59 -> 0 | Y45: =L45/$L$59 -> 0 | Z45: =M45/$M$59 -> 0 | AA45: =SUM(O45:Z45) -> 0
A46: Smith's Tool Hire | N46: =SUM(B46:M46) -> 0 | O46: =B46/$B$59 -> 0 | P46: =C46/$C$59 -> 0 | Q46: =D46/$D$59 -> 0 | R46: =E46/$E$59 -> 0 | S46: =F46/$F$59 -> 0 | T46: =G46/$G$59 -> 0 | U46: =H46/$H$59 -> 0 | V46: =I46/$I$59 -> 0 | W46: =J46/$J$59 -> 0 | X46: =K46/$K$59 -> 0 | Y46: =L46/$L$59 -> 0 | Z46: =M46/$M$59 -> 0 | AA46: =SUM(O46:Z46) -> 0
A47: Strathroy Dairies | N47: =SUM(B47:M47) -> 0 | O47: =B47/$B$59 -> 0 | P47: =C47/$C$59 -> 0 | Q47: =D47/$D$59 -> 0 | R47: =E47/$E$59 -> 0 | S47: =F47/$F$59 -> 0 | T47: =G47/$G$59 -> 0 | U47: =H47/$H$59 -> 0 | V47: =I47/$I$59 -> 0 | W47: =J47/$J$59 -> 0 | X47: =K47/$K$59 -> 0 | Y47: =L47/$L$59 -> 0 | Z47: =M47/$M$59 -> 0 | AA47: =SUM(O47:Z47) -> 0
A48: T&A Building | N48: =SUM(B48:M48) -> 0 | O48: =B48/$B$59 -> 0 | P48: =C48/$C$59 -> 0 | Q48: =D48/$D$59 -> 0 | R48: =E48/$E$59 -> 0 | S48: =F48/$F$59 -> 0 | T48: =G48/$G$59 -> 0 | U48: =H48/$H$59 -> 0 | V48: =I48/$I$59 -> 0 | W48: =J48/$J$59 -> 0 | X48: =K48/$K$59 -> 0 | Y48: =L48/$L$59 -> 0 | Z48: =M48/$M$59 -> 0 | AA48: =SUM(O48:Z48) -> 0
A49: Wallaces Homevalue Hardware | B49: 210 | C49: 63.35 | E49: 665 | F49: 5880 | G49: 9100 | H49: 10080 | I49: 2870 | J49: 455 | K49: 350 | N49: =SUM(B49:M49) -> 29673.35 | O49: =B49/$B$59 -> 217.2721 | P49: =C49/$C$59 -> 65.953172 | Q49: =D49/$D$59 -> 0 | R49: =E49/$E$59 -> 747.04832 | S49: =F49/$F$59 -> 6631.554 | T49: =G49/$G$59 -> 10483.026 | U49: =H49/$H$59 -> 11779.829 | V49: =I49/$I$59 -> 3342.7676 | W49: =J49/$J$59 -> 533.73686 | X49: =K49/$K$59 -> 407.53592 | Y49: =L49/$L$59 -> 0 | Z49: =M49/$M$59 -> 0 | AA49: =SUM(O49:Z49) -> 34208.723
A50: Wolseley | B50: 1890 | N50: =SUM(B50:M50) -> 1890 | O50: =B50/$B$59 -> 1955.4489 | P50: =C50/$C$59 -> 0 | Q50: =D50/$D$59 -> 0 | R50: =E50/$E$59 -> 0 | S50: =F50/$F$59 -> 0 | T50: =G50/$G$59 -> 0 | U50: =H50/$H$59 -> 0 | V50: =I50/$I$59 -> 0 | W50: =J50/$J$59 -> 0 | X50: =K50/$K$59 -> 0 | Y50: =L50/$L$59 -> 0 | Z50: =M50/$M$59 -> 0 | AA50: =SUM(O50:Z50) -> 1955.4489
A51: Adj | N51: =SUM(B51:M51) -> 0 | O51: =B51/$B$59 -> 0 | P51: =C51/$C$59 -> 0 | Q51: =D51/$D$59 -> 0 | R51: =E51/$E$59 -> 0 | S51: =F51/$F$59 -> 0 | T51: =G51/$G$59 -> 0 | U51: =H51/$H$59 -> 0 | V51: =I51/$I$59 -> 0 | W51: =J51/$J$59 -> 0 | X51: =K51/$K$59 -> 0 | Y51: =L51/$L$59 -> 0 | Z51: =M51/$M$59 -> 0 | AA51: =SUM(O51:Z51) -> 0
S52: =F52/$F$59 -> 0 | AA52: =SUM(O52:Z52) -> 0
B53: =SUM(B2:B52) -> 59055.59 | C53: =SUM(C2:C52) -> 68997.27 | D53: =SUM(D2:D52) -> 79482.58 | E53: =SUM(E2:E52) -> 50099.42 | F53: =SUM(F2:F52) -> 50150.05 | G53: =SUM(G2:G52) -> 63461.5 | H53: =SUM(H2:H52) -> 34719.99 | I53: =SUM(I2:I52) -> 33294.68 | J53: =SUM(J2:J51) -> 23209.99 | K53: =SUM(K2:K51) -> 37655.44 | L53: =SUM(L2:L51) -> 79077.94 | M53: =SUM(M2:M51) -> 55189.18 | N53: =SUM(B53:M53) -> 634393.63 | O53: =SUM(O2:O52) -> 61100.628 | P53: =SUM(P2:P52) -> 71832.499 | Q53: =SUM(Q2:Q52) -> 85713.063 | R53: =SUM(R2:R52) -> 56280.733 | S53: =SUM(S2:S52) -> 56559.994 | T53: =SUM(T2:T52) -> 73106.432 | U53: =SUM(U2:U52) -> 40574.956 | V53: =SUM(V2:V52) -> 38779.226 | ... Z53: =SUM(Z2:Z52) -> 64640.985 | AA53: =SUM(O53:Z53) -> 711077.97
A55: GP Balance | B55: 59055.59 | C55: 68997.27 | D55: 79482.58 | E55: 50099.42 | F55: 50150.05 | G55: 63461.5 | H55: 34719.99 | I55: 33294.68 | J55: 23209.99 | K55: 37655.44 | L55: 79077.94 | M55: 55189.18
A57: Variance | B57: =B53-B55 -> 0 | C57: =C53-C55 -> 0 | D57: =D53-D55 -> 0 | E57: =E53-E55 -> 0 | F57: =F53-F55 -> 0 | G57: =G53-G55 -> 0 | H57: =H53-H55 -> 0 | I57: =I53-I55 -> 0 | ... M57: =M53-M55 -> 0
B59: 0.96653 | C59: 0.96053 | D59: 0.92731 | E59: 0.89017 | F59: 0.88667 | G59: 0.86807 | H59: 0.8557 | I59: 0.85857 | J59: 0.85248 | K59: 0.85882 | L59: 0.86502 | M59: 0.85378
M60: Total | N60: =N53 -> 634393.63 | O60: =AA53 -> 711077.97
M61: BPC
M62: Variance | N62: =N60-N61 -> 634393.63 | O62: =O60-O61 -> 711077.97

Sheet Licence
A2: Customer | B2: January | C2: February | D2: March | E2: April | F2: May | G2: June | H2: July | I2: August | J2: September | K2: October | L2: November | M2: December | N2: Consol EUR | O2: JAN USD | P2: FEB USD | Q2: MAR USD | R2: APR USD | S2: MAY USD | T2: JUNE USD | U2: JULY USD | V2: AUG USD | W2: SEPT USD | X2: OCT USD | Y2: NOV USD | Z2: DEC USD | AA2: CONSOL USD
A3: Arrabawn Co-Op Society | E3: 35160 | G3: 5755 | L3: 10422.22 | M3: 12077.78 | N3: =SUM(B3:M3) -> 63415 | O3: =B3/$B$58 -> 0 | P3: =C3/$C$58 -> 0 | Q3: =D3/$D$58 -> 0 | R3: =E3/$E$58 -> 39498.073 | S3: =F3/$F$58 -> 0 | T3: =G3/$G$58 -> 6629.6497 | U3: =H3/$H$58 -> 0 | V3: =I3/$I$58 -> 0 | W3: =J3/$J$58 -> 0 | X3: =K3/$K$58 -> 0 | Y3: =L3/$L$58 -> 12048.531 | Z3: =M3/$M$58 -> 14146.244 | AA3: =SUM(O3:Z3) -> 72322.498
A4: AIB Merchant Services | F4: 3000 | N4: =SUM(B4:M4) -> 3000 | O4: =B4/$B$58 -> 0 | P4: =C4/$C$58 -> 0 | Q4: =D4/$D$58 -> 0 | R4: =E4/$E$58 -> 0 | S4: =F4/$F$58 -> 3383.4459 | T4: =G4/$G$58 -> 0 | U4: =H4/$H$58 -> 0 | V4: =I4/$I$58 -> 0 | W4: =J4/$J$58 -> 0 | X4: =K4/$K$58 -> 0 | Y4: =L4/$L$58 -> 0 | Z4: =M4/$M$58 -> 0 | AA4: =SUM(O4:Z4) -> 3383.4459
A5: Aurivo Co-Op | B5: =11400+2100 -> 13500 | C5: 775 | N5: =SUM(B5:M5) -> 14275 | O5: =B5/$B$58 -> 13967.492 | P5: =C5/$C$58 -> 806.84622 | Q5: =D5/$D$58 -> 0 | R5: =E5/$E$58 -> 0 | S5: =F5/$F$58 -> 0 | T5: =G5/$G$58 -> 0 | U5: =H5/$H$58 -> 0 | V5: =I5/$I$58 -> 0 | W5: =J5/$J$58 -> 0 | X5: =K5/$K$58 -> 0 | Y5: =L5/$L$58 -> 0 | Z5: =M5/$M$58 -> 0 | AA5: =SUM(O5:Z5) -> 14774.338
A6: BallyJamesDuff Co-Op | N6: =SUM(B6:M6) -> 0 | O6: =B6/$B$58 -> 0 | P6: =C6/$C$58 -> 0 | Q6: =D6/$D$58 -> 0 | R6: =E6/$E$58 -> 0 | S6: =F6/$F$58 -> 0 | T6: =G6/$G$58 -> 0 | U6: =H6/$H$58 -> 0 | V6: =I6/$I$58 -> 0 | W6: =J6/$J$58 -> 0 | X6: =K6/$K$58 -> 0 | Y6: =L6/$L$58 -> 0 | Z6: =M6/$M$58 -> 0 | AA6: =SUM(O6:Z6) -> 0
A7: Bandon Co-Op | N7: =SUM(B7:M7) -> 0 | O7: =B7/$B$58 -> 0 | P7: =C7/$C$58 -> 0 | Q7: =D7/$D$58 -> 0 | R7: =E7/$E$58 -> 0 | S7: =F7/$F$58 -> 0 | T7: =G7/$G$58 -> 0 | U7: =H7/$H$58 -> 0 | V7: =I7/$I$58 -> 0 | W7: =J7/$J$58 -> 0 | X7: =K7/$K$58 -> 0 | Y7: =L7/$L$58 -> 0 | Z7: =M7/$M$58 -> 0 | AA7: =SUM(O7:Z7) -> 0
A8: Bandon Vale Cheese | N8: =SUM(B8:M8) -> 0 | O8: =B8/$B$58 -> 0 | P8: =C8/$C$58 -> 0 | Q8: =D8/$D$58 -> 0 | R8: =E8/$E$58 -> 0 | S8: =F8/$F$58 -> 0 | T8: =G8/$G$58 -> 0 | U8: =H8/$H$58 -> 0 | V8: =I8/$I$58 -> 0 | W8: =J8/$J$58 -> 0 | X8: =K8/$K$58 -> 0 | Y8: =L8/$L$58 -> 0 | Z8: =M8/$M$58 -> 0 | AA8: =SUM(O8:Z8) -> 0
A9: Barryroe Co-Op | N9: =SUM(B9:M9) -> 0 | O9: =B9/$B$58 -> 0 | P9: =C9/$C$58 -> 0 | Q9: =D9/$D$58 -> 0 | R9: =E9/$E$58 -> 0 | S9: =F9/$F$58 -> 0 | T9: =G9/$G$58 -> 0 | U9: =H9/$H$58 -> 0 | V9: =I9/$I$58 -> 0 | W9: =J9/$J$58 -> 0 | X9: =K9/$K$58 -> 0 | Y9: =L9/$L$58 -> 0 | Z9: =M9/$M$58 -> 0 | AA9: =SUM(O9:Z9) -> 0
A10: Brett Brothers | B10: 8448 | C10: 800 | D10: 2080 | N10: =SUM(B10:M10) -> 11328 | O10: =B10/$B$58 -> 8740.5461 | P10: =C10/$C$58 -> 832.87352 | Q10: =D10/$D$58 -> 2243.0471 | R10: =E10/$E$58 -> 0 | S10: =F10/$F$58 -> 0 | T10: =G10/$G$58 -> 0 | U10: =H10/$H$58 -> 0 | V10: =I10/$I$58 -> 0 | W10: =J10/$J$58 -> 0 | X10: =K10/$K$58 -> 0 | Y10: =L10/$L$58 -> 0 | Z10: =M10/$M$58 -> 0 | AA10: =SUM(O10:Z10) -> 11816.467
A11: Callan Co-Op | C11: 9588.67 | D11: 8063.33 | E11: 3000 | F11: 180 | G11: 3060 | K11: 180 | L11: 2430 | N11: =SUM(B11:M11) -> 26502 | O11: =B11/$B$58 -> 0 | P11: =C11/$C$58 -> 9982.6866 | Q11: =D11/$D$58 -> 8695.3985 | R11: =E11/$E$58 -> 3370.1428 | S11: =F11/$F$58 -> 203.00676 | T11: =G11/$G$58 -> 3525.0613 | U11: =H11/$H$58 -> 0 | V11: =I11/$I$58 -> 0 | W11: =J11/$J$58 -> 0 | X11: =K11/$K$58 -> 209.5899 | Y11: =L11/$L$58 -> 2809.1836 | Z11: =M11/$M$58 -> 0 | AA11: =SUM(O11:Z11) -> 28795.07
A12: Carbery Group | N12: =SUM(B12:M12) -> 0 | O12: =B12/$B$58 -> 0 | P12: =C12/$C$58 -> 0 | Q12: =D12/$D$58 -> 0 | R12: =E12/$E$58 -> 0 | S12: =F12/$F$58 -> 0 | T12: =G12/$G$58 -> 0 | U12: =H12/$H$58 -> 0 | V12: =I12/$I$58 -> 0 | W12: =J12/$J$58 -> 0 | X12: =K12/$K$58 -> 0 | Y12: =L12/$L$58 -> 0 | Z12: =M12/$M$58 -> 0 | AA12: =SUM(O12:Z12) -> 0
A13: Centenary Thurles Fresh Milk | N13: =SUM(B13:M13) -> 0 | O13: =B13/$B$58 -> 0 | P13: =C13/$C$58 -> 0 | Q13: =D13/$D$58 -> 0 | R13: =E13/$E$58 -> 0 | S13: =F13/$F$58 -> 0 | T13: =G13/$G$58 -> 0 | U13: =H13/$H$58 -> 0 | V13: =I13/$I$58 -> 0 | W13: =J13/$J$58 -> 0 | X13: =K13/$K$58 -> 0 | Y13: =L13/$L$58 -> 0 | Z13: =M13/$M$58 -> 0 | AA13: =SUM(O13:Z13) -> 0
A14: Centenary Thurles Co-Op | N14: =SUM(B14:M14) -> 0 | O14: =B14/$B$58 -> 0 | P14: =C14/$C$58 -> 0 | Q14: =D14/$D$58 -> 0 | R14: =E14/$E$58 -> 0 | S14: =F14/$F$58 -> 0 | T14: =G14/$G$58 -> 0 | U14: =H14/$H$58 -> 0 | V14: =I14/$I$58 -> 0 | W14: =J14/$J$58 -> 0 | X14: =K14/$K$58 -> 0 | Y14: =L14/$L$58 -> 0 | Z14: =M14/$M$58 -> 0 | AA14: =SUM(O14:Z14) -> 0
A15: Centenary Thurles Stores | N15: =SUM(B15:M15) -> 0 | O15: =B15/$B$58 -> 0 | P15: =C15/$C$58 -> 0 | Q15: =D15/$D$58 -> 0 | R15: =E15/$E$58 -> 0 | S15: =F15/$F$58 -> 0 | T15: =G15/$G$58 -> 0 | U15: =H15/$H$58 -> 0 | V15: =I15/$I$58 -> 0 | W15: =J15/$J$58 -> 0 | X15: =K15/$K$58 -> 0 | Y15: =L15/$L$58 -> 0 | Z15: =M15/$M$58 -> 0 | AA15: =SUM(O15:Z15) -> 0
A16: Centenary Thurles Feed & Grain | N16: =SUM(B16:M16) -> 0 | O16: =B16/$B$58 -> 0 | P16: =C16/$C$58 -> 0 | Q16: =D16/$D$58 -> 0 | R16: =E16/$E$58 -> 0 | S16: =F16/$F$58 -> 0 | T16: =G16/$G$58 -> 0 | U16: =H16/$H$58 -> 0 | V16: =I16/$I$58 -> 0 | W16: =J16/$J$58 -> 0 | X16: =K16/$K$58 -> 0 | Y16: =L16/$L$58 -> 0 | Z16: =M16/$M$58 -> 0 | AA16: =SUM(O16:Z16) -> 0
A17: Dan O'Connor Feeds | N17: =SUM(B17:M17) -> 0 | O17: =B17/$B$58 -> 0 | P17: =C17/$C$58 -> 0 | Q17: =D17/$D$58 -> 0 | R17: =E17/$E$58 -> 0 | S17: =F17/$F$58 -> 0 | T17: =G17/$G$58 -> 0 | U17: =H17/$H$58 -> 0 | V17: =I17/$I$58 -> 0 | W17: =J17/$J$58 -> 0 | X17: =K17/$K$58 -> 0 | Y17: =L17/$L$58 -> 0 | Z17: =M17/$M$58 -> 0 | AA17: =SUM(O17:Z17) -> 0
A18: Denis Brinicombe Group | N18: =SUM(B18:M18) -> 0 | O18: =B18/$B$58 -> 0 | P18: =C18/$C$58 -> 0 | Q18: =D18/$D$58 -> 0 | R18: =E18/$E$58 -> 0 | S18: =F18/$F$58 -> 0 | T18: =G18/$G$58 -> 0 | U18: =H18/$H$58 -> 0 | V18: =I18/$I$58 -> 0 | W18: =J18/$J$58 -> 0 | X18: =K18/$K$58 -> 0 | Y18: =L18/$L$58 -> 0 | Z18: =M18/$M$58 -> 0 | AA18: =SUM(O18:Z18) -> 0
A19: Drinagh Co-Op | I19: 833.33 | J19: 944.44 | K19: =3082.22+0.01 -> 3082.23 | L19: 900 | M19: 2500 | N19: =SUM(B19:M19) -> 8260 | O19: =B19/$B$58 -> 0 | P19: =C19/$C$58 -> 0 | Q19: =D19/$D$58 -> 0 | R19: =E19/$E$58 -> 0 | S19: =F19/$F$58 -> 0 | T19: =G19/$G$58 -> 0 | U19: =H19/$H$58 -> 0 | V19: =I19/$I$58 -> 970.60228 | W19: =J19/$J$58 -> 1107.8735 | X19: =K19/$K$58 -> 3588.9127 | Y19: =L19/$L$58 -> 1040.4384 | Z19: =M19/$M$58 -> 2928.1548 | AA19: =SUM(O19:Z19) -> 9635.9816
A20: Drinagh Dairies | N20: =SUM(B20:M20) -> 0 | O20: =B20/$B$58 -> 0 | P20: =C20/$C$58 -> 0 | Q20: =D20/$D$58 -> 0 | R20: =E20/$E$58 -> 0 | S20: =F20/$F$58 -> 0 | T20: =G20/$G$58 -> 0 | U20: =H20/$H$58 -> 0 | V20: =I20/$I$58 -> 0 | W20: =J20/$J$58 -> 0 | X20: =K20/$K$58 -> 0 | Y20: =L20/$L$58 -> 0 | Z20: =M20/$M$58 -> 0 | AA20: =SUM(O20:Z20) -> 0
A21: East Coast Viners | B21: 900 | G21: 2100 | H21: 1110 | K21: 400 | M21: 400 | N21: =SUM(B21:M21) -> 4910 | O21: =B21/$B$58 -> 931.16613 | P21: =C21/$C$58 -> 0 | Q21: =D21/$D$58 -> 0 | R21: =E21/$E$58 -> 0 | S21: =F21/$F$58 -> 0 | T21: =G21/$G$58 -> 2419.1597 | U21: =H21/$H$58 -> 1297.1836 | V21: =I21/$I$58 -> 0 | W21: =J21/$J$58 -> 0 | X21: =K21/$K$58 -> 465.75534 | Y21: =L21/$L$58 -> 0 | Z21: =M21/$M$58 -> 468.50477 | AA21: =SUM(O21:Z21) -> 5581.7696
A22: Tirlan | N22: =SUM(B22:M22) -> 0 | O22: =B22/$B$58 -> 0 | P22: =C22/$C$58 -> 0 | Q22: =D22/$D$58 -> 0 | R22: =E22/$E$58 -> 0 | S22: =F22/$F$58 -> 0 | T22: =G22/$G$58 -> 0 | U22: =H22/$H$58 -> 0 | V22: =I22/$I$58 -> 0 | W22: =J22/$J$58 -> 0 | X22: =K22/$K$58 -> 0 | Y22: =L22/$L$58 -> 0 | Z22: =M22/$M$58 -> 0 | AA22: =SUM(O22:Z22) -> 0
A23: Heat Merchants Group | N23: =SUM(B23:M23) -> 0 | O23: =B23/$B$58 -> 0 | P23: =C23/$C$58 -> 0 | Q23: =D23/$D$58 -> 0 | R23: =E23/$E$58 -> 0 | S23: =F23/$F$58 -> 0 | T23: =G23/$G$58 -> 0 | U23: =H23/$H$58 -> 0 | V23: =I23/$I$58 -> 0 | W23: =J23/$J$58 -> 0 | X23: =K23/$K$58 -> 0 | Y23: =L23/$L$58 -> 0 | Z23: =M23/$M$58 -> 0 | AA23: =SUM(O23:Z23) -> 0
A24: Hopkins Homevalue Hardware | N24: =SUM(B24:M24) -> 0 | O24: =B24/$B$58 -> 0 | P24: =C24/$C$58 -> 0 | Q24: =D24/$D$58 -> 0 | R24: =E24/$E$58 -> 0 | S24: =F24/$F$58 -> 0 | T24: =G24/$G$58 -> 0 | U24: =H24/$H$58 -> 0 | V24: =I24/$I$58 -> 0 | W24: =J24/$J$58 -> 0 | X24: =K24/$K$58 -> 0 | Y24: =L24/$L$58 -> 0 | Z24: =M24/$M$58 -> 0 | AA24: =SUM(O24:Z24) -> 0
A25: ICMSA | N25: =SUM(B25:M25) -> 0 | O25: =B25/$B$58 -> 0 | P25: =C25/$C$58 -> 0 | Q25: =D25/$D$58 -> 0 | R25: =E25/$E$58 -> 0 | S25: =F25/$F$58 -> 0 | T25: =G25/$G$58 -> 0 | U25: =H25/$H$58 -> 0 | V25: =I25/$I$58 -> 0 | W25: =J25/$J$58 -> 0 | X25: =K25/$K$58 -> 0 | Y25: =L25/$L$58 -> 0 | Z25: =M25/$M$58 -> 0 | AA25: =SUM(O25:Z25) -> 0
A26: Irish International Traders | N26: =SUM(B26:M26) -> 0 | O26: =B26/$B$58 -> 0 | P26: =C26/$C$58 -> 0 | Q26: =D26/$D$58 -> 0 | R26: =E26/$E$58 -> 0 | S26: =F26/$F$58 -> 0 | T26: =G26/$G$58 -> 0 | U26: =H26/$H$58 -> 0 | V26: =I26/$I$58 -> 0 | W26: =J26/$J$58 -> 0 | X26: =K26/$K$58 -> 0 | Y26: =L26/$L$58 -> 0 | Z26: =M26/$M$58 -> 0 | AA26: =SUM(O26:Z26) -> 0
A27: John R. McCarthy | N27: =SUM(B27:M27) -> 0 | O27: =B27/$B$58 -> 0 | P27: =C27/$C$58 -> 0 | Q27: =D27/$D$58 -> 0 | R27: =E27/$E$58 -> 0 | S27: =F27/$F$58 -> 0 | T27: =G27/$G$58 -> 0 | U27: =H27/$H$58 -> 0 | V27: =I27/$I$58 -> 0 | W27: =J27/$J$58 -> 0 | X27: =K27/$K$58 -> 0 | Y27: =L27/$L$58 -> 0 | Z27: =M27/$M$58 -> 0 | AA27: =SUM(O27:Z27) -> 0
A28: J. McKenna Ltd | N28: =SUM(B28:M28) -> 0 | O28: =B28/$B$58 -> 0 | P28: =C28/$C$58 -> 0 | Q28: =D28/$D$58 -> 0 | R28: =E28/$E$58 -> 0 | S28: =F28/$F$58 -> 0 | T28: =G28/$G$58 -> 0 | U28: =H28/$H$58 -> 0 | V28: =I28/$I$58 -> 0 | W28: =J28/$J$58 -> 0 | X28: =K28/$K$58 -> 0 | Y28: =L28/$L$58 -> 0 | Z28: =M28/$M$58 -> 0 | AA28: =SUM(O28:Z28) -> 0
A29: Kellihers Mills | N29: =SUM(B29:M29) -> 0 | O29: =B29/$B$58 -> 0 | P29: =C29/$C$58 -> 0 | Q29: =D29/$D$58 -> 0 | R29: =E29/$E$58 -> 0 | S29: =F29/$F$58 -> 0 | T29: =G29/$G$58 -> 0 | U29: =H29/$H$58 -> 0 | V29: =I29/$I$58 -> 0 | W29: =J29/$J$58 -> 0 | X29: =K29/$K$58 -> 0 | Y29: =L29/$L$58 -> 0 | Z29: =M29/$M$58 -> 0 | AA29: =SUM(O29:Z29) -> 0
A30: Kerry Agribusiness | N30: =SUM(B30:M30) -> 0 | O30: =B30/$B$58 -> 0 | P30: =C30/$C$58 -> 0 | Q30: =D30/$D$58 -> 0 | R30: =E30/$E$58 -> 0 | S30: =F30/$F$58 -> 0 | T30: =G30/$G$58 -> 0 | U30: =H30/$H$58 -> 0 | V30: =I30/$I$58 -> 0 | W30: =J30/$J$58 -> 0 | X30: =K30/$K$58 -> 0 | Y30: =L30/$L$58 -> 0 | Z30: =M30/$M$58 -> 0 | AA30: =SUM(O30:Z30) -> 0
A31: Kiernan | J31: 30070 | L31: 2040 | N31: =SUM(B31:M31) -> 32110 | O31: =B31/$B$58 -> 0 | P31: =C31/$C$58 -> 0 | Q31: =D31/$D$58 -> 0 | R31: =E31/$E$58 -> 0 | S31: =F31/$F$58 -> 0 | T31: =G31/$G$58 -> 0 | U31: =H31/$H$58 -> 0 | V31: =I31/$I$58 -> 0 | W31: =J31/$J$58 -> 35273.555 | X31: =K31/$K$58 -> 0 | Y31: =L31/$L$58 -> 2358.327 | Z31: =M31/$M$58 -> 0 | AA31: =SUM(O31:Z31) -> 37631.882
A32: Lacpatrick | N32: =SUM(B32:M32) -> 0 | O32: =B32/$B$58 -> 0 | P32: =C32/$C$58 -> 0 | Q32: =D32/$D$58 -> 0 | R32: =E32/$E$58 -> 0 | S32: =F32/$F$58 -> 0 | T32: =G32/$G$58 -> 0 | U32: =H32/$H$58 -> 0 | V32: =I32/$I$58 -> 0 | W32: =J32/$J$58 -> 0 | X32: =K32/$K$58 -> 0 | Y32: =L32/$L$58 -> 0 | Z32: =M32/$M$58 -> 0 | AA32: =SUM(O32:Z32) -> 0
A33: Lakeland | N33: =SUM(B33:M33) -> 0 | O33: =B33/$B$58 -> 0 | P33: =C33/$C$58 -> 0 | Q33: =D33/$D$58 -> 0 | R33: =E33/$E$58 -> 0 | S33: =F33/$F$58 -> 0 | T33: =G33/$G$58 -> 0 | U33: =H33/$H$58 -> 0 | V33: =I33/$I$58 -> 0 | W33: =J33/$J$58 -> 0 | X33: =K33/$K$58 -> 0 | Y33: =L33/$L$58 -> 0 | Z33: =M33/$M$58 -> 0 | AA33: =SUM(O33:Z33) -> 0
A34: Lee Strand Dairies | N34: =SUM(B34:M34) -> 0 | O34: =B34/$B$58 -> 0 | P34: =C34/$C$58 -> 0 | Q34: =D34/$D$58 -> 0 | R34: =E34/$E$58 -> 0 | S34: =F34/$F$58 -> 0 | T34: =G34/$G$58 -> 0 | U34: =H34/$H$58 -> 0 | V34: =I34/$I$58 -> 0 | W34: =J34/$J$58 -> 0 | X34: =K34/$K$58 -> 0 | Y34: =L34/$L$58 -> 0 | Z34: =M34/$M$58 -> 0 | AA34: =SUM(O34:Z34) -> 0
A35: Lisavaird Co-Op | D35: 2550 | F35: 2550 | I35: 666.67 | L35: 8400 | M35: -66.67 | N35: =SUM(B35:M35) -> 14100 | O35: =B35/$B$58 -> 0 | P35: =C35/$C$58 -> 0 | Q35: =D35/$D$58 -> 2749.8895 | R35: =E35/$E$58 -> 0 | S35: =F35/$F$58 -> 2875.929 | T35: =G35/$G$58 -> 0 | U35: =H35/$H$58 -> 0 | V35: =I35/$I$58 -> 776.48881 | W35: =J35/$J$58 -> 0 | X35: =K35/$K$58 -> 0 | Y35: =L35/$L$58 -> 9710.7581 | Z35: =M35/$M$58 -> -78.088032 | AA35: =SUM(O35:Z35) -> 16034.977
A36: McDonnell Bros Ltd | I36: 2850 | N36: =SUM(B36:M36) -> 2850 | O36: =B36/$B$58 -> 0 | P36: =C36/$C$58 -> 0 | Q36: =D36/$D$58 -> 0 | R36: =E36/$E$58 -> 0 | S36: =F36/$F$58 -> 0 | T36: =G36/$G$58 -> 0 | U36: =H36/$H$58 -> 0 | V36: =I36/$I$58 -> 3319.4731 | W36: =J36/$J$58 -> 0 | X36: =K36/$K$58 -> 0 | Y36: =L36/$L$58 -> 0 | Z36: =M36/$M$58 -> 0 | AA36: =SUM(O36:Z36) -> 3319.4731
A37: McDonogh Trade Centre Ltd | N37: =SUM(B37:M37) -> 0 | O37: =B37/$B$58 -> 0 | P37: =C37/$C$58 -> 0 | Q37: =D37/$D$58 -> 0 | R37: =E37/$E$58 -> 0 | S37: =F37/$F$58 -> 0 | T37: =G37/$G$58 -> 0 | U37: =H37/$H$58 -> 0 | V37: =I37/$I$58 -> 0 | W37: =J37/$J$58 -> 0 | X37: =K37/$K$58 -> 0 | Y37: =L37/$L$58 -> 0 | Z37: =M37/$M$58 -> 0 | AA37: =SUM(O37:Z37) -> 0
A38: M.D O'Shea & Sons Ltd | B38: 149.11 | C38: 139.78 | D38: -0.79 | F38: 4550 | G38: 14800 | H38: -0.31 | M38: 1900 | N38: =SUM(B38:M38) -> 21537.79 | O38: =B38/$B$58 -> 154.27354 | P38: =C38/$C$58 -> 145.52383 | Q38: =D38/$D$58 -> -0.85192654 | R38: =E38/$E$58 -> 0 | S38: =F38/$F$58 -> 5131.5597 | T38: =G38/$G$58 -> 17049.316 | U38: =H38/$H$58 -> -0.3622765 | V38: =I38/$I$58 -> 0 | W38: =J38/$J$58 -> 0 | X38: =K38/$K$58 -> 0 | Y38: =L38/$L$58 -> 0 | Z38: =M38/$M$58 -> 2225.3976 | AA38: =SUM(O38:Z38) -> 24704.857
A39: Morris DIY & Building | I39: 900 | M39: 1350 | N39: =SUM(B39:M39) -> 2250 | O39: =B39/$B$58 -> 0 | P39: =C39/$C$58 -> 0 | Q39: =D39/$D$58 -> 0 | R39: =E39/$E$58 -> 0 | S39: =F39/$F$58 -> 0 | T39: =G39/$G$58 -> 0 | U39: =H39/$H$58 -> 0 | V39: =I39/$I$58 -> 1048.2547 | W39: =J39/$J$58 -> 0 | X39: =K39/$K$58 -> 0 | Y39: =L39/$L$58 -> 0 | Z39: =M39/$M$58 -> 1581.2036 | AA39: =SUM(O39:Z39) -> 2629.4582
A40: NewMarket Co-Op Creameries Ltd | N40: =SUM(B40:M40) -> 0 | O40: =B40/$B$58 -> 0 | P40: =C40/$C$58 -> 0 | Q40: =D40/$D$58 -> 0 | R40: =E40/$E$58 -> 0 | S40: =F40/$F$58 -> 0 | T40: =G40/$G$58 -> 0 | U40: =H40/$H$58 -> 0 | V40: =I40/$I$58 -> 0 | W40: =J40/$J$58 -> 0 | X40: =K40/$K$58 -> 0 | Y40: =L40/$L$58 -> 0 | Z40: =M40/$M$58 -> 0 | AA40: =SUM(O40:Z40) -> 0
A41: North Cork Co-Op | N41: =SUM(B41:M41) -> 0 | O41: =B41/$B$58 -> 0 | P41: =C41/$C$58 -> 0 | Q41: =D41/$D$58 -> 0 | R41: =E41/$E$58 -> 0 | S41: =F41/$F$58 -> 0 | T41: =G41/$G$58 -> 0 | U41: =H41/$H$58 -> 0 | V41: =I41/$I$58 -> 0 | W41: =J41/$J$58 -> 0 | X41: =K41/$K$58 -> 0 | Y41: =L41/$L$58 -> 0 | Z41: =M41/$M$58 -> 0 | AA41: =SUM(O41:Z41) -> 0
A42: Organic Herd | N42: =SUM(B42:M42) -> 0 | O42: =B42/$B$58 -> 0 | P42: =C42/$C$58 -> 0 | Q42: =D42/$D$58 -> 0 | R42: =E42/$E$58 -> 0 | S42: =F42/$F$58 -> 0 | T42: =G42/$G$58 -> 0 | U42: =H42/$H$58 -> 0 | V42: =I42/$I$58 -> 0 | W42: =J42/$J$58 -> 0 | X42: =K42/$K$58 -> 0 | Y42: =L42/$L$58 -> 0 | Z42: =M42/$M$58 -> 0 | AA42: =SUM(O42:Z42) -> 0
A43: Peter Curran Electrical | N43: =SUM(B43:M43) -> 0 | O43: =B43/$B$58 -> 0 | P43: =C43/$C$58 -> 0 | Q43: =D43/$D$58 -> 0 | R43: =E43/$E$58 -> 0 | S43: =F43/$F$58 -> 0 | T43: =G43/$G$58 -> 0 | U43: =H43/$H$58 -> 0 | V43: =I43/$I$58 -> 0 | W43: =J43/$J$58 -> 0 | X43: =K43/$K$58 -> 0 | Y43: =L43/$L$58 -> 0 | Z43: =M43/$M$58 -> 0 | AA43: =SUM(O43:Z43) -> 0
A44: Richard Boyle & Sons Ltd | N44: =SUM(B44:M44) -> 0 | O44: =B44/$B$58 -> 0 | P44: =C44/$C$58 -> 0 | Q44: =D44/$D$58 -> 0 | R44: =E44/$E$58 -> 0 | S44: =F44/$F$58 -> 0 | T44: =G44/$G$58 -> 0 | U44: =H44/$H$58 -> 0 | V44: =I44/$I$58 -> 0 | W44: =J44/$J$58 -> 0 | X44: =K44/$K$58 -> 0 | Y44: =L44/$L$58 -> 0 | Z44: =M44/$M$58 -> 0 | AA44: =SUM(O44:Z44) -> 0
A45: Smith's Building supplies | N45: =SUM(B45:M45) -> 0 | O45: =B45/$B$58 -> 0 | P45: =C45/$C$58 -> 0 | Q45: =D45/$D$58 -> 0 | R45: =E45/$E$58 -> 0 | S45: =F45/$F$58 -> 0 | T45: =G45/$G$58 -> 0 | U45: =H45/$H$58 -> 0 | V45: =I45/$I$58 -> 0 | W45: =J45/$J$58 -> 0 | X45: =K45/$K$58 -> 0 | Y45: =L45/$L$58 -> 0 | Z45: =M45/$M$58 -> 0 | AA45: =SUM(O45:Z45) -> 0
A46: Smith's Tool Hire | N46: =SUM(B46:M46) -> 0 | O46: =B46/$B$58 -> 0 | P46: =C46/$C$58 -> 0 | Q46: =D46/$D$58 -> 0 | R46: =E46/$E$58 -> 0 | S46: =F46/$F$58 -> 0 | T46: =G46/$G$58 -> 0 | U46: =H46/$H$58 -> 0 | V46: =I46/$I$58 -> 0 | W46: =J46/$J$58 -> 0 | X46: =K46/$K$58 -> 0 | Y46: =L46/$L$58 -> 0 | Z46: =M46/$M$58 -> 0 | AA46: =SUM(O46:Z46) -> 0
A47: Strathroy Dairies | N47: =SUM(B47:M47) -> 0 | O47: =B47/$B$58 -> 0 | P47: =C47/$C$58 -> 0 | Q47: =D47/$D$58 -> 0 | R47: =E47/$E$58 -> 0 | S47: =F47/$F$58 -> 0 | T47: =G47/$G$58 -> 0 | U47: =H47/$H$58 -> 0 | V47: =I47/$I$58 -> 0 | W47: =J47/$J$58 -> 0 | X47: =K47/$K$58 -> 0 | Y47: =L47/$L$58 -> 0 | Z47: =M47/$M$58 -> 0 | AA47: =SUM(O47:Z47) -> 0
A48: T&A Building | N48: =SUM(B48:M48) -> 0 | O48: =B48/$B$58 -> 0 | P48: =C48/$C$58 -> 0 | Q48: =D48/$D$58 -> 0 | R48: =E48/$E$58 -> 0 | S48: =F48/$F$58 -> 0 | T48: =G48/$G$58 -> 0 | U48: =H48/$H$58 -> 0 | V48: =I48/$I$58 -> 0 | W48: =J48/$J$58 -> 0 | X48: =K48/$K$58 -> 0 | Y48: =L48/$L$58 -> 0 | Z48: =M48/$M$58 -> 0 | AA48: =SUM(O48:Z48) -> 0
A49: Wallaces Homevalue Hardware | E49: 471.54 | F49: 4039.32 | G49: 2910.92 | H49: 1552.03 | J49: 157.49 | K49: 384 | L49: 84.71 | N49: =SUM(B49:M49) -> 9600.01 | O49: =B49/$B$58 -> 0 | P49: =C49/$C$58 -> 0 | Q49: =D49/$D$58 -> 0 | R49: =E49/$E$58 -> 529.71904 | S49: =F49/$F$58 -> 4555.6069 | T49: =G49/$G$58 -> 3353.324 | U49: =H49/$H$58 -> 1813.7548 | V49: =I49/$I$58 -> 0 | W49: =J49/$J$58 -> 184.74334 | X49: =K49/$K$58 -> 447.12513 | Y49: =L49/$L$58 -> 97.928372 | Z49: =M49/$M$58 -> 0 | AA49: =SUM(O49:Z49) -> 10982.202
A50: Discount
B52: =SUM(B3:B50) -> 22997.11 | C52: =SUM(C3:C51) -> 11303.45 | D52: =SUM(D3:D49) -> 12692.54 | E52: =SUM(E3:E51) -> 38631.54 | F52: =SUM(F3:F50) -> 14319.32 | G52: =SUM(G3:G49) -> 28625.92 | H52: =SUM(H3:H50) -> 2661.72 | I52: =SUM(I3:I49) -> 5250 | J52: =SUM(J3:J49) -> 31171.93 | K52: =SUM(K3:K50) -> 4046.23 | L52: =SUM(L3:L49) -> 24276.93 | M52: =SUM(M3:M49) -> 18161.11 | N52: =SUM(B52:M52) -> 214137.8 | O52: =SUM(O3:O50) -> 23793.478 | P52: =C52/$C$58 -> 11767.93 | Q52: =SUM(Q3:Q50) -> 13687.483 | R52: =SUM(R3:R50) -> 43397.935 | S52: =SUM(S3:S50) -> 16149.548 | T52: =SUM(T3:T50) -> 32976.511 | U52: =SUM(U3:U50) -> 3110.5761 | V52: =SUM(V3:V50) -> 6114.8188 | W52: =SUM(W3:W50) -> 36566.172 | X52: =SUM(X3:X50) -> 4711.3831 | ... AA52: =SUM(AA3:AA50) -> 241612.42
A54: GP Balance | B54: 22997.11 | C54: 11303.45 | D54: 12692.54 | E54: 38631.54 | F54: 14319.32 | G54: 28625.92 | H54: 2661.72 | I54: 5250 | J54: 31171.93 | K54: 4046.23 | L54: 24276.93 | M54: 18161.11 | O54: =B52/B58 -> 23793.478 | P54: =C52/C58 -> 11767.93 | Q54: =D52/D58 -> 13687.483 | R54: =E52/E58 -> 43397.935 | S54: =F52/F58 -> 16149.548 | T54: =G52/G58 -> 32976.511 | U54: =H52/H58 -> 3110.5761 | V54: =I52/I58 -> 6114.8188 | ... Z54: =M52/M58 -> 21271.417
A56: Variance | B56: =B52-B54 -> 0 | C56: =C52-C54 -> 0 | D56: =D52-D54 -> 0 | E56: =E52-E54 -> 0 | F56: =F52-F54 -> 0 | G56: =G52-G54 -> 0 | H56: =H52-H54 -> 0 | I56: =I52-I54 -> 0 | ... M56: =M52-M54 -> 0
B58: 0.96653 | C58: 0.96053 | D58: 0.92731 | E58: 0.89017 | F58: 0.88667 | G58: 0.86807 | H58: 0.8557 | I58: 0.85857 | J58: 0.85248 | K58: 0.85882 | L58: 0.86502 | M58: 0.85378
M60: Total | N60: =N52 -> 214137.8 | O60: =AA52 -> 241612.42
M61: BPC
M62: Variance | N62: =N60-N61 -> 214137.8 | O62: =O60-O61 -> 241612.42

Sheet 5050-10
A1: Customer | B1: January | C1: February | D1: March | E1: April | F1: May | G1: June | H1: July | I1: August | J1: September | K1: October | L1: November | M1: December | N1: Total | O1: Jan USD | P1: Feb USD | Q1: March USD | R1: April USD | S1: May USD | T1: June USD | U1: July USD | V1: August USD | W1: September USD | X1: October USD | Y1: November USD | Z1: December USD | AA1: Consol USD
A2: Kiernan's | F2: -32 | G2: 23.5 | H2: -85.5 | I2: 253.2 | J2: 319.6 | K2: 234.6 | L2: 0 | M2: -713.4 | N2: =SUM(B2:M2) -> 0 | O2: =B2/B4 -> 0 | P2: =C2/C4 -> 0 | Q2: =D2/D4 -> 0 | R2: =E2/E4 -> 0 | S2: =F2/F4 -> -34.5845 | T2: =G2/G4 -> 25.282682 | U2: =H2/H4 -> -92.759346 | V2: =I2/I4 -> 278.9007 | ... Z2: =M2/M4 -> -747.21914 | AA2: 146.07
B4: 0.9166 | C4: 0.9267 | D4: 0.92048 | E4: 0.93279 | F4: 0.92527 | G4: 0.92949 | H4: 0.92174 | I4: 0.90785 | J4: 0.90039 | K4: 0.9176 | L4: 0.94127 | M4: 0.95474
